Workbook

Sheet Provider
A1: First Name | B1: Last Name | C1: Gender | D1: Professional Suffix 1 | E1: Professional Suffix 2 | F1: Professional Suffix 3 | G1: Specialty 1 | H1: Specialty 2 | I1: Specialty 3 | J1: Specialty 4 | K1: Specialty 5 | L1: Patients Accepted | M1: Practice Name | N1: Location 1 | O1: Location 2 | P1: Location 3 | Q1: Location 4 | R1: Location 5 | S1: NPI Number | T1: Headshot Link | U1: Education 1 | V1: Education 2 | W1: Education 3 | X1: Education 4 | Y1: Education 5 | Z1: Professional Statement | AA1: Board Certification 1 | AB1: Sub Board Certification 1 | AC1: Board Certification 2 | AD1: Sub Board Certification 2 | AE1: Board Certification 3 | AF1: Sub Board Certification 3 | AG1: Board Certification 4 | AH1: Sub Board Certification 4 | AI1: Board Certification 5 | AJ1: Sub Board Certification 5 | AK1: Professional Memberships 1 | AL1: Professional Memberships 2 | AM1: Professional Memberships 3 | AN1: Professional Memberships 4 | AO1: Professional Memberships 5 | AP1: Awards and Publications 1 | AQ1: Awards and Publications 2 | AR1: Awards and Publications 3 | AS1: Awards and Publications 4 | AT1: Awards and Publications 5 | AU1: Hospital Affiliation 1 | AV1: Hospital Affiliation 2 | AW1: Hospital Affiliation 3 | AX1: Hospital Affiliation 4 | AY1: Hospital Affiliation 5 | AZ1: Additional Languages Spoken 1 | BA1: Additional Languages Spoken 2 | BB1: Additional Languages Spoken 3 | BC1: Practice Cloud ID | BD1: Provider Cloud ID | BE1: Provider Type | BF1: Salesforce Contact ID | BG1: Enterprise Scheduling Flag | BH1: Opt Out of Ratings | BI1: Provider Type (Substatus) ID | BJ1: Professional Suffix ID 1 | BK1: Professional Suffix ID 2 | BL1: Professional Suffix ID 3 | BM1: Specialty ID 1 | BN1: Specialty ID 2 | BO1: Specialty ID 3 | BP1: Specialty ID 4 | BQ1: Specialty ID 5 | BR1: Location ID 1 | BS1: Location ID 2 | BT1: Location ID 3 | BU1: Location ID 4 | BV1: Location ID 5 | BW1: Board Cert ID 1 | BX1: Sub Board Cert ID 1 | BY1: Board Cert ID 2 | BZ1: Sub Board Cert ID 2 | CA1: Board Cert ID 3 | CB1: Sub Board Cert ID 3 | CC1: Board Cert ID 4 | CD1: Sub Board Cert ID 4 | CE1: Board Cert ID 5 | CF1: Sub Board Cert ID 5 | CG1: Hospital Affiliation ID 1 | CH1: Hospital Affiliation ID 2 | CI1: Hospital Affiliation ID 3 | CJ1: Hospital Affiliation ID 4 | CK1: Hospital Affiliation ID 5 | CL1: Language ID 1 | CM1: Language ID 2 | CN1: Language ID 3 | CO1: Facility Address | CP1: Facility City | CQ1: Facility Zip | CR1: Facility State | CS1: Address line 2 | CT1: Matched
A2: Amanda | B2: Walker | C2: Female | G2: =IFERROR(VLOOKUP(BM2, ValidationAndReference!J:K, 2, FALSE), "") | L2: Both | M2: LifeStance Health | N2: =IFERROR(INDEX(Location!X:X, MATCH(BR2, Location!W:W, 0)), "") | O2: =IFERROR(INDEX(Location!X:X, MATCH(BS2, Location!W:W, 0)), "") | S2: 1003055393 | T2: https://prod-clinicians-photo.s3.amazonaws.com/1003055393.jpg | U2: PhD, Binghamton University | Z2: Amanda Walker, LCSW, provides compassionate and goaloriented therapy to individuals, couples, and families across Massachusetts. She works with adolescents, young adults, and adults, helping them navigate lifeâs challenges with a supportive and collaborative approach. Whether addressing anxiety, bipolar disorder, or relationship concerns, Amanda tailors treatment to meet each clientâs unique needs, fostering resilience and emotional wellbeing. Amanda has a deep passion for working with individuals facing major life transitions, including midlife changes, reproductive challenges, and postpartum depression and anxiety. She understands the emotional toll these experiences can take and strives to create a safe space where clients can process their emotions and develop coping strategies. With a strong commitment to supporting womenâs mental health, she empowers clients to regain confidence and balance in their lives. Specializing in both individual and couples therapy, Amanda integrates evidencebased techniques such as Cognitive Behavioral Therapy CBT, and Dialectical Behavior Therapy DBT to promote meaningful change. She is particularly skilled in working with first responders, LGBTQ individuals, and veterans, addressing the unique mental health concerns these communities may face. Her approach is rooted in empathy, understanding, and a dedication to helping clients achieve personal growth. Outside of her work, Amanda enjoys painting, cooking, and engaging in sports. She finds joy in creativity and movement, using these activities as a source of relaxation and personal fulfillment. Amanda is honored to serve individuals and families across Massachusetts, providing the guidance and support needed to navigate lifeâs complexities with strength and clarity. | AZ2: English | BC2: pt_B8LtUoRcYkWdny_20xbxdB | BE2: Practitioner - Full Profile | BG2: No | BI2: =IFERROR(INDEX(ValidationAndReference!P:P, MATCH(BE2, ValidationAndReference!Q:Q, 0)), "") | BJ2: =IFERROR(INDEX(ValidationAndReference!F:F, MATCH(D2, ValidationAndReference!G:G, 0)), "") | BK2: =IFERROR(INDEX(ValidationAndReference!F:F, MATCH(E2, ValidationAndReference!G:G, 0)), "") | BL2: =IFERROR(INDEX(ValidationAndReference!F:F, MATCH(F2, ValidationAndReference!G:G, 0)), "") | BR2: lo_mif8U7nWSU-EYq8liS2VYB | BS2: lo_N-mYRnhFs0OO_SnP_I3_wx | CL2: =IFERROR(INDEX(ValidationAndReference!V:V, MATCH(AZ2, ValidationAndReference!W:W, 0)), "") | CM2: =IFERROR(INDEX(ValidationAndReference!V:V, MATCH(BA2, ValidationAndReference!W:W, 0)), "") | CN2: =IFERROR(INDEX(ValidationAndReference!V:V, MATCH(BB2, ValidationAndReference!W:W, 0)), "") | CO2: 5 Hampshire St | CP2: Mansfield | CQ2: 2048 | CR2: MA | CT2: No - Facility Zip
A3: Amanda | B3: Walker | C3: Female | G3: =IFERROR(VLOOKUP(BM3, ValidationAndReference!J:K, 2, FALSE), "") | L3: Both | M3: LifeStance Health | N3: =IFERROR(INDEX(Location!X:X, MATCH(BR3, Location!W:W, 0)), "") | O3: =IFERROR(INDEX(Location!X:X, MATCH(BS3, Location!W:W, 0)), "") | S3: 1003055393 | T3: https://prod-clinicians-photo.s3.amazonaws.com/1003055393.jpg | U3: PhD, Binghamton University | Z3: Amanda Walker, LCSW, provides compassionate and goaloriented therapy to individuals, couples, and families across Massachusetts. She works with adolescents, young adults, and adults, helping them navigate lifeâs challenges with a supportive and collaborative approach. Whether addressing anxiety, bipolar disorder, or relationship concerns, Amanda tailors treatment to meet each clientâs unique needs, fostering resilience and emotional wellbeing. Amanda has a deep passion for working with individuals facing major life transitions, including midlife changes, reproductive challenges, and postpartum depression and anxiety. She understands the emotional toll these experiences can take and strives to create a safe space where clients can process their emotions and develop coping strategies. With a strong commitment to supporting womenâs mental health, she empowers clients to regain confidence and balance in their lives. Specializing in both individual and couples therapy, Amanda integrates evidencebased techniques such as Cognitive Behavioral Therapy CBT, and Dialectical Behavior Therapy DBT to promote meaningful change. She is particularly skilled in working with first responders, LGBTQ individuals, and veterans, addressing the unique mental health concerns these communities may face. Her approach is rooted in empathy, understanding, and a dedication to helping clients achieve personal growth. Outside of her work, Amanda enjoys painting, cooking, and engaging in sports. She finds joy in creativity and movement, using these activities as a source of relaxation and personal fulfillment. Amanda is honored to serve individuals and families across Massachusetts, providing the guidance and support needed to navigate lifeâs complexities with strength and clarity. | AZ3: English | BC3: pt_B8LtUoRcYkWdny_20xbxdB | BE3: Practitioner - Full Profile | BG3: No | BI3: =IFERROR(INDEX(ValidationAndReference!P:P, MATCH(BE3, ValidationAndReference!Q:Q, 0)), "") | BJ3: =IFERROR(INDEX(ValidationAndReference!F:F, MATCH(D3, ValidationAndReference!G:G, 0)), "") | BK3: =IFERROR(INDEX(ValidationAndReference!F:F, MATCH(E3, ValidationAndReference!G:G, 0)), "") | BL3: =IFERROR(INDEX(ValidationAndReference!F:F, MATCH(F3, ValidationAndReference!G:G, 0)), "") | BR3: lo_mif8U7nWSU-EYq8liS2VYB | BS3: lo_N-mYRnhFs0OO_SnP_I3_wx | CL3: =IFERROR(INDEX(ValidationAndReference!V:V, MATCH(AZ3, ValidationAndReference!W:W, 0)), "") | CM3: =IFERROR(INDEX(ValidationAndReference!V:V, MATCH(BA3, ValidationAndReference!W:W, 0)), "") | CN3: =IFERROR(INDEX(ValidationAndReference!V:V, MATCH(BB3, ValidationAndReference!W:W, 0)), "") | CO3: 5 Hampshire St | CP3: Mansfield | CQ3: 2048 | CR3: MA | CT3: No - Facility Zip
A4: Marci | B4: Langevin | C4: Female | D4: MSW | E4: LICSW | G4: =IFERROR(VLOOKUP(BM4, ValidationAndReference!J:K, 2, FALSE), "") | L4: Both | M4: LifeStance Health | N4: =IFERROR(INDEX(Location!X:X, MATCH(BR4, Location!W:W, 0)), "") | O4: =IFERROR(INDEX(Location!X:X, MATCH(BS4, Location!W:W, 0)), "") | S4: 1003065186 | T4: https://prod-clinicians-photo.s3.amazonaws.com/1003065186.jpg | U4: MSW, Bridgewater State College | Z4: Marci Langevin is an Independently Licensed Clinical Social Worker and Mental Health Provider who has a top notch ability to hear the voice of her clientsâ and truly understand their experience. Marci specializes in cognitive behavioral therapy and motivational counseling that helps propel clients to reach therapeutic goal achievement. Marciâs compassion and skill in helping individuals and families is of such value in a time when so many desire a safe therapeutic environment where they can receive caring help that really makes a difference in their life. From the moment you meet Marci it is clear that her style is to identify the mental health and wellness needs of her clients with care. She is genuinely interested in her clientsâ thoughts and feelings. Her therapeutic methodology is to help her clients to identify their presenting problem, understand their thoughts and behaviors, and guide them towards awareness and resolution. She holds a masterâs degree in Social Work. Prior to joining our team, Marci provided individual, couple, and family counseling in an outpatient mental health facility in MA. In addition, she holds a research based background in issues of discrimination and oppression, has created and facilitated several therapeutic treatment groups including drug and alcohol recovery, and the use of artistic and creative expression for those experiencing depression, anxiety andor trauma. | AZ4: English | BC4: pt_B8LtUoRcYkWdny_20xbxdB | BE4: Practitioner - Full Profile | BG4: No | BI4: =IFERROR(INDEX(ValidationAndReference!P:P, MATCH(BE4, ValidationAndReference!Q:Q, 0)), "") | BJ4: =IFERROR(INDEX(ValidationAndReference!F:F, MATCH(D4, ValidationAndReference!G:G, 0)), "") | BK4: =IFERROR(INDEX(ValidationAndReference!F:F, MATCH(E4, ValidationAndReference!G:G, 0)), "") | BL4: =IFERROR(INDEX(ValidationAndReference!F:F, MATCH(F4, ValidationAndReference!G:G, 0)), "") | BM4: 352 | BR4: lo_mif8U7nWSU-EYq8liS2VYB | BS4: lo_N-mYRnhFs0OO_SnP_I3_wx | CL4: =IFERROR(INDEX(ValidationAndReference!V:V, MATCH(AZ4, ValidationAndReference!W:W, 0)), "") | CM4: =IFERROR(INDEX(ValidationAndReference!V:V, MATCH(BA4, ValidationAndReference!W:W, 0)), "") | CN4: =IFERROR(INDEX(ValidationAndReference!V:V, MATCH(BB4, ValidationAndReference!W:W, 0)), "") | CO4: 5 Hampshire St | CP4: Mansfield | CQ4: 2048 | CR4: MA | CT4: No - Facility Zip
A5: Marci | B5: Langevin | C5: Female | D5: MSW | E5: LICSW | G5: =IFERROR(VLOOKUP(BM5, ValidationAndReference!J:K, 2, FALSE), "") | L5: Both | M5: LifeStance Health | N5: =IFERROR(INDEX(Location!X:X, MATCH(BR5, Location!W:W, 0)), "") | O5: =IFERROR(INDEX(Location!X:X, MATCH(BS5, Location!W:W, 0)), "") | S5: 1003065186 | T5: https://prod-clinicians-photo.s3.amazonaws.com/1003065186.jpg | U5: MSW, Bridgewater State College | Z5: Marci Langevin is an Independently Licensed Clinical Social Worker and Mental Health Provider who has a top notch ability to hear the voice of her clientsâ and truly understand their experience. Marci specializes in cognitive behavioral therapy and motivational counseling that helps propel clients to reach therapeutic goal achievement. Marciâs compassion and skill in helping individuals and families is of such value in a time when so many desire a safe therapeutic environment where they can receive caring help that really makes a difference in their life. From the moment you meet Marci it is clear that her style is to identify the mental health and wellness needs of her clients with care. She is genuinely interested in her clientsâ thoughts and feelings. Her therapeutic methodology is to help her clients to identify their presenting problem, understand their thoughts and behaviors, and guide them towards awareness and resolution. She holds a masterâs degree in Social Work. Prior to joining our team, Marci provided individual, couple, and family counseling in an outpatient mental health facility in MA. In addition, she holds a research based background in issues of discrimination and oppression, has created and facilitated several therapeutic treatment groups including drug and alcohol recovery, and the use of artistic and creative expression for those experiencing depression, anxiety andor trauma. | AZ5: English | BC5: pt_B8LtUoRcYkWdny_20xbxdB | BE5: Practitioner - Full Profile | BG5: No | BI5: =IFERROR(INDEX(ValidationAndReference!P:P, MATCH(BE5, ValidationAndReference!Q:Q, 0)), "") | BJ5: =IFERROR(INDEX(ValidationAndReference!F:F, MATCH(D5, ValidationAndReference!G:G, 0)), "") | BK5: =IFERROR(INDEX(ValidationAndReference!F:F, MATCH(E5, ValidationAndReference!G:G, 0)), "") | BL5: =IFERROR(INDEX(ValidationAndReference!F:F, MATCH(F5, ValidationAndReference!G:G, 0)), "") | BM5: 352 | BR5: lo_mif8U7nWSU-EYq8liS2VYB | BS5: lo_N-mYRnhFs0OO_SnP_I3_wx | CL5: =IFERROR(INDEX(ValidationAndReference!V:V, MATCH(AZ5, ValidationAndReference!W:W, 0)), "") | CM5: =IFERROR(INDEX(ValidationAndReference!V:V, MATCH(BA5, ValidationAndReference!W:W, 0)), "") | CN5: =IFERROR(INDEX(ValidationAndReference!V:V, MATCH(BB5, ValidationAndReference!W:W, 0)), "") | CO5: 5 Hampshire St | CP5: Mansfield | CQ5: 2048 | CR5: MA | CT5: No - Facility Zip
A6: Marci | B6: Langevin | C6: Female | D6: MSW | E6: LICSW | G6: =IFERROR(VLOOKUP(BM6, ValidationAndReference!J:K, 2, FALSE), "") | L6: Both | M6: LifeStance Health | N6: =IFERROR(INDEX(Location!X:X, MATCH(BR6, Location!W:W, 0)), "") | O6: =IFERROR(INDEX(Location!X:X, MATCH(BS6, Location!W:W, 0)), "") | S6: 1003065186 | T6: https://prod-clinicians-photo.s3.amazonaws.com/1003065186.jpg | U6: MSW, Bridgewater State College | Z6: Marci Langevin is an Independently Licensed Clinical Social Worker and Mental Health Provider who has a top notch ability to hear the voice of her clientsâ and truly understand their experience. Marci specializes in cognitive behavioral therapy and motivational counseling that helps propel clients to reach therapeutic goal achievement. Marciâs compassion and skill in helping individuals and families is of such value in a time when so many desire a safe therapeutic environment where they can receive caring help that really makes a difference in their life. From the moment you meet Marci it is clear that her style is to identify the mental health and wellness needs of her clients with care. She is genuinely interested in her clientsâ thoughts and feelings. Her therapeutic methodology is to help her clients to identify their presenting problem, understand their thoughts and behaviors, and guide them towards awareness and resolution. She holds a masterâs degree in Social Work. Prior to joining our team, Marci provided individual, couple, and family counseling in an outpatient mental health facility in MA. In addition, she holds a research based background in issues of discrimination and oppression, has created and facilitated several therapeutic treatment groups including drug and alcohol recovery, and the use of artistic and creative expression for those experiencing depression, anxiety andor trauma. | AZ6: English | BC6: pt_B8LtUoRcYkWdny_20xbxdB | BE6: Practitioner - Full Profile | BG6: No | BI6: =IFERROR(INDEX(ValidationAndReference!P:P, MATCH(BE6, ValidationAndReference!Q:Q, 0)), "") | BJ6: =IFERROR(INDEX(ValidationAndReference!F:F, MATCH(D6, ValidationAndReference!G:G, 0)), "") | BK6: =IFERROR(INDEX(ValidationAndReference!F:F, MATCH(E6, ValidationAndReference!G:G, 0)), "") | BL6: =IFERROR(INDEX(ValidationAndReference!F:F, MATCH(F6, ValidationAndReference!G:G, 0)), "") | BM6: 352 | BR6: lo_te0vo8TuekWyL5gMnjPK1w | BS6: lo_c9GJzBULJ0KYW9u1EWEsUB | CL6: =IFERROR(INDEX(ValidationAndReference!V:V, MATCH(AZ6, ValidationAndReference!W:W, 0)), "") | CM6: =IFERROR(INDEX(ValidationAndReference!V:V, MATCH(BA6, ValidationAndReference!W:W, 0)), "") | CN6: =IFERROR(INDEX(ValidationAndReference!V:V, MATCH(BB6, ValidationAndReference!W:W, 0)), "") | CO6: 45 Shawmut Rd | CP6: Canton | CQ6: 2021 | CR6: MA | CT6: No - Facility Zip
A7: Marci | B7: Langevin | C7: Female | D7: MSW | E7: LICSW | G7: =IFERROR(VLOOKUP(BM7, ValidationAndReference!J:K, 2, FALSE), "") | L7: Both | M7: LifeStance Health | N7: =IFERROR(INDEX(Location!X:X, MATCH(BR7, Location!W:W, 0)), "") | O7: =IFERROR(INDEX(Location!X:X, MATCH(BS7, Location!W:W, 0)), "") | S7: 1003065186 | T7: https://prod-clinicians-photo.s3.amazonaws.com/1003065186.jpg | U7: MSW, Bridgewater State College | Z7: Marci Langevin is an Independently Licensed Clinical Social Worker and Mental Health Provider who has a top notch ability to hear the voice of her clientsâ and truly understand their experience. Marci specializes in cognitive behavioral therapy and motivational counseling that helps propel clients to reach therapeutic goal achievement. Marciâs compassion and skill in helping individuals and families is of such value in a time when so many desire a safe therapeutic environment where they can receive caring help that really makes a difference in their life. From the moment you meet Marci it is clear that her style is to identify the mental health and wellness needs of her clients with care. She is genuinely interested in her clientsâ thoughts and feelings. Her therapeutic methodology is to help her clients to identify their presenting problem, understand their thoughts and behaviors, and guide them towards awareness and resolution. She holds a masterâs degree in Social Work. Prior to joining our team, Marci provided individual, couple, and family counseling in an outpatient mental health facility in MA. In addition, she holds a research based background in issues of discrimination and oppression, has created and facilitated several therapeutic treatment groups including drug and alcohol recovery, and the use of artistic and creative expression for those experiencing depression, anxiety andor trauma. | AZ7: English | BC7: pt_B8LtUoRcYkWdny_20xbxdB | BE7: Practitioner - Full Profile | BG7: No | BI7: =IFERROR(INDEX(ValidationAndReference!P:P, MATCH(BE7, ValidationAndReference!Q:Q, 0)), "") | BJ7: =IFERROR(INDEX(ValidationAndReference!F:F, MATCH(D7, ValidationAndReference!G:G, 0)), "") | BK7: =IFERROR(INDEX(ValidationAndReference!F:F, MATCH(E7, ValidationAndReference!G:G, 0)), "") | BL7: =IFERROR(INDEX(ValidationAndReference!F:F, MATCH(F7, ValidationAndReference!G:G, 0)), "") | BM7: 352 | BR7: lo_te0vo8TuekWyL5gMnjPK1w | BS7: lo_c9GJzBULJ0KYW9u1EWEsUB | CL7: =IFERROR(INDEX(ValidationAndReference!V:V, MATCH(AZ7, ValidationAndReference!W:W, 0)), "") | CM7: =IFERROR(INDEX(ValidationAndReference!V:V, MATCH(BA7, ValidationAndReference!W:W, 0)), "") | CN7: =IFERROR(INDEX(ValidationAndReference!V:V, MATCH(BB7, ValidationAndReference!W:W, 0)), "") | CO7: 45 Shawmut Rd | CP7: Canton | CQ7: 2021 | CR7: MA | CT7: No - Facility Zip
A8: Marci | B8: Langevin | C8: Female | D8: MSW | E8: LICSW | G8: =IFERROR(VLOOKUP(BM8, ValidationAndReference!J:K, 2, FALSE), "") | L8: Both | M8: LifeStance Health | N8: =IFERROR(INDEX(Location!X:X, MATCH(BR8, Location!W:W, 0)), "") | O8: =IFERROR(INDEX(Location!X:X, MATCH(BS8, Location!W:W, 0)), "") | S8: 1003065186 | T8: https://prod-clinicians-photo.s3.amazonaws.com/1003065186.jpg | U8: MSW, Bridgewater State College | Z8: Marci Langevin is an Independently Licensed Clinical Social Worker and Mental Health Provider who has a top notch ability to hear the voice of her clientsâ and truly understand their experience. Marci specializes in cognitive behavioral therapy and motivational counseling that helps propel clients to reach therapeutic goal achievement. Marciâs compassion and skill in helping individuals and families is of such value in a time when so many desire a safe therapeutic environment where they can receive caring help that really makes a difference in their life. From the moment you meet Marci it is clear that her style is to identify the mental health and wellness needs of her clients with care. She is genuinely interested in her clientsâ thoughts and feelings. Her therapeutic methodology is to help her clients to identify their presenting problem, understand their thoughts and behaviors, and guide them towards awareness and resolution. She holds a masterâs degree in Social Work. Prior to joining our team, Marci provided individual, couple, and family counseling in an outpatient mental health facility in MA. In addition, she holds a research based background in issues of discrimination and oppression, has created and facilitated several therapeutic treatment groups including drug and alcohol recovery, and the use of artistic and creative expression for those experiencing depression, anxiety andor trauma. | AZ8: English | BC8: pt_B8LtUoRcYkWdny_20xbxdB | BE8: Practitioner - Full Profile | BG8: No | BI8: =IFERROR(INDEX(ValidationAndReference!P:P, MATCH(BE8, ValidationAndReference!Q:Q, 0)), "") | BJ8: =IFERROR(INDEX(ValidationAndReference!F:F, MATCH(D8, ValidationAndReference!G:G, 0)), "") | BK8: =IFERROR(INDEX(ValidationAndReference!F:F, MATCH(E8, ValidationAndReference!G:G, 0)), "") | BL8: =IFERROR(INDEX(ValidationAndReference!F:F, MATCH(F8, ValidationAndReference!G:G, 0)), "") | BM8: 352 | BR8: lo_WGSx6xN8302ASv6YVggXbh | BS8: lo_8kwZD7BrWkmw6LTpfZ-4yB | CL8: =IFERROR(INDEX(ValidationAndReference!V:V, MATCH(AZ8, ValidationAndReference!W:W, 0)), "") | CM8: =IFERROR(INDEX(ValidationAndReference!V:V, MATCH(BA8, ValidationAndReference!W:W, 0)), "") | CN8: =IFERROR(INDEX(ValidationAndReference!V:V, MATCH(BB8, ValidationAndReference!W:W, 0)), "") | CO8: 175 Paramount Dr | CP8: Raynham | CQ8: 2767 | CR8: MA | CT8: No - Facility Zip
A9: Marci | B9: Langevin | C9: Female | D9: MSW | E9: LICSW | G9: =IFERROR(VLOOKUP(BM9, ValidationAndReference!J:K, 2, FALSE), "") | L9: Both | M9: LifeStance Health | N9: =IFERROR(INDEX(Location!X:X, MATCH(BR9, Location!W:W, 0)), "") | O9: =IFERROR(INDEX(Location!X:X, MATCH(BS9, Location!W:W, 0)), "") | S9: 1003065186 | T9: https://prod-clinicians-photo.s3.amazonaws.com/1003065186.jpg | U9: MSW, Bridgewater State College | Z9: Marci Langevin is an Independently Licensed Clinical Social Worker and Mental Health Provider who has a top notch ability to hear the voice of her clientsâ and truly understand their experience. Marci specializes in cognitive behavioral therapy and motivational counseling that helps propel clients to reach therapeutic goal achievement. Marciâs compassion and skill in helping individuals and families is of such value in a time when so many desire a safe therapeutic environment where they can receive caring help that really makes a difference in their life. From the moment you meet Marci it is clear that her style is to identify the mental health and wellness needs of her clients with care. She is genuinely interested in her clientsâ thoughts and feelings. Her therapeutic methodology is to help her clients to identify their presenting problem, understand their thoughts and behaviors, and guide them towards awareness and resolution. She holds a masterâs degree in Social Work. Prior to joining our team, Marci provided individual, couple, and family counseling in an outpatient mental health facility in MA. In addition, she holds a research based background in issues of discrimination and oppression, has created and facilitated several therapeutic treatment groups including drug and alcohol recovery, and the use of artistic and creative expression for those experiencing depression, anxiety andor trauma. | AZ9: English | BC9: pt_B8LtUoRcYkWdny_20xbxdB | BE9: Practitioner - Full Profile | BG9: No | BI9: =IFERROR(INDEX(ValidationAndReference!P:P, MATCH(BE9, ValidationAndReference!Q:Q, 0)), "") | BJ9: =IFERROR(INDEX(ValidationAndReference!F:F, MATCH(D9, ValidationAndReference!G:G, 0)), "") | BK9: =IFERROR(INDEX(ValidationAndReference!F:F, MATCH(E9, ValidationAndReference!G:G, 0)), "") | BL9: =IFERROR(INDEX(ValidationAndReference!F:F, MATCH(F9, ValidationAndReference!G:G, 0)), "") | BM9: 352 | BR9: lo_WGSx6xN8302ASv6YVggXbh | BS9: lo_8kwZD7BrWkmw6LTpfZ-4yB | CL9: =IFERROR(INDEX(ValidationAndReference!V:V, MATCH(AZ9, ValidationAndReference!W:W, 0)), "") | CM9: =IFERROR(INDEX(ValidationAndReference!V:V, MATCH(BA9, ValidationAndReference!W:W, 0)), "") | CN9: =IFERROR(INDEX(ValidationAndReference!V:V, MATCH(BB9, ValidationAndReference!W:W, 0)), "") | CO9: 175 Paramount Dr | CP9: Raynham | CQ9: 2767 | CR9: MA | CT9: No - Facility Zip
A10: Kara | B10: Naylon | C10: Female | D10: PsyD | E10: PhD | G10: =IFERROR(VLOOKUP(BM10, ValidationAndReference!J:K, 2, FALSE), "") | L10: Both | M10: LifeStance Health | N10: =IFERROR(INDEX(Location!X:X, MATCH(BR10, Location!W:W, 0)), "") | O10: =IFERROR(INDEX(Location!X:X, MATCH(BS10, Location!W:W, 0)), "") | S10: 1003446782 | T10: https://prod-clinicians-photo.s3.amazonaws.com/1003446782.jpg | U10: PsyD, Adler University | Z10: Dr. Naylon is a clinical neuropsychologist who provides comprehensive neuropsychological evaluations and treatment for adults with a wide range of neurological, neurodegenerative, medical, and psychological conditions and complications that impact cognitive functioning. Evaluations consist of an indepth clinical interview to obtain a thorough and unique understanding of each individual, their background, and their presenting concerns followed by comprehensive neuropsychological testing. Assessment results are interpreted in the context of each individualâs unique circumstances. Feedback on results and interpretation is provided to patients and includes detailed descriptions of strengths and weaknesses, diagnostic impressions and implications, and tailored recommendations to ameliorate presenting concerns and improve daily life experience. Dr. Naylonâs clinical interests include neurodegenerative and neurological conditions dementia, movement disorders, epilepsy, multiple sclerosis, etc., complex medical complicationsconditions and impact on cognition, the impact of sleep and psychological symptomsconditions on cognition, eating disorders, traumatic brain injury, and stroke. Dr. Naylon provides more indepth intervention and treatment to facilitate implementation of tailored recommendations yielded from neuropsychological evaluations. She provides cognitive rehabilitation therapy to help patients capitalize on cognitive strengths and ameliorate weaknesses. She also provides cognitive behavioral therapy for insomnia to improve sleep and, subsequently, cognitive and mood symptoms. Dr. Naylon received her bachelorâs degree in Biology and Psychology from John Carroll University. She received her doctoral degree in Clinical Psychology with specialization in Neuropsychology from Adler University. She completed a predoctoral internship in Clinical Neuropsychology at the VA North Texas Healthcare System and a twoyear fellowship in Clinical Neuropsychology at the University of Massachusetts Medical School. | AZ10: English | BC10: pt_B8LtUoRcYkWdny_20xbxdB | BE10: Practitioner - Full Profile | BG10: No | BI10: =IFERROR(INDEX(ValidationAndReference!P:P, MATCH(BE10, ValidationAndReference!Q:Q, 0)), "") | BJ10: =IFERROR(INDEX(ValidationAndReference!F:F, MATCH(D10, ValidationAndReference!G:G, 0)), "") | BK10: =IFERROR(INDEX(ValidationAndReference!F:F, MATCH(E10, ValidationAndReference!G:G, 0)), "") | BL10: =IFERROR(INDEX(ValidationAndReference!F:F, MATCH(F10, ValidationAndReference!G:G, 0)), "") | BM10: 337 | BR10: lo_WTxCl_PGJkydSgfSTKd1mx | BS10: lo_6Q6bTr0VKkuCN9evdqEA9B | CL10: =IFERROR(INDEX(ValidationAndReference!V:V, MATCH(AZ10, ValidationAndReference!W:W, 0)), "") | CM10: =IFERROR(INDEX(ValidationAndReference!V:V, MATCH(BA10, ValidationAndReference!W:W, 0)), "") | CN10: =IFERROR(INDEX(ValidationAndReference!V:V, MATCH(BB10, ValidationAndReference!W:W, 0)), "") | CO10: 169 Libbey Pkwy | CP10: Weymouth | CQ10: 2189 | CR10: MA | CT10: No - Facility Zip
A11: Kara | B11: Naylon | C11: Female | D11: PsyD | E11: PhD | G11: =IFERROR(VLOOKUP(BM11, ValidationAndReference!J:K, 2, FALSE), "") | L11: Both | M11: LifeStance Health | N11: =IFERROR(INDEX(Location!X:X, MATCH(BR11, Location!W:W, 0)), "") | O11: =IFERROR(INDEX(Location!X:X, MATCH(BS11, Location!W:W, 0)), "") | S11: 1003446782 | T11: https://prod-clinicians-photo.s3.amazonaws.com/1003446782.jpg | U11: PsyD, Adler University | Z11: Dr. Naylon is a clinical neuropsychologist who provides comprehensive neuropsychological evaluations and treatment for adults with a wide range of neurological, neurodegenerative, medical, and psychological conditions and complications that impact cognitive functioning. Evaluations consist of an indepth clinical interview to obtain a thorough and unique understanding of each individual, their background, and their presenting concerns followed by comprehensive neuropsychological testing. Assessment results are interpreted in the context of each individualâs unique circumstances. Feedback on results and interpretation is provided to patients and includes detailed descriptions of strengths and weaknesses, diagnostic impressions and implications, and tailored recommendations to ameliorate presenting concerns and improve daily life experience. Dr. Naylonâs clinical interests include neurodegenerative and neurological conditions dementia, movement disorders, epilepsy, multiple sclerosis, etc., complex medical complicationsconditions and impact on cognition, the impact of sleep and psychological symptomsconditions on cognition, eating disorders, traumatic brain injury, and stroke. Dr. Naylon provides more indepth intervention and treatment to facilitate implementation of tailored recommendations yielded from neuropsychological evaluations. She provides cognitive rehabilitation therapy to help patients capitalize on cognitive strengths and ameliorate weaknesses. She also provides cognitive behavioral therapy for insomnia to improve sleep and, subsequently, cognitive and mood symptoms. Dr. Naylon received her bachelorâs degree in Biology and Psychology from John Carroll University. She received her doctoral degree in Clinical Psychology with specialization in Neuropsychology from Adler University. She completed a predoctoral internship in Clinical Neuropsychology at the VA North Texas Healthcare System and a twoyear fellowship in Clinical Neuropsychology at the University of Massachusetts Medical School. | AZ11: English | BC11: pt_B8LtUoRcYkWdny_20xbxdB | BE11: Practitioner - Full Profile | BG11: No | BI11: =IFERROR(INDEX(ValidationAndReference!P:P, MATCH(BE11, ValidationAndReference!Q:Q, 0)), "") | BJ11: =IFERROR(INDEX(ValidationAndReference!F:F, MATCH(D11, ValidationAndReference!G:G, 0)), "") | BK11: =IFERROR(INDEX(ValidationAndReference!F:F, MATCH(E11, ValidationAndReference!G:G, 0)), "") | BL11: =IFERROR(INDEX(ValidationAndReference!F:F, MATCH(F11, ValidationAndReference!G:G, 0)), "") | BM11: 337 | BR11: lo_Gu1H1AlMKkGM7YEE-cV0Mx | BS11: lo_SgGZ9ru7iU62TuMizXbvrx | CL11: =IFERROR(INDEX(ValidationAndReference!V:V, MATCH(AZ11, ValidationAndReference!W:W, 0)), "") | CM11: =IFERROR(INDEX(ValidationAndReference!V:V, MATCH(BA11, ValidationAndReference!W:W, 0)), "") | CN11: =IFERROR(INDEX(ValidationAndReference!V:V, MATCH(BB11, ValidationAndReference!W:W, 0)), "") | CO11: 185 Devonshire St | CP11: Boston | CQ11: 2110 | CR11: MA | CT11: No - Facility Zip
A12: Enid | B12: Levangie | C12: Female | D12: MSW | E12: LCSW | G12: =IFERROR(VLOOKUP(BM12, ValidationAndReference!J:K, 2, FALSE), "") | L12: Both | M12: LifeStance Health | N12: =IFERROR(INDEX(Location!X:X, MATCH(BR12, Location!W:W, 0)), "") | O12: =IFERROR(INDEX(Location!X:X, MATCH(BS12, Location!W:W, 0)), "") | S12: 1003694183 | T12: https://prod-clinicians-photo.s3.amazonaws.com/1003694183.jpg | U12: MSW, Simmons University | Z12: Enid Levangie is a Licensed Clinical Social Worker in Massachusetts who has been practicing since 2023. She obtained her Masterâs in Social Work from Simmons University and her Bachelorâs in psychology from Michigan State University. Enid sees children, adolescents, young adults, and adults individually as well as families and groups. She works with clients who are experiencing a wide range of issues, including depression, anxiety, traumaPTSD, and selfesteem. Enid uses a strengthbased, personcentered, and holistic approach, which is designed to meet clients where they are and provide a safe and comfortable space to help clients explore areas they want to work on in treatment and to learn and grow in ways that will improve their overall wellbeing. Enid uses many different theories and modalities in her treatment approach that include, but are not limited to personcentered therapy, cognitive behavioral therapy, Narrative therapy, Solutionfocused therapy, motivational interviewing, EMDR, and mindfulness and meditation. In her free time, Enid enjoys hiking, running, yoga, reading, and paddle boarding. | AZ12: English | BC12: pt_B8LtUoRcYkWdny_20xbxdB | BE12: Practitioner - Full Profile | BG12: No | BI12: =IFERROR(INDEX(ValidationAndReference!P:P, MATCH(BE12, ValidationAndReference!Q:Q, 0)), "") | BJ12: =IFERROR(INDEX(ValidationAndReference!F:F, MATCH(D12, ValidationAndReference!G:G, 0)), "") | BK12: =IFERROR(INDEX(ValidationAndReference!F:F, MATCH(E12, ValidationAndReference!G:G, 0)), "") | BL12: =IFERROR(INDEX(ValidationAndReference!F:F, MATCH(F12, ValidationAndReference!G:G, 0)), "") | BM12: 352 | BR12: lo_lEHs7EV-Q0q1ZVBScjqtKx | BS12: lo_Anm_Viii6U65HIuJ7sGPah | CL12: =IFERROR(INDEX(ValidationAndReference!V:V, MATCH(AZ12, ValidationAndReference!W:W, 0)), "") | CM12: =IFERROR(INDEX(ValidationAndReference!V:V, MATCH(BA12, ValidationAndReference!W:W, 0)), "") | CN12: =IFERROR(INDEX(ValidationAndReference!V:V, MATCH(BB12, ValidationAndReference!W:W, 0)), "") | CO12: 288 Walnut St | CP12: Newton | CQ12: 2460 | CR12: MA | CT12: No - Facility Zip
A13: Christopher | B13: Welch | C13: Male | D13: PsyD | E13: LCP | G13: =IFERROR(VLOOKUP(BM13, ValidationAndReference!J:K, 2, FALSE), "") | L13: Both | M13: LifeStance Health | N13: =IFERROR(INDEX(Location!X:X, MATCH(BR13, Location!W:W, 0)), "") | O13: =IFERROR(INDEX(Location!X:X, MATCH(BS13, Location!W:W, 0)), "") | S13: 1013039809 | T13: https://prod-clinicians-photo.s3.amazonaws.com/1013039809.jpg | U13: PsyD, Georgia School of Professional Psychology | Z13: Dr. Welch utilizes a curious, empathic, encouraging and pragmatic style to therapy with adolescents and adults who are experiencing challenges related to depressionanger, mood, anxiety and trauma, family conflict, and emotional regulationbehavioral control. He has a particular interest and specializes in assisting individuals who are in the process of negotiating the myriad changes associated with transitions that occur during adolescence through early adulthood, such as individuation, perceived inadequacyimpostor syndrome, identity confusion and relationship concerns. He often employs stress reduction and relaxation techniques, cognitivebehavioral therapy CBT and mindfulness approaches, notably Acceptance and Commitment Therapy ACT, to foster the development and application of skills that help clients to realize the changes they desire. | AZ13: English | BC13: pt_B8LtUoRcYkWdny_20xbxdB | BE13: Practitioner - Full Profile | BG13: No | BI13: =IFERROR(INDEX(ValidationAndReference!P:P, MATCH(BE13, ValidationAndReference!Q:Q, 0)), "") | BJ13: =IFERROR(INDEX(ValidationAndReference!F:F, MATCH(D13, ValidationAndReference!G:G, 0)), "") | BK13: =IFERROR(INDEX(ValidationAndReference!F:F, MATCH(E13, ValidationAndReference!G:G, 0)), "") | BL13: =IFERROR(INDEX(ValidationAndReference!F:F, MATCH(F13, ValidationAndReference!G:G, 0)), "") | BM13: 337 | BR13: lo_HsSHXkMbXkmjKV9DTQwrRg | BS13: lo_X1n8nk7odk6kG9Qth0jnUR | CL13: =IFERROR(INDEX(ValidationAndReference!V:V, MATCH(AZ13, ValidationAndReference!W:W, 0)), "") | CM13: =IFERROR(INDEX(ValidationAndReference!V:V, MATCH(BA13, ValidationAndReference!W:W, 0)), "") | CN13: =IFERROR(INDEX(ValidationAndReference!V:V, MATCH(BB13, ValidationAndReference!W:W, 0)), "") | CO13: 22 Ml St | CP13: Arlington | CQ13: 2476 | CR13: MA | CT13: No - Facility Address (try converting 'Ml' to 'MILL'; try converting 'St' to 'ST'; try converting 'St' to 'STREET'; try converting 'St' to 'STRT'; try converting 'St' to 'ST'; try converting 'St' to 'STR'), Facility Zip
A14: Melanie | B14: Blount | C14: Female | D14: PhD | E14: LP | G14: =IFERROR(VLOOKUP(BM14, ValidationAndReference!J:K, 2, FALSE), "") | L14: Adult | M14: LifeStance Health | N14: =IFERROR(INDEX(Location!X:X, MATCH(BR14, Location!W:W, 0)), "") | O14: =IFERROR(INDEX(Location!X:X, MATCH(BS14, Location!W:W, 0)), "") | S14: 1013103589 | T14: https://prod-clinicians-photo.s3.amazonaws.com/1013103589.jpg | U14: PsyD, Massachusetts School of Professional Psychology | Z14: Dr. Blount is a licensed psychologist offering individual psychotherapy for adults and adolescents as well as assistance for parents with infants struggling with attachment concerns. Her clinical interests include treatment of postpartum concerns, depression, anxiety, griefloss, and traumaPTSD. Dr. Blount integrates various therapeutic approaches based on what suits each clientâs needs best. Attachment theory guides much of her conceptual understanding, and she utilizes cognitivebehavioral, psychodynamic, and relational approaches depending on the clientâs needs. She believes that the therapeutic relationship â namely the trust, genuineness, and warmth between the therapist and client â is of most importance in having treatment be successful and is the foundation through which change can occur. Dr. Blount earned her doctorate in clinical psychology from William James College and her Masterâs in psychology in education from Columbia University. She completed an APAaccredited predoctoral internship and postdoctoral fellowship at Lynn Community Health Center in Lynn, MA. She has worked with a variety of adults, adolescents, and children within community clinics, school based health centers, and private practice. | AZ14: English | BC14: pt_B8LtUoRcYkWdny_20xbxdB | BE14: Practitioner - Full Profile | BG14: No | BI14: =IFERROR(INDEX(ValidationAndReference!P:P, MATCH(BE14, ValidationAndReference!Q:Q, 0)), "") | BJ14: =IFERROR(INDEX(ValidationAndReference!F:F, MATCH(D14, ValidationAndReference!G:G, 0)), "") | BK14: =IFERROR(INDEX(ValidationAndReference!F:F, MATCH(E14, ValidationAndReference!G:G, 0)), "") | BL14: =IFERROR(INDEX(ValidationAndReference!F:F, MATCH(F14, ValidationAndReference!G:G, 0)), "") | BM14: 337 | BR14: lo_yG3WQGVBVUynSkFssssbHg | CL14: =IFERROR(INDEX(ValidationAndReference!V:V, MATCH(AZ14, ValidationAndReference!W:W, 0)), "") | CM14: =IFERROR(INDEX(ValidationAndReference!V:V, MATCH(BA14, ValidationAndReference!W:W, 0)), "") | CN14: =IFERROR(INDEX(ValidationAndReference!V:V, MATCH(BB14, ValidationAndReference!W:W, 0)), "") | CO14: 625 Mt Auburn St | CP14: Cambridge | CQ14: 2138 | CR14: MA | CT14: No - Facility Zip
A15: William | B15: Sutton-Ohannesian | C15: Male | D15: DNP | E15: PMHNP-BC | G15: =IFERROR(VLOOKUP(BM15, ValidationAndReference!J:K, 2, FALSE), "") | L15: Both | M15: LifeStance Health | N15: =IFERROR(INDEX(Location!X:X, MATCH(BR15, Location!W:W, 0)), "") | O15: =IFERROR(INDEX(Location!X:X, MATCH(BS15, Location!W:W, 0)), "") | S15: 1013261965 | T15: https://prod-clinicians-photo.s3.amazonaws.com/1013261965.jpg | U15: DNP, University of Maryland Baltimore County | Z15: Dr. Will SuttonOhannesian is a Psychiatric Mental Health Nurse Practitioner in Massachusetts who has been practicing since 2018. He holds a Doctorate in Nursing Practice from the University of Maryland and a BSN from Boston College. Dr. SuttonOhannesian provides medication management, brief psychotherapy, and psychoeducation. He is experienced with patients with various psychiatric disorders including refractory depression, schizoaffective disorder, and gender dysphoria. Dr. SuttonOhannesian has practiced in emergency psychiatry, nursing homes, assisted living facilities, as well as outpatient practice locations, and has a history of providing TMS treatments and has assisted with ECT. Outside of work, Dr. SuttonOhannesian is a collector, a pianist, and enjoys spending time with his cats. | AZ15: English | BA15: Spanish | BC15: pt_B8LtUoRcYkWdny_20xbxdB | BE15: Practitioner - Full Profile | BG15: No | BI15: =IFERROR(INDEX(ValidationAndReference!P:P, MATCH(BE15, ValidationAndReference!Q:Q, 0)), "") | BJ15: =IFERROR(INDEX(ValidationAndReference!F:F, MATCH(D15, ValidationAndReference!G:G, 0)), "") | BK15: =IFERROR(INDEX(ValidationAndReference!F:F, MATCH(E15, ValidationAndReference!G:G, 0)), "") | BL15: =IFERROR(INDEX(ValidationAndReference!F:F, MATCH(F15, ValidationAndReference!G:G, 0)), "") | BM15: 405 | BR15: lo_n8Umo4IPt0OAdtKpVzV4Eg | CL15: =IFERROR(INDEX(ValidationAndReference!V:V, MATCH(AZ15, ValidationAndReference!W:W, 0)), "") | CM15: =IFERROR(INDEX(ValidationAndReference!V:V, MATCH(BA15, ValidationAndReference!W:W, 0)), "") | CN15: =IFERROR(INDEX(ValidationAndReference!V:V, MATCH(BB15, ValidationAndReference!W:W, 0)), "") | CO15: 4 Collins Ave | CP15: Plymouth | CQ15: 2360 | CR15: MA | CT15: No - Facility Zip
A16: Michael | B16: Wiehe | C16: Male | D16: MSW | E16: LICSW | G16: =IFERROR(VLOOKUP(BM16, ValidationAndReference!J:K, 2, FALSE), "") | L16: Adult | M16: LifeStance Health | N16: =IFERROR(INDEX(Location!X:X, MATCH(BR16, Location!W:W, 0)), "") | O16: =IFERROR(INDEX(Location!X:X, MATCH(BS16, Location!W:W, 0)), "") | S16: 1013295930 | T16: https://prod-clinicians-photo.s3.amazonaws.com/1013295930.jpg | U16: MSW, San Diego State University | Z16: Michael Wiehe provides evidence based psychotherapy and treatment for adults suffering from mood disorders, depression and anxiety. He utilizes cognitive behavior therapy CBT as a primary approach, along with with aspects of solution focused treatment and motivational interviewing. After completing his Masters degree in 2011, Michael joined South Bay Mental Health as a therapist on the dualdiagnoses team. He took a concurrent position as a group facilitator at South Bay Day Servicesâ partial hospitalization program where he ran groups for the PHP and IOP programs. Following his time at South Bay, he worked as an outpatient therapist at Wilmington Family counseling for three years, with a focus on mood disorders and dual diagnosis. Before joining LifeStance in 2020, Mr. Wiehe was the Clinical Director of Arbour Counselingâs Partial Hospitalization Program in Woburn, starting in 2017, after working as a group facilitator at that program. Mr. Wiehe joins our Woburn office, where he provides assessment and treatment for the adult population. | AZ16: English | BC16: pt_B8LtUoRcYkWdny_20xbxdB | BE16: Practitioner - Full Profile | BG16: No | BI16: =IFERROR(INDEX(ValidationAndReference!P:P, MATCH(BE16, ValidationAndReference!Q:Q, 0)), "") | BJ16: =IFERROR(INDEX(ValidationAndReference!F:F, MATCH(D16, ValidationAndReference!G:G, 0)), "") | BK16: =IFERROR(INDEX(ValidationAndReference!F:F, MATCH(E16, ValidationAndReference!G:G, 0)), "") | BL16: =IFERROR(INDEX(ValidationAndReference!F:F, MATCH(F16, ValidationAndReference!G:G, 0)), "") | BM16: 352 | BR16: lo_OVMZ6PsRXEqHzEFN4lLt_A | BS16: lo_ayvzZmw2UU2gH1k_iwnvJB | CL16: =IFERROR(INDEX(ValidationAndReference!V:V, MATCH(AZ16, ValidationAndReference!W:W, 0)), "") | CM16: =IFERROR(INDEX(ValidationAndReference!V:V, MATCH(BA16, ValidationAndReference!W:W, 0)), "") | CN16: =IFERROR(INDEX(ValidationAndReference!V:V, MATCH(BB16, ValidationAndReference!W:W, 0)), "") | CO16: 12 Alfred St | CP16: Woburn | CQ16: 1801 | CR16: MA | CT16: No - Facility Zip
A17: Julie | B17: West | C17: Female | D17: DNP | E17: PMHNP-BC | G17: =IFERROR(VLOOKUP(BM17, ValidationAndReference!J:K, 2, FALSE), "") | L17: Both | M17: LifeStance Health | N17: =IFERROR(INDEX(Location!X:X, MATCH(BR17, Location!W:W, 0)), "") | O17: =IFERROR(INDEX(Location!X:X, MATCH(BS17, Location!W:W, 0)), "") | S17: 1013527423 | T17: https://prod-clinicians-photo.s3.amazonaws.com/1013527423.jpg | U17: DNP, Columbia University School of Nursing | Z17: Julie West, NP, PMHNP, is a dedicated psychiatric nurse practitioner at LifeStance Health who provides compassionate, evidencebased care to individuals across Massachusetts. Serving adults and seniors, Julie helps patients navigate complex mental health challenges through individualized psychiatric evaluations, accurate diagnoses, and tailored treatment plans. By focusing on the biological, psychological, and social factors that contribute to mental health disorders, she strives to empower her patients on their path to healing. Julie is particularly passionate about supporting patients with anxiety, depression, and PTSD. She has a strong focus on addressing reproductive challenges and postpartum depressionanxiety, as well as helping individuals facing midlife and laterlife transitions. With a deep understanding of the unique needs these experiences present, Julie takes a holistic, collaborative approach to treatment, ensuring her patients feel supported every step of the way. She integrates psychotherapy and medication management to promote longlasting positive change. In addition to her specialized focus on womenâs issues and reproductive mental health, Julie is experienced in treating substance use disorders, psychosis, and traumarelated conditions. She is committed to helping military veterans, first responders, and individuals in the LGBTQ community overcome mental health challenges and achieve greater emotional wellbeing. Julies approach prioritizes the development of trusting, therapeutic relationships, allowing patients to openly share their concerns and work towards a healthier, more fulfilling life. Outside of her clinical work, Julie enjoys spending time with her family and dogs, embracing the outdoors when the weather allows, and indulging in a cozy pajama day indoors every once in a while. Her balance of professional dedication and personal selfcare enhances her ability to provide thoughtful and compassionate mental health care. Julie West is committed to serving patients across Massachusetts, helping them achieve their mental health goals through comprehensive, individualized care. | AZ17: English | BC17: pt_B8LtUoRcYkWdny_20xbxdB | BE17: Practitioner - Full Profile | BG17: No | BI17: =IFERROR(INDEX(ValidationAndReference!P:P, MATCH(BE17, ValidationAndReference!Q:Q, 0)), "") | BJ17: =IFERROR(INDEX(ValidationAndReference!F:F, MATCH(D17, ValidationAndReference!G:G, 0)), "") | BK17: =IFERROR(INDEX(ValidationAndReference!F:F, MATCH(E17, ValidationAndReference!G:G, 0)), "") | BL17: =IFERROR(INDEX(ValidationAndReference!F:F, MATCH(F17, ValidationAndReference!G:G, 0)), "") | BM17: 405 | BR17: lo_L3CIiVDHYESqWdC6bOuAqh | BS17: lo_bn7sE2w_SkyP7nJ0v5wixh | CL17: =IFERROR(INDEX(ValidationAndReference!V:V, MATCH(AZ17, ValidationAndReference!W:W, 0)), "") | CM17: =IFERROR(INDEX(ValidationAndReference!V:V, MATCH(BA17, ValidationAndReference!W:W, 0)), "") | CN17: =IFERROR(INDEX(ValidationAndReference!V:V, MATCH(BB17, ValidationAndReference!W:W, 0)), "") | CO17: 110 Hartwell Ave | CP17: Lexington | CQ17: 2421 | CR17: MA | CT17: No - Facility Zip
A18: Patricia | B18: Donahue Kennedy | C18: Female | D18: MSW | E18: LICSW | G18: =IFERROR(VLOOKUP(BM18, ValidationAndReference!J:K, 2, FALSE), "") | L18: Both | M18: LifeStance Health | N18: =IFERROR(INDEX(Location!X:X, MATCH(BR18, Location!W:W, 0)), "") | O18: =IFERROR(INDEX(Location!X:X, MATCH(BS18, Location!W:W, 0)), "") | S18: 1033288196 | T18: https://prod-clinicians-photo.s3.amazonaws.com/1033288196.jpg | U18: MSSW, Boston University | Z18: LICSW specializing in children and teenagers. I received my Masters in Social Work from Boston University in 2006. I have been working with children and families for over 20 years. I practice psychotherapy methods of CBT and play therapy. I am able to connect with children and am able to easily engage my clients. I use humor in my work and play therapy as well as mindfulness. I have a vast amount of experience in working as a clinical therapist in many settings through out the span of my career. I enjoy working with clients and helping them in with their emotional and mental health. | AZ18: English | BC18: pt_B8LtUoRcYkWdny_20xbxdB | BE18: Practitioner - Full Profile | BG18: No | BI18: =IFERROR(INDEX(ValidationAndReference!P:P, MATCH(BE18, ValidationAndReference!Q:Q, 0)), "") | BJ18: =IFERROR(INDEX(ValidationAndReference!F:F, MATCH(D18, ValidationAndReference!G:G, 0)), "") | BK18: =IFERROR(INDEX(ValidationAndReference!F:F, MATCH(E18, ValidationAndReference!G:G, 0)), "") | BL18: =IFERROR(INDEX(ValidationAndReference!F:F, MATCH(F18, ValidationAndReference!G:G, 0)), "") | BM18: 352 | BR18: lo_WGSx6xN8302ASv6YVggXbh | BS18: lo_8kwZD7BrWkmw6LTpfZ-4yB | CL18: =IFERROR(INDEX(ValidationAndReference!V:V, MATCH(AZ18, ValidationAndReference!W:W, 0)), "") | CM18: =IFERROR(INDEX(ValidationAndReference!V:V, MATCH(BA18, ValidationAndReference!W:W, 0)), "") | CN18: =IFERROR(INDEX(ValidationAndReference!V:V, MATCH(BB18, ValidationAndReference!W:W, 0)), "") | CO18: 175 Paramount Dr | CP18: Raynham | CQ18: 2767 | CR18: MA | CT18: No - Facility Zip
A19: Patricia | B19: Donahue Kennedy | C19: Female | D19: MSW | E19: LICSW | G19: =IFERROR(VLOOKUP(BM19, ValidationAndReference!J:K, 2, FALSE), "") | L19: Both | M19: LifeStance Health | N19: =IFERROR(INDEX(Location!X:X, MATCH(BR19, Location!W:W, 0)), "") | O19: =IFERROR(INDEX(Location!X:X, MATCH(BS19, Location!W:W, 0)), "") | S19: 1033288196 | T19: https://prod-clinicians-photo.s3.amazonaws.com/1033288196.jpg | U19: MSSW, Boston University | Z19: LICSW specializing in children and teenagers. I received my Masters in Social Work from Boston University in 2006. I have been working with children and families for over 20 years. I practice psychotherapy methods of CBT and play therapy. I am able to connect with children and am able to easily engage my clients. I use humor in my work and play therapy as well as mindfulness. I have a vast amount of experience in working as a clinical therapist in many settings through out the span of my career. I enjoy working with clients and helping them in with their emotional and mental health. | AZ19: English | BC19: pt_B8LtUoRcYkWdny_20xbxdB | BE19: Practitioner - Full Profile | BG19: No | BI19: =IFERROR(INDEX(ValidationAndReference!P:P, MATCH(BE19, ValidationAndReference!Q:Q, 0)), "") | BJ19: =IFERROR(INDEX(ValidationAndReference!F:F, MATCH(D19, ValidationAndReference!G:G, 0)), "") | BK19: =IFERROR(INDEX(ValidationAndReference!F:F, MATCH(E19, ValidationAndReference!G:G, 0)), "") | BL19: =IFERROR(INDEX(ValidationAndReference!F:F, MATCH(F19, ValidationAndReference!G:G, 0)), "") | BM19: 352 | BR19: lo_WGSx6xN8302ASv6YVggXbh | BS19: lo_8kwZD7BrWkmw6LTpfZ-4yB | CL19: =IFERROR(INDEX(ValidationAndReference!V:V, MATCH(AZ19, ValidationAndReference!W:W, 0)), "") | CM19: =IFERROR(INDEX(ValidationAndReference!V:V, MATCH(BA19, ValidationAndReference!W:W, 0)), "") | CN19: =IFERROR(INDEX(ValidationAndReference!V:V, MATCH(BB19, ValidationAndReference!W:W, 0)), "") | CO19: 175 Paramount Dr | CP19: Raynham | CQ19: 2767 | CR19: MA | CT19: No - Facility Zip
A20: Allison | B20: Moore | C20: Female | D20: MSW | E20: LICSW | G20: =IFERROR(VLOOKUP(BM20, ValidationAndReference!J:K, 2, FALSE), "") | L20: Both | M20: LifeStance Health | N20: =IFERROR(INDEX(Location!X:X, MATCH(BR20, Location!W:W, 0)), "") | O20: =IFERROR(INDEX(Location!X:X, MATCH(BS20, Location!W:W, 0)), "") | S20: 1033808506 | T20: https://prod-clinicians-photo.s3.amazonaws.com/1033808506.jpg | U20: MSW, University of New Hampshire- Durham | Z20: Allison Moore is a Licensed Independent Clinical Social Worker in New Hampshire who has been practicing since 2018. She has a Master of Social Work and a Masters of Business Administration. Allison helps clients navigating the changes and challenges that life brings, including starting at a new job or school, changes in independence, relationship concerns, lifestyle changes, and building a family. She is passionate about interpersonal skill building, improvement of selfesteem, navigating difficult relationships, making long term lifestyle changes, and selfregulation. Outside of work, Allison enjoys spending time with her family, being an outdoor enthusiast, hiking, biking, spending time with her dogs, and camping. | AZ20: English | BC20: pt_B8LtUoRcYkWdny_20xbxdB | BE20: Practitioner - Full Profile | BG20: No | BI20: =IFERROR(INDEX(ValidationAndReference!P:P, MATCH(BE20, ValidationAndReference!Q:Q, 0)), "") | BJ20: =IFERROR(INDEX(ValidationAndReference!F:F, MATCH(D20, ValidationAndReference!G:G, 0)), "") | BK20: =IFERROR(INDEX(ValidationAndReference!F:F, MATCH(E20, ValidationAndReference!G:G, 0)), "") | BL20: =IFERROR(INDEX(ValidationAndReference!F:F, MATCH(F20, ValidationAndReference!G:G, 0)), "") | BM20: 352 | BR20: lo_3hIK25O-lEqM6hnbD-8HXh | BS20: lo_y_6qaxOiQUSFScBKd0V0Dh | CL20: =IFERROR(INDEX(ValidationAndReference!V:V, MATCH(AZ20, ValidationAndReference!W:W, 0)), "") | CM20: =IFERROR(INDEX(ValidationAndReference!V:V, MATCH(BA20, ValidationAndReference!W:W, 0)), "") | CN20: =IFERROR(INDEX(ValidationAndReference!V:V, MATCH(BB20, ValidationAndReference!W:W, 0)), "") | CO20: 120 Boston Rd | CP20: Groton | CQ20: 1450 | CR20: MA | CS20: Ste 200 | CT20: No - Facility Zip
A21: Anniken | B21: Genova | C21: Female | D21: MA | E21: LMHC | G21: =IFERROR(VLOOKUP(BM21, ValidationAndReference!J:K, 2, FALSE), "") | L21: Both | M21: LifeStance Health | N21: =IFERROR(INDEX(Location!X:X, MATCH(BR21, Location!W:W, 0)), "") | O21: =IFERROR(INDEX(Location!X:X, MATCH(BS21, Location!W:W, 0)), "") | S21: 1033926993 | T21: https://prod-clinicians-photo.s3.amazonaws.com/1033926993.jpg | U21: MA, Framingham State University | Z21: Anniken Genova, LMHC, is a compassionate therapist at LifeStance Health, providing individual therapy to adolescents and adults in Massachusetts. She is dedicated to creating a supportive, nonjudgmental space where clients can explore their thoughts, emotions, and behaviors. Whether struggling with anxiety, depression, mood disorders, or trauma, Anniken helps clients develop coping strategies to foster resilience and personal growth. She tailors treatment to each individualâs needs, ensuring they feel heard and empowered throughout their healing process. Anniken specializes in treating anxiety, PTSDtrauma, and depression, offering evidencebased interventions to support clients facing these challenges. She understands the complex impact of trauma and anxietyrelated disorders on daily life and works closely with clients to address their symptoms in a meaningful way. Her approach integrates Cognitive Behavioral Therapy CBT, Dialectical Behavior Therapy DBT, and Acceptance & Commitment Therapy ACT, equipping clients with practical tools to navigate distress, regulate emotions, and improve overall wellbeing. In addition to her primary specialties, Anniken has a strong focus on supporting womenâs mental health, including postpartum depression and anxiety, midlife transitions, and personal identity struggles. She also provides guidance for individuals navigating adoption and foster care experiences. Her empathetic and collaborative approach allows clients to work through lifeâs challenges with confidence and selfcompassion. Outside of her practice, Anniken enjoys spending time with her family, hiking, traveling, knitting, and soaking up the sun at the beach. | AZ21: English | BA21: Norwegian | BC21: pt_B8LtUoRcYkWdny_20xbxdB | BE21: Practitioner - Full Profile | BG21: No | BI21: =IFERROR(INDEX(ValidationAndReference!P:P, MATCH(BE21, ValidationAndReference!Q:Q, 0)), "") | BJ21: =IFERROR(INDEX(ValidationAndReference!F:F, MATCH(D21, ValidationAndReference!G:G, 0)), "") | BK21: =IFERROR(INDEX(ValidationAndReference!F:F, MATCH(E21, ValidationAndReference!G:G, 0)), "") | BL21: =IFERROR(INDEX(ValidationAndReference!F:F, MATCH(F21, ValidationAndReference!G:G, 0)), "") | BM21: 352 | BR21: lo_J3bUpmaXpUWalQ11VmCr4R | BS21: lo_-ThUCWj4EkKTcIpHZ58qdB | CL21: =IFERROR(INDEX(ValidationAndReference!V:V, MATCH(AZ21, ValidationAndReference!W:W, 0)), "") | CM21: =IFERROR(INDEX(ValidationAndReference!V:V, MATCH(BA21, ValidationAndReference!W:W, 0)), "") | CN21: =IFERROR(INDEX(ValidationAndReference!V:V, MATCH(BB21, ValidationAndReference!W:W, 0)), "") | CO21: 25 Birch St | CP21: Milford | CQ21: 1757 | CR21: MA | CT21: No - Facility Zip
A22: Christine | B22: Ciccone | C22: Female | D22: MSW | E22: LCSW | G22: =IFERROR(VLOOKUP(BM22, ValidationAndReference!J:K, 2, FALSE), "") | L22: Both | M22: LifeStance Health | N22: =IFERROR(INDEX(Location!X:X, MATCH(BR22, Location!W:W, 0)), "") | O22: =IFERROR(INDEX(Location!X:X, MATCH(BS22, Location!W:W, 0)), "") | S22: 1043011919 | T22: https://prod-clinicians-photo.s3.amazonaws.com/1043011919.jpg | U22: Masters In Social Work, Simmons University | Z22: ChristineÂ Ciccone provides compassionate and evidencebased mental health care to individuals across Massachusetts. She specializes in supporting children, teens, and adults dealing with anxiety,Â depression, ADHD, and PTSDtrauma. Through individual and group therapy, she helps clients navigate lifeâs challenges, develop coping strategies,Â increase confidence and build resilience. Christine tailors her approach to meet each personâs needs, fostering a safe and supportive space for healing and growth. Christine is especially passionate about working with individuals facingÂ anxiety,Â trauma, relationship issues, school avoidance, sleep struggles and childhood behavioral issues. She understands how these concerns can impact daily life, academic success, and overall wellbeing. By integrating Cognitive Behavioral Therapy CBT, supportive therapy, motivational interviewing and mindfulness techniques, she empowers clients to regain confidence, establish structure, and improve their emotional regulation. Christine has extensive experience working with diverse populations, including individuals with anxiety, PTSDÂ and those who have experienced adoption or foster care, and military personnel. She believes in a holistic approach that considers the unique circumstances of each client, ensuring personalized and effective treatment. Outside of her clinical work, Christine enjoys staying active through exercise, spending time with animals, and expressing her creativity through drawing and music. She is committed to making a meaningful difference in the lives of those she serves throughout Massachusetts | AZ22: English | BC22: pt_B8LtUoRcYkWdny_20xbxdB | BE22: Practitioner - Full Profile | BG22: No | BI22: =IFERROR(INDEX(ValidationAndReference!P:P, MATCH(BE22, ValidationAndReference!Q:Q, 0)), "") | BJ22: =IFERROR(INDEX(ValidationAndReference!F:F, MATCH(D22, ValidationAndReference!G:G, 0)), "") | BK22: =IFERROR(INDEX(ValidationAndReference!F:F, MATCH(E22, ValidationAndReference!G:G, 0)), "") | BL22: =IFERROR(INDEX(ValidationAndReference!F:F, MATCH(F22, ValidationAndReference!G:G, 0)), "") | BM22: 352 | BR22: lo_wbOgzP_WJEygi97MC_jrTR | BS22: lo_dbyhA5ooZkuCGYkAlS8emB | CL22: =IFERROR(INDEX(ValidationAndReference!V:V, MATCH(AZ22, ValidationAndReference!W:W, 0)), "") | CM22: =IFERROR(INDEX(ValidationAndReference!V:V, MATCH(BA22, ValidationAndReference!W:W, 0)), "") | CN22: =IFERROR(INDEX(ValidationAndReference!V:V, MATCH(BB22, ValidationAndReference!W:W, 0)), "") | CO22: 800 Tpke St | CP22: North Andover | CQ22: 1845 | CR22: MA | CT22: No - Facility Address (try converting 'Tpke' to 'TRNPK'; try converting 'Tpke' to 'TURNPIKE'; try converting 'Tpke' to 'TURNPK'; try converting 'St' to 'ST'; try converting 'St' to 'STREET'; try converting 'St' to 'STRT'; try converting 'St' to 'ST'; try converting 'St' to 'STR'), Facility Zip
A23: Claudia | B23: Orfao-Martin | C23: Female | D23: MSW | E23: LICSW | G23: =IFERROR(VLOOKUP(BM23, ValidationAndReference!J:K, 2, FALSE), "") | L23: Both | M23: LifeStance Health | N23: =IFERROR(INDEX(Location!X:X, MATCH(BR23, Location!W:W, 0)), "") | O23: =IFERROR(INDEX(Location!X:X, MATCH(BS23, Location!W:W, 0)), "") | S23: 1043220676 | T23: https://prod-clinicians-photo.s3.amazonaws.com/1043220676.jpg | U23: MSW, University of Connecticut | Z23: Claudia OrfaoMartin, LICSW, brings over 47 years of dedicated experience in providing mental health treatment to individuals across various age groups in Massachusetts. At LifeStance Health, Claudia is committed to offering comprehensive care tailored to meet the unique needs of each client. Her extensive experience encompasses working with children, adolescents, adults, couples, and families, ensuring a compassionate and expert approach to mental health challenges. Specializing in treating anxiety, depression, ADHD, and grief and loss, Claudiaâs passion lies in helping clients navigate these oftenoverwhelming conditions. Her approach integrates Cognitive Behavioral Therapy CBT, Dialectical Behavior Therapy DBT, and Acceptance &amp Commitment Therapy ACT to create individualized treatment plans. Claudia is particularly adept at supporting clients through life transitions, addressing childhood behavior issues, and managing postpartum depression and anxiety. Claudias clinical expertise extends to working with diverse populations, including individuals facing developmental disabilities, autism spectrum disorders, and those who have experienced head injuries. Her proficiency in family therapy and parenting skills development further supports families in creating harmonious and supportive home environments. In addition to her clinical practice, Claudia is deeply involved in the training of service dogs, a passion project that underscores her commitment to therapeutic and supportive care. This involvement reflects her dedication to improving the quality of life for individuals through various therapeutic avenues. | AZ23: English | BC23: pt_B8LtUoRcYkWdny_20xbxdB | BE23: Practitioner - Full Profile | BG23: No | BI23: =IFERROR(INDEX(ValidationAndReference!P:P, MATCH(BE23, ValidationAndReference!Q:Q, 0)), "") | BJ23: =IFERROR(INDEX(ValidationAndReference!F:F, MATCH(D23, ValidationAndReference!G:G, 0)), "") | BK23: =IFERROR(INDEX(ValidationAndReference!F:F, MATCH(E23, ValidationAndReference!G:G, 0)), "") | BL23: =IFERROR(INDEX(ValidationAndReference!F:F, MATCH(F23, ValidationAndReference!G:G, 0)), "") | BM23: 352 | BR23: lo_WGSx6xN8302ASv6YVggXbh | BS23: lo_8kwZD7BrWkmw6LTpfZ-4yB | CL23: =IFERROR(INDEX(ValidationAndReference!V:V, MATCH(AZ23, ValidationAndReference!W:W, 0)), "") | CM23: =IFERROR(INDEX(ValidationAndReference!V:V, MATCH(BA23, ValidationAndReference!W:W, 0)), "") | CN23: =IFERROR(INDEX(ValidationAndReference!V:V, MATCH(BB23, ValidationAndReference!W:W, 0)), "") | CO23: 175 Paramount Dr | CP23: Raynham | CQ23: 2767 | CR23: MA | CT23: No - Facility Zip
A24: Claudia | B24: Orfao-Martin | C24: Female | D24: MSW | E24: LICSW | G24: =IFERROR(VLOOKUP(BM24, ValidationAndReference!J:K, 2, FALSE), "") | L24: Both | M24: LifeStance Health | N24: =IFERROR(INDEX(Location!X:X, MATCH(BR24, Location!W:W, 0)), "") | O24: =IFERROR(INDEX(Location!X:X, MATCH(BS24, Location!W:W, 0)), "") | S24: 1043220676 | T24: https://prod-clinicians-photo.s3.amazonaws.com/1043220676.jpg | U24: MSW, University of Connecticut | Z24: Claudia OrfaoMartin, LICSW, brings over 47 years of dedicated experience in providing mental health treatment to individuals across various age groups in Massachusetts. At LifeStance Health, Claudia is committed to offering comprehensive care tailored to meet the unique needs of each client. Her extensive experience encompasses working with children, adolescents, adults, couples, and families, ensuring a compassionate and expert approach to mental health challenges. Specializing in treating anxiety, depression, ADHD, and grief and loss, Claudiaâs passion lies in helping clients navigate these oftenoverwhelming conditions. Her approach integrates Cognitive Behavioral Therapy CBT, Dialectical Behavior Therapy DBT, and Acceptance &amp Commitment Therapy ACT to create individualized treatment plans. Claudia is particularly adept at supporting clients through life transitions, addressing childhood behavior issues, and managing postpartum depression and anxiety. Claudias clinical expertise extends to working with diverse populations, including individuals facing developmental disabilities, autism spectrum disorders, and those who have experienced head injuries. Her proficiency in family therapy and parenting skills development further supports families in creating harmonious and supportive home environments. In addition to her clinical practice, Claudia is deeply involved in the training of service dogs, a passion project that underscores her commitment to therapeutic and supportive care. This involvement reflects her dedication to improving the quality of life for individuals through various therapeutic avenues. | AZ24: English | BC24: pt_B8LtUoRcYkWdny_20xbxdB | BE24: Practitioner - Full Profile | BG24: No | BI24: =IFERROR(INDEX(ValidationAndReference!P:P, MATCH(BE24, ValidationAndReference!Q:Q, 0)), "") | BJ24: =IFERROR(INDEX(ValidationAndReference!F:F, MATCH(D24, ValidationAndReference!G:G, 0)), "") | BK24: =IFERROR(INDEX(ValidationAndReference!F:F, MATCH(E24, ValidationAndReference!G:G, 0)), "") | BL24: =IFERROR(INDEX(ValidationAndReference!F:F, MATCH(F24, ValidationAndReference!G:G, 0)), "") | BM24: 352 | BR24: lo_WGSx6xN8302ASv6YVggXbh | BS24: lo_8kwZD7BrWkmw6LTpfZ-4yB | CL24: =IFERROR(INDEX(ValidationAndReference!V:V, MATCH(AZ24, ValidationAndReference!W:W, 0)), "") | CM24: =IFERROR(INDEX(ValidationAndReference!V:V, MATCH(BA24, ValidationAndReference!W:W, 0)), "") | CN24: =IFERROR(INDEX(ValidationAndReference!V:V, MATCH(BB24, ValidationAndReference!W:W, 0)), "") | CO24: 175 Paramount Dr | CP24: Raynham | CQ24: 2767 | CR24: MA | CT24: No - Facility Zip
A25: Claudia | B25: Orfao-Martin | C25: Female | D25: MSW | E25: LICSW | G25: =IFERROR(VLOOKUP(BM25, ValidationAndReference!J:K, 2, FALSE), "") | L25: Both | M25: LifeStance Health | N25: =IFERROR(INDEX(Location!X:X, MATCH(BR25, Location!W:W, 0)), "") | O25: =IFERROR(INDEX(Location!X:X, MATCH(BS25, Location!W:W, 0)), "") | S25: 1043220676 | T25: https://prod-clinicians-photo.s3.amazonaws.com/1043220676.jpg | U25: MSW, University of Connecticut | Z25: Claudia OrfaoMartin, LICSW, brings over 47 years of dedicated experience in providing mental health treatment to individuals across various age groups in Massachusetts. At LifeStance Health, Claudia is committed to offering comprehensive care tailored to meet the unique needs of each client. Her extensive experience encompasses working with children, adolescents, adults, couples, and families, ensuring a compassionate and expert approach to mental health challenges. Specializing in treating anxiety, depression, ADHD, and grief and loss, Claudiaâs passion lies in helping clients navigate these oftenoverwhelming conditions. Her approach integrates Cognitive Behavioral Therapy CBT, Dialectical Behavior Therapy DBT, and Acceptance &amp Commitment Therapy ACT to create individualized treatment plans. Claudia is particularly adept at supporting clients through life transitions, addressing childhood behavior issues, and managing postpartum depression and anxiety. Claudias clinical expertise extends to working with diverse populations, including individuals facing developmental disabilities, autism spectrum disorders, and those who have experienced head injuries. Her proficiency in family therapy and parenting skills development further supports families in creating harmonious and supportive home environments. In addition to her clinical practice, Claudia is deeply involved in the training of service dogs, a passion project that underscores her commitment to therapeutic and supportive care. This involvement reflects her dedication to improving the quality of life for individuals through various therapeutic avenues. | AZ25: English | BC25: pt_B8LtUoRcYkWdny_20xbxdB | BE25: Practitioner - Full Profile | BG25: No | BI25: =IFERROR(INDEX(ValidationAndReference!P:P, MATCH(BE25, ValidationAndReference!Q:Q, 0)), "") | BJ25: =IFERROR(INDEX(ValidationAndReference!F:F, MATCH(D25, ValidationAndReference!G:G, 0)), "") | BK25: =IFERROR(INDEX(ValidationAndReference!F:F, MATCH(E25, ValidationAndReference!G:G, 0)), "") | BL25: =IFERROR(INDEX(ValidationAndReference!F:F, MATCH(F25, ValidationAndReference!G:G, 0)), "") | BM25: 352 | BR25: lo_WGSx6xN8302ASv6YVggXbh | BS25: lo_8kwZD7BrWkmw6LTpfZ-4yB | CL25: =IFERROR(INDEX(ValidationAndReference!V:V, MATCH(AZ25, ValidationAndReference!W:W, 0)), "") | CM25: =IFERROR(INDEX(ValidationAndReference!V:V, MATCH(BA25, ValidationAndReference!W:W, 0)), "") | CN25: =IFERROR(INDEX(ValidationAndReference!V:V, MATCH(BB25, ValidationAndReference!W:W, 0)), "") | CO25: 175 Paramount Dr | CP25: Raynham | CQ25: 2767 | CR25: MA | CT25: No - Facility Zip
A26: Kathleen | B26: Coughlin | C26: Female | D26: MTC | E26: LMHC | G26: =IFERROR(VLOOKUP(BM26, ValidationAndReference!J:K, 2, FALSE), "") | L26: Adult | M26: LifeStance Health | N26: =IFERROR(INDEX(Location!X:X, MATCH(BR26, Location!W:W, 0)), "") | O26: =IFERROR(INDEX(Location!X:X, MATCH(BS26, Location!W:W, 0)), "") | S26: 1043380397 | T26: https://prod-clinicians-photo.s3.amazonaws.com/1043380397.jpg | U26: M.Ed, Cambridge College | Z26: Kathy is accustomed to working with individuals with general adjustment issues, as well as with individuals who have complex and challenging health problems, and emotional adjustment issues related to such problems. She is especially sensitive to the demands placed on parents of disabled children, caretakers working with the elderly, and caretakers of, or individuals with terminal illness. She has particular interests in differential diagnosis and the mindbody connection, and utilizes a variety of approaches, including cognitive behavior therapy, interpersonal therapy, clinical hypnotherapy, and mindfulnessbased stress reduction practices to treat adults with either general lifeadjustment issues, or major mood disorders depressionanxiety, bipolar disorder, PTSD and other stressrelated conditions. | AZ26: English | BC26: pt_B8LtUoRcYkWdny_20xbxdB | BE26: Practitioner - Full Profile | BG26: No | BI26: =IFERROR(INDEX(ValidationAndReference!P:P, MATCH(BE26, ValidationAndReference!Q:Q, 0)), "") | BJ26: =IFERROR(INDEX(ValidationAndReference!F:F, MATCH(D26, ValidationAndReference!G:G, 0)), "") | BK26: =IFERROR(INDEX(ValidationAndReference!F:F, MATCH(E26, ValidationAndReference!G:G, 0)), "") | BL26: =IFERROR(INDEX(ValidationAndReference!F:F, MATCH(F26, ValidationAndReference!G:G, 0)), "") | BM26: 352 | BR26: lo_WTxCl_PGJkydSgfSTKd1mx | BS26: lo_6Q6bTr0VKkuCN9evdqEA9B | CL26: =IFERROR(INDEX(ValidationAndReference!V:V, MATCH(AZ26, ValidationAndReference!W:W, 0)), "") | CM26: =IFERROR(INDEX(ValidationAndReference!V:V, MATCH(BA26, ValidationAndReference!W:W, 0)), "") | CN26: =IFERROR(INDEX(ValidationAndReference!V:V, MATCH(BB26, ValidationAndReference!W:W, 0)), "") | CO26: 169 Libbey Pkwy | CP26: Weymouth | CQ26: 2189 | CR26: MA | CT26: No - Facility Zip
A27: Judith | B27: Fernando | C27: Female | D27: MD | G27: =IFERROR(VLOOKUP(BM27, ValidationAndReference!J:K, 2, FALSE), "") | L27: Both | M27: LifeStance Health | N27: =IFERROR(INDEX(Location!X:X, MATCH(BR27, Location!W:W, 0)), "") | O27: =IFERROR(INDEX(Location!X:X, MATCH(BS27, Location!W:W, 0)), "") | S27: 1043631591 | T27: https://prod-clinicians-photo.s3.amazonaws.com/1043631591.jpg | U27: MD, George Washington University | Z27: Dr. Fernando is a Board Certified Child, Adolescent, and Adult psychiatrist offering comprehensive psychiatric diagnostic assessments and medication consultation. Dr. Fernando believes in empathic and openminded listening to establish a therapeutic alliance, and uses a patientcentered, culturally sensitive approach in psychoeducation and treatment planning. She strongly values collaborative goalsetting with each of her patients and works with them towards emotionally healthy and fulfilling lives. She treats a broad range of diagnoses including mood, ADHD, PTSD and other trauma related disorders, OCD, and anxiety disorders. Dr. Fernando earned her masters degree in Public Health with a focus in maternal and child health from Harvard School of Public Health. She graduated from the George Washington University School of Medicine and Health Sciences in Washington DC. Dr. Fernando completed her residency training in Adult Psychiatry at the DC Department of Behavioral Healths Saint Elizabeth Hospital, and her subspecialty training in Child and Adolescent Psychiatry at Dartmouth Hitchcock Medical Center in NH. She sees patients in the NewtonWatertown office. | AZ27: English | BC27: pt_B8LtUoRcYkWdny_20xbxdB | BE27: Practitioner - Full Profile | BG27: No | BI27: =IFERROR(INDEX(ValidationAndReference!P:P, MATCH(BE27, ValidationAndReference!Q:Q, 0)), "") | BJ27: =IFERROR(INDEX(ValidationAndReference!F:F, MATCH(D27, ValidationAndReference!G:G, 0)), "") | BK27: =IFERROR(INDEX(ValidationAndReference!F:F, MATCH(E27, ValidationAndReference!G:G, 0)), "") | BL27: =IFERROR(INDEX(ValidationAndReference!F:F, MATCH(F27, ValidationAndReference!G:G, 0)), "") | BM27: 122 | BR27: lo_4QIZgfh7dUWNnuSD1q2zqA | CL27: =IFERROR(INDEX(ValidationAndReference!V:V, MATCH(AZ27, ValidationAndReference!W:W, 0)), "") | CM27: =IFERROR(INDEX(ValidationAndReference!V:V, MATCH(BA27, ValidationAndReference!W:W, 0)), "") | CN27: =IFERROR(INDEX(ValidationAndReference!V:V, MATCH(BB27, ValidationAndReference!W:W, 0)), "") | CO27: 313 Washington St | CP27: Newton | CQ27: 2458 | CR27: MA | CS27: Ste 402 | CT27: No - Facility Zip
A28: Lauren | B28: Posner | C28: Female | D28: MSW | E28: LICSW | G28: =IFERROR(VLOOKUP(BM28, ValidationAndReference!J:K, 2, FALSE), "") | L28: Adult | M28: LifeStance Health | N28: =IFERROR(INDEX(Location!X:X, MATCH(BR28, Location!W:W, 0)), "") | O28: =IFERROR(INDEX(Location!X:X, MATCH(BS28, Location!W:W, 0)), "") | S28: 1043908809 | T28: https://prod-clinicians-photo.s3.amazonaws.com/1043908809.jpg | U28: MSW, Simmons University | Z28: Lauren Posner is a Licensed Clinical Social Worker in Massachusetts who has been practicing since 2022. Lauren believes authentic rapportbuilding is the first step to any therapeutic relationship. She uses a strengthsbased approach to view her clients as people capable of healing and living full lives. When clients come to therapy feeling lost or stuck, Lauren sees her role as a collaborator and gentle guide. She utilizes a lot of humor in her work with clients to create an informal and relaxed space. Her Clinical background includes working with both adults and adolescents with eating disorders, and she is trained in familybased therapy FBT. Lauren has a passion for the transformative power of exposure therapy when managing anxiety disorders and also utilizes cognitive behavioral therapy CBT and dialectical behavior therapy DBT in her work. Outside of work, Lauren enjoys singing, traveling, and continually brainstorming effective ways to enact change around societal stigma of folks living in larger bodies. | AZ28: English | BC28: pt_B8LtUoRcYkWdny_20xbxdB | BE28: Practitioner - Full Profile | BG28: No | BI28: =IFERROR(INDEX(ValidationAndReference!P:P, MATCH(BE28, ValidationAndReference!Q:Q, 0)), "") | BJ28: =IFERROR(INDEX(ValidationAndReference!F:F, MATCH(D28, ValidationAndReference!G:G, 0)), "") | BK28: =IFERROR(INDEX(ValidationAndReference!F:F, MATCH(E28, ValidationAndReference!G:G, 0)), "") | BL28: =IFERROR(INDEX(ValidationAndReference!F:F, MATCH(F28, ValidationAndReference!G:G, 0)), "") | BM28: 352 | BR28: lo_WTxCl_PGJkydSgfSTKd1mx | BS28: lo_6Q6bTr0VKkuCN9evdqEA9B | CL28: =IFERROR(INDEX(ValidationAndReference!V:V, MATCH(AZ28, ValidationAndReference!W:W, 0)), "") | CM28: =IFERROR(INDEX(ValidationAndReference!V:V, MATCH(BA28, ValidationAndReference!W:W, 0)), "") | CN28: =IFERROR(INDEX(ValidationAndReference!V:V, MATCH(BB28, ValidationAndReference!W:W, 0)), "") | CO28: 169 Libbey Pkwy | CP28: Weymouth | CQ28: 2189 | CR28: MA | CT28: No - Facility Zip
A29: Sydney | B29: Espy | C29: Female | D29: LCSW | G29: =IFERROR(VLOOKUP(BM29, ValidationAndReference!J:K, 2, FALSE), "") | L29: Both | M29: LifeStance Health | N29: =IFERROR(INDEX(Location!X:X, MATCH(BR29, Location!W:W, 0)), "") | O29: =IFERROR(INDEX(Location!X:X, MATCH(BS29, Location!W:W, 0)), "") | S29: 1053112516 | T29: https://prod-clinicians-photo.s3.amazonaws.com/1053112516.jpg | U29: Masters in Social Work, Lesley University | Z29: Sydney Espy, LCSW, helps individuals across Massachusetts navigate lifeâs challenges through a collaborative, empowering therapeutic approach tailored to their unique needs. She works with children, teens, and adults, offering both individual and group therapy to support clients managing anxiety, ADHD, depression, and more. With a focus on building a strong therapeutic alliance, Sydney creates a safe, affirming space where clients feel seen and supported in their journey toward healing and selfdiscovery. Sydney is especially passionate about helping individuals who are neurodivergent or navigating complex identity development, including those on the autism spectrum or who identify as LGBTQ. Her work centers on supporting clients in understanding themselves, finding balance, and building skills to thrive in a world that can often feel overwhelming. She is deeply committed to guiding clients through difficult emotions and life transitions with compassion and clinical insight. Using evidencebased interventions such as Cognitive Behavioral Therapy CBT, Dialectical Behavior Therapy DBT, and Acceptance and Commitment Therapy ACT, Sydney integrates mindfulness practices to support emotional regulation and selfawareness. Her experience includes working with individuals facing developmental disabilities and womenâs issues, and she offers additional services beyond her core specialties to meet the diverse needs of her clients. Sydney finds inspiration in artâwhether she is creating her own or experiencing it in galleries, museums, or the natural world. This creative lens informs her therapeutic style, helping her connect with clients in meaningful and intuitive ways. She is proud to serve individuals across Massachusetts. | AZ29: English | BC29: pt_B8LtUoRcYkWdny_20xbxdB | BE29: Practitioner - Full Profile | BG29: No | BI29: =IFERROR(INDEX(ValidationAndReference!P:P, MATCH(BE29, ValidationAndReference!Q:Q, 0)), "") | BJ29: =IFERROR(INDEX(ValidationAndReference!F:F, MATCH(D29, ValidationAndReference!G:G, 0)), "") | BK29: =IFERROR(INDEX(ValidationAndReference!F:F, MATCH(E29, ValidationAndReference!G:G, 0)), "") | BL29: =IFERROR(INDEX(ValidationAndReference!F:F, MATCH(F29, ValidationAndReference!G:G, 0)), "") | BM29: 352 | BR29: lo_4QIZgfh7dUWNnuSD1q2zqA | CL29: =IFERROR(INDEX(ValidationAndReference!V:V, MATCH(AZ29, ValidationAndReference!W:W, 0)), "") | CM29: =IFERROR(INDEX(ValidationAndReference!V:V, MATCH(BA29, ValidationAndReference!W:W, 0)), "") | CN29: =IFERROR(INDEX(ValidationAndReference!V:V, MATCH(BB29, ValidationAndReference!W:W, 0)), "") | CO29: 313 Washington St | CP29: Newton | CQ29: 2458 | CR29: MA | CS29: Ste 402 | CT29: No - Facility Zip
A30: Zachary | B30: Cottrell | C30: Male | D30: MA | E30: LMHC | G30: =IFERROR(VLOOKUP(BM30, ValidationAndReference!J:K, 2, FALSE), "") | L30: Both | M30: LifeStance Health | N30: =IFERROR(INDEX(Location!X:X, MATCH(BR30, Location!W:W, 0)), "") | O30: =IFERROR(INDEX(Location!X:X, MATCH(BS30, Location!W:W, 0)), "") | S30: 1053661165 | T30: https://prod-clinicians-photo.s3.amazonaws.com/1053661165.jpg | U30: PsyD, William James College | Z30: Dr. Cottrell provides psychotherapy, clinical evaluation and consultation for individuals 18 years of age and older. The emphasis of his work as a therapist is supporting individuals and families experiencing various mental health and psychological conditions. Though he works with a wide range of clients, he has a particular clinical interest and focus with TwiceExceptional 2E individuals experiencing ADHD and gifted intelligence. He utilizes a Systems, SolutionsFocused, and StrengthBased approach to therapy in addition to Cognitive Behavioral Therapy CBT, Dialectical Behavioral Therapy DBT, Narrative Therapy, and Expressive Arts especially with Music as he collaborates with individuals and their families in order to embrace their interests and goals for their development, wellbeing, growth, and success. Dr. Cottrell received his doctorate in Clinical Psychology from William James College. Upon graduation, he completed a PostDoctoral Fellowship in Pediatric Neuropsychology prior to joining Lifestance. He also completed an APA predoctoral internship at the North Shore Medical Center Salem, MA. During that time, Dr. Cottrells work included providing neuropsychological and psychological testing at Mass General for Children as well as providing behavioral health consultation services at the North Shore Physicianâs Group at Union Hospital. Prior to doctoral training, Dr. Cottrell obtained his Masterâs Degree in Mental Health Counseling and Human Development at Walsh University North Canton, OH, and he has worked for over 12 years as a Licensed Mental Health Counselor LMHC in a variety of settings including Private Practice, Hospitals, Community Mental Health, and College Counseling Centers. In addition to providing clinical care, Dr. Cottrell focuses on research and development for utilizing technology to improve mental health and executive function regulation through mobileweb based apps. | AZ30: English | BC30: pt_B8LtUoRcYkWdny_20xbxdB | BE30: Practitioner - Full Profile | BG30: No | BI30: =IFERROR(INDEX(ValidationAndReference!P:P, MATCH(BE30, ValidationAndReference!Q:Q, 0)), "") | BJ30: =IFERROR(INDEX(ValidationAndReference!F:F, MATCH(D30, ValidationAndReference!G:G, 0)), "") | BK30: =IFERROR(INDEX(ValidationAndReference!F:F, MATCH(E30, ValidationAndReference!G:G, 0)), "") | BL30: =IFERROR(INDEX(ValidationAndReference!F:F, MATCH(F30, ValidationAndReference!G:G, 0)), "") | BM30: 352 | BR30: lo_te0vo8TuekWyL5gMnjPK1w | BS30: lo_c9GJzBULJ0KYW9u1EWEsUB | CL30: =IFERROR(INDEX(ValidationAndReference!V:V, MATCH(AZ30, ValidationAndReference!W:W, 0)), "") | CM30: =IFERROR(INDEX(ValidationAndReference!V:V, MATCH(BA30, ValidationAndReference!W:W, 0)), "") | CN30: =IFERROR(INDEX(ValidationAndReference!V:V, MATCH(BB30, ValidationAndReference!W:W, 0)), "") | CO30: 45 Shawmut Rd | CP30: Canton | CQ30: 2021 | CR30: MA | CT30: No - Facility Zip
A31: Matthew | B31: Shang | C31: Male | D31: PhD | E31: LP | G31: =IFERROR(VLOOKUP(BM31, ValidationAndReference!J:K, 2, FALSE), "") | L31: Adult | M31: LifeStance Health | N31: =IFERROR(INDEX(Location!X:X, MATCH(BR31, Location!W:W, 0)), "") | O31: =IFERROR(INDEX(Location!X:X, MATCH(BS31, Location!W:W, 0)), "") | S31: 1053827428 | T31: https://prod-clinicians-photo.s3.amazonaws.com/1053827428.jpg | U31: PsyD, Chicago School of Professional Psychology | Z31: Dr. Shang is a licensed psychologist who provides individual therapy for adults. He practices from a psychodynamic and interpersonalrelational lens while incorporating elements of cognitive behavioral therapy. Dr. Shangâs background includes experience working with children and adolescents, families, and adults from a variety of racial, cultural, sexual, and socioeconomic backgrounds. He acknowledges each clientâs unique set of values while fostering a safe and trusting environment that encourages the client to comfortably engage in selfexploration and be genuinely understood. Dr. Shang emphasizes a therapeutic alliance in which he and his clients work collaboratively to deepen oneâs insight by identifying and then examining the factors that are impacting oneâs current wellbeing. He is dedicated to helping clients untangle the complexities in their lives and derive new meaning that better empowers them to experience a more satisfying, enriching, and fulfilling lifestyle. Dr. Shang has a range of clinical interests and areas of specialty, which include Â Anxiety Â Depression Â Trauma Â Life Transitions Â Relationship Issues Â Race & Ethnicity Â Immigration & Acculturation Â Gender & Sexuality Â Men & Masculinity Dr. Shang completed his doctoral work at The Chicago School of Professional Psychology â Chicago Campus and completed his predoctoral internship and postdoctoral residency at Nova Southeastern Universityâs Psychology Services Center. Dr. Shang provides psychotherapy and counseling services in our North Station office. Pronouns HeHimHis | AZ31: English | BC31: pt_B8LtUoRcYkWdny_20xbxdB | BE31: Practitioner - Full Profile | BG31: No | BI31: =IFERROR(INDEX(ValidationAndReference!P:P, MATCH(BE31, ValidationAndReference!Q:Q, 0)), "") | BJ31: =IFERROR(INDEX(ValidationAndReference!F:F, MATCH(D31, ValidationAndReference!G:G, 0)), "") | BK31: =IFERROR(INDEX(ValidationAndReference!F:F, MATCH(E31, ValidationAndReference!G:G, 0)), "") | BL31: =IFERROR(INDEX(ValidationAndReference!F:F, MATCH(F31, ValidationAndReference!G:G, 0)), "") | BM31: 337 | BR31: lo_K0fvuA3m106nJ1lN6zPeSh | BS31: lo_f6iUikhoXkGdN4TUipYUgR | CL31: =IFERROR(INDEX(ValidationAndReference!V:V, MATCH(AZ31, ValidationAndReference!W:W, 0)), "") | CM31: =IFERROR(INDEX(ValidationAndReference!V:V, MATCH(BA31, ValidationAndReference!W:W, 0)), "") | CN31: =IFERROR(INDEX(ValidationAndReference!V:V, MATCH(BB31, ValidationAndReference!W:W, 0)), "") | CO31: 225 Friend St | CP31: Boston | CQ31: 2114 | CR31: MA | CT31: No - Facility Zip
A32: Briana | B32: Cast-Clifton | C32: Female | D32: MSW | E32: LICSW | G32: =IFERROR(VLOOKUP(BM32, ValidationAndReference!J:K, 2, FALSE), "") | L32: Both | M32: LifeStance Health | N32: =IFERROR(INDEX(Location!X:X, MATCH(BR32, Location!W:W, 0)), "") | O32: =IFERROR(INDEX(Location!X:X, MATCH(BS32, Location!W:W, 0)), "") | S32: 1063058329 | T32: https://prod-clinicians-photo.s3.amazonaws.com/1063058329.jpg | U32: MSW, Simmons School of Social Work | Z32: Briana Cast is a Licensed Independent Clinical Social Worker in Massachusetts who has been practicing since 2018. She has a Bachelor of Science degree from UMass Amherst with a Certificate in Social Work and Criminal Justice and a Master of Social Work degree from Simmons College. In addition to providing a safe and supportive therapeutic environment, Brianaâs unique approach stems from a combination of her training, personal experiences, and areas of expertise. First and foremost, Briana strongly believes in the power of empathy and active listening. She strives to truly understand her clientsâ perspectives, emotions, and struggles, creating a nonjudgmental space where they can freely express themselves. Furthermore, Briana brings a holistic perspective to therapy, recognizing that individuals are complex beings with interconnected mental, emotional, and physical dimensions. She considers the broader context of her clientsâ lives, including their relationships, cultural background, and personal values, to gain a comprehensive understanding of their experiences. Drawing from her background in social work, Briana offers specialized knowledge and techniques that are particularly relevant to certain client populations or issues. This allows her to tailor her interventions and strategies to address specific concerns effectively. Lastly, Briana places a strong emphasis on collaborative goal setting. She believes that therapy should be a partnership between therapist and client, where they work together to define meaningful objectives and develop an actionable plan to achieve them. By involving clients actively in their own therapeutic process, Briana fosters empowerment and a sense of ownership over their growth and progress. Overall, her unique combination of empathy, holistic perspective, specialized knowledge, collaborative goal setting, and commitment to ongoing professional growth enables Briana to offer a personalized and effective therapeutic experience to her clients. Outside of work, Briana enjoys learning calligraphy, reading, spending time with family, and professional organizing. | AZ32: English | BC32: pt_B8LtUoRcYkWdny_20xbxdB | BE32: Practitioner - Full Profile | BG32: No | BI32: =IFERROR(INDEX(ValidationAndReference!P:P, MATCH(BE32, ValidationAndReference!Q:Q, 0)), "") | BJ32: =IFERROR(INDEX(ValidationAndReference!F:F, MATCH(D32, ValidationAndReference!G:G, 0)), "") | BK32: =IFERROR(INDEX(ValidationAndReference!F:F, MATCH(E32, ValidationAndReference!G:G, 0)), "") | BL32: =IFERROR(INDEX(ValidationAndReference!F:F, MATCH(F32, ValidationAndReference!G:G, 0)), "") | BM32: 352 | BR32: lo_te0vo8TuekWyL5gMnjPK1w | BS32: lo_c9GJzBULJ0KYW9u1EWEsUB | CL32: =IFERROR(INDEX(ValidationAndReference!V:V, MATCH(AZ32, ValidationAndReference!W:W, 0)), "") | CM32: =IFERROR(INDEX(ValidationAndReference!V:V, MATCH(BA32, ValidationAndReference!W:W, 0)), "") | CN32: =IFERROR(INDEX(ValidationAndReference!V:V, MATCH(BB32, ValidationAndReference!W:W, 0)), "") | CO32: 45 Shawmut Rd | CP32: Canton | CQ32: 2021 | CR32: MA | CT32: No - Facility Zip
A33: Briana | B33: Cast-Clifton | C33: Female | D33: MSW | E33: LICSW | G33: =IFERROR(VLOOKUP(BM33, ValidationAndReference!J:K, 2, FALSE), "") | L33: Both | M33: LifeStance Health | N33: =IFERROR(INDEX(Location!X:X, MATCH(BR33, Location!W:W, 0)), "") | O33: =IFERROR(INDEX(Location!X:X, MATCH(BS33, Location!W:W, 0)), "") | S33: 1063058329 | T33: https://prod-clinicians-photo.s3.amazonaws.com/1063058329.jpg | U33: MSW, Simmons School of Social Work | Z33: Briana Cast is a Licensed Independent Clinical Social Worker in Massachusetts who has been practicing since 2018. She has a Bachelor of Science degree from UMass Amherst with a Certificate in Social Work and Criminal Justice and a Master of Social Work degree from Simmons College. In addition to providing a safe and supportive therapeutic environment, Brianaâs unique approach stems from a combination of her training, personal experiences, and areas of expertise. First and foremost, Briana strongly believes in the power of empathy and active listening. She strives to truly understand her clientsâ perspectives, emotions, and struggles, creating a nonjudgmental space where they can freely express themselves. Furthermore, Briana brings a holistic perspective to therapy, recognizing that individuals are complex beings with interconnected mental, emotional, and physical dimensions. She considers the broader context of her clientsâ lives, including their relationships, cultural background, and personal values, to gain a comprehensive understanding of their experiences. Drawing from her background in social work, Briana offers specialized knowledge and techniques that are particularly relevant to certain client populations or issues. This allows her to tailor her interventions and strategies to address specific concerns effectively. Lastly, Briana places a strong emphasis on collaborative goal setting. She believes that therapy should be a partnership between therapist and client, where they work together to define meaningful objectives and develop an actionable plan to achieve them. By involving clients actively in their own therapeutic process, Briana fosters empowerment and a sense of ownership over their growth and progress. Overall, her unique combination of empathy, holistic perspective, specialized knowledge, collaborative goal setting, and commitment to ongoing professional growth enables Briana to offer a personalized and effective therapeutic experience to her clients. Outside of work, Briana enjoys learning calligraphy, reading, spending time with family, and professional organizing. | AZ33: English | BC33: pt_B8LtUoRcYkWdny_20xbxdB | BE33: Practitioner - Full Profile | BG33: No | BI33: =IFERROR(INDEX(ValidationAndReference!P:P, MATCH(BE33, ValidationAndReference!Q:Q, 0)), "") | BJ33: =IFERROR(INDEX(ValidationAndReference!F:F, MATCH(D33, ValidationAndReference!G:G, 0)), "") | BK33: =IFERROR(INDEX(ValidationAndReference!F:F, MATCH(E33, ValidationAndReference!G:G, 0)), "") | BL33: =IFERROR(INDEX(ValidationAndReference!F:F, MATCH(F33, ValidationAndReference!G:G, 0)), "") | BM33: 352 | BR33: lo_te0vo8TuekWyL5gMnjPK1w | BS33: lo_c9GJzBULJ0KYW9u1EWEsUB | CL33: =IFERROR(INDEX(ValidationAndReference!V:V, MATCH(AZ33, ValidationAndReference!W:W, 0)), "") | CM33: =IFERROR(INDEX(ValidationAndReference!V:V, MATCH(BA33, ValidationAndReference!W:W, 0)), "") | CN33: =IFERROR(INDEX(ValidationAndReference!V:V, MATCH(BB33, ValidationAndReference!W:W, 0)), "") | CO33: 45 Shawmut Rd | CP33: Canton | CQ33: 2021 | CR33: MA | CT33: No - Facility Zip
A34: Ashlyn | B34: Cunningham | C34: Female | D34: LCSW | G34: =IFERROR(VLOOKUP(BM34, ValidationAndReference!J:K, 2, FALSE), "") | L34: Both | M34: LifeStance Health | N34: =IFERROR(INDEX(Location!X:X, MATCH(BR34, Location!W:W, 0)), "") | O34: =IFERROR(INDEX(Location!X:X, MATCH(BS34, Location!W:W, 0)), "") | S34: 1063111763 | T34: https://prod-clinicians-photo.s3.amazonaws.com/1063111763.jpg | U34: MSW, Salisbury University | Z34: Ashlyn Cunningham is a Licensed Clinical Social Worker LCSW who works with children, adolescents, and adults, helping them navigate lifeâs challenges with compassion and understanding. She takes a humanistic and relational approach to therapy, creating a welcoming and supportive environment where clients feel seen, heard, and empowered. Ashlyn integrates evidencebased interventions such as Cognitive Behavioral Therapy CBT, Dialectical Behavior Therapy DBT, and Acceptance and Commitment Therapy ACT, alongside relational interventions, to tailor care to each clientâs unique needs. She specializes in supporting individuals facing attachment issues, life transitions, grief, and challenges in interpersonal relationships. Ashlyn earned her masterâs degree from Salisbury University through the advanced standing program. Outside of her professional life, she enjoys practicing yoga, walking outdoors, and spending time with her beloved dog. Ashlyn is committed to fostering a safe and collaborative space where clients can grow, heal, and connect with their strengths. | AZ34: English | BC34: pt_B8LtUoRcYkWdny_20xbxdB | BE34: Practitioner - Full Profile | BG34: No | BI34: =IFERROR(INDEX(ValidationAndReference!P:P, MATCH(BE34, ValidationAndReference!Q:Q, 0)), "") | BJ34: =IFERROR(INDEX(ValidationAndReference!F:F, MATCH(D34, ValidationAndReference!G:G, 0)), "") | BK34: =IFERROR(INDEX(ValidationAndReference!F:F, MATCH(E34, ValidationAndReference!G:G, 0)), "") | BL34: =IFERROR(INDEX(ValidationAndReference!F:F, MATCH(F34, ValidationAndReference!G:G, 0)), "") | BM34: 352 | BR34: lo_Gu1H1AlMKkGM7YEE-cV0Mx | BS34: lo_SgGZ9ru7iU62TuMizXbvrx | CL34: =IFERROR(INDEX(ValidationAndReference!V:V, MATCH(AZ34, ValidationAndReference!W:W, 0)), "") | CM34: =IFERROR(INDEX(ValidationAndReference!V:V, MATCH(BA34, ValidationAndReference!W:W, 0)), "") | CN34: =IFERROR(INDEX(ValidationAndReference!V:V, MATCH(BB34, ValidationAndReference!W:W, 0)), "") | CO34: 185 Devonshire St | CP34: Boston | CQ34: 2110 | CR34: MA | CT34: No - Facility Zip
A35: Kelsey | B35: Berry | C35: Female | D35: MSW | E35: LICSW | G35: =IFERROR(VLOOKUP(BM35, ValidationAndReference!J:K, 2, FALSE), "") | L35: Both | M35: LifeStance Health | N35: =IFERROR(INDEX(Location!X:X, MATCH(BR35, Location!W:W, 0)), "") | O35: =IFERROR(INDEX(Location!X:X, MATCH(BS35, Location!W:W, 0)), "") | S35: 1063123552 | T35: https://prod-clinicians-photo.s3.amazonaws.com/1063123552.jpg | U35: MSW, Boston College School of Social Work | Z35: Kelsey Berry is a Licensed Independent Clinical Social Worker in Massachusetts who has been practicing since 2020. She studied at Boston College School of Social Work and Bates College. Kelseyâs work with clients stems from a passion to help others discover and redefine what âœhealthâ_x009d_ means to them. Our physical and mental wellbeing is so individualized and impacted by our environment, our trauma, and various factors throughout our lives. Kelseyâs services offer an opportunity to work towards longterm goals or build skills to simply make it through the day. She strongly believes in the importance of creating a space free of judgment and one of safety. Kelsey believes in working through a strengthsbased perspective and honoring clients where they are. Kelsey has experience and continued interest in growing in the treatment of eating disorders, anxiety disorders, depression, OCD, PTSD, and trauma. Outside of work, Kelsey is a BIG Celtics fan and has a very real obsession with dogs all types, largely golden retrievers and pitbull mixes. She has been teaching yoga at various locations since 2017, and finds that exercise, while it looks a bit different as she becomes older, remains her most consistent coping mechanism for lifeâs daily stressors. Sheâs a food lover, an extroverted introvert, and has a passion for social justice and challenging the systemic issues within our country and beyond. | AZ35: English | BC35: pt_B8LtUoRcYkWdny_20xbxdB | BE35: Practitioner - Full Profile | BG35: No | BI35: =IFERROR(INDEX(ValidationAndReference!P:P, MATCH(BE35, ValidationAndReference!Q:Q, 0)), "") | BJ35: =IFERROR(INDEX(ValidationAndReference!F:F, MATCH(D35, ValidationAndReference!G:G, 0)), "") | BK35: =IFERROR(INDEX(ValidationAndReference!F:F, MATCH(E35, ValidationAndReference!G:G, 0)), "") | BL35: =IFERROR(INDEX(ValidationAndReference!F:F, MATCH(F35, ValidationAndReference!G:G, 0)), "") | BM35: 352 | BR35: lo_swkHQlrzCkqk5-946P0yNw | BS35: lo_-7_Lw0GOaECGLFCsOyOoWR | CL35: =IFERROR(INDEX(ValidationAndReference!V:V, MATCH(AZ35, ValidationAndReference!W:W, 0)), "") | CM35: =IFERROR(INDEX(ValidationAndReference!V:V, MATCH(BA35, ValidationAndReference!W:W, 0)), "") | CN35: =IFERROR(INDEX(ValidationAndReference!V:V, MATCH(BB35, ValidationAndReference!W:W, 0)), "") | CO35: 175 Highland Ave | CP35: Needham | CQ35: 2494 | CR35: MA | CT35: No - Facility Zip
A36: Andrew | B36: Grego | C36: Male | D36: PhD | G36: =IFERROR(VLOOKUP(BM36, ValidationAndReference!J:K, 2, FALSE), "") | L36: Pediatric | M36: LifeStance Health | N36: =IFERROR(INDEX(Location!X:X, MATCH(BR36, Location!W:W, 0)), "") | O36: =IFERROR(INDEX(Location!X:X, MATCH(BS36, Location!W:W, 0)), "") | S36: 1063176402 | T36: https://prod-clinicians-photo.s3.amazonaws.com/1063176402.jpg | U36: Ph.D., Nova Southeastern University | Z36: Andrew Grego is a dedicated clinician practicing at LifeStance Health in Massachusetts, offering compassionate and effective therapy for individuals across a wide age range, from children to seniors. He specializes in helping patients manage conditions like anxiety, depression, and ADHD, as well as those facing challenges with trauma, grief, and life transitions. With expertise in Cognitive Behavioral Therapy CBT, Exposure Therapy, and Family Therapy, Andrew provides customized treatment plans designed to empower patients to overcome their struggles and achieve emotional wellbeing. Andrewâs greatest passion lies in supporting those with ADHD and anxiety, as well as helping individuals cope with the complexities of later life transitions. He is committed to creating a safe, nonjudgmental space where clients feel heard and respected, particularly for those navigating challenging situations like grief, addiction, and trauma. Whether itâs managing stress, overcoming school avoidance, or addressing gender identity concerns, Andrewâs therapeutic approach is rooted in collaboration and understanding. He treats a diverse population, including individuals with developmental disabilities, autism spectrum disorders, and militaryveteran backgrounds. In addition to individual therapy, Andrew provides family therapy and neuropsychological testing to further support his clients mental health journeys. Outside of work, Andrew enjoys a variety of hobbies such as Taekwondo, flag football, skiing, and paddleboarding. He also loves cooking, sourdough baking, and preserving food. Serving Massachusetts, he is dedicated to helping individuals and families navigate lifeâs challenges. | AZ36: English | BC36: pt_B8LtUoRcYkWdny_20xbxdB | BE36: Practitioner - Full Profile | BG36: No | BI36: =IFERROR(INDEX(ValidationAndReference!P:P, MATCH(BE36, ValidationAndReference!Q:Q, 0)), "") | BJ36: =IFERROR(INDEX(ValidationAndReference!F:F, MATCH(D36, ValidationAndReference!G:G, 0)), "") | BK36: =IFERROR(INDEX(ValidationAndReference!F:F, MATCH(E36, ValidationAndReference!G:G, 0)), "") | BL36: =IFERROR(INDEX(ValidationAndReference!F:F, MATCH(F36, ValidationAndReference!G:G, 0)), "") | BM36: 337 | BR36: lo_ICAU0TvahEuLSyeDtv-uIQ | BS36: lo_FkhegZ_500izJ5pb7f47iB | CL36: =IFERROR(INDEX(ValidationAndReference!V:V, MATCH(AZ36, ValidationAndReference!W:W, 0)), "") | CM36: =IFERROR(INDEX(ValidationAndReference!V:V, MATCH(BA36, ValidationAndReference!W:W, 0)), "") | CN36: =IFERROR(INDEX(ValidationAndReference!V:V, MATCH(BB36, ValidationAndReference!W:W, 0)), "") | CO36: 89 Access Rd | CP36: Norwood | CQ36: 2062 | CR36: MA | CT36: No - Facility Zip
A37: Andrew | B37: Grego | C37: Male | D37: PhD | G37: =IFERROR(VLOOKUP(BM37, ValidationAndReference!J:K, 2, FALSE), "") | L37: Pediatric | M37: LifeStance Health | N37: =IFERROR(INDEX(Location!X:X, MATCH(BR37, Location!W:W, 0)), "") | O37: =IFERROR(INDEX(Location!X:X, MATCH(BS37, Location!W:W, 0)), "") | S37: 1063176402 | T37: https://prod-clinicians-photo.s3.amazonaws.com/1063176402.jpg | U37: Ph.D., Nova Southeastern University | Z37: Andrew Grego is a dedicated clinician practicing at LifeStance Health in Massachusetts, offering compassionate and effective therapy for individuals across a wide age range, from children to seniors. He specializes in helping patients manage conditions like anxiety, depression, and ADHD, as well as those facing challenges with trauma, grief, and life transitions. With expertise in Cognitive Behavioral Therapy CBT, Exposure Therapy, and Family Therapy, Andrew provides customized treatment plans designed to empower patients to overcome their struggles and achieve emotional wellbeing. Andrewâs greatest passion lies in supporting those with ADHD and anxiety, as well as helping individuals cope with the complexities of later life transitions. He is committed to creating a safe, nonjudgmental space where clients feel heard and respected, particularly for those navigating challenging situations like grief, addiction, and trauma. Whether itâs managing stress, overcoming school avoidance, or addressing gender identity concerns, Andrewâs therapeutic approach is rooted in collaboration and understanding. He treats a diverse population, including individuals with developmental disabilities, autism spectrum disorders, and militaryveteran backgrounds. In addition to individual therapy, Andrew provides family therapy and neuropsychological testing to further support his clients mental health journeys. Outside of work, Andrew enjoys a variety of hobbies such as Taekwondo, flag football, skiing, and paddleboarding. He also loves cooking, sourdough baking, and preserving food. Serving Massachusetts, he is dedicated to helping individuals and families navigate lifeâs challenges. | AZ37: English | BC37: pt_B8LtUoRcYkWdny_20xbxdB | BE37: Practitioner - Full Profile | BG37: No | BI37: =IFERROR(INDEX(ValidationAndReference!P:P, MATCH(BE37, ValidationAndReference!Q:Q, 0)), "") | BJ37: =IFERROR(INDEX(ValidationAndReference!F:F, MATCH(D37, ValidationAndReference!G:G, 0)), "") | BK37: =IFERROR(INDEX(ValidationAndReference!F:F, MATCH(E37, ValidationAndReference!G:G, 0)), "") | BL37: =IFERROR(INDEX(ValidationAndReference!F:F, MATCH(F37, ValidationAndReference!G:G, 0)), "") | BM37: 337 | BR37: lo_ICAU0TvahEuLSyeDtv-uIQ | BS37: lo_FkhegZ_500izJ5pb7f47iB | CL37: =IFERROR(INDEX(ValidationAndReference!V:V, MATCH(AZ37, ValidationAndReference!W:W, 0)), "") | CM37: =IFERROR(INDEX(ValidationAndReference!V:V, MATCH(BA37, ValidationAndReference!W:W, 0)), "") | CN37: =IFERROR(INDEX(ValidationAndReference!V:V, MATCH(BB37, ValidationAndReference!W:W, 0)), "") | CO37: 89 Access Rd | CP37: Norwood | CQ37: 2062 | CR37: MA | CT37: No - Facility Zip
A38: Andrew | B38: Grego | C38: Male | D38: PhD | G38: =IFERROR(VLOOKUP(BM38, ValidationAndReference!J:K, 2, FALSE), "") | L38: Pediatric | M38: LifeStance Health | N38: =IFERROR(INDEX(Location!X:X, MATCH(BR38, Location!W:W, 0)), "") | O38: =IFERROR(INDEX(Location!X:X, MATCH(BS38, Location!W:W, 0)), "") | S38: 1063176402 | T38: https://prod-clinicians-photo.s3.amazonaws.com/1063176402.jpg | U38: Ph.D., Nova Southeastern University | Z38: Andrew Grego is a dedicated clinician practicing at LifeStance Health in Massachusetts, offering compassionate and effective therapy for individuals across a wide age range, from children to seniors. He specializes in helping patients manage conditions like anxiety, depression, and ADHD, as well as those facing challenges with trauma, grief, and life transitions. With expertise in Cognitive Behavioral Therapy CBT, Exposure Therapy, and Family Therapy, Andrew provides customized treatment plans designed to empower patients to overcome their struggles and achieve emotional wellbeing. Andrewâs greatest passion lies in supporting those with ADHD and anxiety, as well as helping individuals cope with the complexities of later life transitions. He is committed to creating a safe, nonjudgmental space where clients feel heard and respected, particularly for those navigating challenging situations like grief, addiction, and trauma. Whether itâs managing stress, overcoming school avoidance, or addressing gender identity concerns, Andrewâs therapeutic approach is rooted in collaboration and understanding. He treats a diverse population, including individuals with developmental disabilities, autism spectrum disorders, and militaryveteran backgrounds. In addition to individual therapy, Andrew provides family therapy and neuropsychological testing to further support his clients mental health journeys. Outside of work, Andrew enjoys a variety of hobbies such as Taekwondo, flag football, skiing, and paddleboarding. He also loves cooking, sourdough baking, and preserving food. Serving Massachusetts, he is dedicated to helping individuals and families navigate lifeâs challenges. | AZ38: English | BC38: pt_B8LtUoRcYkWdny_20xbxdB | BE38: Practitioner - Full Profile | BG38: No | BI38: =IFERROR(INDEX(ValidationAndReference!P:P, MATCH(BE38, ValidationAndReference!Q:Q, 0)), "") | BJ38: =IFERROR(INDEX(ValidationAndReference!F:F, MATCH(D38, ValidationAndReference!G:G, 0)), "") | BK38: =IFERROR(INDEX(ValidationAndReference!F:F, MATCH(E38, ValidationAndReference!G:G, 0)), "") | BL38: =IFERROR(INDEX(ValidationAndReference!F:F, MATCH(F38, ValidationAndReference!G:G, 0)), "") | BM38: 337 | BR38: lo_te0vo8TuekWyL5gMnjPK1w | BS38: lo_c9GJzBULJ0KYW9u1EWEsUB | CL38: =IFERROR(INDEX(ValidationAndReference!V:V, MATCH(AZ38, ValidationAndReference!W:W, 0)), "") | CM38: =IFERROR(INDEX(ValidationAndReference!V:V, MATCH(BA38, ValidationAndReference!W:W, 0)), "") | CN38: =IFERROR(INDEX(ValidationAndReference!V:V, MATCH(BB38, ValidationAndReference!W:W, 0)), "") | CO38: 45 Shawmut Rd | CP38: Canton | CQ38: 2021 | CR38: MA | CT38: No - Facility Zip
A39: Andrew | B39: Grego | C39: Male | D39: PhD | G39: =IFERROR(VLOOKUP(BM39, ValidationAndReference!J:K, 2, FALSE), "") | L39: Pediatric | M39: LifeStance Health | N39: =IFERROR(INDEX(Location!X:X, MATCH(BR39, Location!W:W, 0)), "") | O39: =IFERROR(INDEX(Location!X:X, MATCH(BS39, Location!W:W, 0)), "") | S39: 1063176402 | T39: https://prod-clinicians-photo.s3.amazonaws.com/1063176402.jpg | U39: Ph.D., Nova Southeastern University | Z39: Andrew Grego is a dedicated clinician practicing at LifeStance Health in Massachusetts, offering compassionate and effective therapy for individuals across a wide age range, from children to seniors. He specializes in helping patients manage conditions like anxiety, depression, and ADHD, as well as those facing challenges with trauma, grief, and life transitions. With expertise in Cognitive Behavioral Therapy CBT, Exposure Therapy, and Family Therapy, Andrew provides customized treatment plans designed to empower patients to overcome their struggles and achieve emotional wellbeing. Andrewâs greatest passion lies in supporting those with ADHD and anxiety, as well as helping individuals cope with the complexities of later life transitions. He is committed to creating a safe, nonjudgmental space where clients feel heard and respected, particularly for those navigating challenging situations like grief, addiction, and trauma. Whether itâs managing stress, overcoming school avoidance, or addressing gender identity concerns, Andrewâs therapeutic approach is rooted in collaboration and understanding. He treats a diverse population, including individuals with developmental disabilities, autism spectrum disorders, and militaryveteran backgrounds. In addition to individual therapy, Andrew provides family therapy and neuropsychological testing to further support his clients mental health journeys. Outside of work, Andrew enjoys a variety of hobbies such as Taekwondo, flag football, skiing, and paddleboarding. He also loves cooking, sourdough baking, and preserving food. Serving Massachusetts, he is dedicated to helping individuals and families navigate lifeâs challenges. | AZ39: English | BC39: pt_B8LtUoRcYkWdny_20xbxdB | BE39: Practitioner - Full Profile | BG39: No | BI39: =IFERROR(INDEX(ValidationAndReference!P:P, MATCH(BE39, ValidationAndReference!Q:Q, 0)), "") | BJ39: =IFERROR(INDEX(ValidationAndReference!F:F, MATCH(D39, ValidationAndReference!G:G, 0)), "") | BK39: =IFERROR(INDEX(ValidationAndReference!F:F, MATCH(E39, ValidationAndReference!G:G, 0)), "") | BL39: =IFERROR(INDEX(ValidationAndReference!F:F, MATCH(F39, ValidationAndReference!G:G, 0)), "") | BM39: 337 | BR39: lo_te0vo8TuekWyL5gMnjPK1w | BS39: lo_c9GJzBULJ0KYW9u1EWEsUB | CL39: =IFERROR(INDEX(ValidationAndReference!V:V, MATCH(AZ39, ValidationAndReference!W:W, 0)), "") | CM39: =IFERROR(INDEX(ValidationAndReference!V:V, MATCH(BA39, ValidationAndReference!W:W, 0)), "") | CN39: =IFERROR(INDEX(ValidationAndReference!V:V, MATCH(BB39, ValidationAndReference!W:W, 0)), "") | CO39: 45 Shawmut Rd | CP39: Canton | CQ39: 2021 | CR39: MA | CT39: No - Facility Zip
A40: Samantha | B40: Wechsler | C40: Female | D40: MSW | E40: LCSW | G40: =IFERROR(VLOOKUP(BM40, ValidationAndReference!J:K, 2, FALSE), "") | L40: Adult | M40: LifeStance Health | N40: =IFERROR(INDEX(Location!X:X, MATCH(BR40, Location!W:W, 0)), "") | O40: =IFERROR(INDEX(Location!X:X, MATCH(BS40, Location!W:W, 0)), "") | S40: 1063274728 | T40: https://prod-clinicians-photo.s3.amazonaws.com/1063274728.jpg | U40: MSW, Boston University School of Social Work | Z40: Samantha Wechsler, LCSW Samantha Wechsler is a Licensed Clinical Social Worker in Massachusetts who has been practicing since 2021. She has a B.A. from Wesleyan University, an MSW from Boston University School of Social Work, completed field placements at MIT and The Albert &amp Jessie Danielsen Institute, and is a recipient of a Social Work Grant Award from the Boston Psychoanalytic Society &amp Institute in 2022. Samantha spent nearly three decades working in the nonprofit and public sectors as a facilitator, leader, consultant, and coach before deciding to focus exclusively on clinical, therapeutic work. She brings a systems perspective to her work with individuals and groups. Samantha offers individual and group psychotherapy grounded in a psychodynamic, relational framework. She seeks to jointly explore the pain, losses, misrecognitions, and traumas that have shaped a personâs approach to life in limiting and selfdefeating ways. Samantha believes that the process begins with close engagement, devoted attentiveness, and the development of safety and trust. Her many years of meditation inform her ability to focus, be with, and listen with sustained attention and keen attunement. With a grounding in psychoanalytic practice, she also is available to work with clients who desire a more intensive therapeutic experience, involving two to three sessions per week. She works with people of all races, genders, and sexual orientations. Outside of work, Samantha enjoys hiking, traveling, reading, dancing, and spending time with family and friends. | AZ40: English | BC40: pt_B8LtUoRcYkWdny_20xbxdB | BE40: Practitioner - Full Profile | BG40: No | BI40: =IFERROR(INDEX(ValidationAndReference!P:P, MATCH(BE40, ValidationAndReference!Q:Q, 0)), "") | BJ40: =IFERROR(INDEX(ValidationAndReference!F:F, MATCH(D40, ValidationAndReference!G:G, 0)), "") | BK40: =IFERROR(INDEX(ValidationAndReference!F:F, MATCH(E40, ValidationAndReference!G:G, 0)), "") | BL40: =IFERROR(INDEX(ValidationAndReference!F:F, MATCH(F40, ValidationAndReference!G:G, 0)), "") | BM40: 352 | BR40: lo_3D1HJe6ly0SMmBdp7PgNPQ | BS40: lo_XChreUGy00CKaewjQqDgth | CL40: =IFERROR(INDEX(ValidationAndReference!V:V, MATCH(AZ40, ValidationAndReference!W:W, 0)), "") | CM40: =IFERROR(INDEX(ValidationAndReference!V:V, MATCH(BA40, ValidationAndReference!W:W, 0)), "") | CN40: =IFERROR(INDEX(ValidationAndReference!V:V, MATCH(BB40, ValidationAndReference!W:W, 0)), "") | CO40: 1 Brookline Pl | CP40: Brookline | CQ40: 2445 | CR40: MA | CT40: No - Facility Zip
A41: Lisa | B41: Scharff | C41: Female | D41: PhD | E41: LP | G41: =IFERROR(VLOOKUP(BM41, ValidationAndReference!J:K, 2, FALSE), "") | L41: Both | M41: LifeStance Health | N41: =IFERROR(INDEX(Location!X:X, MATCH(BR41, Location!W:W, 0)), "") | O41: =IFERROR(INDEX(Location!X:X, MATCH(BS41, Location!W:W, 0)), "") | S41: 1063584597 | T41: https://prod-clinicians-photo.s3.amazonaws.com/1063584597.jpg | U41: PhD, State University of New York | Z41: Clinical Psychologist with over 20 years of experience. My practice is science and evidencebased using CBT, behavioral treatments, acceptance approaches, exposure, and critical thinking skills. | AZ41: English | BC41: pt_B8LtUoRcYkWdny_20xbxdB | BE41: Practitioner - Full Profile | BG41: No | BI41: =IFERROR(INDEX(ValidationAndReference!P:P, MATCH(BE41, ValidationAndReference!Q:Q, 0)), "") | BJ41: =IFERROR(INDEX(ValidationAndReference!F:F, MATCH(D41, ValidationAndReference!G:G, 0)), "") | BK41: =IFERROR(INDEX(ValidationAndReference!F:F, MATCH(E41, ValidationAndReference!G:G, 0)), "") | BL41: =IFERROR(INDEX(ValidationAndReference!F:F, MATCH(F41, ValidationAndReference!G:G, 0)), "") | BM41: 337 | BR41: lo_OVMZ6PsRXEqHzEFN4lLt_A | BS41: lo_ayvzZmw2UU2gH1k_iwnvJB | CL41: =IFERROR(INDEX(ValidationAndReference!V:V, MATCH(AZ41, ValidationAndReference!W:W, 0)), "") | CM41: =IFERROR(INDEX(ValidationAndReference!V:V, MATCH(BA41, ValidationAndReference!W:W, 0)), "") | CN41: =IFERROR(INDEX(ValidationAndReference!V:V, MATCH(BB41, ValidationAndReference!W:W, 0)), "") | CO41: 12 Alfred St | CP41: Woburn | CQ41: 1801 | CR41: MA | CT41: No - Facility Zip
A42: Carol | B42: Marchetti | C42: Female | D42: MSN | E42: CNP | G42: =IFERROR(VLOOKUP(BM42, ValidationAndReference!J:K, 2, FALSE), "") | L42: Both | M42: LifeStance Health | N42: =IFERROR(INDEX(Location!X:X, MATCH(BR42, Location!W:W, 0)), "") | O42: =IFERROR(INDEX(Location!X:X, MATCH(BS42, Location!W:W, 0)), "") | S42: 1063677391 | T42: https://prod-clinicians-photo.s3.amazonaws.com/1063677391.jpg | U42: PhD, Boston College | Z42: Carol Anne Marchetti, PhD, is a boardcertified PsychiatricMental Health Nurse Practitioner PMHNP and Clinical Professor at Northeastern University, BouvÃ College of Health Sciences School of Nursing. She earned Bachelors degrees in ManagementMarketing, and Nursing, from UMass Boston and received a masters degree, postgraduate teaching certificate, and PhD from Boston College. She completed postgraduate fellowships through Harvard Vanguard and the Massachusetts Institute of Psychoanalysis. Along with broad and diverse training as a PMHNP, Carol is a seasoned registered nurse who has worked on neonatal and pediatric intensive care units inpatient and outpatient psychiatric units and as a sexual assault nurse examiner. She is the former president and current Massachusetts representative of the New England Chapter of the American Psychiatric Nurses Association, and she serves as a Massachusetts Department of Public Health Rehabilitation Evaluation Committee Member for the Unified Recovery and Monitoring Program. She is a Visiting Scholar at Boston College Connell School of Nursing and the University of Hawaii at Manoa Nancy AtmosperaWalch School of Nursing. Carol is grateful to have had so many rich professional and clinical experiences and believes they enhance her practice in meaningful ways. In her practice at LifeStance Health, Carol specializes in working with people who are experiencing anxiety and depression and provides medication management and psychotherapy. | AZ42: English | BC42: pt_B8LtUoRcYkWdny_20xbxdB | BE42: Practitioner - Full Profile | BG42: No | BI42: =IFERROR(INDEX(ValidationAndReference!P:P, MATCH(BE42, ValidationAndReference!Q:Q, 0)), "") | BJ42: =IFERROR(INDEX(ValidationAndReference!F:F, MATCH(D42, ValidationAndReference!G:G, 0)), "") | BK42: =IFERROR(INDEX(ValidationAndReference!F:F, MATCH(E42, ValidationAndReference!G:G, 0)), "") | BL42: =IFERROR(INDEX(ValidationAndReference!F:F, MATCH(F42, ValidationAndReference!G:G, 0)), "") | BM42: 405 | BR42: lo_lEHs7EV-Q0q1ZVBScjqtKx | BS42: lo_Anm_Viii6U65HIuJ7sGPah | CL42: =IFERROR(INDEX(ValidationAndReference!V:V, MATCH(AZ42, ValidationAndReference!W:W, 0)), "") | CM42: =IFERROR(INDEX(ValidationAndReference!V:V, MATCH(BA42, ValidationAndReference!W:W, 0)), "") | CN42: =IFERROR(INDEX(ValidationAndReference!V:V, MATCH(BB42, ValidationAndReference!W:W, 0)), "") | CO42: 288 Walnut St | CP42: Newton | CQ42: 2460 | CR42: MA | CT42: No - Facility Zip
A43: Kimberly | B43: Leary | C43: Female | D43: MSN | E43: PMHNP-BC | G43: =IFERROR(VLOOKUP(BM43, ValidationAndReference!J:K, 2, FALSE), "") | L43: Both | M43: LifeStance Health | N43: =IFERROR(INDEX(Location!X:X, MATCH(BR43, Location!W:W, 0)), "") | O43: =IFERROR(INDEX(Location!X:X, MATCH(BS43, Location!W:W, 0)), "") | S43: 1063888121 | T43: https://prod-clinicians-photo.s3.amazonaws.com/1063888121.jpg | U43: Master of Science in Nursing (MSN), Mgh Institute of Health Professions | Z43: Kimberly Leary, a dedicated prescriber at LifeStance Health, offers compassionate and evidencebased psychiatric care to adults in Massachusetts. With a focus on collaborative medication management, Kimberly helps patients address a wide range of mental health challenges, including anxiety, depression, ADHD, bipolar disorder, and traumarelated conditions. She works closely with individuals to tailor treatment plans that support both symptom relief and longterm wellness, serving patients throughout the state via telehealth and inperson sessions. Kimberly is particularly passionate about supporting patients navigating substance use issues and recovery. With specialized experience in managing alcohol and drug use concerns through medicationassisted treatment, she provides a nonjudgmental and structured approach to care. She values helping patients find stability and rediscover purpose as they heal. Kimberly also works with individuals coping with sleep disturbances, postpartum depression and anxiety, and obsessivecompulsive disorder. As a nurse practitioner who has supported diverse populations, Kimberly brings deep understanding and clinical sensitivity to her work with military veterans, first responders, and LGBTQ individuals. Her treatment approach integrates medication management with evidencebased therapeutic techniques, such as Cognitive Behavioral Therapy CBT and mindfulness practices, to help patients build resilience and sustain emotional balance. She offers additional expertise in psychosis, schizophrenia, and PTSD and welcomes adults at any stage of their mental health journey. Outside of her clinical work, Kimberly enjoys quality time with her family and her dog, Pesto. A lifelong reader and fitness enthusiast, she also finds joy on the golf course. Her grounding in both professional and personal balance shapes the empathetic care she provides. Kimberly serves clients across Massachusetts. | AZ43: English | BC43: pt_B8LtUoRcYkWdny_20xbxdB | BE43: Practitioner - Full Profile | BG43: No | BI43: =IFERROR(INDEX(ValidationAndReference!P:P, MATCH(BE43, ValidationAndReference!Q:Q, 0)), "") | BJ43: =IFERROR(INDEX(ValidationAndReference!F:F, MATCH(D43, ValidationAndReference!G:G, 0)), "") | BK43: =IFERROR(INDEX(ValidationAndReference!F:F, MATCH(E43, ValidationAndReference!G:G, 0)), "") | BL43: =IFERROR(INDEX(ValidationAndReference!F:F, MATCH(F43, ValidationAndReference!G:G, 0)), "") | BM43: 405 | BR43: lo_0VH1qyYZrUiwqrC1wlOUAw | BS43: lo_R2LJAYGLbkqW73K1acvGxh | CL43: =IFERROR(INDEX(ValidationAndReference!V:V, MATCH(AZ43, ValidationAndReference!W:W, 0)), "") | CM43: =IFERROR(INDEX(ValidationAndReference!V:V, MATCH(BA43, ValidationAndReference!W:W, 0)), "") | CN43: =IFERROR(INDEX(ValidationAndReference!V:V, MATCH(BB43, ValidationAndReference!W:W, 0)), "") | CO43: 101 Accord Park Dr | CP43: Norwell | CQ43: 2061 | CR43: MA | CT43: No - Facility Zip
A44: Ellen | B44: Gillander | C44: Female | D44: PhD | E44: PsyD | G44: =IFERROR(VLOOKUP(BM44, ValidationAndReference!J:K, 2, FALSE), "") | L44: Both | M44: LifeStance Health | N44: =IFERROR(INDEX(Location!X:X, MATCH(BR44, Location!W:W, 0)), "") | O44: =IFERROR(INDEX(Location!X:X, MATCH(BS44, Location!W:W, 0)), "") | S44: 1073144978 | T44: https://prod-clinicians-photo.s3.amazonaws.com/1073144978.jpg | U44: PsyD, William James College | Z44: Ellen Gillander is a psychologist, who has been with LifeStance Health since 2020. She graduated from William James College with a doctoral degree in Clinical Psychology and a focus in Forensic Psychology. She completed both an APA internship, as well as a postdoctoral fellowship, at the Arkansas State Hospital before returning to Massachusetts in 2019. Ellen believes in using a personcentered holistic approach to therapy and care. She utilizes modalities such as Cognitive Behavioral, Dialectic Behavioral, and Narrative therapies along with mindfulness, motivational interviewing, and behavior management techniques. Ellen works with adolescents and adults who are experiencing difficult adjustments in their education, relationships, or careers. She helps them challenge negative and limiting thoughts and assists them in discovering new perspectives to help them move towards their goals. Ellen believes in helping all individuals achieve their life of meaning and takes an adaptive approach to support individual needs. In her spare time, Ellen enjoys individual and social pursuits. She is a supporter of lifelong learning and enjoys taking classes, trying a new craft technique or recipe, and learning new games. Ellen also enjoys being in nature and kayaking. She believes that selfcare is flexible and changes her activities to fit the need. | AZ44: English | BC44: pt_B8LtUoRcYkWdny_20xbxdB | BE44: Practitioner - Full Profile | BG44: No | BI44: =IFERROR(INDEX(ValidationAndReference!P:P, MATCH(BE44, ValidationAndReference!Q:Q, 0)), "") | BJ44: =IFERROR(INDEX(ValidationAndReference!F:F, MATCH(D44, ValidationAndReference!G:G, 0)), "") | BK44: =IFERROR(INDEX(ValidationAndReference!F:F, MATCH(E44, ValidationAndReference!G:G, 0)), "") | BL44: =IFERROR(INDEX(ValidationAndReference!F:F, MATCH(F44, ValidationAndReference!G:G, 0)), "") | BM44: 337 | BR44: lo_EJl5br2vEUulYA_LC-JlXQ | BS44: lo_wahJ8Erlp0O5UzLJZMTCah | CL44: =IFERROR(INDEX(ValidationAndReference!V:V, MATCH(AZ44, ValidationAndReference!W:W, 0)), "") | CM44: =IFERROR(INDEX(ValidationAndReference!V:V, MATCH(BA44, ValidationAndReference!W:W, 0)), "") | CN44: =IFERROR(INDEX(ValidationAndReference!V:V, MATCH(BB44, ValidationAndReference!W:W, 0)), "") | CO44: 2300 Crown Colony Dr | CP44: Quincy | CQ44: 2169 | CR44: MA | CT44: No - Facility Zip
A45: Ellen | B45: Gillander | C45: Female | D45: PhD | E45: PsyD | G45: =IFERROR(VLOOKUP(BM45, ValidationAndReference!J:K, 2, FALSE), "") | L45: Both | M45: LifeStance Health | N45: =IFERROR(INDEX(Location!X:X, MATCH(BR45, Location!W:W, 0)), "") | O45: =IFERROR(INDEX(Location!X:X, MATCH(BS45, Location!W:W, 0)), "") | S45: 1073144978 | T45: https://prod-clinicians-photo.s3.amazonaws.com/1073144978.jpg | U45: PsyD, William James College | Z45: Ellen Gillander is a psychologist, who has been with LifeStance Health since 2020. She graduated from William James College with a doctoral degree in Clinical Psychology and a focus in Forensic Psychology. She completed both an APA internship, as well as a postdoctoral fellowship, at the Arkansas State Hospital before returning to Massachusetts in 2019. Ellen believes in using a personcentered holistic approach to therapy and care. She utilizes modalities such as Cognitive Behavioral, Dialectic Behavioral, and Narrative therapies along with mindfulness, motivational interviewing, and behavior management techniques. Ellen works with adolescents and adults who are experiencing difficult adjustments in their education, relationships, or careers. She helps them challenge negative and limiting thoughts and assists them in discovering new perspectives to help them move towards their goals. Ellen believes in helping all individuals achieve their life of meaning and takes an adaptive approach to support individual needs. In her spare time, Ellen enjoys individual and social pursuits. She is a supporter of lifelong learning and enjoys taking classes, trying a new craft technique or recipe, and learning new games. Ellen also enjoys being in nature and kayaking. She believes that selfcare is flexible and changes her activities to fit the need. | AZ45: English | BC45: pt_B8LtUoRcYkWdny_20xbxdB | BE45: Practitioner - Full Profile | BG45: No | BI45: =IFERROR(INDEX(ValidationAndReference!P:P, MATCH(BE45, ValidationAndReference!Q:Q, 0)), "") | BJ45: =IFERROR(INDEX(ValidationAndReference!F:F, MATCH(D45, ValidationAndReference!G:G, 0)), "") | BK45: =IFERROR(INDEX(ValidationAndReference!F:F, MATCH(E45, ValidationAndReference!G:G, 0)), "") | BL45: =IFERROR(INDEX(ValidationAndReference!F:F, MATCH(F45, ValidationAndReference!G:G, 0)), "") | BM45: 337 | BR45: lo_te0vo8TuekWyL5gMnjPK1w | BS45: lo_c9GJzBULJ0KYW9u1EWEsUB | CL45: =IFERROR(INDEX(ValidationAndReference!V:V, MATCH(AZ45, ValidationAndReference!W:W, 0)), "") | CM45: =IFERROR(INDEX(ValidationAndReference!V:V, MATCH(BA45, ValidationAndReference!W:W, 0)), "") | CN45: =IFERROR(INDEX(ValidationAndReference!V:V, MATCH(BB45, ValidationAndReference!W:W, 0)), "") | CO45: 45 Shawmut Rd | CP45: Canton | CQ45: 2021 | CR45: MA | CT45: No - Facility Zip
A46: Shannon | B46: Costa | C46: Female | D46: MA | E46: LMHC | G46: =IFERROR(VLOOKUP(BM46, ValidationAndReference!J:K, 2, FALSE), "") | L46: Adult | M46: LifeStance Health | N46: =IFERROR(INDEX(Location!X:X, MATCH(BR46, Location!W:W, 0)), "") | O46: =IFERROR(INDEX(Location!X:X, MATCH(BS46, Location!W:W, 0)), "") | S46: 1073169918 | T46: https://prod-clinicians-photo.s3.amazonaws.com/1073169918.jpg | U46: MA, Boston College | Z46: Shannon provides a multidimensional approach to therapy. She believes in treating the whole person rather thanjust symptoms. Shannon has experience in working with people in managing difficulties stemming from depression, anxiety, substance use and trauma. Using evidencedbased practices including Motivational Interviewing MI, Cognitive Behavioral Therapy CBT, SolutionFocused Treatment, and mindfulnessrelaxation and meditation methods, Shannon works with adults to improve their overall wellness and their sense of selves Education & Certifications Shannon received her masters degree in mental health counseling from Boston College.. | AZ46: English | BC46: pt_B8LtUoRcYkWdny_20xbxdB | BE46: Practitioner - Full Profile | BG46: No | BI46: =IFERROR(INDEX(ValidationAndReference!P:P, MATCH(BE46, ValidationAndReference!Q:Q, 0)), "") | BJ46: =IFERROR(INDEX(ValidationAndReference!F:F, MATCH(D46, ValidationAndReference!G:G, 0)), "") | BK46: =IFERROR(INDEX(ValidationAndReference!F:F, MATCH(E46, ValidationAndReference!G:G, 0)), "") | BL46: =IFERROR(INDEX(ValidationAndReference!F:F, MATCH(F46, ValidationAndReference!G:G, 0)), "") | BM46: 352 | BR46: lo_J3bUpmaXpUWalQ11VmCr4R | BS46: lo_-ThUCWj4EkKTcIpHZ58qdB | CL46: =IFERROR(INDEX(ValidationAndReference!V:V, MATCH(AZ46, ValidationAndReference!W:W, 0)), "") | CM46: =IFERROR(INDEX(ValidationAndReference!V:V, MATCH(BA46, ValidationAndReference!W:W, 0)), "") | CN46: =IFERROR(INDEX(ValidationAndReference!V:V, MATCH(BB46, ValidationAndReference!W:W, 0)), "") | CO46: 25 Birch St | CP46: Milford | CQ46: 1757 | CR46: MA | CT46: No - Facility Zip
A47: Shannon | B47: Costa | C47: Female | D47: MA | E47: LMHC | G47: =IFERROR(VLOOKUP(BM47, ValidationAndReference!J:K, 2, FALSE), "") | L47: Adult | M47: LifeStance Health | N47: =IFERROR(INDEX(Location!X:X, MATCH(BR47, Location!W:W, 0)), "") | O47: =IFERROR(INDEX(Location!X:X, MATCH(BS47, Location!W:W, 0)), "") | S47: 1073169918 | T47: https://prod-clinicians-photo.s3.amazonaws.com/1073169918.jpg | U47: MA, Boston College | Z47: Shannon provides a multidimensional approach to therapy. She believes in treating the whole person rather thanjust symptoms. Shannon has experience in working with people in managing difficulties stemming from depression, anxiety, substance use and trauma. Using evidencedbased practices including Motivational Interviewing MI, Cognitive Behavioral Therapy CBT, SolutionFocused Treatment, and mindfulnessrelaxation and meditation methods, Shannon works with adults to improve their overall wellness and their sense of selves Education & Certifications Shannon received her masters degree in mental health counseling from Boston College.. | AZ47: English | BC47: pt_B8LtUoRcYkWdny_20xbxdB | BE47: Practitioner - Full Profile | BG47: No | BI47: =IFERROR(INDEX(ValidationAndReference!P:P, MATCH(BE47, ValidationAndReference!Q:Q, 0)), "") | BJ47: =IFERROR(INDEX(ValidationAndReference!F:F, MATCH(D47, ValidationAndReference!G:G, 0)), "") | BK47: =IFERROR(INDEX(ValidationAndReference!F:F, MATCH(E47, ValidationAndReference!G:G, 0)), "") | BL47: =IFERROR(INDEX(ValidationAndReference!F:F, MATCH(F47, ValidationAndReference!G:G, 0)), "") | BM47: 352 | BR47: lo_xjXZjxgu4Eqi9ucQhjEm7w | BS47: lo_5W9oxV-0F0qIMIqZ78b7nh | CL47: =IFERROR(INDEX(ValidationAndReference!V:V, MATCH(AZ47, ValidationAndReference!W:W, 0)), "") | CM47: =IFERROR(INDEX(ValidationAndReference!V:V, MATCH(BA47, ValidationAndReference!W:W, 0)), "") | CN47: =IFERROR(INDEX(ValidationAndReference!V:V, MATCH(BB47, ValidationAndReference!W:W, 0)), "") | CO47: 1003 South Main St | CP47: Bellingham | CQ47: 2019 | CR47: MA | CT47: No - Facility Zip
A48: Nicolina | B48: Calfa | C48: Female | D48: PhD | E48: LP | G48: =IFERROR(VLOOKUP(BM48, ValidationAndReference!J:K, 2, FALSE), "") | L48: Adult | M48: LifeStance Health | N48: =IFERROR(INDEX(Location!X:X, MATCH(BR48, Location!W:W, 0)), "") | O48: =IFERROR(INDEX(Location!X:X, MATCH(BS48, Location!W:W, 0)), "") | S48: 1073947453 | T48: https://prod-clinicians-photo.s3.amazonaws.com/1073947453.jpg | U48: PhD, University of Texas | Z48: Dr. Calfa is a licensed psychologist offering counseling services for adults, with a specialization in health psychology. Dr. Calfa helps clients understand how psychological factors significantly influence their health, including physical illnesses and stress, and aids them in coping with the impact of medical issues on their daily lives. She provides health interventions for individuals coping with acute andor chronic medical conditions such as headaches, diabetes, gastrointestinal problems, chronic pain, and cystic fibrosis. In addition to her work in health psychology, Dr. Calfa also maintains a strong interest in treating clients experiencing anxiety, panic attacks, obsessivecompulsive disorder, depression, and situational or chronic stress. Dr. Calfa works with individuals coping with relationship issues, adjustment to significant life changes or losses, and reproductive concerns including primary and secondary infertility, and use of fertility treatments. Dr. Calfaâs therapeutic style incorporates cognitivebehavioral, interpersonal, and family systems approaches. She incorporates relaxation techniques, including biofeedback, in her work with clients to improve mood regulation and stress management. As a warm, compassionate therapist, Dr. Calfa creates a safe, neutral therapeutic space within the context of a collaborative relationship for each client. Dr. Calfa received her doctoral degree in counseling psychology from the University of Texas at Austin and masterâs degree in counseling from Arizona State University. She completed her psychology internship and postdoctoral fellowship training at Harvard Medical SchoolBoston Childrenâs Hospital, including clinical work with both youth and adults, and training in behavioral medicine and outpatient mental health. Dr. Calfa currently provides psychotherapy services through telehealth and is associated with the Boston Financial District office. | AZ48: English | BC48: pt_B8LtUoRcYkWdny_20xbxdB | BE48: Practitioner - Full Profile | BG48: No | BI48: =IFERROR(INDEX(ValidationAndReference!P:P, MATCH(BE48, ValidationAndReference!Q:Q, 0)), "") | BJ48: =IFERROR(INDEX(ValidationAndReference!F:F, MATCH(D48, ValidationAndReference!G:G, 0)), "") | BK48: =IFERROR(INDEX(ValidationAndReference!F:F, MATCH(E48, ValidationAndReference!G:G, 0)), "") | BL48: =IFERROR(INDEX(ValidationAndReference!F:F, MATCH(F48, ValidationAndReference!G:G, 0)), "") | BM48: 337 | BR48: lo_Gu1H1AlMKkGM7YEE-cV0Mx | BS48: lo_SgGZ9ru7iU62TuMizXbvrx | CL48: =IFERROR(INDEX(ValidationAndReference!V:V, MATCH(AZ48, ValidationAndReference!W:W, 0)), "") | CM48: =IFERROR(INDEX(ValidationAndReference!V:V, MATCH(BA48, ValidationAndReference!W:W, 0)), "") | CN48: =IFERROR(INDEX(ValidationAndReference!V:V, MATCH(BB48, ValidationAndReference!W:W, 0)), "") | CO48: 185 Devonshire St | CP48: Boston | CQ48: 2110 | CR48: MA | CT48: No - Facility Zip
A49: Brendon | B49: McCue | C49: Male | D49: MA | E49: LMHC | G49: =IFERROR(VLOOKUP(BM49, ValidationAndReference!J:K, 2, FALSE), "") | L49: Adult | M49: LifeStance Health | N49: =IFERROR(INDEX(Location!X:X, MATCH(BR49, Location!W:W, 0)), "") | O49: =IFERROR(INDEX(Location!X:X, MATCH(BS49, Location!W:W, 0)), "") | S49: 1083055057 | T49: https://prod-clinicians-photo.s3.amazonaws.com/1083055057.jpg | U49: PsyD, William James College | Z49: Dr. McCue is an Advanced PostDoctoral Fellow. He has experience providing clinical care to young and older adults with a variety of concerns including depression, anxiety, bipolar disorders, PTSD, substance abuse, as well as various interpersonal difficulties and other behavioral issues. Dr. McCue utilizes an integrative approach drawing on a variety of modalities depending on clients needs, including cognitivebehavior therapy CBT, stressmanagementrelaxation techniques, mindfulnessbased interventions and Motivational Interviewing MI. | AZ49: English | BC49: pt_B8LtUoRcYkWdny_20xbxdB | BE49: Practitioner - Full Profile | BG49: No | BI49: =IFERROR(INDEX(ValidationAndReference!P:P, MATCH(BE49, ValidationAndReference!Q:Q, 0)), "") | BJ49: =IFERROR(INDEX(ValidationAndReference!F:F, MATCH(D49, ValidationAndReference!G:G, 0)), "") | BK49: =IFERROR(INDEX(ValidationAndReference!F:F, MATCH(E49, ValidationAndReference!G:G, 0)), "") | BL49: =IFERROR(INDEX(ValidationAndReference!F:F, MATCH(F49, ValidationAndReference!G:G, 0)), "") | BR49: lo_EJl5br2vEUulYA_LC-JlXQ | BS49: lo_wahJ8Erlp0O5UzLJZMTCah | CL49: =IFERROR(INDEX(ValidationAndReference!V:V, MATCH(AZ49, ValidationAndReference!W:W, 0)), "") | CM49: =IFERROR(INDEX(ValidationAndReference!V:V, MATCH(BA49, ValidationAndReference!W:W, 0)), "") | CN49: =IFERROR(INDEX(ValidationAndReference!V:V, MATCH(BB49, ValidationAndReference!W:W, 0)), "") | CO49: 2300 Crown Colony Dr | CP49: Quincy | CQ49: 2169 | CR49: MA | CT49: No - Facility Zip
A50: Jennifer | B50: Pollock | C50: Female | D50: MTC | E50: LMHC | G50: =IFERROR(VLOOKUP(BM50, ValidationAndReference!J:K, 2, FALSE), "") | L50: Both | M50: LifeStance Health | N50: =IFERROR(INDEX(Location!X:X, MATCH(BR50, Location!W:W, 0)), "") | O50: =IFERROR(INDEX(Location!X:X, MATCH(BS50, Location!W:W, 0)), "") | S50: 1083076962 | T50: https://prod-clinicians-photo.s3.amazonaws.com/1083076962.jpg | U50: MA, Assumption College | Z50: Jennifer Pollock, LMHC, provides individual therapy to children, adolescents, young adults, adults, and families. She provides evidencedbased treatment modalities for treating depression, anxiety, communication difficulties, and adjustment such as Cognitive Behavioral therapy, DBT, Motivational Interviewing, and Mindfulness. Jennâs approach to therapy encompasses an individualâs strengths and looks at the therapeutic relationship as a powerful tool to help individuals increase hisher insight into their emotions, behaviors, and relationships. Jennifer received her Masterâs Degree in Counseling Psychology, with additional certifications in both the Cognitive Behavioral Therapy and Child and Family Interventions through Assumption College in Worcester, Ma. Upon receiving her degree, she went on to work with the Department of Youth Services in a wide range of capacities including juvenile detention, residential treatment, and recidivism working with adolescents, families, and young adults. | AZ50: English | BC50: pt_B8LtUoRcYkWdny_20xbxdB | BE50: Practitioner - Full Profile | BG50: No | BI50: =IFERROR(INDEX(ValidationAndReference!P:P, MATCH(BE50, ValidationAndReference!Q:Q, 0)), "") | BJ50: =IFERROR(INDEX(ValidationAndReference!F:F, MATCH(D50, ValidationAndReference!G:G, 0)), "") | BK50: =IFERROR(INDEX(ValidationAndReference!F:F, MATCH(E50, ValidationAndReference!G:G, 0)), "") | BL50: =IFERROR(INDEX(ValidationAndReference!F:F, MATCH(F50, ValidationAndReference!G:G, 0)), "") | BM50: 352 | BR50: lo_3hIK25O-lEqM6hnbD-8HXh | BS50: lo_y_6qaxOiQUSFScBKd0V0Dh | CL50: =IFERROR(INDEX(ValidationAndReference!V:V, MATCH(AZ50, ValidationAndReference!W:W, 0)), "") | CM50: =IFERROR(INDEX(ValidationAndReference!V:V, MATCH(BA50, ValidationAndReference!W:W, 0)), "") | CN50: =IFERROR(INDEX(ValidationAndReference!V:V, MATCH(BB50, ValidationAndReference!W:W, 0)), "") | CO50: 120 Boston Rd | CP50: Groton | CQ50: 1450 | CR50: MA | CS50: Ste 200 | CT50: No - Facility Zip
A51: Catherine | B51: Cavanaugh | C51: Female | D51: MS | E51: LMHC | G51: =IFERROR(VLOOKUP(BM51, ValidationAndReference!J:K, 2, FALSE), "") | L51: Both | M51: LifeStance Health | N51: =IFERROR(INDEX(Location!X:X, MATCH(BR51, Location!W:W, 0)), "") | O51: =IFERROR(INDEX(Location!X:X, MATCH(BS51, Location!W:W, 0)), "") | S51: 1083203103 | T51: https://prod-clinicians-photo.s3.amazonaws.com/1083203103.jpg | U51: MS, Suffolk University | Z51: Catherine Cavanaugh is a Licensed Mental Health Counselor in Connecticut who has been practicing since 2019. She earned her Masterâs in Mental Health Counseling at Suffolk University. Catherine provides a multidimensional approach to therapy. She believes in partnering with individuals to develop insight into their experience and works to foster selfconfidence and selfworth. Catherine has worked with people experiencing a broad range of symptoms and stressors, including depression, anxiety, trauma, and family conflict. She uses a variety of evidencebased practices which include Motivational Interviewing MI, Cognitive Behavioral Therapy CBT and personcentered therapy. Outside of work, Catherineâs focus is on her family. She enjoys being outside, taking walks and baking. | AZ51: English | BC51: pt_B8LtUoRcYkWdny_20xbxdB | BE51: Practitioner - Full Profile | BG51: No | BI51: =IFERROR(INDEX(ValidationAndReference!P:P, MATCH(BE51, ValidationAndReference!Q:Q, 0)), "") | BJ51: =IFERROR(INDEX(ValidationAndReference!F:F, MATCH(D51, ValidationAndReference!G:G, 0)), "") | BK51: =IFERROR(INDEX(ValidationAndReference!F:F, MATCH(E51, ValidationAndReference!G:G, 0)), "") | BL51: =IFERROR(INDEX(ValidationAndReference!F:F, MATCH(F51, ValidationAndReference!G:G, 0)), "") | BM51: 352 | BR51: lo_hW04XNHRKkq32Uh5tJ2q_g | BS51: lo_qmkneyE9q0GzaHfdaGyF7R | CL51: =IFERROR(INDEX(ValidationAndReference!V:V, MATCH(AZ51, ValidationAndReference!W:W, 0)), "") | CM51: =IFERROR(INDEX(ValidationAndReference!V:V, MATCH(BA51, ValidationAndReference!W:W, 0)), "") | CN51: =IFERROR(INDEX(ValidationAndReference!V:V, MATCH(BB51, ValidationAndReference!W:W, 0)), "") | CO51: 2 Executive Park Dr | CP51: Newton | CQ51: 2462 | CR51: MA | CT51: No - Facility Zip
A52: Matthew | B52: Rinaldi | C52: Male | D52: MSW | E52: LCSW | G52: =IFERROR(VLOOKUP(BM52, ValidationAndReference!J:K, 2, FALSE), "") | L52: Both | M52: LifeStance Health | N52: =IFERROR(INDEX(Location!X:X, MATCH(BR52, Location!W:W, 0)), "") | O52: =IFERROR(INDEX(Location!X:X, MATCH(BS52, Location!W:W, 0)), "") | S52: 1083377667 | T52: https://prod-clinicians-photo.s3.amazonaws.com/1083377667.jpg | U52: MSW, Merrimack College | Z52: Matthew Rinaldi, a licensed clinical social worker at LifeStance Health, provides individualized therapy for teens, adults, and seniors across Massachusetts. With a compassionate, clientcentered approach, Matthew supports individuals navigating challenges such as anxiety, depression, and trauma. His holistic style emphasizes trustbuilding, collaboration, and empowerment, guiding clients to create sustainable goals and meaningful change in their lives. Matthew is especially passionate about helping individuals with a history of trauma, including those managing posttraumatic stress from military or first responder experiences. He is dedicated to supporting those facing life transitionsâwhether itâs adjusting to midlife, dealing with grief, or navigating the complexities of aging. Through the use of evidencebased interventions like Cognitive Behavioral Therapy CBT and Exposure Therapy, he helps clients regain a sense of control and resilience, while reinforcing their personal strengths and sense of self. In addition to his work with the general adult population, Matthew has experience supporting first responders, military veterans, and individuals experiencing ADHD or childhood behavior challenges during adolescence. His therapeutic work is rooted in empathy and advocacy, with a focus on helping each person feel seen, heard, and understood. Outside the therapy room, Matthew enjoys rucking, going to the gym, and taking scenic drives through the back roads of New England. He finds inspiration in the arts and enjoys cooking as a creative outlet. He is proud to serve individuals and families throughout Massachusetts, providing thoughtful, personalized care designed to help clients heal and thrive. | AZ52: English | BC52: pt_B8LtUoRcYkWdny_20xbxdB | BE52: Practitioner - Full Profile | BG52: No | BI52: =IFERROR(INDEX(ValidationAndReference!P:P, MATCH(BE52, ValidationAndReference!Q:Q, 0)), "") | BJ52: =IFERROR(INDEX(ValidationAndReference!F:F, MATCH(D52, ValidationAndReference!G:G, 0)), "") | BK52: =IFERROR(INDEX(ValidationAndReference!F:F, MATCH(E52, ValidationAndReference!G:G, 0)), "") | BL52: =IFERROR(INDEX(ValidationAndReference!F:F, MATCH(F52, ValidationAndReference!G:G, 0)), "") | BR52: lo_QZkg7A6X0EiHIeSWJQTcoB | BS52: lo_AuV0lLTkGUueOysG18-xhg | CL52: =IFERROR(INDEX(ValidationAndReference!V:V, MATCH(AZ52, ValidationAndReference!W:W, 0)), "") | CM52: =IFERROR(INDEX(ValidationAndReference!V:V, MATCH(BA52, ValidationAndReference!W:W, 0)), "") | CN52: =IFERROR(INDEX(ValidationAndReference!V:V, MATCH(BB52, ValidationAndReference!W:W, 0)), "") | CO52: 200 Baker Ave | CP52: Concord | CQ52: 1742 | CR52: MA | CT52: No - Facility Zip
A53: Mathilde | B53: McAlpin | C53: Female | D53: MSW | E53: LCSW | G53: =IFERROR(VLOOKUP(BM53, ValidationAndReference!J:K, 2, FALSE), "") | L53: Both | M53: LifeStance Health | N53: =IFERROR(INDEX(Location!X:X, MATCH(BR53, Location!W:W, 0)), "") | O53: =IFERROR(INDEX(Location!X:X, MATCH(BS53, Location!W:W, 0)), "") | S53: 1083487516 | T53: https://prod-clinicians-photo.s3.amazonaws.com/1083487516.jpg | U53: MSW, University of Illinois | Z53: Mathilde McAlpin is a Licensed Clinical Social Worker in Massachusetts who has been practicing since 2023. She earned an MSW at the University of Illinois, UC. Mathilde employs a compassionate approach, seamlessly blending CBT, DBT, MBSR, and motivational interviewing to explore the intricate links between thoughts, beliefs, and behaviors. With a diverse background in inpatient and partial hospitalization programs, she creates a secure haven for adults facing challenges like anxiety, depression, eating disorders, bipolar disorder, schizophrenia, mood disorders, and personality disorders. Mathilde specializes in enhancing interpersonal effectiveness, emotional regulation, and distress tolerance, guiding individuals through transformative life moments such as aging, retirement, divorce, marriage, and family blending. Proficient in providing both longterm support and resolving current interpersonal issues, she collaborates with clients using solutionoriented psychotherapy and motivational interviewing, revealing effective coping strategies. Mathildes unwavering commitment is evident in her dedication to fostering collaborative therapeutic relationships, turning sessions into a sanctuary for authentic storysharing. Her overarching goal is to equip you with invaluable tools for gracefully navigating lifes inevitable fluctuations. Step into a space where your wellbeing is prioritized and cherished, where you are heard, understood, and supported with unparalleled compassion. Mathilde is devoted to creating a therapeutic environment where you can openly express your thoughts without fear of judgment. She firmly believes in your expertise in your healing journey, actively collaborating with you to identify and achieve your treatment goals. Employing strengthsbased methodologies and evidencebased approaches, Mathilde ensures a personalized and effective therapeutic experience. Outside of work, Mathilde enjoys yoga, pottery, live music, hiking, cooking, and cycling. | AZ53: English | BC53: pt_B8LtUoRcYkWdny_20xbxdB | BE53: Practitioner - Full Profile | BG53: No | BI53: =IFERROR(INDEX(ValidationAndReference!P:P, MATCH(BE53, ValidationAndReference!Q:Q, 0)), "") | BJ53: =IFERROR(INDEX(ValidationAndReference!F:F, MATCH(D53, ValidationAndReference!G:G, 0)), "") | BK53: =IFERROR(INDEX(ValidationAndReference!F:F, MATCH(E53, ValidationAndReference!G:G, 0)), "") | BL53: =IFERROR(INDEX(ValidationAndReference!F:F, MATCH(F53, ValidationAndReference!G:G, 0)), "") | BM53: 352 | BR53: lo_L3CIiVDHYESqWdC6bOuAqh | BS53: lo_bn7sE2w_SkyP7nJ0v5wixh | CL53: =IFERROR(INDEX(ValidationAndReference!V:V, MATCH(AZ53, ValidationAndReference!W:W, 0)), "") | CM53: =IFERROR(INDEX(ValidationAndReference!V:V, MATCH(BA53, ValidationAndReference!W:W, 0)), "") | CN53: =IFERROR(INDEX(ValidationAndReference!V:V, MATCH(BB53, ValidationAndReference!W:W, 0)), "") | CO53: 110 Hartwell Ave | CP53: Lexington | CQ53: 2421 | CR53: MA | CT53: No - Facility Zip
A54: Mathilde | B54: McAlpin | C54: Female | D54: MSW | E54: LCSW | G54: =IFERROR(VLOOKUP(BM54, ValidationAndReference!J:K, 2, FALSE), "") | L54: Both | M54: LifeStance Health | N54: =IFERROR(INDEX(Location!X:X, MATCH(BR54, Location!W:W, 0)), "") | O54: =IFERROR(INDEX(Location!X:X, MATCH(BS54, Location!W:W, 0)), "") | S54: 1083487516 | T54: https://prod-clinicians-photo.s3.amazonaws.com/1083487516.jpg | U54: MSW, University of Illinois | Z54: Mathilde McAlpin is a Licensed Clinical Social Worker in Massachusetts who has been practicing since 2023. She earned an MSW at the University of Illinois, UC. Mathilde employs a compassionate approach, seamlessly blending CBT, DBT, MBSR, and motivational interviewing to explore the intricate links between thoughts, beliefs, and behaviors. With a diverse background in inpatient and partial hospitalization programs, she creates a secure haven for adults facing challenges like anxiety, depression, eating disorders, bipolar disorder, schizophrenia, mood disorders, and personality disorders. Mathilde specializes in enhancing interpersonal effectiveness, emotional regulation, and distress tolerance, guiding individuals through transformative life moments such as aging, retirement, divorce, marriage, and family blending. Proficient in providing both longterm support and resolving current interpersonal issues, she collaborates with clients using solutionoriented psychotherapy and motivational interviewing, revealing effective coping strategies. Mathildes unwavering commitment is evident in her dedication to fostering collaborative therapeutic relationships, turning sessions into a sanctuary for authentic storysharing. Her overarching goal is to equip you with invaluable tools for gracefully navigating lifes inevitable fluctuations. Step into a space where your wellbeing is prioritized and cherished, where you are heard, understood, and supported with unparalleled compassion. Mathilde is devoted to creating a therapeutic environment where you can openly express your thoughts without fear of judgment. She firmly believes in your expertise in your healing journey, actively collaborating with you to identify and achieve your treatment goals. Employing strengthsbased methodologies and evidencebased approaches, Mathilde ensures a personalized and effective therapeutic experience. Outside of work, Mathilde enjoys yoga, pottery, live music, hiking, cooking, and cycling. | AZ54: English | BC54: pt_B8LtUoRcYkWdny_20xbxdB | BE54: Practitioner - Full Profile | BG54: No | BI54: =IFERROR(INDEX(ValidationAndReference!P:P, MATCH(BE54, ValidationAndReference!Q:Q, 0)), "") | BJ54: =IFERROR(INDEX(ValidationAndReference!F:F, MATCH(D54, ValidationAndReference!G:G, 0)), "") | BK54: =IFERROR(INDEX(ValidationAndReference!F:F, MATCH(E54, ValidationAndReference!G:G, 0)), "") | BL54: =IFERROR(INDEX(ValidationAndReference!F:F, MATCH(F54, ValidationAndReference!G:G, 0)), "") | BM54: 352 | BR54: lo_L3CIiVDHYESqWdC6bOuAqh | BS54: lo_bn7sE2w_SkyP7nJ0v5wixh | CL54: =IFERROR(INDEX(ValidationAndReference!V:V, MATCH(AZ54, ValidationAndReference!W:W, 0)), "") | CM54: =IFERROR(INDEX(ValidationAndReference!V:V, MATCH(BA54, ValidationAndReference!W:W, 0)), "") | CN54: =IFERROR(INDEX(ValidationAndReference!V:V, MATCH(BB54, ValidationAndReference!W:W, 0)), "") | CO54: 110 Hartwell Ave | CP54: Lexington | CQ54: 2421 | CR54: MA | CT54: No - Facility Zip
A55: Sherrie | B55: Sharp | C55: Female | D55: MD | G55: =IFERROR(VLOOKUP(BM55, ValidationAndReference!J:K, 2, FALSE), "") | L55: Both | M55: LifeStance Health | N55: =IFERROR(INDEX(Location!X:X, MATCH(BR55, Location!W:W, 0)), "") | O55: =IFERROR(INDEX(Location!X:X, MATCH(BS55, Location!W:W, 0)), "") | S55: 1083639447 | T55: https://prod-clinicians-photo.s3.amazonaws.com/1083639447.jpg | U55: MD, Boston University | Z55: Sherrie Sharp is a thoughtful and integrative physician at LifeStance Health who provides compassionate, evidencebased psychiatric care to children, adolescents, and adults across Massachusetts. She offers individual therapy, family therapy, and medication management services, tailoring her approach to support mental, emotional, and developmental wellbeing throughout each stage of life. With a focus on creating collaborative, patientcentered care plans, Sherrie empowers individuals and families to achieve lasting wellness. Sherrie is especially passionate about supporting patients navigating anxiety, ADHD, and traumarelated conditions. Her work includes early intervention for children experiencing behavioral challenges, as well as care for teens and adults struggling with PTSD, school avoidance, or mood instability. By combining clinical precision with an empathetic understanding of her patientsâ lived experiences, she helps individuals build coping strategies that promote resilience and stability. Drawing from a holistic and valuesinformed approach, Sherrie incorporates Christian counseling and faithbased treatment for those who desire spiritual integration in their care. She also provides parenting support and family therapy, addressing complex family dynamics and behavioral concerns. Sherrie has extensive experience working with populations such as foster youth, individuals with autism spectrum or developmental disabilities, first responders, and women navigating unique mental health needs. Outside of her clinical work, Sherrie is committed to wholeperson wellness. She enjoys practicing yoga, exploring nutritional health, and traveling to broaden her perspective. Her dedication to integrative care and mental health advocacy makes her a trusted resource for families and individuals seeking support in Massachusetts. | AZ55: English | BC55: pt_B8LtUoRcYkWdny_20xbxdB | BE55: Practitioner - Full Profile | BG55: No | BI55: =IFERROR(INDEX(ValidationAndReference!P:P, MATCH(BE55, ValidationAndReference!Q:Q, 0)), "") | BJ55: =IFERROR(INDEX(ValidationAndReference!F:F, MATCH(D55, ValidationAndReference!G:G, 0)), "") | BK55: =IFERROR(INDEX(ValidationAndReference!F:F, MATCH(E55, ValidationAndReference!G:G, 0)), "") | BL55: =IFERROR(INDEX(ValidationAndReference!F:F, MATCH(F55, ValidationAndReference!G:G, 0)), "") | BM55: 250 | BR55: lo_J3bUpmaXpUWalQ11VmCr4R | BS55: lo_-ThUCWj4EkKTcIpHZ58qdB | CL55: =IFERROR(INDEX(ValidationAndReference!V:V, MATCH(AZ55, ValidationAndReference!W:W, 0)), "") | CM55: =IFERROR(INDEX(ValidationAndReference!V:V, MATCH(BA55, ValidationAndReference!W:W, 0)), "") | CN55: =IFERROR(INDEX(ValidationAndReference!V:V, MATCH(BB55, ValidationAndReference!W:W, 0)), "") | CO55: 25 Birch St | CP55: Milford | CQ55: 1757 | CR55: MA | CT55: No - Facility Zip
A56: Judith | B56: Faberman | C56: Female | D56: MSW | E56: LICSW | G56: =IFERROR(VLOOKUP(BM56, ValidationAndReference!J:K, 2, FALSE), "") | L56: Adult | M56: LifeStance Health | N56: =IFERROR(INDEX(Location!X:X, MATCH(BR56, Location!W:W, 0)), "") | O56: =IFERROR(INDEX(Location!X:X, MATCH(BS56, Location!W:W, 0)), "") | S56: 1083660831 | T56: https://prod-clinicians-photo.s3.amazonaws.com/1083660831.jpg | U56: MSW, Boston College Graduate School of Social Work | Z56: Judy Faberman is a Licensed Independent Clinical Social Worker providing individual therapy. Her clinical interests and background include the treatment of mood and anxiety disorders, trauma, adjustment disorders and substance use disorders. Judy uses a combination of relational and evidencebased psychotherapies, including motivational interviewing, insight oriented therapy, cognitive behavioral therapy, and dialectical behavioral therapy in her work. She believes in building a strong therapeutic alliance through empathic listening and collaboration as the keys to healing and change. | AZ56: English | BC56: pt_B8LtUoRcYkWdny_20xbxdB | BE56: Practitioner - Full Profile | BG56: No | BI56: =IFERROR(INDEX(ValidationAndReference!P:P, MATCH(BE56, ValidationAndReference!Q:Q, 0)), "") | BJ56: =IFERROR(INDEX(ValidationAndReference!F:F, MATCH(D56, ValidationAndReference!G:G, 0)), "") | BK56: =IFERROR(INDEX(ValidationAndReference!F:F, MATCH(E56, ValidationAndReference!G:G, 0)), "") | BL56: =IFERROR(INDEX(ValidationAndReference!F:F, MATCH(F56, ValidationAndReference!G:G, 0)), "") | BM56: 352 | BR56: lo_4QIZgfh7dUWNnuSD1q2zqA | CL56: =IFERROR(INDEX(ValidationAndReference!V:V, MATCH(AZ56, ValidationAndReference!W:W, 0)), "") | CM56: =IFERROR(INDEX(ValidationAndReference!V:V, MATCH(BA56, ValidationAndReference!W:W, 0)), "") | CN56: =IFERROR(INDEX(ValidationAndReference!V:V, MATCH(BB56, ValidationAndReference!W:W, 0)), "") | CO56: 313 Washington St | CP56: Newton | CQ56: 2458 | CR56: MA | CS56: Ste 402 | CT56: No - Facility Zip
A57: Olga | B57: Smetkov | C57: Female | D57: MD | G57: =IFERROR(VLOOKUP(BM57, ValidationAndReference!J:K, 2, FALSE), "") | L57: Both | M57: LifeStance Health | N57: =IFERROR(INDEX(Location!X:X, MATCH(BR57, Location!W:W, 0)), "") | O57: =IFERROR(INDEX(Location!X:X, MATCH(BS57, Location!W:W, 0)), "") | S57: 1083705511 | T57: https://prod-clinicians-photo.s3.amazonaws.com/1083705511.jpg | U57: MD, Moscow Medical Stomatology Institute | Z57: Dr. Smetkov is providing consultations and psychopharmacological treatment to children and families. She is seeing her professional goal as helping children and families to grow healthy and being able to achieve full potential. | AZ57: English | BA57: Russian | BC57: pt_B8LtUoRcYkWdny_20xbxdB | BE57: Practitioner - Full Profile | BG57: No | BI57: =IFERROR(INDEX(ValidationAndReference!P:P, MATCH(BE57, ValidationAndReference!Q:Q, 0)), "") | BJ57: =IFERROR(INDEX(ValidationAndReference!F:F, MATCH(D57, ValidationAndReference!G:G, 0)), "") | BK57: =IFERROR(INDEX(ValidationAndReference!F:F, MATCH(E57, ValidationAndReference!G:G, 0)), "") | BL57: =IFERROR(INDEX(ValidationAndReference!F:F, MATCH(F57, ValidationAndReference!G:G, 0)), "") | BM57: 122 | BR57: lo_w5HIr6bzGkyc7vBT20scrA | BS57: lo_04KqQKPgc0uBY59wTWWXKR | CL57: =IFERROR(INDEX(ValidationAndReference!V:V, MATCH(AZ57, ValidationAndReference!W:W, 0)), "") | CM57: =IFERROR(INDEX(ValidationAndReference!V:V, MATCH(BA57, ValidationAndReference!W:W, 0)), "") | CN57: =IFERROR(INDEX(ValidationAndReference!V:V, MATCH(BB57, ValidationAndReference!W:W, 0)), "") | CO57: 372 Washington St | CP57: Wellesley | CQ57: 2481 | CR57: MA | CT57: No - Facility Zip
A58: Frank Jay | B58: Gallo | C58: Male | D58: PhD | E58: LCP | G58: =IFERROR(VLOOKUP(BM58, ValidationAndReference!J:K, 2, FALSE), "") | L58: Pediatric | M58: LifeStance Health | N58: =IFERROR(INDEX(Location!X:X, MATCH(BR58, Location!W:W, 0)), "") | O58: =IFERROR(INDEX(Location!X:X, MATCH(BS58, Location!W:W, 0)), "") | S58: 1093008963 | T58: https://prod-clinicians-photo.s3.amazonaws.com/1093008963.jpg | U58: PhD, University of Wisconsin - Milwaukee | Z58: Dr. Gallo is a pediatric neuropsychologist who assesses problems with thinking, learning, and daily functioning in children, adolescents, and teens. He has specialized training in evaluation of children with neurological or medical conditions that can affect the brain, such as seizure, stroke, head trauma, premature birth, prenatal alcoholdrug exposure, and genetic abnormalities. He also specializes in the evaluation of developmental disorders, such as ADHD, Autism Spectrum Disorder, Learning Disabilities, and Intellectual Disabilities. As children transition to adulthood, evaluations can help to determine readiness and possible need for specialized support or guardianship. Dr. Gallo collaborates with a range of child specialists, including educators, pediatricians, pediatric neurologists, and behavioral health providers. He makes certain that every parent he works with gains a thorough understanding of their childâs unique set of strengths and weaknesses. After he develops a customized treatment plan to help optimize the childâs development and daily functioning, he makes certain that parents are confident in their ability to follow through with recommended treatments. He is also available for followup consultations and reevaluations to help monitor the childâs development and progress, explore new concerns, and update treatment recommendations. Dr. Gallo earned his doctorate in Clinical Psychology from the University of Wisconsin â Milwaukee. He completed his postdoctoral fellowship in Pediatric Neuropsychology at the Medical College of Wisconsin. He has obtained board certification in Clinical Neuropsychology, as well as Subspecialty Certification in Pediatric Clinical Neuropsychology from the American Board of Professional Psychology. | AZ58: English | BC58: pt_B8LtUoRcYkWdny_20xbxdB | BE58: Practitioner - Full Profile | BG58: No | BI58: =IFERROR(INDEX(ValidationAndReference!P:P, MATCH(BE58, ValidationAndReference!Q:Q, 0)), "") | BJ58: =IFERROR(INDEX(ValidationAndReference!F:F, MATCH(D58, ValidationAndReference!G:G, 0)), "") | BK58: =IFERROR(INDEX(ValidationAndReference!F:F, MATCH(E58, ValidationAndReference!G:G, 0)), "") | BL58: =IFERROR(INDEX(ValidationAndReference!F:F, MATCH(F58, ValidationAndReference!G:G, 0)), "") | BM58: 337 | BR58: lo_RbtQmFKyVEmDbBl7Kvl-Zx | BS58: lo_tL2ZF_Cy_E29efQqM8D7ax | CL58: =IFERROR(INDEX(ValidationAndReference!V:V, MATCH(AZ58, ValidationAndReference!W:W, 0)), "") | CM58: =IFERROR(INDEX(ValidationAndReference!V:V, MATCH(BA58, ValidationAndReference!W:W, 0)), "") | CN58: =IFERROR(INDEX(ValidationAndReference!V:V, MATCH(BB58, ValidationAndReference!W:W, 0)), "") | CO58: 6 Kimball Ln | CP58: Lynnfield | CQ58: 1940 | CR58: MA | CT58: No - Facility Zip
A59: Joanna | B59: Budz | C59: Female | D59: PsyD | G59: =IFERROR(VLOOKUP(BM59, ValidationAndReference!J:K, 2, FALSE), "") | L59: Both | M59: LifeStance Health | N59: =IFERROR(INDEX(Location!X:X, MATCH(BR59, Location!W:W, 0)), "") | O59: =IFERROR(INDEX(Location!X:X, MATCH(BS59, Location!W:W, 0)), "") | S59: 1093128787 | T59: https://prod-clinicians-photo.s3.amazonaws.com/1093128787.jpg | U59: PsyD, William James College | Z59: Dr. Budz is a licensed clinical psychologist providing individual therapy for adults. Her therapeutic approach is integrative, drawing from cognitive behavioral and insightbased treatments. Dr. Budz believes that a strong therapeutic relationship is key to fostering therapeutic engagement, insight, awareness, selfacceptance, and growth. She most enjoys working with clients who are struggling with anxiety, depression, relationship issues, interpersonal communication issues, worklife balance, and the management of life transitions. With all clients, she works to increase mindfulness and the use of adaptive coping skills. Dr. Budz received her clinical doctoral degree from the Massachusetts School of Professional Psychology. She completed her predoctoral internships at the Dr. Solomon Carter Fuller Mental Health Center and also at the Brandeis University Psychological Counseling Center. Dr. Budz completed her postdoctoral fellowship at Harvard Vanguard Medical Associates. Dr. Budz treats clients in our Financial District office. | AZ59: English | BC59: pt_B8LtUoRcYkWdny_20xbxdB | BE59: Practitioner - Full Profile | BG59: No | BI59: =IFERROR(INDEX(ValidationAndReference!P:P, MATCH(BE59, ValidationAndReference!Q:Q, 0)), "") | BJ59: =IFERROR(INDEX(ValidationAndReference!F:F, MATCH(D59, ValidationAndReference!G:G, 0)), "") | BK59: =IFERROR(INDEX(ValidationAndReference!F:F, MATCH(E59, ValidationAndReference!G:G, 0)), "") | BL59: =IFERROR(INDEX(ValidationAndReference!F:F, MATCH(F59, ValidationAndReference!G:G, 0)), "") | BM59: 337 | BR59: lo_Gu1H1AlMKkGM7YEE-cV0Mx | BS59: lo_SgGZ9ru7iU62TuMizXbvrx | CL59: =IFERROR(INDEX(ValidationAndReference!V:V, MATCH(AZ59, ValidationAndReference!W:W, 0)), "") | CM59: =IFERROR(INDEX(ValidationAndReference!V:V, MATCH(BA59, ValidationAndReference!W:W, 0)), "") | CN59: =IFERROR(INDEX(ValidationAndReference!V:V, MATCH(BB59, ValidationAndReference!W:W, 0)), "") | CO59: 185 Devonshire St | CP59: Boston | CQ59: 2110 | CR59: MA | CT59: No - Facility Zip
A60: Magda | B60: Kozdrowicz | C60: Female | D60: MTC | E60: LMHC | G60: =IFERROR(VLOOKUP(BM60, ValidationAndReference!J:K, 2, FALSE), "") | L60: Adult | M60: LifeStance Health | N60: =IFERROR(INDEX(Location!X:X, MATCH(BR60, Location!W:W, 0)), "") | O60: =IFERROR(INDEX(Location!X:X, MATCH(BS60, Location!W:W, 0)), "") | S60: 1093887655 | T60: https://prod-clinicians-photo.s3.amazonaws.com/1093887655.jpg | U60: MA, Lesley University | Z60: Magda is a licensed mental health counselor, who provides individual psychotherapy to adolescents and adults. She has experience in supporting patients with various mental health issues such as anxiety, performance anxiety, depression, ADHD, and stress related to chronic health problems or life transitions. She specializes in treating PTSDtrauma and attachment issues using evidencebased interventions such as EMDR, Trauma Focused CBT, somatic therapies, mindfulness and meditation, DBT, and ACT. Magda is also an Expressive Art Therapist, and she enjoys integrating music and art with traditional talk therapy, upon request. She approaches her work with warmth, openness, compassion and empathy, which helps her to connect with her patients to promote healing, growth and finding meaning in their lives. | AZ60: English | BA60: Polish | BC60: pt_B8LtUoRcYkWdny_20xbxdB | BE60: Practitioner - Full Profile | BG60: No | BI60: =IFERROR(INDEX(ValidationAndReference!P:P, MATCH(BE60, ValidationAndReference!Q:Q, 0)), "") | BJ60: =IFERROR(INDEX(ValidationAndReference!F:F, MATCH(D60, ValidationAndReference!G:G, 0)), "") | BK60: =IFERROR(INDEX(ValidationAndReference!F:F, MATCH(E60, ValidationAndReference!G:G, 0)), "") | BL60: =IFERROR(INDEX(ValidationAndReference!F:F, MATCH(F60, ValidationAndReference!G:G, 0)), "") | BM60: 352 | BR60: lo_oYipqaXH4EyoVFlGdyf8dx | CL60: =IFERROR(INDEX(ValidationAndReference!V:V, MATCH(AZ60, ValidationAndReference!W:W, 0)), "") | CM60: =IFERROR(INDEX(ValidationAndReference!V:V, MATCH(BA60, ValidationAndReference!W:W, 0)), "") | CN60: =IFERROR(INDEX(ValidationAndReference!V:V, MATCH(BB60, ValidationAndReference!W:W, 0)), "") | CO60: 266 Main St | CP60: Medfield | CQ60: 2052 | CR60: MA | CS60: Building 3 | CT60: No - Facility Zip
A61: Cara | B61: Streit | C61: Female | D61: MSW | E61: LCSW | G61: =IFERROR(VLOOKUP(BM61, ValidationAndReference!J:K, 2, FALSE), "") | L61: Both | M61: LifeStance Health | N61: =IFERROR(INDEX(Location!X:X, MATCH(BR61, Location!W:W, 0)), "") | O61: =IFERROR(INDEX(Location!X:X, MATCH(BS61, Location!W:W, 0)), "") | S61: 1093901746 | T61: https://prod-clinicians-photo.s3.amazonaws.com/1093901746.jpg | U61: EdD, Boston University | Z61: Cara Streit is a Licensed Clinical Social Worker in Massachusetts who has been practicing since 2009. She has a Master of Social Work and Doctorate in Special Education. Cara has experience working with people who are autistichave autism, and people with ADHD, generalized or social anxiety, depression, and learning, developmental, or intellectual disabilities. Her strengthsbased approach is neurodiversityaffirming, and she uses empathy and gentle humor to build strong therapeutic relationships. Cara pulls from a range of methods and techniques, including ACT, CBT, and motivational interviewing, to tailor support specific to each individual. From the stresses of becoming a new parent to special education planning and the transition into college and adult life, Cara appreciates gaining deep understanding of people and partnering to help them build and maintain fulfilling lives. Outside of work, Cara has a passion for international travel, has been to every continent except Antarctica, and runs a small nonprofit organization that supports adults with intellectual disabilities in accessing educational tours. | AZ61: English | BC61: pt_B8LtUoRcYkWdny_20xbxdB | BE61: Practitioner - Full Profile | BG61: No | BI61: =IFERROR(INDEX(ValidationAndReference!P:P, MATCH(BE61, ValidationAndReference!Q:Q, 0)), "") | BJ61: =IFERROR(INDEX(ValidationAndReference!F:F, MATCH(D61, ValidationAndReference!G:G, 0)), "") | BK61: =IFERROR(INDEX(ValidationAndReference!F:F, MATCH(E61, ValidationAndReference!G:G, 0)), "") | BL61: =IFERROR(INDEX(ValidationAndReference!F:F, MATCH(F61, ValidationAndReference!G:G, 0)), "") | BM61: 352 | BR61: lo_L3CIiVDHYESqWdC6bOuAqh | BS61: lo_bn7sE2w_SkyP7nJ0v5wixh | CL61: =IFERROR(INDEX(ValidationAndReference!V:V, MATCH(AZ61, ValidationAndReference!W:W, 0)), "") | CM61: =IFERROR(INDEX(ValidationAndReference!V:V, MATCH(BA61, ValidationAndReference!W:W, 0)), "") | CN61: =IFERROR(INDEX(ValidationAndReference!V:V, MATCH(BB61, ValidationAndReference!W:W, 0)), "") | CO61: 110 Hartwell Ave | CP61: Lexington | CQ61: 2421 | CR61: MA | CT61: No - Facility Zip
A62: Kristen | B62: Calapa | C62: Female | D62: MEd | E62: LMHC | G62: =IFERROR(VLOOKUP(BM62, ValidationAndReference!J:K, 2, FALSE), "") | L62: Both | M62: LifeStance Health | N62: =IFERROR(INDEX(Location!X:X, MATCH(BR62, Location!W:W, 0)), "") | O62: =IFERROR(INDEX(Location!X:X, MATCH(BS62, Location!W:W, 0)), "") | S62: 1104194190 | T62: https://prod-clinicians-photo.s3.amazonaws.com/1104194190.jpg | U62: M.Ed, Bridgewater State University | Z62: Kristen Calapa is dedicated to helping individuals across Massachusetts navigate lifes complexities and achieve their mental health goals. As a therapist at LifeStance Health, Kristen provides personalized care to adults and seniors, working collaboratively to foster resilience and empower clients to take charge of their emotional wellbeing. Whether addressing anxiety, depression, or bipolar disorder, Kristen tailors her approach to meet the unique needs of each individual, ensuring they feel supported and understood throughout their therapeutic journey. Kristen is particularly passionate about helping individuals manage laterlife and midlife transitions, providing compassionate guidance during these pivotal moments. She also specializes in addressing PTSD and trauma, utilizing evidencebased interventions to help clients process distressing experiences and build healthier coping mechanisms. Additionally, Kristen works extensively with individuals facing obsessivecompulsive disorder OCD, offering structured strategies to alleviate symptoms and enhance daily functioning. Drawing on expertise in Cognitive Behavioral Therapy CBT, Kristen creates a practical and solutionfocused therapeutic environment. She has experience supporting a wide range of populations, including military veterans, first responders, and individuals within the LGBTQ community. Kristen also has specialized knowledge in addressing mental health concerns for those with developmental disabilities or autism spectrum disorders. Her approach is inclusive and empathetic, helping clients from diverse backgrounds feel seen and heard as they work toward meaningful change. Outside of her clinical practice, Kristen enjoys engaging in a variety of hobbies that bring balance and fulfillment to her life. Her multifaceted interests enrich her perspective and contribute to her holistic approach to mental health care. Kristen is committed to providing exceptional care to individuals throughout Massachusetts, offering a path to greater emotional health and wellbeing. | AZ62: English | BC62: pt_B8LtUoRcYkWdny_20xbxdB | BE62: Practitioner - Full Profile | BG62: No | BI62: =IFERROR(INDEX(ValidationAndReference!P:P, MATCH(BE62, ValidationAndReference!Q:Q, 0)), "") | BJ62: =IFERROR(INDEX(ValidationAndReference!F:F, MATCH(D62, ValidationAndReference!G:G, 0)), "") | BK62: =IFERROR(INDEX(ValidationAndReference!F:F, MATCH(E62, ValidationAndReference!G:G, 0)), "") | BL62: =IFERROR(INDEX(ValidationAndReference!F:F, MATCH(F62, ValidationAndReference!G:G, 0)), "") | BM62: 352 | BR62: lo_0VH1qyYZrUiwqrC1wlOUAw | BS62: lo_R2LJAYGLbkqW73K1acvGxh | CL62: =IFERROR(INDEX(ValidationAndReference!V:V, MATCH(AZ62, ValidationAndReference!W:W, 0)), "") | CM62: =IFERROR(INDEX(ValidationAndReference!V:V, MATCH(BA62, ValidationAndReference!W:W, 0)), "") | CN62: =IFERROR(INDEX(ValidationAndReference!V:V, MATCH(BB62, ValidationAndReference!W:W, 0)), "") | CO62: 101 Accord Park Dr | CP62: Norwell | CQ62: 2061 | CR62: MA | CT62: No - Facility Zip
A63: Samuel | B63: Kitchens | C63: Male | D63: MSW | E63: LCSW | G63: =IFERROR(VLOOKUP(BM63, ValidationAndReference!J:K, 2, FALSE), "") | L63: Both | M63: LifeStance Health | N63: =IFERROR(INDEX(Location!X:X, MATCH(BR63, Location!W:W, 0)), "") | O63: =IFERROR(INDEX(Location!X:X, MATCH(BS63, Location!W:W, 0)), "") | S63: 1104651843 | T63: https://prod-clinicians-photo.s3.amazonaws.com/1104651843.jpg | U63: MSW, Simmons School of Social Work | Z63: Sam Kitchens, LCSW, is a compassionate therapist at LifeStance Health, serving individuals across Massachusetts. He brings a wealth of experience helping clients 18 navigate a wide range of challenges, particularly those related to ADHD, anxiety, LGBT and behavioral habit issues. Sam is known for his ability to offer practical tools for managing organizational difficulties and motivation problems, especially for clients with ADHD. He is skilled in using behavioral strategies to address unwanted behaviors, including exposure therapy, and supports anxious adults in restructuring their thought patterns to foster healthier coping mechanisms. He helps people better understand their behavior and equips them with effective strategies to foster positive selfgrowth development. Sam graduated from Tufts University in 2017 with a BA degree in Clinical Psychology. He then went on to study at Simmons University where he received a Masters in Social Work. | AZ63: English | BC63: pt_B8LtUoRcYkWdny_20xbxdB | BE63: Practitioner - Full Profile | BG63: No | BI63: =IFERROR(INDEX(ValidationAndReference!P:P, MATCH(BE63, ValidationAndReference!Q:Q, 0)), "") | BJ63: =IFERROR(INDEX(ValidationAndReference!F:F, MATCH(D63, ValidationAndReference!G:G, 0)), "") | BK63: =IFERROR(INDEX(ValidationAndReference!F:F, MATCH(E63, ValidationAndReference!G:G, 0)), "") | BL63: =IFERROR(INDEX(ValidationAndReference!F:F, MATCH(F63, ValidationAndReference!G:G, 0)), "") | BM63: 352 | BR63: lo_4QIZgfh7dUWNnuSD1q2zqA | CL63: =IFERROR(INDEX(ValidationAndReference!V:V, MATCH(AZ63, ValidationAndReference!W:W, 0)), "") | CM63: =IFERROR(INDEX(ValidationAndReference!V:V, MATCH(BA63, ValidationAndReference!W:W, 0)), "") | CN63: =IFERROR(INDEX(ValidationAndReference!V:V, MATCH(BB63, ValidationAndReference!W:W, 0)), "") | CO63: 313 Washington St | CP63: Newton | CQ63: 2458 | CR63: MA | CS63: Ste 402 | CT63: No - Facility Zip
A64: Lisa | B64: Nutter | C64: Female | D64: MSN | E64: CNP | G64: =IFERROR(VLOOKUP(BM64, ValidationAndReference!J:K, 2, FALSE), "") | L64: Both | M64: LifeStance Health | N64: =IFERROR(INDEX(Location!X:X, MATCH(BR64, Location!W:W, 0)), "") | O64: =IFERROR(INDEX(Location!X:X, MATCH(BS64, Location!W:W, 0)), "") | S64: 1114114410 | T64: https://prod-clinicians-photo.s3.amazonaws.com/1114114410.jpg | U64: MS, University of Massachusetts | Z64: Lisa Nutter CNP, PCNS joined Psychological Care Associates in 2009. She provides psychiatric assessment and treatment for ages sixteen and up. | AZ64: English | BC64: pt_B8LtUoRcYkWdny_20xbxdB | BE64: Practitioner - Full Profile | BG64: No | BI64: =IFERROR(INDEX(ValidationAndReference!P:P, MATCH(BE64, ValidationAndReference!Q:Q, 0)), "") | BJ64: =IFERROR(INDEX(ValidationAndReference!F:F, MATCH(D64, ValidationAndReference!G:G, 0)), "") | BK64: =IFERROR(INDEX(ValidationAndReference!F:F, MATCH(E64, ValidationAndReference!G:G, 0)), "") | BL64: =IFERROR(INDEX(ValidationAndReference!F:F, MATCH(F64, ValidationAndReference!G:G, 0)), "") | BM64: 352 | BR64: lo_Oui2sL2bGkW93Fc4nv2cbx | BS64: lo_3RYpLUKgUEiDipjLTBOswB | CL64: =IFERROR(INDEX(ValidationAndReference!V:V, MATCH(AZ64, ValidationAndReference!W:W, 0)), "") | CM64: =IFERROR(INDEX(ValidationAndReference!V:V, MATCH(BA64, ValidationAndReference!W:W, 0)), "") | CN64: =IFERROR(INDEX(ValidationAndReference!V:V, MATCH(BB64, ValidationAndReference!W:W, 0)), "") | CO64: 321 Billerica Rd | CP64: Chelmsford | CQ64: 1824 | CR64: MA | CT64: No - Facility Zip
A65: Hilary | B65: Scott | C65: Female | D65: MSW | E65: LICSW | G65: =IFERROR(VLOOKUP(BM65, ValidationAndReference!J:K, 2, FALSE), "") | L65: Both | M65: LifeStance Health | N65: =IFERROR(INDEX(Location!X:X, MATCH(BR65, Location!W:W, 0)), "") | O65: =IFERROR(INDEX(Location!X:X, MATCH(BS65, Location!W:W, 0)), "") | S65: 1114469293 | T65: https://prod-clinicians-photo.s3.amazonaws.com/1114469293.jpg | U65: MSW, Simmons College | Z65: Hilary utilizes a clientfocused, strengthsbased approach in addition to cognitivebehavioral and mindbody therapies. She specializes in working with adolescents, teens, and adults with expertise treating anxiety, depression, ADHD, low selfesteem, and adjustment issues. She has particular interest in integrating mindfulness, breathing exercises, and guided imagery into her work to help clients live more fully in the present. | AZ65: English | BA65: Spanish | BC65: pt_B8LtUoRcYkWdny_20xbxdB | BE65: Practitioner - Full Profile | BG65: No | BI65: =IFERROR(INDEX(ValidationAndReference!P:P, MATCH(BE65, ValidationAndReference!Q:Q, 0)), "") | BJ65: =IFERROR(INDEX(ValidationAndReference!F:F, MATCH(D65, ValidationAndReference!G:G, 0)), "") | BK65: =IFERROR(INDEX(ValidationAndReference!F:F, MATCH(E65, ValidationAndReference!G:G, 0)), "") | BL65: =IFERROR(INDEX(ValidationAndReference!F:F, MATCH(F65, ValidationAndReference!G:G, 0)), "") | BM65: 352 | BR65: lo_ICAU0TvahEuLSyeDtv-uIQ | BS65: lo_FkhegZ_500izJ5pb7f47iB | CL65: =IFERROR(INDEX(ValidationAndReference!V:V, MATCH(AZ65, ValidationAndReference!W:W, 0)), "") | CM65: =IFERROR(INDEX(ValidationAndReference!V:V, MATCH(BA65, ValidationAndReference!W:W, 0)), "") | CN65: =IFERROR(INDEX(ValidationAndReference!V:V, MATCH(BB65, ValidationAndReference!W:W, 0)), "") | CO65: 89 Access Rd | CP65: Norwood | CQ65: 2062 | CR65: MA | CT65: No - Facility Zip
A66: Rebecca | B66: Stubbs | C66: Female | D66: MSW | E66: LCSW | G66: =IFERROR(VLOOKUP(BM66, ValidationAndReference!J:K, 2, FALSE), "") | L66: Both | M66: LifeStance Health | N66: =IFERROR(INDEX(Location!X:X, MATCH(BR66, Location!W:W, 0)), "") | O66: =IFERROR(INDEX(Location!X:X, MATCH(BS66, Location!W:W, 0)), "") | S66: 1114598224 | T66: https://prod-clinicians-photo.s3.amazonaws.com/1114598224.jpg | U66: MSW, Boston University | Z66: Becca Stubbs is a Licensed Clinical Social Worker in Massachusetts who has been practicing since 2022. Becca offers her clients patience and a calm, LGBTQfriendly environment. Outside of work, Becca enjoys reading, video games, social deduction games, and crafts. | AZ66: English | BC66: pt_B8LtUoRcYkWdny_20xbxdB | BE66: Practitioner - Full Profile | BG66: No | BI66: =IFERROR(INDEX(ValidationAndReference!P:P, MATCH(BE66, ValidationAndReference!Q:Q, 0)), "") | BJ66: =IFERROR(INDEX(ValidationAndReference!F:F, MATCH(D66, ValidationAndReference!G:G, 0)), "") | BK66: =IFERROR(INDEX(ValidationAndReference!F:F, MATCH(E66, ValidationAndReference!G:G, 0)), "") | BL66: =IFERROR(INDEX(ValidationAndReference!F:F, MATCH(F66, ValidationAndReference!G:G, 0)), "") | BM66: 352 | BR66: lo_swkHQlrzCkqk5-946P0yNw | BS66: lo_-7_Lw0GOaECGLFCsOyOoWR | CL66: =IFERROR(INDEX(ValidationAndReference!V:V, MATCH(AZ66, ValidationAndReference!W:W, 0)), "") | CM66: =IFERROR(INDEX(ValidationAndReference!V:V, MATCH(BA66, ValidationAndReference!W:W, 0)), "") | CN66: =IFERROR(INDEX(ValidationAndReference!V:V, MATCH(BB66, ValidationAndReference!W:W, 0)), "") | CO66: 175 Highland Ave | CP66: Needham | CQ66: 2494 | CR66: MA | CT66: No - Facility Zip
A67: Nicole | B67: Perez Elias | C67: Female | D67: MSW | E67: LICSW | G67: =IFERROR(VLOOKUP(BM67, ValidationAndReference!J:K, 2, FALSE), "") | L67: Both | M67: LifeStance Health | N67: =IFERROR(INDEX(Location!X:X, MATCH(BR67, Location!W:W, 0)), "") | O67: =IFERROR(INDEX(Location!X:X, MATCH(BS67, Location!W:W, 0)), "") | S67: 1114634870 | T67: https://prod-clinicians-photo.s3.amazonaws.com/1114634870.jpg | U67: MSW, Boston College | Z67: Nicole Perez Elias is a Licensed Clinical Social Worker in Massachusetts who has been practicing since 2021. She has a BSW from Salve Regina University and an MSW from Boston College School of Social Work. Nicole believes that everyone is worthy of a good quality of life. Nicoleâs after work routine starts with playing her favorite computer game, Sims 4. After that, she takes some time reading a book recommendations are always welcome. Lastly, sheâll most likely watch a good show on Netflix or journal. | AZ67: English | BA67: Spanish | BC67: pt_B8LtUoRcYkWdny_20xbxdB | BE67: Practitioner - Full Profile | BG67: No | BI67: =IFERROR(INDEX(ValidationAndReference!P:P, MATCH(BE67, ValidationAndReference!Q:Q, 0)), "") | BJ67: =IFERROR(INDEX(ValidationAndReference!F:F, MATCH(D67, ValidationAndReference!G:G, 0)), "") | BK67: =IFERROR(INDEX(ValidationAndReference!F:F, MATCH(E67, ValidationAndReference!G:G, 0)), "") | BL67: =IFERROR(INDEX(ValidationAndReference!F:F, MATCH(F67, ValidationAndReference!G:G, 0)), "") | BM67: 352 | BR67: lo_EJl5br2vEUulYA_LC-JlXQ | BS67: lo_wahJ8Erlp0O5UzLJZMTCah | CL67: =IFERROR(INDEX(ValidationAndReference!V:V, MATCH(AZ67, ValidationAndReference!W:W, 0)), "") | CM67: =IFERROR(INDEX(ValidationAndReference!V:V, MATCH(BA67, ValidationAndReference!W:W, 0)), "") | CN67: =IFERROR(INDEX(ValidationAndReference!V:V, MATCH(BB67, ValidationAndReference!W:W, 0)), "") | CO67: 2300 Crown Colony Dr | CP67: Quincy | CQ67: 2169 | CR67: MA | CT67: No - Facility Zip
A68: Yangmu | B68: Xu | C68: Female | D68: PhD | E68: LP | G68: =IFERROR(VLOOKUP(BM68, ValidationAndReference!J:K, 2, FALSE), "") | L68: Both | M68: LifeStance Health | N68: =IFERROR(INDEX(Location!X:X, MATCH(BR68, Location!W:W, 0)), "") | O68: =IFERROR(INDEX(Location!X:X, MATCH(BS68, Location!W:W, 0)), "") | S68: 1124672522 | T68: https://prod-clinicians-photo.s3.amazonaws.com/1124672522.jpg | U68: PhD, Loma Linda University | Z68: Dr. Xu received her doctorate degree in clinical psychology from Loma Linda University. She completed her doctoral internship in clinical psychology in the neuropsychology track and her postdoctoral fellowship in neuropsychology at Beth Israel Deaconess Medical CenterMassachusetts Mental Health CenterHarvard Medical School. She is a member of the International Neuropsychological Society and the Massachusetts Neuropsychological Society. Dr. Xu has published and presented research at many conferences and in peerreviewed journals. She continues to collaborate on research projects examining predictors and mediators of psychiatric conditions on neuropsychological performances. Dr. Xu provides neuropsychological evaluation and treatments for individuals with medicalneurological conditions including dementia, movement disorders, multiple sclerosis, head injury, brain tumor, epilepsy, sleep disorders, substance use, psychiatric disorders including depression, anxiety, bipolar disorder, schizophrenia, and neurodevelopmental disorders including ADHD, learning disorders, autism spectrum disorder, intellectual disability. She values the importance of individualized care by providing patients and their families with an indepth understanding of their level of cognitive functioning. Her goal is to optimize their functional and cognitive status by providing recommendationsinterventions, implementing potential compensatory strategies for symptom management, addressing modifiable lifestyle factors, while collaborating with members of the treatment team to improve their overall quality of life. | AZ68: English | BA68: Mandarin | BC68: pt_B8LtUoRcYkWdny_20xbxdB | BE68: Practitioner - Full Profile | BG68: No | BI68: =IFERROR(INDEX(ValidationAndReference!P:P, MATCH(BE68, ValidationAndReference!Q:Q, 0)), "") | BJ68: =IFERROR(INDEX(ValidationAndReference!F:F, MATCH(D68, ValidationAndReference!G:G, 0)), "") | BK68: =IFERROR(INDEX(ValidationAndReference!F:F, MATCH(E68, ValidationAndReference!G:G, 0)), "") | BL68: =IFERROR(INDEX(ValidationAndReference!F:F, MATCH(F68, ValidationAndReference!G:G, 0)), "") | BM68: 455 | BR68: lo_EJl5br2vEUulYA_LC-JlXQ | BS68: lo_wahJ8Erlp0O5UzLJZMTCah | CL68: =IFERROR(INDEX(ValidationAndReference!V:V, MATCH(AZ68, ValidationAndReference!W:W, 0)), "") | CM68: =IFERROR(INDEX(ValidationAndReference!V:V, MATCH(BA68, ValidationAndReference!W:W, 0)), "") | CN68: =IFERROR(INDEX(ValidationAndReference!V:V, MATCH(BB68, ValidationAndReference!W:W, 0)), "") | CO68: 2300 Crown Colony Dr | CP68: Quincy | CQ68: 2169 | CR68: MA | CT68: No - Facility Zip
A69: Yangmu | B69: Xu | C69: Female | D69: PhD | E69: LP | G69: =IFERROR(VLOOKUP(BM69, ValidationAndReference!J:K, 2, FALSE), "") | L69: Both | M69: LifeStance Health | N69: =IFERROR(INDEX(Location!X:X, MATCH(BR69, Location!W:W, 0)), "") | O69: =IFERROR(INDEX(Location!X:X, MATCH(BS69, Location!W:W, 0)), "") | S69: 1124672522 | T69: https://prod-clinicians-photo.s3.amazonaws.com/1124672522.jpg | U69: PhD, Loma Linda University | Z69: Dr. Xu received her doctorate degree in clinical psychology from Loma Linda University. She completed her doctoral internship in clinical psychology in the neuropsychology track and her postdoctoral fellowship in neuropsychology at Beth Israel Deaconess Medical CenterMassachusetts Mental Health CenterHarvard Medical School. She is a member of the International Neuropsychological Society and the Massachusetts Neuropsychological Society. Dr. Xu has published and presented research at many conferences and in peerreviewed journals. She continues to collaborate on research projects examining predictors and mediators of psychiatric conditions on neuropsychological performances. Dr. Xu provides neuropsychological evaluation and treatments for individuals with medicalneurological conditions including dementia, movement disorders, multiple sclerosis, head injury, brain tumor, epilepsy, sleep disorders, substance use, psychiatric disorders including depression, anxiety, bipolar disorder, schizophrenia, and neurodevelopmental disorders including ADHD, learning disorders, autism spectrum disorder, intellectual disability. She values the importance of individualized care by providing patients and their families with an indepth understanding of their level of cognitive functioning. Her goal is to optimize their functional and cognitive status by providing recommendationsinterventions, implementing potential compensatory strategies for symptom management, addressing modifiable lifestyle factors, while collaborating with members of the treatment team to improve their overall quality of life. | AZ69: English | BA69: Mandarin | BC69: pt_B8LtUoRcYkWdny_20xbxdB | BE69: Practitioner - Full Profile | BG69: No | BI69: =IFERROR(INDEX(ValidationAndReference!P:P, MATCH(BE69, ValidationAndReference!Q:Q, 0)), "") | BJ69: =IFERROR(INDEX(ValidationAndReference!F:F, MATCH(D69, ValidationAndReference!G:G, 0)), "") | BK69: =IFERROR(INDEX(ValidationAndReference!F:F, MATCH(E69, ValidationAndReference!G:G, 0)), "") | BL69: =IFERROR(INDEX(ValidationAndReference!F:F, MATCH(F69, ValidationAndReference!G:G, 0)), "") | BM69: 455 | BR69: lo_WTxCl_PGJkydSgfSTKd1mx | BS69: lo_6Q6bTr0VKkuCN9evdqEA9B | CL69: =IFERROR(INDEX(ValidationAndReference!V:V, MATCH(AZ69, ValidationAndReference!W:W, 0)), "") | CM69: =IFERROR(INDEX(ValidationAndReference!V:V, MATCH(BA69, ValidationAndReference!W:W, 0)), "") | CN69: =IFERROR(INDEX(ValidationAndReference!V:V, MATCH(BB69, ValidationAndReference!W:W, 0)), "") | CO69: 169 Libbey Pkwy | CP69: Weymouth | CQ69: 2189 | CR69: MA | CT69: No - Facility Zip
A70: Shengmei | B70: Xu | C70: Female | D70: LMHC | G70: =IFERROR(VLOOKUP(BM70, ValidationAndReference!J:K, 2, FALSE), "") | L70: Both | M70: LifeStance Health | N70: =IFERROR(INDEX(Location!X:X, MATCH(BR70, Location!W:W, 0)), "") | O70: =IFERROR(INDEX(Location!X:X, MATCH(BS70, Location!W:W, 0)), "") | S70: 1124811351 | T70: https://prod-clinicians-photo.s3.amazonaws.com/1124811351.jpg | U70: Master of Education, University of Illinois Urbana-Champaign | Z70: Shengmei Xu helps adults of all ages in Massachusetts navigate lifeâs challenges through a compassionate, evidencebased therapeutic approach. Whether you are seeking support for anxiety, depression, substance use, or major life transitions, Shengmei provides a safe space to explore your experiences and build the skills necessary to move toward greater emotional balance and wellbeing. She offers individual therapy services through LifeStance Health to meet clients where they areâboth emotionally and clinically. Shengmei is deeply passionate about helping individuals with dual diagnoses, particularly those managing both mental health conditions and substance use concerns. She brings an integrated perspective to recovery, using modalities such as Acceptance and Commitment Therapy ACT, Dialectical Behavior Therapy DBT, and Cognitive Behavioral Therapy CBT to guide clients toward sustainable healing. She is also skilled in supporting individuals facing PTSDtrauma, eating disorders, and sleep disorders, tailoring her approach to support the unique experiences of each person. She works with a broad range of adults, including those within the LGBTQ community, individuals with developmental disabilities or autism spectrum disorders, and those with adoption or foster care experiences. Her holistic approach bridges mental health and physical wellbeing, particularly for those dealing with health psychology concerns or later life transitions. Outside the therapy room, Shengmei finds joy in swimming, rock climbing, and playing tennisâactivities that keep her grounded and energized. She brings that same energy and balance into her work with clients across Massachusetts. | AZ70: English | BA70: Chinese | BC70: pt_B8LtUoRcYkWdny_20xbxdB | BE70: Practitioner - Full Profile | BG70: No | BI70: =IFERROR(INDEX(ValidationAndReference!P:P, MATCH(BE70, ValidationAndReference!Q:Q, 0)), "") | BJ70: =IFERROR(INDEX(ValidationAndReference!F:F, MATCH(D70, ValidationAndReference!G:G, 0)), "") | BK70: =IFERROR(INDEX(ValidationAndReference!F:F, MATCH(E70, ValidationAndReference!G:G, 0)), "") | BL70: =IFERROR(INDEX(ValidationAndReference!F:F, MATCH(F70, ValidationAndReference!G:G, 0)), "") | BM70: 352 | BR70: lo_3D1HJe6ly0SMmBdp7PgNPQ | BS70: lo_XChreUGy00CKaewjQqDgth | CL70: =IFERROR(INDEX(ValidationAndReference!V:V, MATCH(AZ70, ValidationAndReference!W:W, 0)), "") | CM70: =IFERROR(INDEX(ValidationAndReference!V:V, MATCH(BA70, ValidationAndReference!W:W, 0)), "") | CN70: =IFERROR(INDEX(ValidationAndReference!V:V, MATCH(BB70, ValidationAndReference!W:W, 0)), "") | CO70: 1 Brookline Pl | CP70: Brookline | CQ70: 2445 | CR70: MA | CT70: No - Facility Zip
A71: Marc | B71: Robert | C71: Male | D71: PhD | E71: PsyD | G71: =IFERROR(VLOOKUP(BM71, ValidationAndReference!J:K, 2, FALSE), "") | L71: Adult | M71: LifeStance Health | N71: =IFERROR(INDEX(Location!X:X, MATCH(BR71, Location!W:W, 0)), "") | O71: =IFERROR(INDEX(Location!X:X, MATCH(BS71, Location!W:W, 0)), "") | S71: 1134311749 | T71: https://prod-clinicians-photo.s3.amazonaws.com/1134311749.jpg | U71: PsyD, Massachusetts School of Professional Psychology (now William James College) | Z71: Marc Robert, PsyD, is a Licensed Clinical Psychologist. Dr. Robert received his Doctorate of Clinical Psychology with a Concentration in Health Psychology from the Massachusetts School of Professional Psychology. He completed his internship and postdoctoral training at Cambridge Health AllianceHarvard Medical School and Boston Behavioral Medicine. Dr. Robert provides evidencebased psychological treatments for adults. His areas of specialty include anxiety disorders, mood disorders, stressrelated disorders e.g., headache, chronic pain, IBS, insomnia, hypertension, and healthbehaviorlifestyle changes. Dr. Robert utilizes a variety of modalities depending on clientsâ needs, including cognitivebehavior therapy CBT, stressmanagementrelaxation techniques, mindfulnessbased interventions, biofeedback, Internal Family Systems IFS, and Motivational Interviewing MI. In addition to his clinical services, Dr. Robert serves as Senior Clinical Director for Lifestance Massachusetts. | AZ71: English | BC71: pt_B8LtUoRcYkWdny_20xbxdB | BE71: Practitioner - Full Profile | BG71: No | BI71: =IFERROR(INDEX(ValidationAndReference!P:P, MATCH(BE71, ValidationAndReference!Q:Q, 0)), "") | BJ71: =IFERROR(INDEX(ValidationAndReference!F:F, MATCH(D71, ValidationAndReference!G:G, 0)), "") | BK71: =IFERROR(INDEX(ValidationAndReference!F:F, MATCH(E71, ValidationAndReference!G:G, 0)), "") | BL71: =IFERROR(INDEX(ValidationAndReference!F:F, MATCH(F71, ValidationAndReference!G:G, 0)), "") | BM71: 337 | BR71: lo_Vh5w3CxH0EykH5kx0U6tFB | BS71: lo_60MBmWeGhUW35I-sOeQCqB | CL71: =IFERROR(INDEX(ValidationAndReference!V:V, MATCH(AZ71, ValidationAndReference!W:W, 0)), "") | CM71: =IFERROR(INDEX(ValidationAndReference!V:V, MATCH(BA71, ValidationAndReference!W:W, 0)), "") | CN71: =IFERROR(INDEX(ValidationAndReference!V:V, MATCH(BB71, ValidationAndReference!W:W, 0)), "") | CO71: 11 Midstate Dr | CP71: Auburn | CQ71: 1501 | CR71: MA | CT71: No - Facility Zip
A72: Steve | B72: Skiffington | C72: Male | D72: MA | E72: LMHC | G72: =IFERROR(VLOOKUP(BM72, ValidationAndReference!J:K, 2, FALSE), "") | L72: Adult | M72: LifeStance Health | N72: =IFERROR(INDEX(Location!X:X, MATCH(BR72, Location!W:W, 0)), "") | O72: =IFERROR(INDEX(Location!X:X, MATCH(BS72, Location!W:W, 0)), "") | S72: 1134677834 | T72: https://prod-clinicians-photo.s3.amazonaws.com/1134677834.jpg | U72: MA, William James College | Z72: Steve Skiffington, LMHC, provides compassionate and effective therapy to individuals in Massachusetts, helping them navigate challenges related to depression, anxiety, PTSDtrauma, and Substance Use. With a cognitiveoriented approach, he works with adults across different life stages, guiding them in examining thought patterns and how these influence their emotions, behaviors, and relationships. By fostering selfawareness and resilience, Steve helps clients develop meaningful strategies to improve their wellbeing and overall life satisfaction. Steve is particularly passionate about helping individuals who struggle with cognitive patterns that impact their daily lives. Whether addressing intrusive thoughts, unhelpful behavioral cycles, or difficulties in emotional regulation, he utilizes Cognitive Behavioral Therapy CBT, Cognitive Processing Therapy CPT and Written Exposure Therapy to create structured, evidencebased treatment plans. Additionally, Steve can help individuals address somatic stress concerns through breathing techniques to build distresstolerance and build ones capacity for relaxation. His approach emphasizes selfexploration and practical skills to promote lasting change. He works with diverse populations, including men, women, and LGBTQ individuals, tailoring therapy to each clientâs unique needs. Through individual therapy, Steve assists clients in developing coping strategies, fostering emotional resilience, and improving overall mental health. His experience spans a broad range of concerns, including trauma recovery, stress management, and selfidentity exploration. Outside of his clinical work, Steve enjoys expressing his creativity through miniature painting, drawing, and sculpting. A passionate fan of fantasy and science fiction, he spends time reading, watching films, and engaging in video gaming. His artistic background enriches his ability to connect with clients who share similar interests, creating a relatable and supportive therapeutic environment. | AZ72: English | BC72: pt_B8LtUoRcYkWdny_20xbxdB | BE72: Practitioner - Full Profile | BG72: No | BI72: =IFERROR(INDEX(ValidationAndReference!P:P, MATCH(BE72, ValidationAndReference!Q:Q, 0)), "") | BJ72: =IFERROR(INDEX(ValidationAndReference!F:F, MATCH(D72, ValidationAndReference!G:G, 0)), "") | BK72: =IFERROR(INDEX(ValidationAndReference!F:F, MATCH(E72, ValidationAndReference!G:G, 0)), "") | BL72: =IFERROR(INDEX(ValidationAndReference!F:F, MATCH(F72, ValidationAndReference!G:G, 0)), "") | BR72: lo_i4ajVD9NG0uUsxIo9EDRXR | BS72: lo_JwksEiSl1UGoIhcEihW17B | CL72: =IFERROR(INDEX(ValidationAndReference!V:V, MATCH(AZ72, ValidationAndReference!W:W, 0)), "") | CM72: =IFERROR(INDEX(ValidationAndReference!V:V, MATCH(BA72, ValidationAndReference!W:W, 0)), "") | CN72: =IFERROR(INDEX(ValidationAndReference!V:V, MATCH(BB72, ValidationAndReference!W:W, 0)), "") | CO72: 10 Cabot Rd | CP72: Medford | CQ72: 2155 | CR72: MA | CT72: No - Facility Zip
A73: Anthony | B73: Primavera | C73: Male | D73: PsyD | E73: LP | G73: =IFERROR(VLOOKUP(BM73, ValidationAndReference!J:K, 2, FALSE), "") | L73: Both | M73: LifeStance Health | N73: =IFERROR(INDEX(Location!X:X, MATCH(BR73, Location!W:W, 0)), "") | O73: =IFERROR(INDEX(Location!X:X, MATCH(BS73, Location!W:W, 0)), "") | S73: 1134856438 | T73: https://prod-clinicians-photo.s3.amazonaws.com/1134856438.jpg | U73: PsyD, Antioch University | Z73: Dr. Anthony Primavera is committed to providing clinical therapy services to clients presenting with a wide range of concerns, including but not limited to anxiety disorders including panic attacks, major depression, relationship struggles, adjustment concerns, addiction struggles, and navigating various life transitions. He has experience in community mental health, integrated care, and college counseling settings. Dr.Primavera primarily provides individual therapy using an integrated, evidencebased approach to treatment that blends elements of ACT Acceptance and Commitment Therapy, PersonCentered Psychotherapy, and SolutionFocused Brief Therapy. He is also experienced in mindfulnessbased approaches to treatment and motivational interviewing. Anthony is attentive to both the struggles his clients experience and to how they can use their strengths and resources to support healthy change. To support the changes that clients wish to make in their lives, those who seek a kind, respectful, and nonjudgmental therapist with a sense of humor, often find working with Dr. Primavera to be a valuable experience. | AZ73: English | BC73: pt_B8LtUoRcYkWdny_20xbxdB | BE73: Practitioner - Full Profile | BG73: No | BI73: =IFERROR(INDEX(ValidationAndReference!P:P, MATCH(BE73, ValidationAndReference!Q:Q, 0)), "") | BJ73: =IFERROR(INDEX(ValidationAndReference!F:F, MATCH(D73, ValidationAndReference!G:G, 0)), "") | BK73: =IFERROR(INDEX(ValidationAndReference!F:F, MATCH(E73, ValidationAndReference!G:G, 0)), "") | BL73: =IFERROR(INDEX(ValidationAndReference!F:F, MATCH(F73, ValidationAndReference!G:G, 0)), "") | BM73: 337 | BR73: lo_oYipqaXH4EyoVFlGdyf8dx | CL73: =IFERROR(INDEX(ValidationAndReference!V:V, MATCH(AZ73, ValidationAndReference!W:W, 0)), "") | CM73: =IFERROR(INDEX(ValidationAndReference!V:V, MATCH(BA73, ValidationAndReference!W:W, 0)), "") | CN73: =IFERROR(INDEX(ValidationAndReference!V:V, MATCH(BB73, ValidationAndReference!W:W, 0)), "") | CO73: 266 Main St | CP73: Medfield | CQ73: 2052 | CR73: MA | CS73: Building 3 | CT73: No - Facility Zip
