Workbook

Sheet Provider
A1: First Name | B1: Last Name | C1: Gender | D1: Professional Suffix 1 | E1: Professional Suffix 2 | F1: Professional Suffix 3 | G1: Specialty 1 | H1: Specialty 2 | I1: Specialty 3 | J1: Specialty 4 | K1: Specialty 5 | L1: Patients Accepted | M1: Practice Name | N1: Location 1 | O1: Location 2 | P1: Location 3 | Q1: Location 4 | R1: Location 5 | S1: NPI Number | T1: Headshot Link | U1: Education 1 | V1: Education 2 | W1: Education 3 | X1: Education 4 | Y1: Education 5 | Z1: Professional Statement | AA1: Board Certification 1 | AB1: Sub Board Certification 1 | AC1: Board Certification 2 | AD1: Sub Board Certification 2 | AE1: Board Certification 3 | AF1: Sub Board Certification 3 | AG1: Board Certification 4 | AH1: Sub Board Certification 4 | AI1: Board Certification 5 | AJ1: Sub Board Certification 5 | AK1: Professional Memberships 1 | AL1: Professional Memberships 2 | AM1: Professional Memberships 3 | AN1: Professional Memberships 4 | AO1: Professional Memberships 5 | AP1: Awards and Publications 1 | AQ1: Awards and Publications 2 | AR1: Awards and Publications 3 | AS1: Awards and Publications 4 | AT1: Awards and Publications 5 | AU1: Hospital Affiliation 1 | AV1: Hospital Affiliation 2 | AW1: Hospital Affiliation 3 | AX1: Hospital Affiliation 4 | AY1: Hospital Affiliation 5 | AZ1: Additional Languages Spoken 1 | BA1: Additional Languages Spoken 2 | BB1: Additional Languages Spoken 3 | BC1: Practice Cloud ID | BD1: Provider Cloud ID | BE1: Provider Type | BF1: Salesforce Contact ID | BG1: Enterprise Scheduling Flag | BH1: Opt Out of Ratings | BI1: Provider Type (Substatus) ID | BJ1: Professional Suffix ID 1 | BK1: Professional Suffix ID 2 | BL1: Professional Suffix ID 3 | BM1: Specialty ID 1 | BN1: Specialty ID 2 | BO1: Specialty ID 3 | BP1: Specialty ID 4 | BQ1: Specialty ID 5 | BR1: Location ID 1 | BS1: Location ID 2 | BT1: Location ID 3 | BU1: Location ID 4 | BV1: Location ID 5 | BW1: Board Cert ID 1 | BX1: Sub Board Cert ID 1 | BY1: Board Cert ID 2 | BZ1: Sub Board Cert ID 2 | CA1: Board Cert ID 3 | CB1: Sub Board Cert ID 3 | CC1: Board Cert ID 4 | CD1: Sub Board Cert ID 4 | CE1: Board Cert ID 5 | CF1: Sub Board Cert ID 5 | CG1: Hospital Affiliation ID 1 | CH1: Hospital Affiliation ID 2 | CI1: Hospital Affiliation ID 3 | CJ1: Hospital Affiliation ID 4 | CK1: Hospital Affiliation ID 5 | CL1: Language ID 1 | CM1: Language ID 2 | CN1: Language ID 3 | CO1: Facility Address | CP1: Facility City | CQ1: Facility Zip | CR1: Facility State | CS1: Address line 2 | CT1: Matched
A2: Rachel | B2: Fitch | C2: Female | D2: DSW | E2: LISW-S | F2: LCSW | G2: =IFERROR(VLOOKUP(BM2, ValidationAndReference!J:K, 2, FALSE), "") | L2: Both | M2: LifeStance Health | N2: =IFERROR(INDEX(Location!X:X, MATCH(BR2, Location!W:W, 0)), "") | O2: =IFERROR(INDEX(Location!X:X, MATCH(BS2, Location!W:W, 0)), "") | S2: 1013105469 | T2: https://prod-clinicians-photo.s3.amazonaws.com/1013105469.jpg | U2: Doctor of Social Work (DSW), University of Kentucky | Z2: Rachel Fitch, LCSW, helps individuals and families across Ohio find healing, hope, and renewed purpose through compassionate, evidencebased care. She works with adolescents, teens, and adults to navigate lifeâs most difficult challenges, including anxiety, depression, relationship struggles, and trauma. Rachel believes that therapy is a collaborative journeyâone that empowers clients to develop greater selfunderstanding, improve communication, and create lasting emotional balance. Rachel provides individual, couples, and family therapy at LifeStance Health, integrating Cognitive Behavioral Therapy CBT, mindfulness, and familybased approaches to support growth and resilience. She is experienced in helping clients facing complex concerns such as ADHD, postpartum depression, PTSDtrauma, and womenâs issues. Her approach combines clinical expertise with genuine warmth, allowing clients to feel supported and understood as they work toward their goals. Rachel is especially passionate about supporting individuals who have recently been discharged from a psychiatric hospital, helping them transition safely and confidently back into daily life. She offers structured guidance and emotional support to promote stability, reduce relapse risk, and strengthen coping skills. Rachel also works extensively with clinicians, first responders, and child welfare professionals experiencing burnout or secondary trauma, helping them rediscover balance and meaning in their personal and professional lives. Her practice welcomes diverse populations, including members of the LGBTQ community, military personnel and veterans, women, and individuals from adoption or foster care backgrounds. Rachelâs dedication to traumainformed and inclusive care ensures that every client feels seen and valued. Outside of her clinical work, Rachel enjoys reading, DIY home projects with her husband, and spending time with their two dogs. These personal passions reflect her belief in creating comfort, connection, and creativityâboth in her home and in her therapeutic work. | AZ2: English | BC2: pt_5pmdAWg-0UuZBxgghGIfih | BE2: Practitioner - Full Profile | BG2: No | BI2: =IFERROR(INDEX(ValidationAndReference!P:P, MATCH(BE2, ValidationAndReference!Q:Q, 0)), "") | BJ2: =IFERROR(INDEX(ValidationAndReference!F:F, MATCH(D2, ValidationAndReference!G:G, 0)), "") | BK2: =IFERROR(INDEX(ValidationAndReference!F:F, MATCH(E2, ValidationAndReference!G:G, 0)), "") | BL2: =IFERROR(INDEX(ValidationAndReference!F:F, MATCH(F2, ValidationAndReference!G:G, 0)), "") | BM2: 352 | BR2: lo_Co2PtuT10kC3DHSCyaUKPh | CL2: =IFERROR(INDEX(ValidationAndReference!V:V, MATCH(AZ2, ValidationAndReference!W:W, 0)), "") | CM2: =IFERROR(INDEX(ValidationAndReference!V:V, MATCH(BA2, ValidationAndReference!W:W, 0)), "") | CN2: =IFERROR(INDEX(ValidationAndReference!V:V, MATCH(BB2, ValidationAndReference!W:W, 0)), "") | CO2: 1077 State Rte 28 | CP2: Milford | CQ2: 45150 | CR2: OH | CS2: Ste 202 | CT2: No - Facility Zip
A3: Rachel | B3: Fitch | C3: Female | D3: DSW | E3: LISW-S | F3: LCSW | G3: =IFERROR(VLOOKUP(BM3, ValidationAndReference!J:K, 2, FALSE), "") | L3: Both | M3: LifeStance Health | N3: =IFERROR(INDEX(Location!X:X, MATCH(BR3, Location!W:W, 0)), "") | O3: =IFERROR(INDEX(Location!X:X, MATCH(BS3, Location!W:W, 0)), "") | S3: 1013105469 | T3: https://prod-clinicians-photo.s3.amazonaws.com/1013105469.jpg | U3: Doctor of Social Work (DSW), University of Kentucky | Z3: Rachel Fitch, LCSW, helps individuals and families across Ohio find healing, hope, and renewed purpose through compassionate, evidencebased care. She works with adolescents, teens, and adults to navigate lifeâs most difficult challenges, including anxiety, depression, relationship struggles, and trauma. Rachel believes that therapy is a collaborative journeyâone that empowers clients to develop greater selfunderstanding, improve communication, and create lasting emotional balance. Rachel provides individual, couples, and family therapy at LifeStance Health, integrating Cognitive Behavioral Therapy CBT, mindfulness, and familybased approaches to support growth and resilience. She is experienced in helping clients facing complex concerns such as ADHD, postpartum depression, PTSDtrauma, and womenâs issues. Her approach combines clinical expertise with genuine warmth, allowing clients to feel supported and understood as they work toward their goals. Rachel is especially passionate about supporting individuals who have recently been discharged from a psychiatric hospital, helping them transition safely and confidently back into daily life. She offers structured guidance and emotional support to promote stability, reduce relapse risk, and strengthen coping skills. Rachel also works extensively with clinicians, first responders, and child welfare professionals experiencing burnout or secondary trauma, helping them rediscover balance and meaning in their personal and professional lives. Her practice welcomes diverse populations, including members of the LGBTQ community, military personnel and veterans, women, and individuals from adoption or foster care backgrounds. Rachelâs dedication to traumainformed and inclusive care ensures that every client feels seen and valued. Outside of her clinical work, Rachel enjoys reading, DIY home projects with her husband, and spending time with their two dogs. These personal passions reflect her belief in creating comfort, connection, and creativityâboth in her home and in her therapeutic work. | AZ3: English | BC3: pt_5pmdAWg-0UuZBxgghGIfih | BE3: Practitioner - Full Profile | BG3: No | BI3: =IFERROR(INDEX(ValidationAndReference!P:P, MATCH(BE3, ValidationAndReference!Q:Q, 0)), "") | BJ3: =IFERROR(INDEX(ValidationAndReference!F:F, MATCH(D3, ValidationAndReference!G:G, 0)), "") | BK3: =IFERROR(INDEX(ValidationAndReference!F:F, MATCH(E3, ValidationAndReference!G:G, 0)), "") | BL3: =IFERROR(INDEX(ValidationAndReference!F:F, MATCH(F3, ValidationAndReference!G:G, 0)), "") | BM3: 352 | BR3: lo_Co2PtuT10kC3DHSCyaUKPh | CL3: =IFERROR(INDEX(ValidationAndReference!V:V, MATCH(AZ3, ValidationAndReference!W:W, 0)), "") | CM3: =IFERROR(INDEX(ValidationAndReference!V:V, MATCH(BA3, ValidationAndReference!W:W, 0)), "") | CN3: =IFERROR(INDEX(ValidationAndReference!V:V, MATCH(BB3, ValidationAndReference!W:W, 0)), "") | CO3: 1077 State Rte 28 | CP3: Milford | CQ3: 45150 | CR3: OH | CS3: Ste 202 | CT3: No - Facility Zip
A4: Rachel | B4: Fitch | C4: Female | D4: DSW | E4: LISW-S | F4: LCSW | G4: =IFERROR(VLOOKUP(BM4, ValidationAndReference!J:K, 2, FALSE), "") | L4: Both | M4: LifeStance Health | N4: =IFERROR(INDEX(Location!X:X, MATCH(BR4, Location!W:W, 0)), "") | O4: =IFERROR(INDEX(Location!X:X, MATCH(BS4, Location!W:W, 0)), "") | S4: 1013105469 | T4: https://prod-clinicians-photo.s3.amazonaws.com/1013105469.jpg | U4: Doctor of Social Work (DSW), University of Kentucky | Z4: Rachel Fitch, LCSW, helps individuals and families across Ohio find healing, hope, and renewed purpose through compassionate, evidencebased care. She works with adolescents, teens, and adults to navigate lifeâs most difficult challenges, including anxiety, depression, relationship struggles, and trauma. Rachel believes that therapy is a collaborative journeyâone that empowers clients to develop greater selfunderstanding, improve communication, and create lasting emotional balance. Rachel provides individual, couples, and family therapy at LifeStance Health, integrating Cognitive Behavioral Therapy CBT, mindfulness, and familybased approaches to support growth and resilience. She is experienced in helping clients facing complex concerns such as ADHD, postpartum depression, PTSDtrauma, and womenâs issues. Her approach combines clinical expertise with genuine warmth, allowing clients to feel supported and understood as they work toward their goals. Rachel is especially passionate about supporting individuals who have recently been discharged from a psychiatric hospital, helping them transition safely and confidently back into daily life. She offers structured guidance and emotional support to promote stability, reduce relapse risk, and strengthen coping skills. Rachel also works extensively with clinicians, first responders, and child welfare professionals experiencing burnout or secondary trauma, helping them rediscover balance and meaning in their personal and professional lives. Her practice welcomes diverse populations, including members of the LGBTQ community, military personnel and veterans, women, and individuals from adoption or foster care backgrounds. Rachelâs dedication to traumainformed and inclusive care ensures that every client feels seen and valued. Outside of her clinical work, Rachel enjoys reading, DIY home projects with her husband, and spending time with their two dogs. These personal passions reflect her belief in creating comfort, connection, and creativityâboth in her home and in her therapeutic work. | AZ4: English | BC4: pt_5pmdAWg-0UuZBxgghGIfih | BE4: Practitioner - Full Profile | BG4: No | BI4: =IFERROR(INDEX(ValidationAndReference!P:P, MATCH(BE4, ValidationAndReference!Q:Q, 0)), "") | BJ4: =IFERROR(INDEX(ValidationAndReference!F:F, MATCH(D4, ValidationAndReference!G:G, 0)), "") | BK4: =IFERROR(INDEX(ValidationAndReference!F:F, MATCH(E4, ValidationAndReference!G:G, 0)), "") | BL4: =IFERROR(INDEX(ValidationAndReference!F:F, MATCH(F4, ValidationAndReference!G:G, 0)), "") | BM4: 352 | BR4: lo_Co2PtuT10kC3DHSCyaUKPh | CL4: =IFERROR(INDEX(ValidationAndReference!V:V, MATCH(AZ4, ValidationAndReference!W:W, 0)), "") | CM4: =IFERROR(INDEX(ValidationAndReference!V:V, MATCH(BA4, ValidationAndReference!W:W, 0)), "") | CN4: =IFERROR(INDEX(ValidationAndReference!V:V, MATCH(BB4, ValidationAndReference!W:W, 0)), "") | CO4: 1077 State Rte 28 | CP4: Milford | CQ4: 45150 | CR4: OH | CS4: Ste 202 | CT4: No - Facility Zip
A5: Ellie | B5: Ettman | C5: Female | D5: LPC | E5: CCTP | G5: =IFERROR(VLOOKUP(BM5, ValidationAndReference!J:K, 2, FALSE), "") | L5: Both | M5: LifeStance Health | N5: =IFERROR(INDEX(Location!X:X, MATCH(BR5, Location!W:W, 0)), "") | O5: =IFERROR(INDEX(Location!X:X, MATCH(BS5, Location!W:W, 0)), "") | S5: 1023668134 | T5: https://prod-clinicians-photo.s3.amazonaws.com/1023668134.jpg | U5: Master in Counseling (MC), Arcadia University | Z5: Ellie Ettman, LPC, helps teens, young adults, and adults in Pennsylvania navigate mental health challenges and improve overall wellbeing through compassionate, individualized care. As a Licensed Professional Counselor at LifeStance Health, she provides support for anxiety, depression, and relationship concerns, helping clients build practical strategies for managing symptoms and achieving personal growth. Ellie works with a diverse range of patients, including those recently discharged from psychiatric hospitals, ensuring each personâs unique circumstances are considered in their treatment plan. Ellie is particularly passionate about working with clients who have recently been discharged from psychiatric care or are navigating current legal matters. She helps individuals manage anxiety, depression, and relationship issues, using interventions such as Cognitive Behavioral Therapy CBT, Acceptance and Commitment Therapy ACT, couples counseling, and parenting skills. She serves populations including LGBTQ individuals, adults with developmental disabilities, and both men and women, creating a safe and inclusive environment for healing and personal development. Outside of her professional work, Ellie enjoys baking, spending time with family and friends, and finding ways to bring joy into everyday life. Her approach to therapy combines clinical expertise with genuine empathy, helping clients explore their goals, strengthen coping strategies, and improve their quality of life. | AZ5: English | BC5: pt_NQMRQWBlP02-a4WEulV9ph | BE5: Practitioner - Full Profile | BG5: No | BI5: =IFERROR(INDEX(ValidationAndReference!P:P, MATCH(BE5, ValidationAndReference!Q:Q, 0)), "") | BJ5: =IFERROR(INDEX(ValidationAndReference!F:F, MATCH(D5, ValidationAndReference!G:G, 0)), "") | BK5: =IFERROR(INDEX(ValidationAndReference!F:F, MATCH(E5, ValidationAndReference!G:G, 0)), "") | BL5: =IFERROR(INDEX(ValidationAndReference!F:F, MATCH(F5, ValidationAndReference!G:G, 0)), "") | BM5: 352 | BR5: lo_El9sSz8bXUelY14uudbaUB | CL5: =IFERROR(INDEX(ValidationAndReference!V:V, MATCH(AZ5, ValidationAndReference!W:W, 0)), "") | CM5: =IFERROR(INDEX(ValidationAndReference!V:V, MATCH(BA5, ValidationAndReference!W:W, 0)), "") | CN5: =IFERROR(INDEX(ValidationAndReference!V:V, MATCH(BB5, ValidationAndReference!W:W, 0)), "") | CO5: 140 W Ge | CP5: Plymouth Meeting | CQ5: 19462 | CR5: PA | CS5: Rmantown Pike Ste 160 | CT5: No - Facility Zip
A6: Ellie | B6: Ettman | C6: Female | D6: LPC | E6: CCTP | G6: =IFERROR(VLOOKUP(BM6, ValidationAndReference!J:K, 2, FALSE), "") | L6: Both | M6: LifeStance Health | N6: =IFERROR(INDEX(Location!X:X, MATCH(BR6, Location!W:W, 0)), "") | O6: =IFERROR(INDEX(Location!X:X, MATCH(BS6, Location!W:W, 0)), "") | S6: 1023668134 | T6: https://prod-clinicians-photo.s3.amazonaws.com/1023668134.jpg | U6: Master in Counseling (MC), Arcadia University | Z6: Ellie Ettman, LPC, helps teens, young adults, and adults in Pennsylvania navigate mental health challenges and improve overall wellbeing through compassionate, individualized care. As a Licensed Professional Counselor at LifeStance Health, she provides support for anxiety, depression, and relationship concerns, helping clients build practical strategies for managing symptoms and achieving personal growth. Ellie works with a diverse range of patients, including those recently discharged from psychiatric hospitals, ensuring each personâs unique circumstances are considered in their treatment plan. Ellie is particularly passionate about working with clients who have recently been discharged from psychiatric care or are navigating current legal matters. She helps individuals manage anxiety, depression, and relationship issues, using interventions such as Cognitive Behavioral Therapy CBT, Acceptance and Commitment Therapy ACT, couples counseling, and parenting skills. She serves populations including LGBTQ individuals, adults with developmental disabilities, and both men and women, creating a safe and inclusive environment for healing and personal development. Outside of her professional work, Ellie enjoys baking, spending time with family and friends, and finding ways to bring joy into everyday life. Her approach to therapy combines clinical expertise with genuine empathy, helping clients explore their goals, strengthen coping strategies, and improve their quality of life. | AZ6: English | BC6: pt_NQMRQWBlP02-a4WEulV9ph | BE6: Practitioner - Full Profile | BG6: No | BI6: =IFERROR(INDEX(ValidationAndReference!P:P, MATCH(BE6, ValidationAndReference!Q:Q, 0)), "") | BJ6: =IFERROR(INDEX(ValidationAndReference!F:F, MATCH(D6, ValidationAndReference!G:G, 0)), "") | BK6: =IFERROR(INDEX(ValidationAndReference!F:F, MATCH(E6, ValidationAndReference!G:G, 0)), "") | BL6: =IFERROR(INDEX(ValidationAndReference!F:F, MATCH(F6, ValidationAndReference!G:G, 0)), "") | BM6: 352 | BR6: lo_El9sSz8bXUelY14uudbaUB | CL6: =IFERROR(INDEX(ValidationAndReference!V:V, MATCH(AZ6, ValidationAndReference!W:W, 0)), "") | CM6: =IFERROR(INDEX(ValidationAndReference!V:V, MATCH(BA6, ValidationAndReference!W:W, 0)), "") | CN6: =IFERROR(INDEX(ValidationAndReference!V:V, MATCH(BB6, ValidationAndReference!W:W, 0)), "") | CO6: 140 W Ge | CP6: Plymouth Meeting | CQ6: 19462 | CR6: PA | CS6: Rmantown Pike Ste 160 | CT6: No - Facility Zip
A7: Mary | B7: Wyman | C7: Female | D7: MSW | E7: LCSW | G7: =IFERROR(VLOOKUP(BM7, ValidationAndReference!J:K, 2, FALSE), "") | L7: Both | M7: LifeStance Health | N7: =IFERROR(INDEX(Location!X:X, MATCH(BR7, Location!W:W, 0)), "") | O7: =IFERROR(INDEX(Location!X:X, MATCH(BS7, Location!W:W, 0)), "") | S7: 1043882244 | T7: https://prod-clinicians-photo.s3.amazonaws.com/1043882244.jpg | U7: Master of Social Work (MSW), California State University - Long Beach | Z7: Mary Lukens Wyman, LCSW, helps individuals in California navigate lifeâs challenges with warmth, compassion, and clinical expertise. She provides a safe and collaborative environment for adults and teens to explore their emotions, develop coping skills, and create meaningful change. Mary works with clients experiencing anxiety, depression, bipolar disorder, and life transitions, offering evidencebased strategies to help them regain balance, improve emotional wellbeing, and enhance daily functioning. Drawing on more than two decades of experience, Mary takes a holistic approach that integrates Cognitive Behavioral Therapy CBT, Dialectical Behavior Therapy DBT, and mindfulness techniques. She believes in helping clients build insight into their thoughts and behaviors while developing tools to foster resilience and selfacceptance. Her therapeutic style emphasizes understanding, practical skillbuilding, and empowering clients to take an active role in their healing process. Mary has a particular passion for supporting individuals through grief, midlife transitions, and postpartum challenges. She is dedicated to helping clients navigate the emotional complexity of these experiences, promoting healing, and guiding them toward renewed purpose and stability. Whether clients are facing loss, adjusting to a new phase of life, or managing the emotional demands of parenthood, Mary provides a compassionate, steady presence. In addition to her clinical work, Mary has specialized experience working with members of the LGBTQ community, individuals with developmental disabilities, and first responders. She values inclusivity and approaches therapy with sensitivity to each clientâs unique life experiences. Outside the therapy room, Mary enjoys ballet, sewing, baking, gardening, biking, and spending time with her dogâall of which nurture her own sense of balance and creativity. | AZ7: English | BC7: pt_06Ie2RxfpECXX_EgrAt4yB | BE7: Practitioner - Full Profile | BG7: No | BI7: =IFERROR(INDEX(ValidationAndReference!P:P, MATCH(BE7, ValidationAndReference!Q:Q, 0)), "") | BJ7: =IFERROR(INDEX(ValidationAndReference!F:F, MATCH(D7, ValidationAndReference!G:G, 0)), "") | BK7: =IFERROR(INDEX(ValidationAndReference!F:F, MATCH(E7, ValidationAndReference!G:G, 0)), "") | BL7: =IFERROR(INDEX(ValidationAndReference!F:F, MATCH(F7, ValidationAndReference!G:G, 0)), "") | BM7: 352 | BR7: lo_Ot2lyEXJIEiykEAMRqlk1R | BS7: lo_H01GEikbXUW62tziz7NntR | CL7: =IFERROR(INDEX(ValidationAndReference!V:V, MATCH(AZ7, ValidationAndReference!W:W, 0)), "") | CM7: =IFERROR(INDEX(ValidationAndReference!V:V, MATCH(BA7, ValidationAndReference!W:W, 0)), "") | CN7: =IFERROR(INDEX(ValidationAndReference!V:V, MATCH(BB7, ValidationAndReference!W:W, 0)), "") | CO7: 4361 Latham St | CP7: Riverside | CQ7: 92501 | CR7: CA | CT7: No - Facility Zip
A8: Argenis | B8: Mendoza | C8: Male | D8: PMHNP-BC | G8: =IFERROR(VLOOKUP(BM8, ValidationAndReference!J:K, 2, FALSE), "") | L8: Both | M8: LifeStance Health | N8: =IFERROR(INDEX(Location!X:X, MATCH(BR8, Location!W:W, 0)), "") | O8: =IFERROR(INDEX(Location!X:X, MATCH(BS8, Location!W:W, 0)), "") | S8: 1114639911 | T8: https://prod-clinicians-photo.s3.amazonaws.com/1114639911.jpg | U8: MSN, West Coast University | Z8: Argenis Alberto Mendoza helps adults across California find clarity, stability, and meaningful relief through thoughtful, collaborative psychiatric care. As a prescriber at LifeStance Health, he supports patients ages 18 through 64 who are seeking help with conditions such as Anxiety, Depression, and ADHD. Argenis approaches treatment with warmth, clinical precision, and a deep respect for each personâs lived experience, ensuring that individuals throughout California receive accessible, patientcentered mental health support. Argenis frequently works with patients managing complex and interrelated concerns, including Bipolar Disorder, Sleep Disorders, Psychosis or Schizophrenia, and Menâs Issues. His practice also includes supporting individuals facing PostPartum Depression and Anxiety, as well as the emotional challenges associated with grief and trauma. With experience treating a wide range of psychiatric conditionsâand with additional areas of expertiseâhe tailors care plans to reflect each patientâs goals, strengths, and cultural context. He is especially passionate about serving Military and Veteran communities, as well as First Responders and Spanishspeaking individuals throughout Southern California. Argenis understands the unique stressors, identity shifts, and resilience inherent within these groups. His approach combines evidencebased medication management with supportive interventions such as Acceptance and Commitment Therapy and Mindfulness strategies to promote emotional regulation, healthier routines, and longterm wellness. Argenis also welcomes men seeking care for challenges ranging from performance stress to emotional suppression, offering a safe space to explore mental health with respect and confidentiality. He provides additional treatment options to meet diverse needs and collaborates closely with each patient to monitor progress and refine care over time. Outside of his clinical work, Argenis enjoys spending time with his family, working out when he can, and playing video games. | AZ8: English | BA8: Spanish | BC8: pt_06Ie2RxfpECXX_EgrAt4yB | BE8: Practitioner - Full Profile | BG8: No | BI8: =IFERROR(INDEX(ValidationAndReference!P:P, MATCH(BE8, ValidationAndReference!Q:Q, 0)), "") | BJ8: =IFERROR(INDEX(ValidationAndReference!F:F, MATCH(D8, ValidationAndReference!G:G, 0)), "") | BK8: =IFERROR(INDEX(ValidationAndReference!F:F, MATCH(E8, ValidationAndReference!G:G, 0)), "") | BL8: =IFERROR(INDEX(ValidationAndReference!F:F, MATCH(F8, ValidationAndReference!G:G, 0)), "") | BM8: 405 | BR8: lo_iNarPd6X7EqUW7XZ-ciqwB | BS8: lo_Ie5kAh72ZUGfcxcTAKUmMx | CL8: =IFERROR(INDEX(ValidationAndReference!V:V, MATCH(AZ8, ValidationAndReference!W:W, 0)), "") | CM8: =IFERROR(INDEX(ValidationAndReference!V:V, MATCH(BA8, ValidationAndReference!W:W, 0)), "") | CN8: =IFERROR(INDEX(ValidationAndReference!V:V, MATCH(BB8, ValidationAndReference!W:W, 0)), "") | CO8: 2300 Boswell Rd | CP8: Chula Vista | CQ8: 91914 | CR8: CA | CT8: No - Facility Zip
A9: Demetrius | B9: Smith | C9: Male | G9: =IFERROR(VLOOKUP(BM9, ValidationAndReference!J:K, 2, FALSE), "") | L9: Adult | M9: LifeStance Health | N9: =IFERROR(INDEX(Location!X:X, MATCH(BR9, Location!W:W, 0)), "") | O9: =IFERROR(INDEX(Location!X:X, MATCH(BS9, Location!W:W, 0)), "") | S9: 1114643400 | T9: https://prod-clinicians-photo.s3.amazonaws.com/1114643400.jpg | U9: Master of Science Psychology (MSPSY), Capella University | Z9: Demetrius Smith helps adults in Georgia navigate anxiety, depression, and trauma with a grounded, compassionate approach designed to support meaningful and lasting change. He provides individual therapy through LifeStance Health and works with adults across a wide range of life stages, offering a steady, collaborative space where clients can explore challenges and build new strategies for emotional wellbeing. A core focus of Demetriusâs work is addressing the impact of race and povertyinduced trauma, an area he is deeply committed to because of the significant ways these stressors affect mental health, resilience, and daily functioning. He integrates this passion into treatment by helping clients unpack complex emotional experiences, strengthen identity, and develop practical tools for navigating environments shaped by adversity. Demetrius specializes in anxiety, depression, and PTSDtrauma and offers additional clinical support for concerns such as ADHD and life transitions. His work frequently involves adults connected to adoption and foster care settings, first responders, and military and veteran communities. He uses evidencebased interventionsâincluding Cognitive Behavioral Therapy, Dialectical Behavior Therapy, and Mindfulnessâand provides additional approaches as clinically appropriate. Demetriusâs dedication to underserved and innercity communities has shaped his longterm mission to expand access, resources, and support systems for individuals who face structural barriers to mental health care. Outside of his clinical work, he enjoys traveling, learning from different cultures, and spending meaningful time with close friends and loved ones. Demetrius serves patients throughout Georgia through LifeStance Health | AZ9: English | BC9: pt_2QxThMYj9E2Jwx1NRXHtxR | BE9: Practitioner - Full Profile | BG9: No | BI9: =IFERROR(INDEX(ValidationAndReference!P:P, MATCH(BE9, ValidationAndReference!Q:Q, 0)), "") | BJ9: =IFERROR(INDEX(ValidationAndReference!F:F, MATCH(D9, ValidationAndReference!G:G, 0)), "") | BK9: =IFERROR(INDEX(ValidationAndReference!F:F, MATCH(E9, ValidationAndReference!G:G, 0)), "") | BL9: =IFERROR(INDEX(ValidationAndReference!F:F, MATCH(F9, ValidationAndReference!G:G, 0)), "") | BM9: 352 | BR9: lo_6OQNV1lLBk2cUdmy1xYQ7B | BS9: lo_2cQf2-zB_k-kwoVM1OfbfB | CL9: =IFERROR(INDEX(ValidationAndReference!V:V, MATCH(AZ9, ValidationAndReference!W:W, 0)), "") | CM9: =IFERROR(INDEX(ValidationAndReference!V:V, MATCH(BA9, ValidationAndReference!W:W, 0)), "") | CN9: =IFERROR(INDEX(ValidationAndReference!V:V, MATCH(BB9, ValidationAndReference!W:W, 0)), "") | CO9: 2801 Buford Hwy | CP9: Brookhaven | CQ9: 30329 | CR9: GA | CS9: Ste 100 | CT9: No - Facility Zip
A10: Terry | B10: Foytek | C10: Female | D10: Professional | E10: Counselor | F10: LPC Associate | G10: =IFERROR(VLOOKUP(BM10, ValidationAndReference!J:K, 2, FALSE), "") | L10: Pediatric | M10: LifeStance Health | N10: =IFERROR(INDEX(Location!X:X, MATCH(BR10, Location!W:W, 0)), "") | O10: =IFERROR(INDEX(Location!X:X, MATCH(BS10, Location!W:W, 0)), "") | S10: 1124997390 | T10: https://prod-clinicians-photo.s3.amazonaws.com/1124997390.jpg | U10: Master of Science in Education in Guidance & Counseling- Elementary School, University of Wisconsin Superior | Z10: Terry Foytek helps children and teens across Oregon strengthen emotional resilience, understand their feelings, and develop healthier ways to cope with lifeâs challenges. She creates a warm, supportive environment where young clientsâranging from early childhood through adolescenceâcan safely explore their concerns and build skills that support longterm wellbeing. Families seeking child therapy in Oregon often turn to Terry for her calm presence, practical strategies, and ability to connect with children at every developmental stage. Terry is especially passionate about supporting young people with ADHD, anxiety, and depressionâconditions that often interfere with school success, relationships, and confidence. She also works extensively with childhood behavior issues and grief, helping children process difficult emotions and learn new ways of communicating and problemsolving. Her approach is collaborative and rooted in evidencebased care that empowers both children and their caregivers. Terry has a dedicated focus on helping children who experience school avoidance, offering structured strategies and supportive guidance to reduce anxiety, rebuild motivation, and strengthen coping skills. She understands how stressful school resistance can be for families and works closely with them to create achievable plans that promote a smoother and more positive school experience. She also provides care for children with Autism Spectrum Disorders and offers additional expertise for families seeking specialized mental health support. Terry integrates Cognitive Behavioral Therapy and mindfulnessbased interventions into her work, tailoring each session to meet the unique needs of her young clients. Outside of her practice, Terry enjoys spending time with family and friends, camping in Oregonâs natural spaces, swimming, and unwinding with a favorite show on Netflix or Hulu. | AZ10: English | BC10: pt_7gzlz71zrUWLpb31Rir9Rh | BE10: Practitioner - Full Profile | BG10: No | BI10: =IFERROR(INDEX(ValidationAndReference!P:P, MATCH(BE10, ValidationAndReference!Q:Q, 0)), "") | BJ10: =IFERROR(INDEX(ValidationAndReference!F:F, MATCH(D10, ValidationAndReference!G:G, 0)), "") | BK10: =IFERROR(INDEX(ValidationAndReference!F:F, MATCH(E10, ValidationAndReference!G:G, 0)), "") | BL10: =IFERROR(INDEX(ValidationAndReference!F:F, MATCH(F10, ValidationAndReference!G:G, 0)), "") | BR10: lo_MoqSTGcEEEuZQyKUwN9mZh | CL10: =IFERROR(INDEX(ValidationAndReference!V:V, MATCH(AZ10, ValidationAndReference!W:W, 0)), "") | CM10: =IFERROR(INDEX(ValidationAndReference!V:V, MATCH(BA10, ValidationAndReference!W:W, 0)), "") | CN10: =IFERROR(INDEX(ValidationAndReference!V:V, MATCH(BB10, ValidationAndReference!W:W, 0)), "") | CO10: 44 Clb Rd | CP10: Eugene | CQ10: 97401 | CR10: OR | CT10: No - Facility Zip
A11: Deepa | B11: Samaroo | C11: Female | D11: MSW | E11: LCSW | G11: =IFERROR(VLOOKUP(BM11, ValidationAndReference!J:K, 2, FALSE), "") | L11: Both | M11: LifeStance Health | N11: =IFERROR(INDEX(Location!X:X, MATCH(BR11, Location!W:W, 0)), "") | O11: =IFERROR(INDEX(Location!X:X, MATCH(BS11, Location!W:W, 0)), "") | S11: 1144678178 | T11: https://prod-clinicians-photo.s3.amazonaws.com/1144678178.jpg | U11: Master of Social Work (MSW), Barry University | Z11: Deepa Samaroo helps children, teens, and adults across Florida navigate emotional challenges and find lasting balance through compassionate, evidencebased therapy. She creates a safe, supportive space where clients can explore lifeâs difficulties, develop coping skills, and strengthen emotional resilience. Deepa provides individual therapy to address a wide range of concerns, including anxiety, depression, trauma, and behavioral issues, helping clients of all ages achieve meaningful change and improved wellbeing. Deepa specializes in working with anxiety, trauma, and moodrelated challenges such as depression and bipolar disorder. Using therapeutic methods like Cognitive Behavioral Therapy CBT, Eye Movement Desensitization and Reprocessing EMDR, and mindfulnessbased interventions, she tailors treatment to meet each personâs unique needs. Her compassionate yet structured approach helps clients uncover patterns that contribute to distress and replace them with healthier, more effective ways of thinking and living. Deepa also provides care for individuals and families navigating complex experiences such as developmental disabilities, adoption or foster care transitions, and stress related to first responder and military service. She understands how these experiences can affect identity, relationships, and mental health, and she works collaboratively to foster healing and strength. In addition, she integrates her training in play therapy and traumafocused care to support younger clients and families in building trust and emotional awareness. Deepaâs work is guided by empathy, insight, and a deep belief in each personâs ability to grow and thrive. She enjoys playing piano and basketball with her husbandâactivities that reflect her appreciation for balance, connection, and creativity both inside and outside the therapy room. Deepa Samaroo practices at LifeStance Health and serves patients throughout Florida. | AZ11: English | BC11: pt_9pBYQvTE2k-LMM9_puwu-h | BE11: Practitioner - Full Profile | BG11: No | BI11: =IFERROR(INDEX(ValidationAndReference!P:P, MATCH(BE11, ValidationAndReference!Q:Q, 0)), "") | BJ11: =IFERROR(INDEX(ValidationAndReference!F:F, MATCH(D11, ValidationAndReference!G:G, 0)), "") | BK11: =IFERROR(INDEX(ValidationAndReference!F:F, MATCH(E11, ValidationAndReference!G:G, 0)), "") | BL11: =IFERROR(INDEX(ValidationAndReference!F:F, MATCH(F11, ValidationAndReference!G:G, 0)), "") | BM11: 352 | BR11: lo_db_IKeI9b0SAE8r0M2VOAx | BS11: lo_U1vZvhOvSUuEPnSfqZ2FvB | CL11: =IFERROR(INDEX(ValidationAndReference!V:V, MATCH(AZ11, ValidationAndReference!W:W, 0)), "") | CM11: =IFERROR(INDEX(ValidationAndReference!V:V, MATCH(BA11, ValidationAndReference!W:W, 0)), "") | CN11: =IFERROR(INDEX(ValidationAndReference!V:V, MATCH(BB11, ValidationAndReference!W:W, 0)), "") | CO11: 10125 West Colonial Dr | CP11: Ocoee | CQ11: 34761 | CR11: FL | CT11: No - Facility Zip
A12: Rebecca | B12: Moore | C12: Female | D12: MD | G12: =IFERROR(VLOOKUP(BM12, ValidationAndReference!J:K, 2, FALSE), "") | L12: Both | M12: LifeStance Health | N12: =IFERROR(INDEX(Location!X:X, MATCH(BR12, Location!W:W, 0)), "") | O12: =IFERROR(INDEX(Location!X:X, MATCH(BS12, Location!W:W, 0)), "") | S12: 1154549269 | T12: https://prod-clinicians-photo.s3.amazonaws.com/1154549269.jpg | U12: M.D., Pennsylvania State University | Z12: Dr. Rebecca Moore helps patients across Colorado find clarity, emotional steadiness, and improved daily functioning through thoughtful psychiatric care grounded in evidencebased treatment. At LifeStance Health, she supports adults and seniors with a warm, collaborative approach to medication management that prioritizes safety, symptom relief, and longterm wellbeing. She is especially passionate about treating trauma and PTSD, somatoform disorders, with expertise in Functional Neurological Disorders, and psychiatric conditions occurring in individuals with autism and other developmental disabilities. Dr. Moore is known for her ability to translate complex mindâbody interactions into practical steps that empower patients, and she approaches trauma work with a focus on restoring both internal stability and confidence in navigating daily life. Her clinical work centers on anxiety, depression, and PTSDtrauma, while also offering care for additional mental health concerns that benefit from targeted medication management. She integrates psychiatric expertise with therapeutic principles such as Cognitive Behavioral Therapy, Mindfulness, and Acceptance and Commitment Therapy. She frequently supports populations including individuals with autism spectrum or developmental disabilities, first responders, and military or veteran communities, and she provides additional services tailored to their unique needs. Outside of her clinical role, Dr. Moore enjoys hiking Coloradoâs trails, running, participating in dog sports, and relaxing with knitting projects that keep her grounded and creative. Dedicated to improving mental health across Colorado, Dr. Moore welcomes patients seeking compassionate, clinically informed medication management. | AZ12: English | BC12: pt_Xdjx281Ba06vQlN0Fjw0Tx | BE12: Practitioner - Full Profile | BG12: No | BI12: =IFERROR(INDEX(ValidationAndReference!P:P, MATCH(BE12, ValidationAndReference!Q:Q, 0)), "") | BJ12: =IFERROR(INDEX(ValidationAndReference!F:F, MATCH(D12, ValidationAndReference!G:G, 0)), "") | BK12: =IFERROR(INDEX(ValidationAndReference!F:F, MATCH(E12, ValidationAndReference!G:G, 0)), "") | BL12: =IFERROR(INDEX(ValidationAndReference!F:F, MATCH(F12, ValidationAndReference!G:G, 0)), "") | BM12: 122 | BR12: lo_FKnY_xlGOUmMpsZqHn3oqB | BS12: lo_y5BCumyPdEuPNBypHIR_8h | CL12: =IFERROR(INDEX(ValidationAndReference!V:V, MATCH(AZ12, ValidationAndReference!W:W, 0)), "") | CM12: =IFERROR(INDEX(ValidationAndReference!V:V, MATCH(BA12, ValidationAndReference!W:W, 0)), "") | CN12: =IFERROR(INDEX(ValidationAndReference!V:V, MATCH(BB12, ValidationAndReference!W:W, 0)), "") | CO12: 7780 S Broadway | CP12: Littleton | CQ12: 80122 | CR12: CO | CT12: No - Facility Zip
A13: Nisha | B13: Jambulingam | C13: Female | D13: DO | G13: =IFERROR(VLOOKUP(BM13, ValidationAndReference!J:K, 2, FALSE), "") | L13: Both | M13: LifeStance Health | N13: =IFERROR(INDEX(Location!X:X, MATCH(BR13, Location!W:W, 0)), "") | O13: =IFERROR(INDEX(Location!X:X, MATCH(BS13, Location!W:W, 0)), "") | S13: 1164097721 | T13: https://prod-clinicians-photo.s3.amazonaws.com/1164097721.jpg | U13: DO, Michigan State University | Z13: Dr. Nisha Jambulingam, DO, provides compassionate, evidencebased psychiatric care to adults across Michigan. She offers medication management for young adults through midlife and beyond, helping individuals better understand and manage conditions that affect daily life, work, and relationships. Her goal is to create a safe, collaborative space where patients feel heard and supported as they work toward greater stability and overall wellbeing. Dr. Jambulingam specializes in treating anxiety and depression, with additional expertise in supporting individuals who have experienced trauma and PTSD. She partners closely with patients to develop treatment plans that address both immediate symptoms and longterm goals. Her approach balances clinical precision with empathy, ensuring that each patientâs care is personalized and effective. Mindfulness is an integral part of her practice, and she often incorporates it into her work to help patients reduce stress, improve focus, and build resilience. Whether someone is navigating persistent anxiety, overcoming the impact of trauma, or seeking greater clarity in daily life, Dr. Jambulingam provides both medical expertise and practical tools for living with calm and confidence. Outside of her work, Dr. Jambulingam enjoys playing tennis and traveling, pursuits that reflect her value of both discipline and exploration. These interests mirror the balance she encourages her patients to cultivate in their own lives. | AZ13: English | BC13: pt_2fAaDQkuJkeZYNO0YaxkCh | BE13: Practitioner - Full Profile | BG13: No | BI13: =IFERROR(INDEX(ValidationAndReference!P:P, MATCH(BE13, ValidationAndReference!Q:Q, 0)), "") | BJ13: =IFERROR(INDEX(ValidationAndReference!F:F, MATCH(D13, ValidationAndReference!G:G, 0)), "") | BK13: =IFERROR(INDEX(ValidationAndReference!F:F, MATCH(E13, ValidationAndReference!G:G, 0)), "") | BL13: =IFERROR(INDEX(ValidationAndReference!F:F, MATCH(F13, ValidationAndReference!G:G, 0)), "") | BR13: lo_BRTn0txJR0mRQSB-7QLaGh | BS13: lo_Sjb2xJj8o0ummoGM57inNB | CL13: =IFERROR(INDEX(ValidationAndReference!V:V, MATCH(AZ13, ValidationAndReference!W:W, 0)), "") | CM13: =IFERROR(INDEX(ValidationAndReference!V:V, MATCH(BA13, ValidationAndReference!W:W, 0)), "") | CN13: =IFERROR(INDEX(ValidationAndReference!V:V, MATCH(BB13, ValidationAndReference!W:W, 0)), "") | CO13: 1760 S Telegraph Rd | CP13: Bloomfield Hills | CQ13: 48302 | CR13: MI | CT13: No - Facility Zip
A14: Frances | B14: Crespo Bonilla | C14: Female | D14: PsyD | G14: =IFERROR(VLOOKUP(BM14, ValidationAndReference!J:K, 2, FALSE), "") | L14: Both | M14: LifeStance Health | N14: =IFERROR(INDEX(Location!X:X, MATCH(BR14, Location!W:W, 0)), "") | O14: =IFERROR(INDEX(Location!X:X, MATCH(BS14, Location!W:W, 0)), "") | S14: 1174870620 | T14: https://prod-clinicians-photo.s3.amazonaws.com/1174870620.jpg | U14: PsyD, Ponce School of Medicine | Z14: Frances Crespo helps children, adolescents, and young adults across Florida understand their cognitive, developmental, and emotional strengths through comprehensive psychological and neuropsychological testing at LifeStance Health. She provides evaluations for young children through individuals in their midtwenties, offering families clarity, diagnostic accuracy, and actionable recommendations that support longterm growth. With a clinical focus on ADHD and childhood behavior issues, Frances specializes in assessments that guide treatment planning, school accommodations, and individualized support strategies. She frequently works with children on the autism spectrum, individuals with developmental disabilities, and LGBTQ youth, tailoring each evaluation to the personâs developmental stage, learning profile, and lived experiences. Her testing process is structured, compassionate, and grounded in evidencebased practice. Although no additional specialties are designated for emphasis, Frances is deeply committed to helping families make sense of complex behavioral and developmental concerns. She understands how overwhelming unanswered questions can feel, especially for caregivers seeking the right resources for a child. Through clear feedback, accessible reports, and thoughtful guidance, she empowers families to move forward with confidence and direction. Frances offers neuropsychological testing and additional assessment services designed to evaluate attention, learning, executive functioning, emotional functioning, and developmental needs. Her goal is to ensure that each client receives an evaluation that is both clinically rigorous and practically useful across school, home, and community settings. Outside of her clinical work, Frances enjoys reading, hiking, biking, running, exploring new cities, appreciating art, spending time in nature, listening to music, and being with her dogs. These interests help her maintain balance and enrich the warm, grounded approach she brings to patients and families throughout Florida. | AZ14: Spanish | BA14: English | BC14: pt_9pBYQvTE2k-LMM9_puwu-h | BE14: Practitioner - Full Profile | BG14: No | BI14: =IFERROR(INDEX(ValidationAndReference!P:P, MATCH(BE14, ValidationAndReference!Q:Q, 0)), "") | BJ14: =IFERROR(INDEX(ValidationAndReference!F:F, MATCH(D14, ValidationAndReference!G:G, 0)), "") | BK14: =IFERROR(INDEX(ValidationAndReference!F:F, MATCH(E14, ValidationAndReference!G:G, 0)), "") | BL14: =IFERROR(INDEX(ValidationAndReference!F:F, MATCH(F14, ValidationAndReference!G:G, 0)), "") | BM14: 337 | BR14: lo_b09w2r967E6ivRuRmRKZBx | BS14: lo_DvgivwgDbUqPLVF2z7n_qR | CL14: =IFERROR(INDEX(ValidationAndReference!V:V, MATCH(AZ14, ValidationAndReference!W:W, 0)), "") | CM14: =IFERROR(INDEX(ValidationAndReference!V:V, MATCH(BA14, ValidationAndReference!W:W, 0)), "") | CN14: =IFERROR(INDEX(ValidationAndReference!V:V, MATCH(BB14, ValidationAndReference!W:W, 0)), "") | CO14: 260 Lookout Place | CP14: Maitland | CQ14: 32751 | CR14: FL | CT14: No - Facility Zip
A15: Kristen | B15: Cook | C15: Female | D15: LPC | G15: =IFERROR(VLOOKUP(BM15, ValidationAndReference!J:K, 2, FALSE), "") | L15: Both | M15: LifeStance Health | N15: =IFERROR(INDEX(Location!X:X, MATCH(BR15, Location!W:W, 0)), "") | O15: =IFERROR(INDEX(Location!X:X, MATCH(BS15, Location!W:W, 0)), "") | S15: 1235017286 | T15: https://prod-clinicians-photo.s3.amazonaws.com/1235017286.jpg | U15: Masters of Arts (MA), Texas A&M University - San Antonio | Z15: Mrs. Kristen Cook helps children, teens, adults, and seniors across Texas navigate lifeâs challenges with greater resilience and emotional balance. Practicing at LifeStance Health, she provides individual therapy in a supportive, engaging environment that encourages growth and healing. Kristen understands that every stage of life brings its own unique struggles, and she works collaboratively with each client to build practical coping skills, strengthen relationships, and foster lasting emotional wellbeing. Kristenâs approach integrates warmth, humor, and honesty to create a safe space where clients can express themselves freely and work toward meaningful change. Drawing from her background as an educator and counselor, she offers specialized care for anxiety, depression, and trauma, helping clients uncover the underlying causes of distress while developing tools to manage symptoms effectively. Her use of Eye Movement Desensitization and Reprocessing EMDR therapy supports healing from traumatic experiences and empowers clients to move forward with confidence and clarity. Kristen is especially passionate about working with individuals managing ADHD, PTSD, and moodrelated challenges such as depression and bipolar disorder. She believes in helping clients rediscover their strengths and find stability, whether they are coping with childhood behavioral issues, academic stress, or major life transitions. Kristen also provides affirming care for individuals with developmental differences and members of the LGBTQ community, ensuring that every person feels valued and understood throughout the therapeutic process. Outside of her clinical work, Kristen enjoys reading and creating crafts activities that inspire creativity, mindfulness, and a sense of calm that she often encourages her clients to cultivate in their own lives. | AZ15: English | BC15: pt_vOTgX4FPvUOFJaL-VrSO1B | BE15: Practitioner - Full Profile | BG15: No | BI15: =IFERROR(INDEX(ValidationAndReference!P:P, MATCH(BE15, ValidationAndReference!Q:Q, 0)), "") | BJ15: =IFERROR(INDEX(ValidationAndReference!F:F, MATCH(D15, ValidationAndReference!G:G, 0)), "") | BK15: =IFERROR(INDEX(ValidationAndReference!F:F, MATCH(E15, ValidationAndReference!G:G, 0)), "") | BL15: =IFERROR(INDEX(ValidationAndReference!F:F, MATCH(F15, ValidationAndReference!G:G, 0)), "") | BM15: 352 | BR15: lo_2they0iD2kme2mzq2VEnRR | BS15: lo_RBNdmowsJ0iESMl8yHZwHB | CL15: =IFERROR(INDEX(ValidationAndReference!V:V, MATCH(AZ15, ValidationAndReference!W:W, 0)), "") | CM15: =IFERROR(INDEX(ValidationAndReference!V:V, MATCH(BA15, ValidationAndReference!W:W, 0)), "") | CN15: =IFERROR(INDEX(ValidationAndReference!V:V, MATCH(BB15, ValidationAndReference!W:W, 0)), "") | CO15: 540 Oak Ctr Dr | CP15: San Antonio | CQ15: 78258 | CR15: TX | CT15: No - Facility Address (try converting 'Ctr' to 'CTR'; try converting 'Ctr' to 'CEN'; try converting 'Ctr' to 'CENT'; try converting 'Ctr' to 'CENTER'; try converting 'Ctr' to 'CENTR'; try converting 'Ctr' to 'CENTRE'; try converting 'Ctr' to 'CNTER'; try converting 'Ctr' to 'CNTR'; try converting 'Ctr' to 'CTR'; try converting 'Dr' to 'DR'; try converting 'Dr' to 'DR'; try converting 'Dr' to 'DRIV'; try converting 'Dr' to 'DRIVE'; try converting 'Dr' to 'DRV'), Facility Zip
A16: Stephanie | B16: Rivera | C16: Female | D16: LCSW | G16: =IFERROR(VLOOKUP(BM16, ValidationAndReference!J:K, 2, FALSE), "") | L16: Both | M16: LifeStance Health | N16: =IFERROR(INDEX(Location!X:X, MATCH(BR16, Location!W:W, 0)), "") | O16: =IFERROR(INDEX(Location!X:X, MATCH(BS16, Location!W:W, 0)), "") | S16: 1255091823 | T16: https://prod-clinicians-photo.s3.amazonaws.com/1255091823.jpg | U16: Master of Social Work (MSW), Boston University | Z16: Stephanie Rivera, LCSW, helps individuals in North Carolina navigate lifeâs challenges with compassion, collaboration, and evidencebased care. She works with children, teens, and adults to address a variety of emotional and behavioral concerns, helping her clients develop the tools they need to manage stress, improve relationships, and build resilience. Stephanie believes therapy should feel like a safe and supportive partnership where growth happens through understanding and empowerment. Stephanie specializes in treating anxiety and depression, drawing on her clinical experience to help clients better understand their thoughts, emotions, and behaviors. Using approaches such as Cognitive Behavioral Therapy CBT and Mindfulness, she supports individuals in identifying unhelpful patterns and creating meaningful change. Her therapeutic style is warm, goaloriented, and adapted to each personâs unique needs and strengths. A particular passion for Stephanie is working with members of the LGBTQ community, especially youth and young adults exploring identity and belonging. She creates an affirming environment where clients can process experiences of stress, anxiety, or selfdoubt while learning to embrace authenticity and selfacceptance. Stephanieâs work in this area reflects her deep commitment to fostering inclusion, empowerment, and emotional wellbeing across diverse backgrounds. Outside of her clinical work, Stephanie enjoys exploring new coffee shops, staying active through exercise, cooking creative meals, and relaxing with video games. | AZ16: English | BA16: Spanish | BC16: pt_JC64JlmALEqey1kShhAOLh | BE16: Practitioner - Full Profile | BG16: No | BI16: =IFERROR(INDEX(ValidationAndReference!P:P, MATCH(BE16, ValidationAndReference!Q:Q, 0)), "") | BJ16: =IFERROR(INDEX(ValidationAndReference!F:F, MATCH(D16, ValidationAndReference!G:G, 0)), "") | BK16: =IFERROR(INDEX(ValidationAndReference!F:F, MATCH(E16, ValidationAndReference!G:G, 0)), "") | BL16: =IFERROR(INDEX(ValidationAndReference!F:F, MATCH(F16, ValidationAndReference!G:G, 0)), "") | BM16: 352 | BR16: lo_CASH_KCrKUGIOjgNUDFxbB | BS16: lo_LozPsG8CpEq6Gr3e5WS5Ph | CL16: =IFERROR(INDEX(ValidationAndReference!V:V, MATCH(AZ16, ValidationAndReference!W:W, 0)), "") | CM16: =IFERROR(INDEX(ValidationAndReference!V:V, MATCH(BA16, ValidationAndReference!W:W, 0)), "") | CN16: =IFERROR(INDEX(ValidationAndReference!V:V, MATCH(BB16, ValidationAndReference!W:W, 0)), "") | CO16: 10620 Park Rd | CP16: Charlotte | CQ16: 28210 | CR16: NC | CT16: No - Facility Zip
A17: Jessica | B17: Kastin | C17: Female | D17: PsyD | G17: =IFERROR(VLOOKUP(BM17, ValidationAndReference!J:K, 2, FALSE), "") | L17: Both | M17: LifeStance Health | N17: =IFERROR(INDEX(Location!X:X, MATCH(BR17, Location!W:W, 0)), "") | O17: =IFERROR(INDEX(Location!X:X, MATCH(BS17, Location!W:W, 0)), "") | S17: 1316839657 | T17: https://prod-clinicians-photo.s3.amazonaws.com/1316839657.jpg | U17: PsyD, Pace University at New York City | Z17: Jessica Kastin provides compassionate, expert psychological testing and support for children, adolescents, and young adults across New York. At LifeStance Health, she is committed to helping clients and their families better understand emotional, behavioral, and developmental concerns through comprehensive evaluations. Jessica creates a safe, affirming space where individuals feel seen and supported, using her deep clinical insight to guide each assessment and treatment recommendation. With a strong focus on early childhood and adolescent development, Jessica specializes in psychological testing for ADHD, anxiety, and childhood behavior issues. She is particularly passionate about helping children and teens navigate the unique challenges related to trauma, school avoidance, and emotional regulation. Her assessments help families gain clarity, access resources, and advocate for the educational and therapeutic support their children need to thrive. Jessica has extensive experience working with youth in foster care and adoption, children on the autism spectrum, and individuals with developmental disabilities. She is especially attuned to the needs of LGBTQ youth and integrates a strengthsbased, identityaffirming approach into her work. Her evaluations are not just diagnostic toolsâthey are empowering experiences that give voice to a clientâs strengths and struggles while informing meaningful paths forward. Outside of her clinical work, Jessica enjoys cooking, baking, reading, and spending time with family and friends. Her warm, approachable style helps build trust with children and caregivers alike, making the evaluation process feel collaborative and supportive. | AZ17: English | BC17: pt_fvIkMYo3p0S6q91GK083xh | BE17: Practitioner - Full Profile | BG17: No | BI17: =IFERROR(INDEX(ValidationAndReference!P:P, MATCH(BE17, ValidationAndReference!Q:Q, 0)), "") | BJ17: =IFERROR(INDEX(ValidationAndReference!F:F, MATCH(D17, ValidationAndReference!G:G, 0)), "") | BK17: =IFERROR(INDEX(ValidationAndReference!F:F, MATCH(E17, ValidationAndReference!G:G, 0)), "") | BL17: =IFERROR(INDEX(ValidationAndReference!F:F, MATCH(F17, ValidationAndReference!G:G, 0)), "") | BM17: 337 | BR17: lo_ckiP2HKaREq2OT5YyitjcQ | BS17: lo_-JYceYOvcUCW42M5kdtHnA | CL17: =IFERROR(INDEX(ValidationAndReference!V:V, MATCH(AZ17, ValidationAndReference!W:W, 0)), "") | CM17: =IFERROR(INDEX(ValidationAndReference!V:V, MATCH(BA17, ValidationAndReference!W:W, 0)), "") | CN17: =IFERROR(INDEX(ValidationAndReference!V:V, MATCH(BB17, ValidationAndReference!W:W, 0)), "") | CO17: 10 Pearl St | CP17: Port Chester | CQ17: 10573 | CR17: NY | CT17: No - Facility Zip
A18: Sherri | B18: Creel | C18: Female | D18: LMHC | E18: MS | G18: =IFERROR(VLOOKUP(BM18, ValidationAndReference!J:K, 2, FALSE), "") | L18: Both | M18: LifeStance Health | N18: =IFERROR(INDEX(Location!X:X, MATCH(BR18, Location!W:W, 0)), "") | O18: =IFERROR(INDEX(Location!X:X, MATCH(BS18, Location!W:W, 0)), "") | S18: 1326168774 | T18: https://prod-clinicians-photo.s3.amazonaws.com/1326168774.jpg | U18: Master of Science in Counseling Psychology, Nova University | Z18: Sherri Lynn Creel helps individuals across Florida navigate emotional challenges with clarity, resilience, and practical therapeutic support. She provides care for children, adolescents, teens, adults, and seniors, offering a steady and compassionate presence for those seeking meaningful progress in their mental health. At LifeStance Health, she works with patients to address the concerns that most impact their daily lives, fostering growth, stability, and wellbeing throughout Florida. Sherri specializes in treating anxiety, depression, and ADHD, using evidencebased methods that help patients better understand their symptoms and build effective coping strategies. She also supports individuals experiencing childhood behavior issues and womenâs mental health concerns, offering additional expertise across a breadth of emotional and behavioral conditions. Her approach emphasizes collaboration, skill building, and helping each patient connect with their strengths. She is particularly passionate about supporting adoption and foster care populations, recognizing the unique emotional, relational, and developmental experiences that shape their mental health needs. Sherri works to create a safe and grounded therapeutic space where children, teens, and adults in these communities can process experiences, strengthen identity, and develop tools for longterm resilience. Sherri offers treatment rooted in Cognitive Behavioral Therapy, Dialectical Behavior Therapy, and mindfulnessbased approaches, with additional interventions available when needed. She tailors therapy to each patientâs goals, integrating parentingfocused strategies when working with families and younger clients. Outside the therapy room, Sherri is an avid runner and enjoys playing pickleball with her husband. She also loves visiting her sons in New York City and Tennessee, spending quality time with family whenever she can. Serving patients throughout Florida, Sherri Lynn Creel welcomes individuals and families seeking thoughtful, experienced mental health care. | AZ18: English | BC18: pt_9pBYQvTE2k-LMM9_puwu-h | BE18: Practitioner - Full Profile | BG18: No | BI18: =IFERROR(INDEX(ValidationAndReference!P:P, MATCH(BE18, ValidationAndReference!Q:Q, 0)), "") | BJ18: =IFERROR(INDEX(ValidationAndReference!F:F, MATCH(D18, ValidationAndReference!G:G, 0)), "") | BK18: =IFERROR(INDEX(ValidationAndReference!F:F, MATCH(E18, ValidationAndReference!G:G, 0)), "") | BL18: =IFERROR(INDEX(ValidationAndReference!F:F, MATCH(F18, ValidationAndReference!G:G, 0)), "") | BM18: 352 | BR18: lo_TNqCKeFZ70ylvjPe3aqLhh | BS18: lo_W97PaBwV8kyxcJadT4VXth | CL18: =IFERROR(INDEX(ValidationAndReference!V:V, MATCH(AZ18, ValidationAndReference!W:W, 0)), "") | CM18: =IFERROR(INDEX(ValidationAndReference!V:V, MATCH(BA18, ValidationAndReference!W:W, 0)), "") | CN18: =IFERROR(INDEX(ValidationAndReference!V:V, MATCH(BB18, ValidationAndReference!W:W, 0)), "") | CO18: 8400 Red Bug Lk Rd | CP18: Oviedo | CQ18: 32765 | CR18: FL | CT18: No - Facility Zip
A19: Barbara | B19: Nunley | C19: Female | D19: MA | E19: LMFT | F19: 157877 | G19: =IFERROR(VLOOKUP(BM19, ValidationAndReference!J:K, 2, FALSE), "") | L19: Both | M19: LifeStance Health | N19: =IFERROR(INDEX(Location!X:X, MATCH(BR19, Location!W:W, 0)), "") | O19: =IFERROR(INDEX(Location!X:X, MATCH(BS19, Location!W:W, 0)), "") | S19: 1346910312 | T19: https://prod-clinicians-photo.s3.amazonaws.com/1346910312.jpg | U19: Master in Counseling (MC), National University | Z19: Mrs. Barbara GloriaâEscobedo Nunley helps individuals and couples across California navigate lifeâs challenges with compassion, clarity, and evidencebased care. She supports adults and seniors through struggles with anxiety, depression, relationship stress, and other emotional or relational concerns, offering a grounded therapeutic presence for those seeking meaningful change. Barbara is passionate about guiding clients through significant life transitions, including midlife shifts, laterlife adjustments, and reproductive or postpartum challenges. She has a special interest in supporting individuals experiencing perinatal and postpartum mood disorders, helping them understand their symptoms, strengthen coping skills, and rebuild confidence during periods that can feel overwhelming or isolating. Her work is deeply informed by respect for each personâs unique history, identity, and resilience. Barbara also brings extensive experience working with First Responders, members of the LGBTQ community, and individuals connected to adoption and foster care. She commonly assists clients facing anxiety, grief, trauma, and couplesâ issues, and she offers additional areas of expertise to meet a wide range of mental health needs. Her therapeutic approach integrates Cognitive Behavioral Therapy, Acceptance and Commitment Therapy, Dialectical Behavior Therapy, and CouplesMarital Counseling, grounded in mindfulness and practical skillbuilding. Clients appreciate Barbaraâs downtoearth style, collaborative mindset, and ability to create a safe, nonjudgmental space where growth feels possible. Outside the therapy room, she enjoys kayaking with her family, engaging with her community through art and music, practicing yoga, supporting local animal rescues, and finding restoration through both DIY and professional spa days. | AZ19: English | BA19: Spanish | BC19: pt_06Ie2RxfpECXX_EgrAt4yB | BE19: Practitioner - Full Profile | BG19: No | BI19: =IFERROR(INDEX(ValidationAndReference!P:P, MATCH(BE19, ValidationAndReference!Q:Q, 0)), "") | BJ19: =IFERROR(INDEX(ValidationAndReference!F:F, MATCH(D19, ValidationAndReference!G:G, 0)), "") | BK19: =IFERROR(INDEX(ValidationAndReference!F:F, MATCH(E19, ValidationAndReference!G:G, 0)), "") | BL19: =IFERROR(INDEX(ValidationAndReference!F:F, MATCH(F19, ValidationAndReference!G:G, 0)), "") | BM19: 352 | BR19: lo_xWY-UiMAMU2c1c_enwoBjg | CL19: =IFERROR(INDEX(ValidationAndReference!V:V, MATCH(AZ19, ValidationAndReference!W:W, 0)), "") | CM19: =IFERROR(INDEX(ValidationAndReference!V:V, MATCH(BA19, ValidationAndReference!W:W, 0)), "") | CN19: =IFERROR(INDEX(ValidationAndReference!V:V, MATCH(BB19, ValidationAndReference!W:W, 0)), "") | CO19: 8881 | CP19: La Mesa | CQ19: 91942 | CR19: CA | CS19: Fletcher Pkwy | CT19: No - Facility Zip
A20: Barbara | B20: Nunley | C20: Female | D20: MA | E20: LMFT | F20: 157877 | G20: =IFERROR(VLOOKUP(BM20, ValidationAndReference!J:K, 2, FALSE), "") | L20: Both | M20: LifeStance Health | N20: =IFERROR(INDEX(Location!X:X, MATCH(BR20, Location!W:W, 0)), "") | O20: =IFERROR(INDEX(Location!X:X, MATCH(BS20, Location!W:W, 0)), "") | S20: 1346910312 | T20: https://prod-clinicians-photo.s3.amazonaws.com/1346910312.jpg | U20: Master in Counseling (MC), National University | Z20: Mrs. Barbara GloriaâEscobedo Nunley helps individuals and couples across California navigate lifeâs challenges with compassion, clarity, and evidencebased care. She supports adults and seniors through struggles with anxiety, depression, relationship stress, and other emotional or relational concerns, offering a grounded therapeutic presence for those seeking meaningful change. Barbara is passionate about guiding clients through significant life transitions, including midlife shifts, laterlife adjustments, and reproductive or postpartum challenges. She has a special interest in supporting individuals experiencing perinatal and postpartum mood disorders, helping them understand their symptoms, strengthen coping skills, and rebuild confidence during periods that can feel overwhelming or isolating. Her work is deeply informed by respect for each personâs unique history, identity, and resilience. Barbara also brings extensive experience working with First Responders, members of the LGBTQ community, and individuals connected to adoption and foster care. She commonly assists clients facing anxiety, grief, trauma, and couplesâ issues, and she offers additional areas of expertise to meet a wide range of mental health needs. Her therapeutic approach integrates Cognitive Behavioral Therapy, Acceptance and Commitment Therapy, Dialectical Behavior Therapy, and CouplesMarital Counseling, grounded in mindfulness and practical skillbuilding. Clients appreciate Barbaraâs downtoearth style, collaborative mindset, and ability to create a safe, nonjudgmental space where growth feels possible. Outside the therapy room, she enjoys kayaking with her family, engaging with her community through art and music, practicing yoga, supporting local animal rescues, and finding restoration through both DIY and professional spa days. | AZ20: English | BA20: Spanish | BC20: pt_06Ie2RxfpECXX_EgrAt4yB | BE20: Practitioner - Full Profile | BG20: No | BI20: =IFERROR(INDEX(ValidationAndReference!P:P, MATCH(BE20, ValidationAndReference!Q:Q, 0)), "") | BJ20: =IFERROR(INDEX(ValidationAndReference!F:F, MATCH(D20, ValidationAndReference!G:G, 0)), "") | BK20: =IFERROR(INDEX(ValidationAndReference!F:F, MATCH(E20, ValidationAndReference!G:G, 0)), "") | BL20: =IFERROR(INDEX(ValidationAndReference!F:F, MATCH(F20, ValidationAndReference!G:G, 0)), "") | BM20: 352 | BR20: lo_xWY-UiMAMU2c1c_enwoBjg | CL20: =IFERROR(INDEX(ValidationAndReference!V:V, MATCH(AZ20, ValidationAndReference!W:W, 0)), "") | CM20: =IFERROR(INDEX(ValidationAndReference!V:V, MATCH(BA20, ValidationAndReference!W:W, 0)), "") | CN20: =IFERROR(INDEX(ValidationAndReference!V:V, MATCH(BB20, ValidationAndReference!W:W, 0)), "") | CO20: 8881 | CP20: La Mesa | CQ20: 91942 | CR20: CA | CS20: Fletcher Pkwy | CT20: No - Facility Zip
A21: Barbara | B21: Nunley | C21: Female | D21: MA | E21: LMFT | F21: 157877 | G21: =IFERROR(VLOOKUP(BM21, ValidationAndReference!J:K, 2, FALSE), "") | L21: Both | M21: LifeStance Health | N21: =IFERROR(INDEX(Location!X:X, MATCH(BR21, Location!W:W, 0)), "") | O21: =IFERROR(INDEX(Location!X:X, MATCH(BS21, Location!W:W, 0)), "") | S21: 1346910312 | T21: https://prod-clinicians-photo.s3.amazonaws.com/1346910312.jpg | U21: Master in Counseling (MC), National University | Z21: Mrs. Barbara GloriaâEscobedo Nunley helps individuals and couples across California navigate lifeâs challenges with compassion, clarity, and evidencebased care. She supports adults and seniors through struggles with anxiety, depression, relationship stress, and other emotional or relational concerns, offering a grounded therapeutic presence for those seeking meaningful change. Barbara is passionate about guiding clients through significant life transitions, including midlife shifts, laterlife adjustments, and reproductive or postpartum challenges. She has a special interest in supporting individuals experiencing perinatal and postpartum mood disorders, helping them understand their symptoms, strengthen coping skills, and rebuild confidence during periods that can feel overwhelming or isolating. Her work is deeply informed by respect for each personâs unique history, identity, and resilience. Barbara also brings extensive experience working with First Responders, members of the LGBTQ community, and individuals connected to adoption and foster care. She commonly assists clients facing anxiety, grief, trauma, and couplesâ issues, and she offers additional areas of expertise to meet a wide range of mental health needs. Her therapeutic approach integrates Cognitive Behavioral Therapy, Acceptance and Commitment Therapy, Dialectical Behavior Therapy, and CouplesMarital Counseling, grounded in mindfulness and practical skillbuilding. Clients appreciate Barbaraâs downtoearth style, collaborative mindset, and ability to create a safe, nonjudgmental space where growth feels possible. Outside the therapy room, she enjoys kayaking with her family, engaging with her community through art and music, practicing yoga, supporting local animal rescues, and finding restoration through both DIY and professional spa days. | AZ21: English | BA21: Spanish | BC21: pt_06Ie2RxfpECXX_EgrAt4yB | BE21: Practitioner - Full Profile | BG21: No | BI21: =IFERROR(INDEX(ValidationAndReference!P:P, MATCH(BE21, ValidationAndReference!Q:Q, 0)), "") | BJ21: =IFERROR(INDEX(ValidationAndReference!F:F, MATCH(D21, ValidationAndReference!G:G, 0)), "") | BK21: =IFERROR(INDEX(ValidationAndReference!F:F, MATCH(E21, ValidationAndReference!G:G, 0)), "") | BL21: =IFERROR(INDEX(ValidationAndReference!F:F, MATCH(F21, ValidationAndReference!G:G, 0)), "") | BM21: 352 | BR21: lo__otK4G5zQ0-cPl63bNOZcx | BS21: lo_-xOnxHsdcUKNrJW38Nx64B | CL21: =IFERROR(INDEX(ValidationAndReference!V:V, MATCH(AZ21, ValidationAndReference!W:W, 0)), "") | CM21: =IFERROR(INDEX(ValidationAndReference!V:V, MATCH(BA21, ValidationAndReference!W:W, 0)), "") | CN21: =IFERROR(INDEX(ValidationAndReference!V:V, MATCH(BB21, ValidationAndReference!W:W, 0)), "") | CO21: 3609 Ocean Rnch Blvd | CP21: Oceanside | CQ21: 92056 | CR21: CA | CT21: No - Facility Zip
A22: Barbara | B22: Nunley | C22: Female | D22: MA | E22: LMFT | F22: 157877 | G22: =IFERROR(VLOOKUP(BM22, ValidationAndReference!J:K, 2, FALSE), "") | L22: Both | M22: LifeStance Health | N22: =IFERROR(INDEX(Location!X:X, MATCH(BR22, Location!W:W, 0)), "") | O22: =IFERROR(INDEX(Location!X:X, MATCH(BS22, Location!W:W, 0)), "") | S22: 1346910312 | T22: https://prod-clinicians-photo.s3.amazonaws.com/1346910312.jpg | U22: Master in Counseling (MC), National University | Z22: Mrs. Barbara GloriaâEscobedo Nunley helps individuals and couples across California navigate lifeâs challenges with compassion, clarity, and evidencebased care. She supports adults and seniors through struggles with anxiety, depression, relationship stress, and other emotional or relational concerns, offering a grounded therapeutic presence for those seeking meaningful change. Barbara is passionate about guiding clients through significant life transitions, including midlife shifts, laterlife adjustments, and reproductive or postpartum challenges. She has a special interest in supporting individuals experiencing perinatal and postpartum mood disorders, helping them understand their symptoms, strengthen coping skills, and rebuild confidence during periods that can feel overwhelming or isolating. Her work is deeply informed by respect for each personâs unique history, identity, and resilience. Barbara also brings extensive experience working with First Responders, members of the LGBTQ community, and individuals connected to adoption and foster care. She commonly assists clients facing anxiety, grief, trauma, and couplesâ issues, and she offers additional areas of expertise to meet a wide range of mental health needs. Her therapeutic approach integrates Cognitive Behavioral Therapy, Acceptance and Commitment Therapy, Dialectical Behavior Therapy, and CouplesMarital Counseling, grounded in mindfulness and practical skillbuilding. Clients appreciate Barbaraâs downtoearth style, collaborative mindset, and ability to create a safe, nonjudgmental space where growth feels possible. Outside the therapy room, she enjoys kayaking with her family, engaging with her community through art and music, practicing yoga, supporting local animal rescues, and finding restoration through both DIY and professional spa days. | AZ22: English | BA22: Spanish | BC22: pt_06Ie2RxfpECXX_EgrAt4yB | BE22: Practitioner - Full Profile | BG22: No | BI22: =IFERROR(INDEX(ValidationAndReference!P:P, MATCH(BE22, ValidationAndReference!Q:Q, 0)), "") | BJ22: =IFERROR(INDEX(ValidationAndReference!F:F, MATCH(D22, ValidationAndReference!G:G, 0)), "") | BK22: =IFERROR(INDEX(ValidationAndReference!F:F, MATCH(E22, ValidationAndReference!G:G, 0)), "") | BL22: =IFERROR(INDEX(ValidationAndReference!F:F, MATCH(F22, ValidationAndReference!G:G, 0)), "") | BM22: 352 | BR22: lo__otK4G5zQ0-cPl63bNOZcx | BS22: lo_-xOnxHsdcUKNrJW38Nx64B | CL22: =IFERROR(INDEX(ValidationAndReference!V:V, MATCH(AZ22, ValidationAndReference!W:W, 0)), "") | CM22: =IFERROR(INDEX(ValidationAndReference!V:V, MATCH(BA22, ValidationAndReference!W:W, 0)), "") | CN22: =IFERROR(INDEX(ValidationAndReference!V:V, MATCH(BB22, ValidationAndReference!W:W, 0)), "") | CO22: 3609 Ocean Rnch Blvd | CP22: Oceanside | CQ22: 92056 | CR22: CA | CT22: No - Facility Zip
A23: Faiz | B23: Faseehuddin | C23: Male | D23: MD | G23: =IFERROR(VLOOKUP(BM23, ValidationAndReference!J:K, 2, FALSE), "") | L23: Both | M23: LifeStance Health | N23: =IFERROR(INDEX(Location!X:X, MATCH(BR23, Location!W:W, 0)), "") | O23: =IFERROR(INDEX(Location!X:X, MATCH(BS23, Location!W:W, 0)), "") | S23: 1407147259 | T23: https://prod-clinicians-photo.s3.amazonaws.com/1407147259.jpg | U23: MD, University of Tennessee Health Science Center | Z23: Dr. Faiz Faseehuddin helps adults and seniors across Colorado find balance and stability through evidencebased mental health care that is compassionate, individualized, and comprehensive. At LifeStance Health, he provides treatment for a wide range of conditions including anxiety, depression, bipolar disorder, and traumarelated issues. With a deep understanding of how biological, psychological, and social factors intertwine, Dr. Faseehuddin partners with his patients to create treatment plans that promote lasting emotional wellness and improved quality of life. Dr. Faseehuddin is especially passionate about helping individuals facing complex challenges such as ADHD, substance use concerns, and sleep disorders. He is also experienced in guiding patients through life transitions, mood disorders, and healthrelated stress. Using a combination of medication management, psychotherapy, and innovative treatments such as Transcranial Magnetic Stimulation TMS, he helps patients achieve meaningful progress and sustainable recovery. A central focus of Dr. Faseehuddinâs work lies in addressing ADHD, anxiety, and mood disordersâareas where he brings both clinical precision and genuine empathy. He understands how these conditions can disrupt relationships, work, and selfesteem, and heâs dedicated to helping his patients rebuild confidence and connection. By integrating Cognitive Behavioral Therapy CBT, mindfulness practices, and Acceptance and Commitment Therapy ACT, he empowers patients to gain insight, build resilience, and live with greater purpose. Dr. Faseehuddin also provides specialized support for diverse populations, including veterans, first responders, and members of the LGBTQ community, tailoring his care to the unique experiences and strengths each individual brings to therapy. Outside of his clinical work, Dr. Faseehuddin is an avid outdoorsman who enjoys hiking and camping throughout Coloradoâs mountain landscapes. He also finds creative fulfillment through music, painting, and drawing activities that reflect his belief in the healing power of expression and balance. Dr. Faseehuddin welcomes patients from across Colorado who are seeking a thoughtful and collaborative approach to mental health care. | AZ23: English | BA23: Hindi | BC23: pt_Xdjx281Ba06vQlN0Fjw0Tx | BE23: Practitioner - Full Profile | BG23: No | BI23: =IFERROR(INDEX(ValidationAndReference!P:P, MATCH(BE23, ValidationAndReference!Q:Q, 0)), "") | BJ23: =IFERROR(INDEX(ValidationAndReference!F:F, MATCH(D23, ValidationAndReference!G:G, 0)), "") | BK23: =IFERROR(INDEX(ValidationAndReference!F:F, MATCH(E23, ValidationAndReference!G:G, 0)), "") | BL23: =IFERROR(INDEX(ValidationAndReference!F:F, MATCH(F23, ValidationAndReference!G:G, 0)), "") | BM23: 122 | BR23: lo_4kHOXsMeCE6ZebdxMvkErR | BS23: lo_QEFqaF9cakWZ_dXcVviSIh | CL23: =IFERROR(INDEX(ValidationAndReference!V:V, MATCH(AZ23, ValidationAndReference!W:W, 0)), "") | CM23: =IFERROR(INDEX(ValidationAndReference!V:V, MATCH(BA23, ValidationAndReference!W:W, 0)), "") | CN23: =IFERROR(INDEX(ValidationAndReference!V:V, MATCH(BB23, ValidationAndReference!W:W, 0)), "") | CO23: 777 29th St | CP23: Boulder | CQ23: 80303 | CR23: CO | CS23: Ste 500 | CT23: No - Facility Zip
A24: Robert | B24: Lloyd | C24: Male | D24: LPC | G24: =IFERROR(VLOOKUP(BM24, ValidationAndReference!J:K, 2, FALSE), "") | L24: Both | M24: LifeStance Health | N24: =IFERROR(INDEX(Location!X:X, MATCH(BR24, Location!W:W, 0)), "") | O24: =IFERROR(INDEX(Location!X:X, MATCH(BS24, Location!W:W, 0)), "") | S24: 1407410103 | T24: https://prod-clinicians-photo.s3.amazonaws.com/1407410103.jpg | U24: Master of Science (MS), Abilene Christian University | Z24: Robert Lloyd helps children, teens, and adults across Texas find greater emotional balance and resilience through compassionate, evidencebased mental health care. Practicing at LifeStance Health, he provides individual, family, and group therapy designed to help clients overcome anxiety, depression, trauma, and relationship challenges. Robert works collaboratively with each person to create a safe, supportive space for growth, healing, and longterm wellbeing. Drawing from extensive experience across inpatient and outpatient settings, Robert integrates Cognitive Behavioral Therapy CBT, Dialectical Behavior Therapy DBT, and Eye Movement Desensitization and Reprocessing EMDR to guide clients toward meaningful change. His clinical approach is practical, goaloriented, and grounded in empathy helping clients develop insight, strengthen coping skills, and build emotional flexibility. Robert is especially passionate about supporting individuals facing ADHD, substance use challenges, and traumarelated concerns such as PTSD. He believes in addressing both the emotional and behavioral aspects of these conditions, helping clients regain control of their lives while fostering selfcompassion and confidence. Whether heâs helping a teen struggling with focus and school stress or an adult navigating recovery and resilience, Robert tailors each treatment plan to meet the unique needs of the individual. He also provides specialized support for populations such as first responders, military veterans, and members of the LGBTQ community, offering a space where clients feel understood and respected. In addition to his counseling expertise, Robert offers psychological testing to help clarify diagnoses and guide personalized treatment recommendations. Outside of his clinical work, Robert enjoys staying active by playing tennis and spending time at the movie theater. These activities help him maintain balance and creativity, values he brings into his therapeutic practice. Serving communities throughout Texas, Robert Lloyd combines deep clinical knowledge with genuine compassion to support clients on their journey toward improved mental health and quality of life. | AZ24: English | BC24: pt_vOTgX4FPvUOFJaL-VrSO1B | BE24: Practitioner - Full Profile | BG24: No | BI24: =IFERROR(INDEX(ValidationAndReference!P:P, MATCH(BE24, ValidationAndReference!Q:Q, 0)), "") | BJ24: =IFERROR(INDEX(ValidationAndReference!F:F, MATCH(D24, ValidationAndReference!G:G, 0)), "") | BK24: =IFERROR(INDEX(ValidationAndReference!F:F, MATCH(E24, ValidationAndReference!G:G, 0)), "") | BL24: =IFERROR(INDEX(ValidationAndReference!F:F, MATCH(F24, ValidationAndReference!G:G, 0)), "") | BM24: 352 | BR24: lo_ldXN2nAAhU6qAuor91CrpB | BS24: lo_Xd10ODB6PE-Q7PwWG6Ca0h | CL24: =IFERROR(INDEX(ValidationAndReference!V:V, MATCH(AZ24, ValidationAndReference!W:W, 0)), "") | CM24: =IFERROR(INDEX(ValidationAndReference!V:V, MATCH(BA24, ValidationAndReference!W:W, 0)), "") | CN24: =IFERROR(INDEX(ValidationAndReference!V:V, MATCH(BB24, ValidationAndReference!W:W, 0)), "") | CO24: 23051 Kingwood Place Dr | CP24: Kingwood | CQ24: 77339 | CR24: TX | CT24: No - Facility Zip
A25: Blaire | B25: Crutchley | C25: Female | D25: MA | E25: LPC | F25: NCC | G25: =IFERROR(VLOOKUP(BM25, ValidationAndReference!J:K, 2, FALSE), "") | L25: Both | M25: LifeStance Health | N25: =IFERROR(INDEX(Location!X:X, MATCH(BR25, Location!W:W, 0)), "") | O25: =IFERROR(INDEX(Location!X:X, MATCH(BS25, Location!W:W, 0)), "") | S25: 1407678394 | T25: https://prod-clinicians-photo.s3.amazonaws.com/1407678394.jpg | U25: Masters of Arts (MA), Northwestern University | Z25: Blaire Crutchley, LPC, helps individuals and families in Ohio feel understood, supported, and empowered to overcome lifeâs challenges. She offers a warm, collaborative space where children, teens, and adults can explore their emotions, build confidence, and develop practical skills for lasting positive change. Whether a client is navigating anxiety, depression, or difficulties at home or school, Blaire walks alongside them with compassion and respect every step of the way. Blaire is especially passionate about helping young people and families overcome childhood behavior concerns and the stressors that may come with emotional or developmental challenges. She frequently supports children and adolescents who struggle with focus, communication, social relationships, or managing big feelings. With experience in both individual and family therapy, she partners closely with caregivers to create sustainable strategies that work in daily life. As a Licensed Professional Counselor at LifeStance Health, Blaire provides care for a wide range of concerns, including anxiety, ADHD, trauma, and behavioral challenges, with additional experience supporting those working through gender identity exploration. She incorporates evidencebased interventions such as Cognitive Behavioral Therapy CBT, Dialectical Behavior Therapy DBT, and Acceptance and Commitment Therapy ACT. Blaire also draws from faithbased approaches and mindfulness when desired, tailoring treatment to each personâs values and needs. She is committed to supporting diverse populations, including LGBTQ individuals, first responders, military members and veterans, autism spectrum and developmental disability communities, and those with head injuries or adoption and foster care experiences. When she isnât working with clients, Blaire enjoys bringing the Pacific Northwest spirit to the Buckeye State. Sheâs an avid Seattle sports fan and loves golfing, playing soccer and softball, traveling, and spending time with her friends, family, and her sweet Rottweiler, Griffey. She also enjoys learning new things and staying active in her community. | AZ25: English | BC25: pt_5pmdAWg-0UuZBxgghGIfih | BE25: Practitioner - Full Profile | BG25: No | BI25: =IFERROR(INDEX(ValidationAndReference!P:P, MATCH(BE25, ValidationAndReference!Q:Q, 0)), "") | BJ25: =IFERROR(INDEX(ValidationAndReference!F:F, MATCH(D25, ValidationAndReference!G:G, 0)), "") | BK25: =IFERROR(INDEX(ValidationAndReference!F:F, MATCH(E25, ValidationAndReference!G:G, 0)), "") | BL25: =IFERROR(INDEX(ValidationAndReference!F:F, MATCH(F25, ValidationAndReference!G:G, 0)), "") | BM25: 352 | BR25: lo_kbIslV_PLk2psDgztnSb1R | BS25: lo_iJy4GfT7Fk-9E6zCN8t_Wx | CL25: =IFERROR(INDEX(ValidationAndReference!V:V, MATCH(AZ25, ValidationAndReference!W:W, 0)), "") | CM25: =IFERROR(INDEX(ValidationAndReference!V:V, MATCH(BA25, ValidationAndReference!W:W, 0)), "") | CN25: =IFERROR(INDEX(ValidationAndReference!V:V, MATCH(BB25, ValidationAndReference!W:W, 0)), "") | CO25: 484 County Line Rd W | CP25: Westerville | CQ25: 43082 | CR25: OH | CS25: Ste 130 | CT25: No - Facility Zip
A26: JoAnna | B26: Sendejo | C26: Female | D26: PsyD | G26: =IFERROR(VLOOKUP(BM26, ValidationAndReference!J:K, 2, FALSE), "") | L26: Both | M26: LifeStance Health | N26: =IFERROR(INDEX(Location!X:X, MATCH(BR26, Location!W:W, 0)), "") | O26: =IFERROR(INDEX(Location!X:X, MATCH(BS26, Location!W:W, 0)), "") | S26: 1417572256 | T26: https://prod-clinicians-photo.s3.amazonaws.com/1417572256.jpg | U26: Doctor of Psychology PsyD, Pacific University | Z26: JoAnna Sendejo helps children, teens, and young adults in Utah build emotional resilience, strengthen family relationships, and find healing from lifeâs challenges. She provides compassionate and evidencebased care for individuals and families navigating anxiety, ADHD, depression, trauma, and behavioral or developmental concerns. With a warm and collaborative approach, JoAnna creates a safe space where clients can explore their emotions, understand the roots of their struggles, and learn practical tools for growth and selfacceptance. JoAnna specializes in working with children and adolescents experiencing behavioral and emotional regulation challenges, including those with neurodevelopmental differences such as Autism Spectrum Disorders or developmental disabilities. She also supports families in improving communication and connection, helping caregivers better understand and respond to their childâs emotional and developmental needs. Her work emphasizes the importance of early intervention and family involvement in fostering longterm emotional wellness. JoAnna has a deep passion for early childhood mental health and perinatal care. She offers support to parents and caregivers adjusting to pregnancy, postpartum transitions, and the complex emotions that can accompany new parenthood. Her expertise in early childhood neurodevelopmental assessment and psychological testing allows her to provide insight into learning, attention, and emotional challenges, helping families gain clarity and access the right resources for support. Her therapeutic style integrates Cognitive Behavioral Therapy CBT, Acceptance and Commitment Therapy ACT, mindfulness, and family therapy techniques, grounded in a traumainformed and culturally sensitive framework. She is also fluent in Spanish and provides bilingual services to ensure inclusivity and accessibility for diverse families. Outside of her work at LifeStance Health, JoAnna enjoys playing or listening to music, exploring new hiking trails, trying new foods, and spending time with her partner and two cats. | AZ26: English | BA26: Spanish | BC26: pt_8xtAi0NRrUG9gZKouBnyBh | BE26: Practitioner - Full Profile | BG26: No | BI26: =IFERROR(INDEX(ValidationAndReference!P:P, MATCH(BE26, ValidationAndReference!Q:Q, 0)), "") | BJ26: =IFERROR(INDEX(ValidationAndReference!F:F, MATCH(D26, ValidationAndReference!G:G, 0)), "") | BK26: =IFERROR(INDEX(ValidationAndReference!F:F, MATCH(E26, ValidationAndReference!G:G, 0)), "") | BL26: =IFERROR(INDEX(ValidationAndReference!F:F, MATCH(F26, ValidationAndReference!G:G, 0)), "") | BM26: 337 | BR26: lo_AkIbOMVubUSWXt3NwWLFPx | BS26: lo_TSKmifpHBki86FuTvomo8x | CL26: =IFERROR(INDEX(ValidationAndReference!V:V, MATCH(AZ26, ValidationAndReference!W:W, 0)), "") | CM26: =IFERROR(INDEX(ValidationAndReference!V:V, MATCH(BA26, ValidationAndReference!W:W, 0)), "") | CN26: =IFERROR(INDEX(ValidationAndReference!V:V, MATCH(BB26, ValidationAndReference!W:W, 0)), "") | CO26: 5965 S 900 E | CP26: Murray | CQ26: 84121 | CR26: UT | CT26: No - Facility Zip
A27: JoAnna | B27: Sendejo | C27: Female | D27: PsyD | G27: =IFERROR(VLOOKUP(BM27, ValidationAndReference!J:K, 2, FALSE), "") | L27: Both | M27: LifeStance Health | N27: =IFERROR(INDEX(Location!X:X, MATCH(BR27, Location!W:W, 0)), "") | O27: =IFERROR(INDEX(Location!X:X, MATCH(BS27, Location!W:W, 0)), "") | S27: 1417572256 | T27: https://prod-clinicians-photo.s3.amazonaws.com/1417572256.jpg | U27: Doctor of Psychology PsyD, Pacific University | Z27: JoAnna Sendejo helps children, teens, and young adults in Utah build emotional resilience, strengthen family relationships, and find healing from lifeâs challenges. She provides compassionate and evidencebased care for individuals and families navigating anxiety, ADHD, depression, trauma, and behavioral or developmental concerns. With a warm and collaborative approach, JoAnna creates a safe space where clients can explore their emotions, understand the roots of their struggles, and learn practical tools for growth and selfacceptance. JoAnna specializes in working with children and adolescents experiencing behavioral and emotional regulation challenges, including those with neurodevelopmental differences such as Autism Spectrum Disorders or developmental disabilities. She also supports families in improving communication and connection, helping caregivers better understand and respond to their childâs emotional and developmental needs. Her work emphasizes the importance of early intervention and family involvement in fostering longterm emotional wellness. JoAnna has a deep passion for early childhood mental health and perinatal care. She offers support to parents and caregivers adjusting to pregnancy, postpartum transitions, and the complex emotions that can accompany new parenthood. Her expertise in early childhood neurodevelopmental assessment and psychological testing allows her to provide insight into learning, attention, and emotional challenges, helping families gain clarity and access the right resources for support. Her therapeutic style integrates Cognitive Behavioral Therapy CBT, Acceptance and Commitment Therapy ACT, mindfulness, and family therapy techniques, grounded in a traumainformed and culturally sensitive framework. She is also fluent in Spanish and provides bilingual services to ensure inclusivity and accessibility for diverse families. Outside of her work at LifeStance Health, JoAnna enjoys playing or listening to music, exploring new hiking trails, trying new foods, and spending time with her partner and two cats. | AZ27: English | BA27: Spanish | BC27: pt_8xtAi0NRrUG9gZKouBnyBh | BE27: Practitioner - Full Profile | BG27: No | BI27: =IFERROR(INDEX(ValidationAndReference!P:P, MATCH(BE27, ValidationAndReference!Q:Q, 0)), "") | BJ27: =IFERROR(INDEX(ValidationAndReference!F:F, MATCH(D27, ValidationAndReference!G:G, 0)), "") | BK27: =IFERROR(INDEX(ValidationAndReference!F:F, MATCH(E27, ValidationAndReference!G:G, 0)), "") | BL27: =IFERROR(INDEX(ValidationAndReference!F:F, MATCH(F27, ValidationAndReference!G:G, 0)), "") | BM27: 337 | BR27: lo_AkIbOMVubUSWXt3NwWLFPx | BS27: lo_TSKmifpHBki86FuTvomo8x | CL27: =IFERROR(INDEX(ValidationAndReference!V:V, MATCH(AZ27, ValidationAndReference!W:W, 0)), "") | CM27: =IFERROR(INDEX(ValidationAndReference!V:V, MATCH(BA27, ValidationAndReference!W:W, 0)), "") | CN27: =IFERROR(INDEX(ValidationAndReference!V:V, MATCH(BB27, ValidationAndReference!W:W, 0)), "") | CO27: 5965 S 900 E | CP27: Murray | CQ27: 84121 | CR27: UT | CT27: No - Facility Zip
A28: Eric | B28: Adams | C28: Male | D28: PMHNP-BC | E28: BCJ | G28: =IFERROR(VLOOKUP(BM28, ValidationAndReference!J:K, 2, FALSE), "") | L28: Both | M28: LifeStance Health | N28: =IFERROR(INDEX(Location!X:X, MATCH(BR28, Location!W:W, 0)), "") | O28: =IFERROR(INDEX(Location!X:X, MATCH(BS28, Location!W:W, 0)), "") | S28: 1427719699 | T28: https://prod-clinicians-photo.s3.amazonaws.com/1427719699.jpg | U28: Master of Science in Nursing (MSN), Northern Kentucky University | Z28: Eric Adams, PMHNP, helps patients in Ohio navigate complex mental health challenges with compassionate, personalized care. He provides expert medication management for individuals facing conditions such as ADHD, anxiety, bipolar disorder, depression, and substance use concerns. Eric works closely with patients to develop treatment plans that balance symptom relief, safety, and longterm wellness, creating a supportive environment for growth and recovery. Eric has a particular focus on thought disorders and supporting noncisgender populations, providing inclusive care tailored to each individualâs needs. He also assists patients who are navigating legal or occupational complexities, including recently discharged psychiatric patients, courtordered treatment, workersâ compensation cases, and disability paperwork. His approach blends clinical expertise with understanding, helping patients regain stability and improve their quality of life. To support mental health recovery, Eric incorporates interventions such as Cognitive Behavioral Therapy CBT, Acceptance and Commitment Therapy ACT, mindfulness practices, and genderaffirmative medical readiness evaluations. He partners with diverse populations, including LGBTQ individuals, first responders, and those with developmental disabilities, offering a safe space to address both mental health and life stressors. Outside of his practice at LifeStance Health, Eric enjoys traveling, photography, staying active through fitness, and spending quality time with his wife and their dog, Findlay. His dedication to holistic wellbeing and patientcentered care reflects his commitment to helping individuals across | AZ28: English | BC28: pt_06Ie2RxfpECXX_EgrAt4yB | BE28: Practitioner - Full Profile | BG28: No | BI28: =IFERROR(INDEX(ValidationAndReference!P:P, MATCH(BE28, ValidationAndReference!Q:Q, 0)), "") | BJ28: =IFERROR(INDEX(ValidationAndReference!F:F, MATCH(D28, ValidationAndReference!G:G, 0)), "") | BK28: =IFERROR(INDEX(ValidationAndReference!F:F, MATCH(E28, ValidationAndReference!G:G, 0)), "") | BL28: =IFERROR(INDEX(ValidationAndReference!F:F, MATCH(F28, ValidationAndReference!G:G, 0)), "") | BM28: 405 | BR28: lo_5jf6GoqAjEmxMsdFBSB-dg | CL28: =IFERROR(INDEX(ValidationAndReference!V:V, MATCH(AZ28, ValidationAndReference!W:W, 0)), "") | CM28: =IFERROR(INDEX(ValidationAndReference!V:V, MATCH(BA28, ValidationAndReference!W:W, 0)), "") | CN28: =IFERROR(INDEX(ValidationAndReference!V:V, MATCH(BB28, ValidationAndReference!W:W, 0)), "") | CO28: 6770 Cincinnati Dayton Rd | CP28: Liberty Township | CQ28: 45044 | CR28: OH | CT28: No - Facility Zip
A29: Kelly | B29: Correa | C29: Female | D29: PhD | G29: =IFERROR(VLOOKUP(BM29, ValidationAndReference!J:K, 2, FALSE), "") | L29: Both | M29: LifeStance Health | N29: =IFERROR(INDEX(Location!X:X, MATCH(BR29, Location!W:W, 0)), "") | O29: =IFERROR(INDEX(Location!X:X, MATCH(BS29, Location!W:W, 0)), "") | S29: 1427948157 | T29: https://prod-clinicians-photo.s3.amazonaws.com/1427948157.jpg | U29: Doctor of Philosophy (PHD), University of Illinois Chicago | Z29: Kelly Correa helps adults across California navigate lifeâs challenges with clarity, compassion, and evidencebased care. She supports individuals facing concerns such as anxiety, depression, and trauma, and offers empowering strategies that help patients build resilience and regain a sense of control. Kelly provides individual therapy for adults of all ages, including young adults, adults in midlife, and seniors, ensuring that care is responsive to each stage of life. Kelly is particularly passionate about helping patients manage ADHD, insomnia and other sleeprelated concerns, and the emotional impact of ongoing medical conditions. She uses practical, researchsupported tools to help individuals strengthen focus, improve sleep, and develop coping strategies that enhance both mental and physical wellbeing. Her approach integrates proven techniques that guide patients in creating meaningful, sustainable change. In her broader work at LifeStance Health, Kelly specializes in treating anxiety, depression, and PTSDtrauma, and has extensive experience supporting LGBTQ adults, women, and military veterans. She draws from Cognitive Behavioral Therapy, Acceptance and Commitment Therapy, and Dialectical Behavior Therapy, and offers additional evidencebased interventions tailored to each patientâs needs. Kelly began practicing in 2016 and believes that therapy should be a collaborative, validating experience where patients feel supported while also challenged to grow. She focuses on helping individuals understand unhelpful patterns, build emotional flexibility, and reconnect with their values. Outside of work, Kelly enjoys spending time with family and friends, discovering new shows and music, exploring local spots around San Diego, and staying grounded through strength training and mindful movement. | AZ29: English | BC29: pt_06Ie2RxfpECXX_EgrAt4yB | BE29: Practitioner - Full Profile | BG29: No | BI29: =IFERROR(INDEX(ValidationAndReference!P:P, MATCH(BE29, ValidationAndReference!Q:Q, 0)), "") | BJ29: =IFERROR(INDEX(ValidationAndReference!F:F, MATCH(D29, ValidationAndReference!G:G, 0)), "") | BK29: =IFERROR(INDEX(ValidationAndReference!F:F, MATCH(E29, ValidationAndReference!G:G, 0)), "") | BL29: =IFERROR(INDEX(ValidationAndReference!F:F, MATCH(F29, ValidationAndReference!G:G, 0)), "") | BM29: 337 | BR29: lo_iVo5k_uLb0iC3LzCFD2s9g | BS29: lo_0yeenQ9Dc0-EYvNcfi8zLg | CL29: =IFERROR(INDEX(ValidationAndReference!V:V, MATCH(AZ29, ValidationAndReference!W:W, 0)), "") | CM29: =IFERROR(INDEX(ValidationAndReference!V:V, MATCH(BA29, ValidationAndReference!W:W, 0)), "") | CN29: =IFERROR(INDEX(ValidationAndReference!V:V, MATCH(BB29, ValidationAndReference!W:W, 0)), "") | CO29: 6386 Alvarado Ct | CP29: San Diego | CQ29: 92120 | CR29: CA | CS29: Ste 210 | CT29: No - Facility Zip
A30: Hazel | B30: Frasier | C30: Female | D30: MSN | G30: =IFERROR(VLOOKUP(BM30, ValidationAndReference!J:K, 2, FALSE), "") | L30: Both | M30: LifeStance Health | N30: =IFERROR(INDEX(Location!X:X, MATCH(BR30, Location!W:W, 0)), "") | O30: =IFERROR(INDEX(Location!X:X, MATCH(BS30, Location!W:W, 0)), "") | S30: 1437493285 | T30: https://prod-clinicians-photo.s3.amazonaws.com/1437493285.jpg | U30: Master of Science in Nursing, University of South Alabama | Z30: Hazel Frasier helps teens, adults, and seniors across Florida find balance and stability in their mental health. With a compassionate, collaborative approach, she supports patients in managing conditions such as anxiety, depression, bipolar disorder, and PTSD, offering both individual therapy and medication management to promote lasting wellbeing. Hazel is especially passionate about helping individuals navigate complex challenges such as psychotic disorders, grief, and laterlife transitions. She takes time to truly understand each patientâs experiences and goals, creating care plans that address both immediate needs and longterm wellness. By incorporating techniques like Acceptance and Commitment Therapy ACT and mindfulness practices, she helps her patients build resilience, develop effective coping strategies, and improve their overall quality of life. Her clinical expertise extends to supporting diverse populations, including members of the LGBTQ community, individuals with autism spectrum disorders, and military veterans. Hazel believes in fostering a safe and respectful space where patients can openly discuss their challenges and actively participate in their path to healing. Outside of her work at LifeStance Health, Hazel enjoys spending time with her family, reading a good book, taking morning walks, and occasionally bingewatching a favorite Netflix series. Hazel is committed to supporting patients across Florida with evidencebased, individualized care that meets them where they are. | AZ30: English | BC30: pt_9pBYQvTE2k-LMM9_puwu-h | BE30: Practitioner - Full Profile | BG30: No | BI30: =IFERROR(INDEX(ValidationAndReference!P:P, MATCH(BE30, ValidationAndReference!Q:Q, 0)), "") | BJ30: =IFERROR(INDEX(ValidationAndReference!F:F, MATCH(D30, ValidationAndReference!G:G, 0)), "") | BK30: =IFERROR(INDEX(ValidationAndReference!F:F, MATCH(E30, ValidationAndReference!G:G, 0)), "") | BL30: =IFERROR(INDEX(ValidationAndReference!F:F, MATCH(F30, ValidationAndReference!G:G, 0)), "") | BM30: 405 | BR30: lo_D7UPQsM22Ea5L8UvZT7o7h | BS30: lo_pXK_eibjxk63tKYrZUHJBx | CL30: =IFERROR(INDEX(ValidationAndReference!V:V, MATCH(AZ30, ValidationAndReference!W:W, 0)), "") | CM30: =IFERROR(INDEX(ValidationAndReference!V:V, MATCH(BA30, ValidationAndReference!W:W, 0)), "") | CN30: =IFERROR(INDEX(ValidationAndReference!V:V, MATCH(BB30, ValidationAndReference!W:W, 0)), "") | CO30: 9995 Gate Pkwy N | CP30: Jacksonville | CQ30: 32246 | CR30: FL | CT30: No - Facility Zip
A31: Emily | B31: Masi | C31: Female | D31: PMHNP | G31: =IFERROR(VLOOKUP(BM31, ValidationAndReference!J:K, 2, FALSE), "") | L31: Both | M31: LifeStance Health | N31: =IFERROR(INDEX(Location!X:X, MATCH(BR31, Location!W:W, 0)), "") | O31: =IFERROR(INDEX(Location!X:X, MATCH(BS31, Location!W:W, 0)), "") | S31: 1437881265 | T31: https://prod-clinicians-photo.s3.amazonaws.com/1437881265.jpg | U31: MSN, University of Southern California | Z31: Emily Masi, PMHNP, helps children, teens, adults, and seniors across California access compassionate, highquality psychiatric care designed to support their stability, resilience, and overall wellbeing. She provides medication management with a warm, attentive, and highly personalized approach, helping patients navigate conditions such as anxiety, depression, ADHD, and traumarelated symptoms. Serving communities throughout California, she partners closely with individuals and families to create treatment plans that feel both clinically effective and deeply supportive. Emily is especially passionate about womenâs mental health and reproductive psychiatry, including care related to puberty, perinatal and postpartum challenges, hormonal transitions, menopause, and reproductive stressors. She also brings strong expertise in supporting individuals experiencing laterlife transitions, grief, and insomnia. Her work centers on helping patients understand the biological, emotional, and environmental factors shaping their symptoms so they can regain a sense of control and confidence in daily life. In addition to her core focus areas, Emily offers medical procedure evaluations and psychological testing, along with Christian counseling for those who wish to integrate faith into treatment. She has extensive experience supporting autism spectrum disorders, developmental disabilities, and first responders and military veterans, and she provides care for additional populations with unique and diverse needs. She also assists with workersâ compensation and disabilityrelated documentation as part of comprehensive patient support. Outside of her clinical work, Emily enjoys exploring new places with her familyâfrom quick weekend getaways around Los Angeles to international travel. She stays actively involved in her community through her book club, volunteer work at her childrenâs school, youth sports, and local event planning. Her home life is rooted in faith, cultural connection, and shared traditions, and she loves celebrating her familyâs Hawaiian and Italian heritage through food, stories, and dance. | AZ31: English | BC31: pt_06Ie2RxfpECXX_EgrAt4yB | BE31: Practitioner - Full Profile | BG31: No | BI31: =IFERROR(INDEX(ValidationAndReference!P:P, MATCH(BE31, ValidationAndReference!Q:Q, 0)), "") | BJ31: =IFERROR(INDEX(ValidationAndReference!F:F, MATCH(D31, ValidationAndReference!G:G, 0)), "") | BK31: =IFERROR(INDEX(ValidationAndReference!F:F, MATCH(E31, ValidationAndReference!G:G, 0)), "") | BL31: =IFERROR(INDEX(ValidationAndReference!F:F, MATCH(F31, ValidationAndReference!G:G, 0)), "") | BM31: 401 | BR31: lo_JC1OjG-aaECZmyGsWUFFkx | BS31: lo_CfPuuOChLUOiTywLG_Ob5R | CL31: =IFERROR(INDEX(ValidationAndReference!V:V, MATCH(AZ31, ValidationAndReference!W:W, 0)), "") | CM31: =IFERROR(INDEX(ValidationAndReference!V:V, MATCH(BA31, ValidationAndReference!W:W, 0)), "") | CN31: =IFERROR(INDEX(ValidationAndReference!V:V, MATCH(BB31, ValidationAndReference!W:W, 0)), "") | CO31: 1000 N Sepulveda Blvd | CP31: Manhattan Beach | CQ31: 90266 | CR31: CA | CT31: No - Facility Zip
A32: Juanita | B32: Bentley | C32: Female | D32: Juanita | E32: M. | F32: Bentley | G32: =IFERROR(VLOOKUP(BM32, ValidationAndReference!J:K, 2, FALSE), "") | L32: Both | M32: LifeStance Health | N32: =IFERROR(INDEX(Location!X:X, MATCH(BR32, Location!W:W, 0)), "") | O32: =IFERROR(INDEX(Location!X:X, MATCH(BS32, Location!W:W, 0)), "") | S32: 1457776791 | T32: https://prod-clinicians-photo.s3.amazonaws.com/1457776791.jpg | U32: Master in Counseling (MC), Mercer University | Z32: Juanita Bentley helps adults across Georgia move toward greater clarity, steadiness, and emotional wellbeing by offering a warm, structured, and clinically informed space for healing. She supports adults and seniors through life transitions, stress, relationship strain, and longstanding patterns that may feel difficult to break. Her approach is collaborative and rooted in helping clients feel seen, supported, and capable of meaningful change. Juanitaâs key specialties include anxiety, depression, and PTSDtrauma, and she offers care for additional concerns such as grief, sleep disordersinsomnia, and womenâs issues. Her work often centers on helping individuals build coping strategies, strengthen emotional resilience, and navigate midlife or laterlife transitions with confidence and clarity. As a LifeStance Health clinician, she offers interventions tailored to each personâs unique story. She primarily incorporates Cognitive Behavioral Therapy, Acceptance and Commitment Therapy, and Mindfulness while offering additional approaches when clinically appropriate. She supports diverse populations, including first responders, militaryveterans, and men, and she welcomes adults seeking a grounded, practical path to better emotional health. Juanitaâs personal passionsâdancing, music, painting, art projects, reading, exploring great food, traveling, and learning about science and ancient historyâhelp fuel her creativity and curiosity, allowing her to bring genuine warmth and connection into the therapeutic process. Juanita is honored to serve adults throughout Georgia and looks forward to supporting individuals on their journey toward greater balance and emotional wellness. | AZ32: English | BC32: pt_1B8gjiHjQE6sp9VlxGW08R | BE32: Practitioner - Full Profile | BG32: No | BI32: =IFERROR(INDEX(ValidationAndReference!P:P, MATCH(BE32, ValidationAndReference!Q:Q, 0)), "") | BJ32: =IFERROR(INDEX(ValidationAndReference!F:F, MATCH(D32, ValidationAndReference!G:G, 0)), "") | BK32: =IFERROR(INDEX(ValidationAndReference!F:F, MATCH(E32, ValidationAndReference!G:G, 0)), "") | BL32: =IFERROR(INDEX(ValidationAndReference!F:F, MATCH(F32, ValidationAndReference!G:G, 0)), "") | BM32: 352 | BR32: lo_o5XJjjvBnES6Qp_cI7FEOh | CL32: =IFERROR(INDEX(ValidationAndReference!V:V, MATCH(AZ32, ValidationAndReference!W:W, 0)), "") | CM32: =IFERROR(INDEX(ValidationAndReference!V:V, MATCH(BA32, ValidationAndReference!W:W, 0)), "") | CN32: =IFERROR(INDEX(ValidationAndReference!V:V, MATCH(BB32, ValidationAndReference!W:W, 0)), "") | CO32: 3991 Hwy 78 W | CP32: Snellville | CQ32: 30039 | CR32: GA | CT32: No - Facility Address (try converting 'Hwy' to 'HWY'; try converting 'Hwy' to 'HIGHWAY'; try converting 'Hwy' to 'HIGHWY'; try converting 'Hwy' to 'HIWAY'; try converting 'Hwy' to 'HIWY'; try converting 'Hwy' to 'HWAY'; try converting 'Hwy' to 'HWY'), Facility Zip
A33: Brittany | B33: Schwarten | C33: Female | D33: LCSW | G33: =IFERROR(VLOOKUP(BM33, ValidationAndReference!J:K, 2, FALSE), "") | L33: Both | M33: LifeStance Health | N33: =IFERROR(INDEX(Location!X:X, MATCH(BR33, Location!W:W, 0)), "") | O33: =IFERROR(INDEX(Location!X:X, MATCH(BS33, Location!W:W, 0)), "") | S33: 1457804833 | T33: https://prod-clinicians-photo.s3.amazonaws.com/1457804833.jpg | U33: MSW, University of Wisconsin - Milwaukee (Graduate School) | Z33: Brittany Schwarten, LCSW, helps individuals in Wisconsin find clarity, confidence, and emotional balance through a compassionate yet goaloriented approach. She provides individual therapy for teens and adults navigating lifeâs challenges, helping them develop the tools and insight needed to move forward with resilience. Brittany is passionate about creating a safe, affirming space where clients can explore their experiences, build emotional regulation skills, and feel empowered to take meaningful steps toward lasting growth. Brittany specializes in supporting individuals managing anxiety, depression, and trauma. She also has extensive experience working with neurodivergent clients, including those with ADHD and level 1 autism. Her approach is both evidencebased and deeply individualizedârecognizing that each personâs path to healing is unique. Drawing from Dialectical Behavior Therapy DBT, EMDR, and mindfulness, Brittany helps clients strengthen coping skills, process difficult emotions, and create sustainable change. Particularly passionate about working with neurodivergent individuals, Brittany brings over 15 years of experience helping clients improve executive functioning, manage overstimulation, and navigate relationships and identity with confidence. She also enjoys supporting women and members of the LGBTQ community in navigating life transitions, building selfacceptance, and finding balance in their personal and professional lives. Outside of her work at LifeStance Health, Brittany enjoys reading, cooking, supporting local restaurants, and traveling. | AZ33: English | BC33: pt_oD_C7_qzX0uCs7dlE5RZOR | BE33: Practitioner - Full Profile | BG33: No | BI33: =IFERROR(INDEX(ValidationAndReference!P:P, MATCH(BE33, ValidationAndReference!Q:Q, 0)), "") | BJ33: =IFERROR(INDEX(ValidationAndReference!F:F, MATCH(D33, ValidationAndReference!G:G, 0)), "") | BK33: =IFERROR(INDEX(ValidationAndReference!F:F, MATCH(E33, ValidationAndReference!G:G, 0)), "") | BL33: =IFERROR(INDEX(ValidationAndReference!F:F, MATCH(F33, ValidationAndReference!G:G, 0)), "") | BM33: 352 | BR33: lo_wgaomZ1Si0ywpcqcRwrvuw | BS33: lo_vV-i28aaOk-bq9uDxBGd3w | CL33: =IFERROR(INDEX(ValidationAndReference!V:V, MATCH(AZ33, ValidationAndReference!W:W, 0)), "") | CM33: =IFERROR(INDEX(ValidationAndReference!V:V, MATCH(BA33, ValidationAndReference!W:W, 0)), "") | CN33: =IFERROR(INDEX(ValidationAndReference!V:V, MATCH(BB33, ValidationAndReference!W:W, 0)), "") | CO33: 1317 W Grand Ave | CP33: Port Washington | CQ33: 53074 | CR33: WI | CT33: No - Facility Zip
A34: Melissa | B34: Houseman | C34: Female | D34: LCSW | G34: =IFERROR(VLOOKUP(BM34, ValidationAndReference!J:K, 2, FALSE), "") | L34: Both | M34: LifeStance Health | N34: =IFERROR(INDEX(Location!X:X, MATCH(BR34, Location!W:W, 0)), "") | O34: =IFERROR(INDEX(Location!X:X, MATCH(BS34, Location!W:W, 0)), "") | S34: 1467128942 | T34: https://prod-clinicians-photo.s3.amazonaws.com/1467128942.jpg | U34: Master of Social Work, University of South Florida | Z34: Melissa Houseman, LCSW, helps individuals, couples, and families in Florida find meaningful healing and lasting change. She provides a warm, nonjudgmental space where clients can explore lifeâs challenges and develop skills to create greater emotional balance and resilience. Melissa works collaboratively with adolescents, adults, and seniors, guiding them through issues such as anxiety, depression, and trauma with compassion and practical strategies. Melissa is particularly passionate about helping clients navigate recovery from trauma, postpartum depression and anxiety, and substance use issues. She understands that these experiences can deeply affect oneâs sense of identity, relationships, and daily life. Using evidencebased techniques like EMDR, Cognitive Behavioral Therapy CBT, and mindfulnessbased interventions, she helps clients process difficult experiences, build healthier coping mechanisms, and reconnect with a sense of purpose and peace. Melissa also integrates faithbased and Christian counseling when requested, offering a holistic approach that supports emotional, mental, and spiritual wellbeing. Her clinical expertise extends to helping those coping with life transitions, grief, and relationship challenges. Melissa is currently expanding her training in the Gottman Method and EMDR to deepen her work with couples and trauma survivors. She also has experience supporting members of the LGBTQ community, women navigating life changes, and military veterans adjusting to civilian life. Melissa believes that therapy is most effective when it honors each personâs individuality and lived experience. Her approach emphasizes selfcompassion, mindfulness, and empowerment, helping clients cultivate a sense of control and confidence in their journey toward wellness. Outside of her clinical work, Melissa practices mindfulness meditation, which informs her grounded and present therapeutic style. She brings that same sense of calm and attentiveness into her sessions, helping clients feel seen and supported. Melissa Houseman provides inperson and virtual therapy for clients throughout Florida. | AZ34: English | BC34: pt_9pBYQvTE2k-LMM9_puwu-h | BE34: Practitioner - Full Profile | BG34: No | BI34: =IFERROR(INDEX(ValidationAndReference!P:P, MATCH(BE34, ValidationAndReference!Q:Q, 0)), "") | BJ34: =IFERROR(INDEX(ValidationAndReference!F:F, MATCH(D34, ValidationAndReference!G:G, 0)), "") | BK34: =IFERROR(INDEX(ValidationAndReference!F:F, MATCH(E34, ValidationAndReference!G:G, 0)), "") | BL34: =IFERROR(INDEX(ValidationAndReference!F:F, MATCH(F34, ValidationAndReference!G:G, 0)), "") | BM34: 352 | BR34: lo_ZpqrzbDRgEubWfZrZXOobx | BS34: lo_7J0UwUDdzk-W79VhxAhCFx | CL34: =IFERROR(INDEX(ValidationAndReference!V:V, MATCH(AZ34, ValidationAndReference!W:W, 0)), "") | CM34: =IFERROR(INDEX(ValidationAndReference!V:V, MATCH(BA34, ValidationAndReference!W:W, 0)), "") | CN34: =IFERROR(INDEX(ValidationAndReference!V:V, MATCH(BB34, ValidationAndReference!W:W, 0)), "") | CO34: 6600 University Pkwy | CP34: Sarasota | CQ34: 34240 | CR34: FL | CT34: No - Facility Zip
A35: Melissa | B35: Houseman | C35: Female | D35: LCSW | G35: =IFERROR(VLOOKUP(BM35, ValidationAndReference!J:K, 2, FALSE), "") | L35: Both | M35: LifeStance Health | N35: =IFERROR(INDEX(Location!X:X, MATCH(BR35, Location!W:W, 0)), "") | O35: =IFERROR(INDEX(Location!X:X, MATCH(BS35, Location!W:W, 0)), "") | S35: 1467128942 | T35: https://prod-clinicians-photo.s3.amazonaws.com/1467128942.jpg | U35: Master of Social Work, University of South Florida | Z35: Melissa Houseman, LCSW, helps individuals, couples, and families in Florida find meaningful healing and lasting change. She provides a warm, nonjudgmental space where clients can explore lifeâs challenges and develop skills to create greater emotional balance and resilience. Melissa works collaboratively with adolescents, adults, and seniors, guiding them through issues such as anxiety, depression, and trauma with compassion and practical strategies. Melissa is particularly passionate about helping clients navigate recovery from trauma, postpartum depression and anxiety, and substance use issues. She understands that these experiences can deeply affect oneâs sense of identity, relationships, and daily life. Using evidencebased techniques like EMDR, Cognitive Behavioral Therapy CBT, and mindfulnessbased interventions, she helps clients process difficult experiences, build healthier coping mechanisms, and reconnect with a sense of purpose and peace. Melissa also integrates faithbased and Christian counseling when requested, offering a holistic approach that supports emotional, mental, and spiritual wellbeing. Her clinical expertise extends to helping those coping with life transitions, grief, and relationship challenges. Melissa is currently expanding her training in the Gottman Method and EMDR to deepen her work with couples and trauma survivors. She also has experience supporting members of the LGBTQ community, women navigating life changes, and military veterans adjusting to civilian life. Melissa believes that therapy is most effective when it honors each personâs individuality and lived experience. Her approach emphasizes selfcompassion, mindfulness, and empowerment, helping clients cultivate a sense of control and confidence in their journey toward wellness. Outside of her clinical work, Melissa practices mindfulness meditation, which informs her grounded and present therapeutic style. She brings that same sense of calm and attentiveness into her sessions, helping clients feel seen and supported. Melissa Houseman provides inperson and virtual therapy for clients throughout Florida. | AZ35: English | BC35: pt_9pBYQvTE2k-LMM9_puwu-h | BE35: Practitioner - Full Profile | BG35: No | BI35: =IFERROR(INDEX(ValidationAndReference!P:P, MATCH(BE35, ValidationAndReference!Q:Q, 0)), "") | BJ35: =IFERROR(INDEX(ValidationAndReference!F:F, MATCH(D35, ValidationAndReference!G:G, 0)), "") | BK35: =IFERROR(INDEX(ValidationAndReference!F:F, MATCH(E35, ValidationAndReference!G:G, 0)), "") | BL35: =IFERROR(INDEX(ValidationAndReference!F:F, MATCH(F35, ValidationAndReference!G:G, 0)), "") | BM35: 352 | BR35: lo_ZpqrzbDRgEubWfZrZXOobx | BS35: lo_7J0UwUDdzk-W79VhxAhCFx | CL35: =IFERROR(INDEX(ValidationAndReference!V:V, MATCH(AZ35, ValidationAndReference!W:W, 0)), "") | CM35: =IFERROR(INDEX(ValidationAndReference!V:V, MATCH(BA35, ValidationAndReference!W:W, 0)), "") | CN35: =IFERROR(INDEX(ValidationAndReference!V:V, MATCH(BB35, ValidationAndReference!W:W, 0)), "") | CO35: 6600 University Pkwy | CP35: Sarasota | CQ35: 34240 | CR35: FL | CT35: No - Facility Zip
A36: Laura | B36: Reuter | C36: Female | D36: MS | E36: LCSW | G36: =IFERROR(VLOOKUP(BM36, ValidationAndReference!J:K, 2, FALSE), "") | L36: Both | M36: LifeStance Health | N36: =IFERROR(INDEX(Location!X:X, MATCH(BR36, Location!W:W, 0)), "") | O36: =IFERROR(INDEX(Location!X:X, MATCH(BS36, Location!W:W, 0)), "") | S36: 1467327726 | T36: https://prod-clinicians-photo.s3.amazonaws.com/1467327726.jpg | U36: Master of Social Work, Bridgewater State University | Z36: Laura Reuter helps patients in Massachusetts navigate emotional challenges with compassion, clarity, and practical tools for meaningful change. She provides individual therapy for adults across early adulthood, midlife, and later life stages, supporting people as they work through anxiety, depression, grief, and major life transitions. Lauraâs warm presence and thoughtful approach create a grounded space where patients can explore their experiences and develop sustainable ways to improve their wellbeing. Laura is particularly passionate about helping patients through laterlife and midlife transitionsâperiods that can bring both uncertainty and opportunity. She partners with individuals to recognize their strengths, understand shifting identities, and build resilience during these life chapters. Her work often focuses on helping patients manage the emotional complexity of changing roles, grief, and evolving family or career dynamics. Her therapeutic style integrates Cognitive Behavioral Therapy and Mindfulness, blending evidencebased techniques with mindful awareness to help patients develop new perspectives and coping strategies. Laura works frequently with LGBTQ adults, individuals with military or veteran backgrounds, and people experiencing significant life changes. In addition to her core areas of focus, she offers support for additional mental health concerns when aligned with her clinical scope. Outside of her work, Laura finds joy in movement and creativity. She enjoys dancing, Tai Chi, hiking, sailing, swimming, racquet sports, gardening, reading, sewing, music, and nurturing her collection of plants. These interests bring balance to her life and deepen her appreciation for the mindbody connection she encourages in therapy. | AZ36: English | BC36: pt_B8LtUoRcYkWdny_20xbxdB | BE36: Practitioner - Full Profile | BG36: No | BI36: =IFERROR(INDEX(ValidationAndReference!P:P, MATCH(BE36, ValidationAndReference!Q:Q, 0)), "") | BJ36: =IFERROR(INDEX(ValidationAndReference!F:F, MATCH(D36, ValidationAndReference!G:G, 0)), "") | BK36: =IFERROR(INDEX(ValidationAndReference!F:F, MATCH(E36, ValidationAndReference!G:G, 0)), "") | BL36: =IFERROR(INDEX(ValidationAndReference!F:F, MATCH(F36, ValidationAndReference!G:G, 0)), "") | BM36: 352 | BR36: lo_WGSx6xN8302ASv6YVggXbh | BS36: lo_8kwZD7BrWkmw6LTpfZ-4yB | CL36: =IFERROR(INDEX(ValidationAndReference!V:V, MATCH(AZ36, ValidationAndReference!W:W, 0)), "") | CM36: =IFERROR(INDEX(ValidationAndReference!V:V, MATCH(BA36, ValidationAndReference!W:W, 0)), "") | CN36: =IFERROR(INDEX(ValidationAndReference!V:V, MATCH(BB36, ValidationAndReference!W:W, 0)), "") | CO36: 175 Paramount Dr | CP36: Raynham | CQ36: 2767 | CR36: MA | CT36: No - Facility Zip
A37: Susan | B37: Yang | C37: Female | D37: C-DBT | G37: =IFERROR(VLOOKUP(BM37, ValidationAndReference!J:K, 2, FALSE), "") | L37: Both | M37: LifeStance Health | N37: =IFERROR(INDEX(Location!X:X, MATCH(BR37, Location!W:W, 0)), "") | O37: =IFERROR(INDEX(Location!X:X, MATCH(BS37, Location!W:W, 0)), "") | S37: 1538029483 | T37: https://prod-clinicians-photo.s3.amazonaws.com/1538029483.jpg | U37: Master of Social Work, Saint Mary's University of Minnesota | Z37: Susan Yang helps patients build emotional resilience, strengthen relationships, and navigate lifeâs challenges through compassionate, evidencebased care. Serving individuals and families across Minnesota, she works with children, adolescents, teens, and adults, offering support for concerns such as anxiety, depression, trauma, and behavioral or developmental challenges. As a provisionally licensed clinician at LifeStance Health, she creates a safe, steady space where clients feel understood, respected, and empowered to grow. Susan offers individual and family therapy with a focus on practical strategies that foster meaningful change. She regularly supports patients working through ADHD, anxiety disorders, and PTSDtrauma, blending insightoriented work with structured therapeutic tools. Her experience with populations including individuals with autism spectrum disorders, developmental disabilities, and members of the LGBTQ community allows her to tailor care with cultural sensitivity and affirming practices. She is especially passionate about helping patients address childhood behavior issues, school avoidance, and postpartum depressionanxiety. Susan is committed to guiding young people and their caregivers through emotionally complex moments while also supporting adults facing identity transitions, grief, and womenâs mental health needs. Her clinical approach integrates Cognitive Behavioral Therapy, Exposure Therapy, and Mindfulness, with additional methods offered based on each patientâs goals. Outside the therapy room, Susan enjoys singing, sports, dancing, reading, hiking, listening to music, and spending time with her family and dogs. These interests strengthen her belief in balance, connection, and creativityâvalues she brings into her work with clients. | AZ37: English | BA37: Hmong | BC37: pt_QjfLYCpQ7k6KRCLDEo9tvh | BE37: Practitioner - Full Profile | BG37: No | BI37: =IFERROR(INDEX(ValidationAndReference!P:P, MATCH(BE37, ValidationAndReference!Q:Q, 0)), "") | BJ37: =IFERROR(INDEX(ValidationAndReference!F:F, MATCH(D37, ValidationAndReference!G:G, 0)), "") | BK37: =IFERROR(INDEX(ValidationAndReference!F:F, MATCH(E37, ValidationAndReference!G:G, 0)), "") | BL37: =IFERROR(INDEX(ValidationAndReference!F:F, MATCH(F37, ValidationAndReference!G:G, 0)), "") | BR37: lo_SvL6N5e1cEOakfVbtedonh | CL37: =IFERROR(INDEX(ValidationAndReference!V:V, MATCH(AZ37, ValidationAndReference!W:W, 0)), "") | CM37: =IFERROR(INDEX(ValidationAndReference!V:V, MATCH(BA37, ValidationAndReference!W:W, 0)), "") | CN37: =IFERROR(INDEX(ValidationAndReference!V:V, MATCH(BB37, ValidationAndReference!W:W, 0)), "") | CO37: 6800 78th Ave N | CP37: Brooklyn Park | CQ37: 55445 | CR37: MN | CT37: No - Facility Zip
A38: Susan | B38: Yang | C38: Female | D38: C-DBT | G38: =IFERROR(VLOOKUP(BM38, ValidationAndReference!J:K, 2, FALSE), "") | L38: Both | M38: LifeStance Health | N38: =IFERROR(INDEX(Location!X:X, MATCH(BR38, Location!W:W, 0)), "") | O38: =IFERROR(INDEX(Location!X:X, MATCH(BS38, Location!W:W, 0)), "") | S38: 1538029483 | T38: https://prod-clinicians-photo.s3.amazonaws.com/1538029483.jpg | U38: Master of Social Work, Saint Mary's University of Minnesota | Z38: Susan Yang helps patients build emotional resilience, strengthen relationships, and navigate lifeâs challenges through compassionate, evidencebased care. Serving individuals and families across Minnesota, she works with children, adolescents, teens, and adults, offering support for concerns such as anxiety, depression, trauma, and behavioral or developmental challenges. As a provisionally licensed clinician at LifeStance Health, she creates a safe, steady space where clients feel understood, respected, and empowered to grow. Susan offers individual and family therapy with a focus on practical strategies that foster meaningful change. She regularly supports patients working through ADHD, anxiety disorders, and PTSDtrauma, blending insightoriented work with structured therapeutic tools. Her experience with populations including individuals with autism spectrum disorders, developmental disabilities, and members of the LGBTQ community allows her to tailor care with cultural sensitivity and affirming practices. She is especially passionate about helping patients address childhood behavior issues, school avoidance, and postpartum depressionanxiety. Susan is committed to guiding young people and their caregivers through emotionally complex moments while also supporting adults facing identity transitions, grief, and womenâs mental health needs. Her clinical approach integrates Cognitive Behavioral Therapy, Exposure Therapy, and Mindfulness, with additional methods offered based on each patientâs goals. Outside the therapy room, Susan enjoys singing, sports, dancing, reading, hiking, listening to music, and spending time with her family and dogs. These interests strengthen her belief in balance, connection, and creativityâvalues she brings into her work with clients. | AZ38: English | BA38: Hmong | BC38: pt_QjfLYCpQ7k6KRCLDEo9tvh | BE38: Practitioner - Full Profile | BG38: No | BI38: =IFERROR(INDEX(ValidationAndReference!P:P, MATCH(BE38, ValidationAndReference!Q:Q, 0)), "") | BJ38: =IFERROR(INDEX(ValidationAndReference!F:F, MATCH(D38, ValidationAndReference!G:G, 0)), "") | BK38: =IFERROR(INDEX(ValidationAndReference!F:F, MATCH(E38, ValidationAndReference!G:G, 0)), "") | BL38: =IFERROR(INDEX(ValidationAndReference!F:F, MATCH(F38, ValidationAndReference!G:G, 0)), "") | BR38: lo_SvL6N5e1cEOakfVbtedonh | CL38: =IFERROR(INDEX(ValidationAndReference!V:V, MATCH(AZ38, ValidationAndReference!W:W, 0)), "") | CM38: =IFERROR(INDEX(ValidationAndReference!V:V, MATCH(BA38, ValidationAndReference!W:W, 0)), "") | CN38: =IFERROR(INDEX(ValidationAndReference!V:V, MATCH(BB38, ValidationAndReference!W:W, 0)), "") | CO38: 6800 78th Ave N | CP38: Brooklyn Park | CQ38: 55445 | CR38: MN | CT38: No - Facility Zip
A39: Elizabeth | B39: Avalos | C39: Female | D39: ALMFT | G39: =IFERROR(VLOOKUP(BM39, ValidationAndReference!J:K, 2, FALSE), "") | L39: Both | M39: LifeStance Health | N39: =IFERROR(INDEX(Location!X:X, MATCH(BR39, Location!W:W, 0)), "") | O39: =IFERROR(INDEX(Location!X:X, MATCH(BS39, Location!W:W, 0)), "") | S39: 1548139728 | T39: https://prod-clinicians-photo.s3.amazonaws.com/1548139728.jpg | U39: Master's Degree, Northwestern University | Z39: Elizabeth Avalos, ALMFT, helps children, teens, adults, couples, and families across Illinois navigate emotional challenges, strengthen relationships, and build healthier patterns of communication. As a therapist with LifeStance Health, she offers a warm, grounded presence and a collaborative approach that supports clients working through anxiety, depression, trauma, and family or relational strain. Elizabeth works with a wide range of agesâfrom children and adolescents through older adultsâproviding individualized care to meet the diverse needs of the communities she serves throughout Illinois. Elizabeth draws particular fulfillment from helping clients facing complex behavioral or relational concerns. Whether she is supporting a child struggling with school avoidance or behavior issues, or guiding a family through conflict or transition, she works to understand the broader system shaping each clientâs experience. Her approach emphasizes safety, connection, and thoughtful insightbuilding, allowing clients to explore challenges at a manageable pace while developing practical tools for daytoday resilience. In her clinical work, Elizabeth integrates Cognitive Behavioral Therapy CBT, Dialectical Behavior Therapy DBT, CouplesMarital Counseling, and Family Therapy, alongside Mindfulness and Parenting Skills strategies. She frequently supports LGBTQ clients, individuals from adoption or foster care backgrounds, and first responders. Her work also extends to concerns such as ADHD, anxiety, mood disorders, and trauma, with additional services available to address broader emotional and relational needs. Elizabeth believes therapy is most effective when clients feel truly seen and supported. She aims to help people gain clarity, improve communication, and build confidence as they navigate lifeâs turning points. Outside the therapy room, she enjoys spending time with family, friends, and her dog, as well as reading, cooking, exploring new restaurants, going on nature walks, listening to music, and attending concerts. | AZ39: English | BC39: pt_6BaNpinqtUOgby24rE9XXx | BE39: Practitioner - Full Profile | BG39: No | BI39: =IFERROR(INDEX(ValidationAndReference!P:P, MATCH(BE39, ValidationAndReference!Q:Q, 0)), "") | BJ39: =IFERROR(INDEX(ValidationAndReference!F:F, MATCH(D39, ValidationAndReference!G:G, 0)), "") | BK39: =IFERROR(INDEX(ValidationAndReference!F:F, MATCH(E39, ValidationAndReference!G:G, 0)), "") | BL39: =IFERROR(INDEX(ValidationAndReference!F:F, MATCH(F39, ValidationAndReference!G:G, 0)), "") | BR39: lo_pT7MGEK3BUCv-9G13C2Xwx | BS39: lo_vQ68tusLRECniOZ3cJmKRh | CL39: =IFERROR(INDEX(ValidationAndReference!V:V, MATCH(AZ39, ValidationAndReference!W:W, 0)), "") | CM39: =IFERROR(INDEX(ValidationAndReference!V:V, MATCH(BA39, ValidationAndReference!W:W, 0)), "") | CN39: =IFERROR(INDEX(ValidationAndReference!V:V, MATCH(BB39, ValidationAndReference!W:W, 0)), "") | CO39: 1616 N Damen Ave | CP39: Chicago | CQ39: 60647 | CR39: IL | CT39: No - Facility Zip
A40: Elizabeth | B40: Avalos | C40: Female | D40: ALMFT | G40: =IFERROR(VLOOKUP(BM40, ValidationAndReference!J:K, 2, FALSE), "") | L40: Both | M40: LifeStance Health | N40: =IFERROR(INDEX(Location!X:X, MATCH(BR40, Location!W:W, 0)), "") | O40: =IFERROR(INDEX(Location!X:X, MATCH(BS40, Location!W:W, 0)), "") | S40: 1548139728 | T40: https://prod-clinicians-photo.s3.amazonaws.com/1548139728.jpg | U40: Master's Degree, Northwestern University | Z40: Elizabeth Avalos, ALMFT, helps children, teens, adults, couples, and families across Illinois navigate emotional challenges, strengthen relationships, and build healthier patterns of communication. As a therapist with LifeStance Health, she offers a warm, grounded presence and a collaborative approach that supports clients working through anxiety, depression, trauma, and family or relational strain. Elizabeth works with a wide range of agesâfrom children and adolescents through older adultsâproviding individualized care to meet the diverse needs of the communities she serves throughout Illinois. Elizabeth draws particular fulfillment from helping clients facing complex behavioral or relational concerns. Whether she is supporting a child struggling with school avoidance or behavior issues, or guiding a family through conflict or transition, she works to understand the broader system shaping each clientâs experience. Her approach emphasizes safety, connection, and thoughtful insightbuilding, allowing clients to explore challenges at a manageable pace while developing practical tools for daytoday resilience. In her clinical work, Elizabeth integrates Cognitive Behavioral Therapy CBT, Dialectical Behavior Therapy DBT, CouplesMarital Counseling, and Family Therapy, alongside Mindfulness and Parenting Skills strategies. She frequently supports LGBTQ clients, individuals from adoption or foster care backgrounds, and first responders. Her work also extends to concerns such as ADHD, anxiety, mood disorders, and trauma, with additional services available to address broader emotional and relational needs. Elizabeth believes therapy is most effective when clients feel truly seen and supported. She aims to help people gain clarity, improve communication, and build confidence as they navigate lifeâs turning points. Outside the therapy room, she enjoys spending time with family, friends, and her dog, as well as reading, cooking, exploring new restaurants, going on nature walks, listening to music, and attending concerts. | AZ40: English | BC40: pt_6BaNpinqtUOgby24rE9XXx | BE40: Practitioner - Full Profile | BG40: No | BI40: =IFERROR(INDEX(ValidationAndReference!P:P, MATCH(BE40, ValidationAndReference!Q:Q, 0)), "") | BJ40: =IFERROR(INDEX(ValidationAndReference!F:F, MATCH(D40, ValidationAndReference!G:G, 0)), "") | BK40: =IFERROR(INDEX(ValidationAndReference!F:F, MATCH(E40, ValidationAndReference!G:G, 0)), "") | BL40: =IFERROR(INDEX(ValidationAndReference!F:F, MATCH(F40, ValidationAndReference!G:G, 0)), "") | BR40: lo_pT7MGEK3BUCv-9G13C2Xwx | BS40: lo_vQ68tusLRECniOZ3cJmKRh | CL40: =IFERROR(INDEX(ValidationAndReference!V:V, MATCH(AZ40, ValidationAndReference!W:W, 0)), "") | CM40: =IFERROR(INDEX(ValidationAndReference!V:V, MATCH(BA40, ValidationAndReference!W:W, 0)), "") | CN40: =IFERROR(INDEX(ValidationAndReference!V:V, MATCH(BB40, ValidationAndReference!W:W, 0)), "") | CO40: 1616 N Damen Ave | CP40: Chicago | CQ40: 60647 | CR40: IL | CT40: No - Facility Zip
A41: Elizabeth | B41: Avalos | C41: Female | D41: ALMFT | G41: =IFERROR(VLOOKUP(BM41, ValidationAndReference!J:K, 2, FALSE), "") | L41: Both | M41: LifeStance Health | N41: =IFERROR(INDEX(Location!X:X, MATCH(BR41, Location!W:W, 0)), "") | O41: =IFERROR(INDEX(Location!X:X, MATCH(BS41, Location!W:W, 0)), "") | S41: 1548139728 | T41: https://prod-clinicians-photo.s3.amazonaws.com/1548139728.jpg | U41: Master's Degree, Northwestern University | Z41: Elizabeth Avalos, ALMFT, helps children, teens, adults, couples, and families across Illinois navigate emotional challenges, strengthen relationships, and build healthier patterns of communication. As a therapist with LifeStance Health, she offers a warm, grounded presence and a collaborative approach that supports clients working through anxiety, depression, trauma, and family or relational strain. Elizabeth works with a wide range of agesâfrom children and adolescents through older adultsâproviding individualized care to meet the diverse needs of the communities she serves throughout Illinois. Elizabeth draws particular fulfillment from helping clients facing complex behavioral or relational concerns. Whether she is supporting a child struggling with school avoidance or behavior issues, or guiding a family through conflict or transition, she works to understand the broader system shaping each clientâs experience. Her approach emphasizes safety, connection, and thoughtful insightbuilding, allowing clients to explore challenges at a manageable pace while developing practical tools for daytoday resilience. In her clinical work, Elizabeth integrates Cognitive Behavioral Therapy CBT, Dialectical Behavior Therapy DBT, CouplesMarital Counseling, and Family Therapy, alongside Mindfulness and Parenting Skills strategies. She frequently supports LGBTQ clients, individuals from adoption or foster care backgrounds, and first responders. Her work also extends to concerns such as ADHD, anxiety, mood disorders, and trauma, with additional services available to address broader emotional and relational needs. Elizabeth believes therapy is most effective when clients feel truly seen and supported. She aims to help people gain clarity, improve communication, and build confidence as they navigate lifeâs turning points. Outside the therapy room, she enjoys spending time with family, friends, and her dog, as well as reading, cooking, exploring new restaurants, going on nature walks, listening to music, and attending concerts. | AZ41: English | BC41: pt_6BaNpinqtUOgby24rE9XXx | BE41: Practitioner - Full Profile | BG41: No | BI41: =IFERROR(INDEX(ValidationAndReference!P:P, MATCH(BE41, ValidationAndReference!Q:Q, 0)), "") | BJ41: =IFERROR(INDEX(ValidationAndReference!F:F, MATCH(D41, ValidationAndReference!G:G, 0)), "") | BK41: =IFERROR(INDEX(ValidationAndReference!F:F, MATCH(E41, ValidationAndReference!G:G, 0)), "") | BL41: =IFERROR(INDEX(ValidationAndReference!F:F, MATCH(F41, ValidationAndReference!G:G, 0)), "") | BR41: lo_pT7MGEK3BUCv-9G13C2Xwx | BS41: lo_vQ68tusLRECniOZ3cJmKRh | CL41: =IFERROR(INDEX(ValidationAndReference!V:V, MATCH(AZ41, ValidationAndReference!W:W, 0)), "") | CM41: =IFERROR(INDEX(ValidationAndReference!V:V, MATCH(BA41, ValidationAndReference!W:W, 0)), "") | CN41: =IFERROR(INDEX(ValidationAndReference!V:V, MATCH(BB41, ValidationAndReference!W:W, 0)), "") | CO41: 1616 N Damen Ave | CP41: Chicago | CQ41: 60647 | CR41: IL | CT41: No - Facility Zip
A42: Pragya | B42: Sitoula | C42: Female | D42: PMHNP | G42: =IFERROR(VLOOKUP(BM42, ValidationAndReference!J:K, 2, FALSE), "") | L42: Both | M42: LifeStance Health | N42: =IFERROR(INDEX(Location!X:X, MATCH(BR42, Location!W:W, 0)), "") | O42: =IFERROR(INDEX(Location!X:X, MATCH(BS42, Location!W:W, 0)), "") | S42: 1558233924 | T42: https://prod-clinicians-photo.s3.amazonaws.com/1558233924.jpg | U42: MSN, South College | Z42: Pragya Sitoula, PMHNP, helps patients across North Carolina find relief and stability through compassionate, evidencebased psychiatric care. She provides treatment for children, adolescents, teens, and adults, offering a safe and supportive environment where individuals and families can explore challenges and discover practical solutions. With a focus on medication management and individualized care, she works closely with patients to promote healing and improve daily functioning. Her clinical expertise includes treating ADHD, anxiety, and bipolar disorder, as well as other mood and behavioral conditions. Pragya often partners with patients facing complex life challenges, blending psychiatric knowledge with thoughtful guidance tailored to each stage of life. She incorporates Cognitive Behavioral Therapy CBT when appropriate to help patients better understand the connection between thoughts, feelings, and behaviors while building skills to manage stress and foster resilience. Pragya is especially passionate about supporting individuals navigating childhood behavior issues, gender identity concerns, and postpartum depression or anxiety. She understands the impact these experiences can have on individuals and families, and she strives to provide care that is both affirming and empowering. Her work with populations such as women, members of the LGBTQ community, and individuals with developmental disabilities or Autism spectrum disorders highlights her commitment to inclusive, respectful treatment for all. Outside of her clinical practice, Pragya enjoys listening to music, cooking, traveling, and playing pickleball. | AZ42: English | BA42: Sign | BC42: pt_JC64JlmALEqey1kShhAOLh | BE42: Practitioner - Full Profile | BG42: No | BI42: =IFERROR(INDEX(ValidationAndReference!P:P, MATCH(BE42, ValidationAndReference!Q:Q, 0)), "") | BJ42: =IFERROR(INDEX(ValidationAndReference!F:F, MATCH(D42, ValidationAndReference!G:G, 0)), "") | BK42: =IFERROR(INDEX(ValidationAndReference!F:F, MATCH(E42, ValidationAndReference!G:G, 0)), "") | BL42: =IFERROR(INDEX(ValidationAndReference!F:F, MATCH(F42, ValidationAndReference!G:G, 0)), "") | BM42: 405 | BR42: lo_F5KcBajookWBLrkrLhugBR | BS42: lo_rvaDwYYUiUyWCke9d-gjqB | CL42: =IFERROR(INDEX(ValidationAndReference!V:V, MATCH(AZ42, ValidationAndReference!W:W, 0)), "") | CM42: =IFERROR(INDEX(ValidationAndReference!V:V, MATCH(BA42, ValidationAndReference!W:W, 0)), "") | CN42: =IFERROR(INDEX(ValidationAndReference!V:V, MATCH(BB42, ValidationAndReference!W:W, 0)), "") | CO42: 122 Gtwy Blvd | CP42: Mooresville | CQ42: 28117 | CR42: NC | CS42: Ste C | CT42: No - Facility Address (try converting 'Gtwy' to 'GTWY'; try converting 'Gtwy' to 'GATEWAY'; try converting 'Gtwy' to 'GATEWY'; try converting 'Gtwy' to 'GATWAY'; try converting 'Gtwy' to 'GTWAY'; try converting 'Gtwy' to 'GTWY'; try converting 'Blvd' to 'BLVD'; try converting 'Blvd' to 'BLVD'; try converting 'Blvd' to 'BOUL'; try converting 'Blvd' to 'BOULEVARD'; try converting 'Blvd' to 'BOULV'), Facility Zip
A43: Maria | B43: Maddalo | C43: Female | D43: PsyD | E43: BCBA | F43: ABSNP | G43: =IFERROR(VLOOKUP(BM43, ValidationAndReference!J:K, 2, FALSE), "") | L43: Both | M43: LifeStance Health | N43: =IFERROR(INDEX(Location!X:X, MATCH(BR43, Location!W:W, 0)), "") | O43: =IFERROR(INDEX(Location!X:X, MATCH(BS43, Location!W:W, 0)), "") | S43: 1568970879 | T43: https://prod-clinicians-photo.s3.amazonaws.com/1568970879.jpg | U43: Doctor of Psychology (PSYD), Philadelphia College of Osteopathic Medicine | Z43: Maria Maddalo, PsyD, provides compassionate, evidencebased support for children, teens, and adults across Pennsylvania who are navigating neurodevelopmental and mental health challenges. She helps patients and their families better understand cognitive, emotional, and behavioral concerns, offering a safe space for exploration and growth. Maria works closely with each individual to create personalized care strategies, helping them develop skills for improved functioning and wellbeing. Maria specializes in ADHD, anxiety, and childhood behavior issues, with a particular passion for supporting individuals with autism and developmental disabilities. She also focuses on executive functioning challenges, using neuropsychological and psychological testing to provide comprehensive assessments that inform targeted interventions. Her expertise helps families and caregivers better understand learning differences, attention challenges, and behavioral patterns, supporting meaningful progress in daily life. In her practice at LifeStance Health, Maria uses interventions such as neuropsychological testing and psychological evaluations to guide treatment planning and track progress. She works with populations including children, adolescents, and individuals with developmental disabilities or autism spectrum disorders, ensuring that each person receives care tailored to their unique strengths and needs. Outside of her clinical work, Maria enjoys spending quality time with her family, which reflects her commitment to nurturing and supportive relationships both personally and professionally. Her dedication to understanding and supporting neurodevelopmental and mental health needs allows patients throughout Pennsylvania to thrive. | AZ43: English | BC43: pt_NQMRQWBlP02-a4WEulV9ph | BE43: Practitioner - Full Profile | BG43: No | BI43: =IFERROR(INDEX(ValidationAndReference!P:P, MATCH(BE43, ValidationAndReference!Q:Q, 0)), "") | BJ43: =IFERROR(INDEX(ValidationAndReference!F:F, MATCH(D43, ValidationAndReference!G:G, 0)), "") | BK43: =IFERROR(INDEX(ValidationAndReference!F:F, MATCH(E43, ValidationAndReference!G:G, 0)), "") | BL43: =IFERROR(INDEX(ValidationAndReference!F:F, MATCH(F43, ValidationAndReference!G:G, 0)), "") | BM43: 337 | BR43: lo_8Vzg5S1xBU6qOfS3Q099Xh | CL43: =IFERROR(INDEX(ValidationAndReference!V:V, MATCH(AZ43, ValidationAndReference!W:W, 0)), "") | CM43: =IFERROR(INDEX(ValidationAndReference!V:V, MATCH(BA43, ValidationAndReference!W:W, 0)), "") | CN43: =IFERROR(INDEX(ValidationAndReference!V:V, MATCH(BB43, ValidationAndReference!W:W, 0)), "") | CO43: 551 W Lanca | CP43: Haverford | CQ43: 19041 | CR43: PA | CS43: Ster Ave Ste 306 | CT43: No - Facility Zip
A44: Joanna | B44: Nichols | C44: Female | D44: MS | E44: IMFT-S | F44: LCDC III | G44: =IFERROR(VLOOKUP(BM44, ValidationAndReference!J:K, 2, FALSE), "") | L44: Both | M44: LifeStance Health | N44: =IFERROR(INDEX(Location!X:X, MATCH(BR44, Location!W:W, 0)), "") | O44: =IFERROR(INDEX(Location!X:X, MATCH(BS44, Location!W:W, 0)), "") | S44: 1578953428 | T44: https://prod-clinicians-photo.s3.amazonaws.com/1578953428.jpg | U44: Master of Science (MS), University of Alabama | Z44: Joanna Nichols, IMFTS, helps teens, young adults, and adults in Ohio navigate lifeâs challenges and improve their mental health through individualized and evidencebased therapy. As a Marriage & Family Therapist at LifeStance Health, she provides compassionate support for those coping with anxiety, depression, and relationship concerns, helping clients develop practical strategies for lasting change. Joanna works with a diverse range of patients, including those involved in legal matters or recently discharged from psychiatric care, ensuring each personâs unique circumstances are considered in their treatment plan. Joanna is particularly passionate about working with clients who have recently been discharged from a psychiatric hospital, those engaged in courtordered treatment, dealing with workersâ compensation issues, parental custody concerns, or current legal matters. She has extensive experience helping individuals and families address anxiety, depression, and couples or familyrelated challenges. Using interventions such as Cognitive Behavioral Therapy CBT, Dialectical Behavior Therapy DBT, family and couples counseling, mindfulness, and parenting skills, she supports clients in building coping skills, improving communication, and fostering healthier relationships. Joanna also works with populations including LGBTQ individuals, first responders, and those in adoption or foster care, creating a safe and inclusive space for growth and healing. Outside of her professional work, Joanna enjoys spending time outdoors walking, creating projects, and watching lighthearted or ridiculous movies. Her approach to therapy reflects a balance of clinical expertise and genuine care, helping clients explore their goals and realize their potential. | AZ44: English | BC44: pt_oD_C7_qzX0uCs7dlE5RZOR | BE44: Practitioner - Full Profile | BG44: No | BI44: =IFERROR(INDEX(ValidationAndReference!P:P, MATCH(BE44, ValidationAndReference!Q:Q, 0)), "") | BJ44: =IFERROR(INDEX(ValidationAndReference!F:F, MATCH(D44, ValidationAndReference!G:G, 0)), "") | BK44: =IFERROR(INDEX(ValidationAndReference!F:F, MATCH(E44, ValidationAndReference!G:G, 0)), "") | BL44: =IFERROR(INDEX(ValidationAndReference!F:F, MATCH(F44, ValidationAndReference!G:G, 0)), "") | BM44: 352 | BR44: lo_UisedZn9JkaThS7rv9Tejx | CL44: =IFERROR(INDEX(ValidationAndReference!V:V, MATCH(AZ44, ValidationAndReference!W:W, 0)), "") | CM44: =IFERROR(INDEX(ValidationAndReference!V:V, MATCH(BA44, ValidationAndReference!W:W, 0)), "") | CN44: =IFERROR(INDEX(ValidationAndReference!V:V, MATCH(BB44, ValidationAndReference!W:W, 0)), "") | CO44: 2135 Dana Ave | CP44: Cincinnati | CQ44: 45207 | CR44: OH | CS44: Ste 220 | CT44: No - Facility Zip
A45: Joanna | B45: Nichols | C45: Female | D45: MS | E45: IMFT-S | F45: LCDC III | G45: =IFERROR(VLOOKUP(BM45, ValidationAndReference!J:K, 2, FALSE), "") | L45: Both | M45: LifeStance Health | N45: =IFERROR(INDEX(Location!X:X, MATCH(BR45, Location!W:W, 0)), "") | O45: =IFERROR(INDEX(Location!X:X, MATCH(BS45, Location!W:W, 0)), "") | S45: 1578953428 | T45: https://prod-clinicians-photo.s3.amazonaws.com/1578953428.jpg | U45: Master of Science (MS), University of Alabama | Z45: Joanna Nichols, IMFTS, helps teens, young adults, and adults in Ohio navigate lifeâs challenges and improve their mental health through individualized and evidencebased therapy. As a Marriage & Family Therapist at LifeStance Health, she provides compassionate support for those coping with anxiety, depression, and relationship concerns, helping clients develop practical strategies for lasting change. Joanna works with a diverse range of patients, including those involved in legal matters or recently discharged from psychiatric care, ensuring each personâs unique circumstances are considered in their treatment plan. Joanna is particularly passionate about working with clients who have recently been discharged from a psychiatric hospital, those engaged in courtordered treatment, dealing with workersâ compensation issues, parental custody concerns, or current legal matters. She has extensive experience helping individuals and families address anxiety, depression, and couples or familyrelated challenges. Using interventions such as Cognitive Behavioral Therapy CBT, Dialectical Behavior Therapy DBT, family and couples counseling, mindfulness, and parenting skills, she supports clients in building coping skills, improving communication, and fostering healthier relationships. Joanna also works with populations including LGBTQ individuals, first responders, and those in adoption or foster care, creating a safe and inclusive space for growth and healing. Outside of her professional work, Joanna enjoys spending time outdoors walking, creating projects, and watching lighthearted or ridiculous movies. Her approach to therapy reflects a balance of clinical expertise and genuine care, helping clients explore their goals and realize their potential. | AZ45: English | BC45: pt_oD_C7_qzX0uCs7dlE5RZOR | BE45: Practitioner - Full Profile | BG45: No | BI45: =IFERROR(INDEX(ValidationAndReference!P:P, MATCH(BE45, ValidationAndReference!Q:Q, 0)), "") | BJ45: =IFERROR(INDEX(ValidationAndReference!F:F, MATCH(D45, ValidationAndReference!G:G, 0)), "") | BK45: =IFERROR(INDEX(ValidationAndReference!F:F, MATCH(E45, ValidationAndReference!G:G, 0)), "") | BL45: =IFERROR(INDEX(ValidationAndReference!F:F, MATCH(F45, ValidationAndReference!G:G, 0)), "") | BM45: 352 | BR45: lo_UisedZn9JkaThS7rv9Tejx | CL45: =IFERROR(INDEX(ValidationAndReference!V:V, MATCH(AZ45, ValidationAndReference!W:W, 0)), "") | CM45: =IFERROR(INDEX(ValidationAndReference!V:V, MATCH(BA45, ValidationAndReference!W:W, 0)), "") | CN45: =IFERROR(INDEX(ValidationAndReference!V:V, MATCH(BB45, ValidationAndReference!W:W, 0)), "") | CO45: 2135 Dana Ave | CP45: Cincinnati | CQ45: 45207 | CR45: OH | CS45: Ste 220 | CT45: No - Facility Zip
A46: Joanna | B46: Nichols | C46: Female | D46: MS | E46: IMFT-S | F46: LCDC III | G46: =IFERROR(VLOOKUP(BM46, ValidationAndReference!J:K, 2, FALSE), "") | L46: Both | M46: LifeStance Health | N46: =IFERROR(INDEX(Location!X:X, MATCH(BR46, Location!W:W, 0)), "") | O46: =IFERROR(INDEX(Location!X:X, MATCH(BS46, Location!W:W, 0)), "") | S46: 1578953428 | T46: https://prod-clinicians-photo.s3.amazonaws.com/1578953428.jpg | U46: Master of Science (MS), University of Alabama | Z46: Joanna Nichols, IMFTS, helps teens, young adults, and adults in Ohio navigate lifeâs challenges and improve their mental health through individualized and evidencebased therapy. As a Marriage & Family Therapist at LifeStance Health, she provides compassionate support for those coping with anxiety, depression, and relationship concerns, helping clients develop practical strategies for lasting change. Joanna works with a diverse range of patients, including those involved in legal matters or recently discharged from psychiatric care, ensuring each personâs unique circumstances are considered in their treatment plan. Joanna is particularly passionate about working with clients who have recently been discharged from a psychiatric hospital, those engaged in courtordered treatment, dealing with workersâ compensation issues, parental custody concerns, or current legal matters. She has extensive experience helping individuals and families address anxiety, depression, and couples or familyrelated challenges. Using interventions such as Cognitive Behavioral Therapy CBT, Dialectical Behavior Therapy DBT, family and couples counseling, mindfulness, and parenting skills, she supports clients in building coping skills, improving communication, and fostering healthier relationships. Joanna also works with populations including LGBTQ individuals, first responders, and those in adoption or foster care, creating a safe and inclusive space for growth and healing. Outside of her professional work, Joanna enjoys spending time outdoors walking, creating projects, and watching lighthearted or ridiculous movies. Her approach to therapy reflects a balance of clinical expertise and genuine care, helping clients explore their goals and realize their potential. | AZ46: English | BC46: pt_oD_C7_qzX0uCs7dlE5RZOR | BE46: Practitioner - Full Profile | BG46: No | BI46: =IFERROR(INDEX(ValidationAndReference!P:P, MATCH(BE46, ValidationAndReference!Q:Q, 0)), "") | BJ46: =IFERROR(INDEX(ValidationAndReference!F:F, MATCH(D46, ValidationAndReference!G:G, 0)), "") | BK46: =IFERROR(INDEX(ValidationAndReference!F:F, MATCH(E46, ValidationAndReference!G:G, 0)), "") | BL46: =IFERROR(INDEX(ValidationAndReference!F:F, MATCH(F46, ValidationAndReference!G:G, 0)), "") | BM46: 352 | BR46: lo_UisedZn9JkaThS7rv9Tejx | CL46: =IFERROR(INDEX(ValidationAndReference!V:V, MATCH(AZ46, ValidationAndReference!W:W, 0)), "") | CM46: =IFERROR(INDEX(ValidationAndReference!V:V, MATCH(BA46, ValidationAndReference!W:W, 0)), "") | CN46: =IFERROR(INDEX(ValidationAndReference!V:V, MATCH(BB46, ValidationAndReference!W:W, 0)), "") | CO46: 2135 Dana Ave | CP46: Cincinnati | CQ46: 45207 | CR46: OH | CS46: Ste 220 | CT46: No - Facility Zip
A47: Angela | B47: Naki | C47: Female | D47: DMFT | E47: LPC | G47: =IFERROR(VLOOKUP(BM47, ValidationAndReference!J:K, 2, FALSE), "") | L47: Both | M47: LifeStance Health | N47: =IFERROR(INDEX(Location!X:X, MATCH(BR47, Location!W:W, 0)), "") | O47: =IFERROR(INDEX(Location!X:X, MATCH(BS47, Location!W:W, 0)), "") | S47: 1598377749 | T47: https://prod-clinicians-photo.s3.amazonaws.com/1598377749.jpg | U47: Doctorate of Marriage and Family Therapy, Northcentral University | Z47: Angela Naki helps patients across Texas find stability, emotional relief, and renewed confidence through thoughtful, evidencebased mental health care. At LifeStance Health, she supports children, adolescents, teens, adults, and seniors, offering both individual and familycentered treatment tailored to the needs of diverse communities throughout the state. She is especially passionate about treating trauma, school avoidance, and complex life transitions. Angela is known for her steady, grounding presence with patients navigating PTSD and traumarelated symptoms, and she works closely with children and adolescents who are struggling to attend school due to anxiety, emotional overwhelm, or family stressors. Her approach emphasizes safety, practical skills, and restoring a sense of empowerment for individuals of all ages. Angelaâs clinical expertise includes anxiety, depression, and PTSDtrauma, along with additional specialties that allow her to support patients with a wide range of concerns. She integrates EMDR, Cognitive Behavioral Therapy, and Dialectical Behavior Therapy, offering additional therapeutic interventions to meet each patientâs needs. She frequently works with first responders, military and veteran populations, and LGBTQ individuals, applying a culturally attuned and compassionate lens. When helpful, she incorporates Psychological Testing to provide deeper clinical insight and guide treatment planning. Outside her work, Angela enjoys reading, traveling, cooking, and baking, and she treasures time spent spoiling her granddaughter and sharing moments with family and friends. | AZ47: English | BC47: pt_vOTgX4FPvUOFJaL-VrSO1B | BE47: Practitioner - Full Profile | BG47: No | BI47: =IFERROR(INDEX(ValidationAndReference!P:P, MATCH(BE47, ValidationAndReference!Q:Q, 0)), "") | BJ47: =IFERROR(INDEX(ValidationAndReference!F:F, MATCH(D47, ValidationAndReference!G:G, 0)), "") | BK47: =IFERROR(INDEX(ValidationAndReference!F:F, MATCH(E47, ValidationAndReference!G:G, 0)), "") | BL47: =IFERROR(INDEX(ValidationAndReference!F:F, MATCH(F47, ValidationAndReference!G:G, 0)), "") | BM47: 352 | BR47: lo_e-uNHzlmfUO9nAanBPwJ9R | BS47: lo_57ryE53Z3UuZ88Swuixurx | CL47: =IFERROR(INDEX(ValidationAndReference!V:V, MATCH(AZ47, ValidationAndReference!W:W, 0)), "") | CM47: =IFERROR(INDEX(ValidationAndReference!V:V, MATCH(BA47, ValidationAndReference!W:W, 0)), "") | CN47: =IFERROR(INDEX(ValidationAndReference!V:V, MATCH(BB47, ValidationAndReference!W:W, 0)), "") | CO47: 2103 Research Frst Dr | CP47: The Woodlands | CQ47: 77380 | CR47: TX | CT47: No - Facility Zip
A48: Angela | B48: Naki | C48: Female | D48: DMFT | E48: LPC | G48: =IFERROR(VLOOKUP(BM48, ValidationAndReference!J:K, 2, FALSE), "") | L48: Both | M48: LifeStance Health | N48: =IFERROR(INDEX(Location!X:X, MATCH(BR48, Location!W:W, 0)), "") | O48: =IFERROR(INDEX(Location!X:X, MATCH(BS48, Location!W:W, 0)), "") | S48: 1598377749 | T48: https://prod-clinicians-photo.s3.amazonaws.com/1598377749.jpg | U48: Doctorate of Marriage and Family Therapy, Northcentral University | Z48: Angela Naki helps patients across Texas find stability, emotional relief, and renewed confidence through thoughtful, evidencebased mental health care. At LifeStance Health, she supports children, adolescents, teens, adults, and seniors, offering both individual and familycentered treatment tailored to the needs of diverse communities throughout the state. She is especially passionate about treating trauma, school avoidance, and complex life transitions. Angela is known for her steady, grounding presence with patients navigating PTSD and traumarelated symptoms, and she works closely with children and adolescents who are struggling to attend school due to anxiety, emotional overwhelm, or family stressors. Her approach emphasizes safety, practical skills, and restoring a sense of empowerment for individuals of all ages. Angelaâs clinical expertise includes anxiety, depression, and PTSDtrauma, along with additional specialties that allow her to support patients with a wide range of concerns. She integrates EMDR, Cognitive Behavioral Therapy, and Dialectical Behavior Therapy, offering additional therapeutic interventions to meet each patientâs needs. She frequently works with first responders, military and veteran populations, and LGBTQ individuals, applying a culturally attuned and compassionate lens. When helpful, she incorporates Psychological Testing to provide deeper clinical insight and guide treatment planning. Outside her work, Angela enjoys reading, traveling, cooking, and baking, and she treasures time spent spoiling her granddaughter and sharing moments with family and friends. | AZ48: English | BC48: pt_vOTgX4FPvUOFJaL-VrSO1B | BE48: Practitioner - Full Profile | BG48: No | BI48: =IFERROR(INDEX(ValidationAndReference!P:P, MATCH(BE48, ValidationAndReference!Q:Q, 0)), "") | BJ48: =IFERROR(INDEX(ValidationAndReference!F:F, MATCH(D48, ValidationAndReference!G:G, 0)), "") | BK48: =IFERROR(INDEX(ValidationAndReference!F:F, MATCH(E48, ValidationAndReference!G:G, 0)), "") | BL48: =IFERROR(INDEX(ValidationAndReference!F:F, MATCH(F48, ValidationAndReference!G:G, 0)), "") | BM48: 352 | BR48: lo_e-uNHzlmfUO9nAanBPwJ9R | BS48: lo_57ryE53Z3UuZ88Swuixurx | CL48: =IFERROR(INDEX(ValidationAndReference!V:V, MATCH(AZ48, ValidationAndReference!W:W, 0)), "") | CM48: =IFERROR(INDEX(ValidationAndReference!V:V, MATCH(BA48, ValidationAndReference!W:W, 0)), "") | CN48: =IFERROR(INDEX(ValidationAndReference!V:V, MATCH(BB48, ValidationAndReference!W:W, 0)), "") | CO48: 2103 Research Frst Dr | CP48: The Woodlands | CQ48: 77380 | CR48: TX | CT48: No - Facility Zip
A49: Angela | B49: Naki | C49: Female | D49: DMFT | E49: LPC | G49: =IFERROR(VLOOKUP(BM49, ValidationAndReference!J:K, 2, FALSE), "") | L49: Both | M49: LifeStance Health | N49: =IFERROR(INDEX(Location!X:X, MATCH(BR49, Location!W:W, 0)), "") | O49: =IFERROR(INDEX(Location!X:X, MATCH(BS49, Location!W:W, 0)), "") | S49: 1598377749 | T49: https://prod-clinicians-photo.s3.amazonaws.com/1598377749.jpg | U49: Doctorate of Marriage and Family Therapy, Northcentral University | Z49: Angela Naki helps patients across Texas find stability, emotional relief, and renewed confidence through thoughtful, evidencebased mental health care. At LifeStance Health, she supports children, adolescents, teens, adults, and seniors, offering both individual and familycentered treatment tailored to the needs of diverse communities throughout the state. She is especially passionate about treating trauma, school avoidance, and complex life transitions. Angela is known for her steady, grounding presence with patients navigating PTSD and traumarelated symptoms, and she works closely with children and adolescents who are struggling to attend school due to anxiety, emotional overwhelm, or family stressors. Her approach emphasizes safety, practical skills, and restoring a sense of empowerment for individuals of all ages. Angelaâs clinical expertise includes anxiety, depression, and PTSDtrauma, along with additional specialties that allow her to support patients with a wide range of concerns. She integrates EMDR, Cognitive Behavioral Therapy, and Dialectical Behavior Therapy, offering additional therapeutic interventions to meet each patientâs needs. She frequently works with first responders, military and veteran populations, and LGBTQ individuals, applying a culturally attuned and compassionate lens. When helpful, she incorporates Psychological Testing to provide deeper clinical insight and guide treatment planning. Outside her work, Angela enjoys reading, traveling, cooking, and baking, and she treasures time spent spoiling her granddaughter and sharing moments with family and friends. | AZ49: English | BC49: pt_vOTgX4FPvUOFJaL-VrSO1B | BE49: Practitioner - Full Profile | BG49: No | BI49: =IFERROR(INDEX(ValidationAndReference!P:P, MATCH(BE49, ValidationAndReference!Q:Q, 0)), "") | BJ49: =IFERROR(INDEX(ValidationAndReference!F:F, MATCH(D49, ValidationAndReference!G:G, 0)), "") | BK49: =IFERROR(INDEX(ValidationAndReference!F:F, MATCH(E49, ValidationAndReference!G:G, 0)), "") | BL49: =IFERROR(INDEX(ValidationAndReference!F:F, MATCH(F49, ValidationAndReference!G:G, 0)), "") | BM49: 352 | BR49: lo_e-uNHzlmfUO9nAanBPwJ9R | BS49: lo_57ryE53Z3UuZ88Swuixurx | CL49: =IFERROR(INDEX(ValidationAndReference!V:V, MATCH(AZ49, ValidationAndReference!W:W, 0)), "") | CM49: =IFERROR(INDEX(ValidationAndReference!V:V, MATCH(BA49, ValidationAndReference!W:W, 0)), "") | CN49: =IFERROR(INDEX(ValidationAndReference!V:V, MATCH(BB49, ValidationAndReference!W:W, 0)), "") | CO49: 2103 Research Frst Dr | CP49: The Woodlands | CQ49: 77380 | CR49: TX | CT49: No - Facility Zip
A50: Zaria | B50: Norman | C50: Female | D50: LPC | G50: =IFERROR(VLOOKUP(BM50, ValidationAndReference!J:K, 2, FALSE), "") | L50: Both | M50: LifeStance Health | N50: =IFERROR(INDEX(Location!X:X, MATCH(BR50, Location!W:W, 0)), "") | O50: =IFERROR(INDEX(Location!X:X, MATCH(BS50, Location!W:W, 0)), "") | S50: 1619843117 | T50: https://prod-clinicians-photo.s3.amazonaws.com/1619843117.jpg | U50: MA Clinical Mental Health Counseling, Colorado Christian University | Z50: Zaria Norman, LPC, helps adults across Colorado navigate lifeâs challenges with compassion, authenticity, and evidencebased care. She provides a safe and supportive space where clients can explore their emotions, understand their behaviors, and develop practical tools for healing and growth. Serving individuals throughout Colorado, Zaria focuses on guiding clients toward lasting change by addressing the root causes of emotional distress and empowering them to build healthier patterns of thought and behavior. At LifeStance Health, Zaria offers individual therapy and support for substance use concerns, integrating proven approaches such as Cognitive Behavioral Therapy CBT, Dialectical Behavior Therapy DBT, and Mindfulness techniques. She specializes in treating anxiety, depression, and alcohol and drug use issues helping clients find stability, balance, and a renewed sense of purpose. Her therapeutic style is collaborative and nonjudgmental, encouraging clients to take an active role in their journey toward emotional wellbeing. Zaria is deeply passionate about helping individuals recover from alcohol and drug use challenges, recognizing that each personâs experience with addiction is unique. She works with clients to rebuild selfworth, strengthen coping strategies, and create meaningful, sustainable change. By blending Acceptance and Commitment Therapy with mindfulnessbased interventions, she helps clients move beyond selfblame, cultivate resilience, and reconnect with their values and goals. Her practice also supports individuals navigating adoption and foster care experiences as well as those living with autism spectrum disorders. Zariaâs approach integrates compassion and evidencebased care to meet the needs of diverse populations while fostering growth and selfacceptance. Beyond her clinical work, Zaria finds fulfillment in exploring new cultures through travel and language learning, spending time outdoors, and connecting with the natural world. These passions mirror her belief in lifelong learning, balance, and the healing power of connection. | AZ50: English | BC50: pt_Xdjx281Ba06vQlN0Fjw0Tx | BE50: Practitioner - Full Profile | BG50: No | BI50: =IFERROR(INDEX(ValidationAndReference!P:P, MATCH(BE50, ValidationAndReference!Q:Q, 0)), "") | BJ50: =IFERROR(INDEX(ValidationAndReference!F:F, MATCH(D50, ValidationAndReference!G:G, 0)), "") | BK50: =IFERROR(INDEX(ValidationAndReference!F:F, MATCH(E50, ValidationAndReference!G:G, 0)), "") | BL50: =IFERROR(INDEX(ValidationAndReference!F:F, MATCH(F50, ValidationAndReference!G:G, 0)), "") | BR50: lo_dz4Gh1OyLES2qHHp5JJexx | BS50: lo_BKMpWDUpnEGeVdKpdOgjhh | CL50: =IFERROR(INDEX(ValidationAndReference!V:V, MATCH(AZ50, ValidationAndReference!W:W, 0)), "") | CM50: =IFERROR(INDEX(ValidationAndReference!V:V, MATCH(BA50, ValidationAndReference!W:W, 0)), "") | CN50: =IFERROR(INDEX(ValidationAndReference!V:V, MATCH(BB50, ValidationAndReference!W:W, 0)), "") | CO50: 6377 S Revere Pkwy | CP50: Centennial | CQ50: 80111 | CR50: CO | CT50: No - Facility Zip
A51: Madeline | B51: Wright | C51: Female | D51: PMHNP-BC | G51: =IFERROR(VLOOKUP(BM51, ValidationAndReference!J:K, 2, FALSE), "") | L51: Both | M51: LifeStance Health | N51: =IFERROR(INDEX(Location!X:X, MATCH(BR51, Location!W:W, 0)), "") | O51: =IFERROR(INDEX(Location!X:X, MATCH(BS51, Location!W:W, 0)), "") | S51: 1629767934 | T51: https://prod-clinicians-photo.s3.amazonaws.com/1629767934.jpg | U51: Master of Science in Nursing, DePaul University | Z51: Madeline Wright, APNP, PMH, RN, helps patients across Colorado improve their mental health and quality of life through evidencebased, compassionate care. She provides comprehensive medication management and individualized therapy to help teens, adults, and seniors manage conditions such as anxiety, depression, ADHD, and bipolar disorder. With a patientcentered approach, Madeline empowers each person to take an active role in their treatment journey, fostering lasting emotional resilience and stability. Madeline is dedicated to helping patients navigate complex challenges such as trauma, substance use, and sleep disorders, offering treatment strategies that address both the mind and body. Her clinical expertise includes the use of mindfulness techniques and advanced interventions such as SpravatoÂ esketamine therapy, which supports patients experiencing treatmentresistant depression. She also provides psychological testing to assist in accurate diagnosis and individualized care planning, ensuring every patient receives the most effective treatment for their unique needs. Madeline is especially passionate about supporting women facing postpartum depression and anxiety, as well as individuals coping with grief and major life transitions. She also works closely with those affected by eating disorders, emphasizing a compassionate, nonjudgmental approach that promotes healing, body acceptance, and selfcompassion. Her experience with special populations, including first responders, military and veterans, and the LGBTQ community, enables her to provide culturally informed care tailored to the realities and stressors these groups often encounter. Outside of her professional work, Madeline enjoys spending time with friends and family, hiking Coloradoâs trails, skiing, running, and caring for her rescue dogs. She also loves reading, traveling, gardening, and exploring new foods, finding balance and joy in everyday experiences. | AZ51: English | BC51: pt_Xdjx281Ba06vQlN0Fjw0Tx | BE51: Practitioner - Full Profile | BG51: No | BI51: =IFERROR(INDEX(ValidationAndReference!P:P, MATCH(BE51, ValidationAndReference!Q:Q, 0)), "") | BJ51: =IFERROR(INDEX(ValidationAndReference!F:F, MATCH(D51, ValidationAndReference!G:G, 0)), "") | BK51: =IFERROR(INDEX(ValidationAndReference!F:F, MATCH(E51, ValidationAndReference!G:G, 0)), "") | BL51: =IFERROR(INDEX(ValidationAndReference!F:F, MATCH(F51, ValidationAndReference!G:G, 0)), "") | BM51: 405 | BR51: lo_5htAS1BwLUa1aardqyvchB | BS51: lo_V_2YX74st0u02btzzta2Vh | CL51: =IFERROR(INDEX(ValidationAndReference!V:V, MATCH(AZ51, ValidationAndReference!W:W, 0)), "") | CM51: =IFERROR(INDEX(ValidationAndReference!V:V, MATCH(BA51, ValidationAndReference!W:W, 0)), "") | CN51: =IFERROR(INDEX(ValidationAndReference!V:V, MATCH(BB51, ValidationAndReference!W:W, 0)), "") | CO51: 8300 Alcott St | CP51: Westminster | CQ51: 80031 | CR51: CO | CT51: No - Facility Zip
A52: Matthew | B52: Masolini | C52: Male | D52: MA | E52: LMFT | G52: =IFERROR(VLOOKUP(BM52, ValidationAndReference!J:K, 2, FALSE), "") | L52: Both | M52: LifeStance Health | N52: =IFERROR(INDEX(Location!X:X, MATCH(BR52, Location!W:W, 0)), "") | O52: =IFERROR(INDEX(Location!X:X, MATCH(BS52, Location!W:W, 0)), "") | S52: 1639741820 | T52: https://prod-clinicians-photo.s3.amazonaws.com/1639741820.jpg | U52: Master of Arts, Hope International University | Z52: Matthew Masolini, LMFT, helps patients across California stabilize, heal, and reclaim control of their lives during some of their most challenging moments. He provides individual and couples therapy for teens and adults, offering a steady, nonjudgmental presence for those navigating anxiety, depression, relationship strain, and major life transitions. As part of LifeStance Health, he is committed to delivering accessible, highquality mental health care to communities throughout California. Matthew is especially passionate about working with individuals who have been recently discharged from a psychiatric hospital or who are participating in courtordered treatment. He understands the uncertainty, fear, and pressure that often come with these circumstances and offers structured, compassionate, and goalfocused support to help patients rebuild stability, confidence, and healthy daily functioning. His clinical expertise includes treating PTSDtrauma, anxiety, and coupleâs issues, and he offers additional support for conditions such as bipolar disorder, OCD, ADHD, and sleep disturbances. Matthew also helps patients facing grief, substancerelated challenges, or genderidentity exploration, providing a grounded and affirming therapeutic environment. Matthew draws from Cognitive Behavioral Therapy, Acceptance and Commitment Therapy, and EMDR, integrating additional modalities such as DBT, mindfulness, and exposurebased work depending on the needs of each patient. He works with diverse communities, including LGBTQ individuals and military veterans, and welcomes men and women seeking a collaborative and practical path toward emotional wellness. Outside of his professional role, Matthew values creativity and balance. In his personal time, he can often be found reading unexpected book recommendations, writing, or playing the guitar activities that help him remain present and energized for his clients. | AZ52: English | BC52: pt_06Ie2RxfpECXX_EgrAt4yB | BE52: Practitioner - Full Profile | BG52: No | BI52: =IFERROR(INDEX(ValidationAndReference!P:P, MATCH(BE52, ValidationAndReference!Q:Q, 0)), "") | BJ52: =IFERROR(INDEX(ValidationAndReference!F:F, MATCH(D52, ValidationAndReference!G:G, 0)), "") | BK52: =IFERROR(INDEX(ValidationAndReference!F:F, MATCH(E52, ValidationAndReference!G:G, 0)), "") | BL52: =IFERROR(INDEX(ValidationAndReference!F:F, MATCH(F52, ValidationAndReference!G:G, 0)), "") | BM52: 352 | BR52: lo_rxWWw-NmbE2Cw20LQT0ryR | BS52: lo_dQLBx9rcd0qebMEosApBMB | CL52: =IFERROR(INDEX(ValidationAndReference!V:V, MATCH(AZ52, ValidationAndReference!W:W, 0)), "") | CM52: =IFERROR(INDEX(ValidationAndReference!V:V, MATCH(BA52, ValidationAndReference!W:W, 0)), "") | CN52: =IFERROR(INDEX(ValidationAndReference!V:V, MATCH(BB52, ValidationAndReference!W:W, 0)), "") | CO52: 1640 Newport Blvd | CP52: Costa Mesa | CQ52: 92627 | CR52: CA | CT52: No - Facility Zip
A53: Matthew | B53: Masolini | C53: Male | D53: MA | E53: LMFT | G53: =IFERROR(VLOOKUP(BM53, ValidationAndReference!J:K, 2, FALSE), "") | L53: Both | M53: LifeStance Health | N53: =IFERROR(INDEX(Location!X:X, MATCH(BR53, Location!W:W, 0)), "") | O53: =IFERROR(INDEX(Location!X:X, MATCH(BS53, Location!W:W, 0)), "") | S53: 1639741820 | T53: https://prod-clinicians-photo.s3.amazonaws.com/1639741820.jpg | U53: Master of Arts, Hope International University | Z53: Matthew Masolini, LMFT, helps patients across California stabilize, heal, and reclaim control of their lives during some of their most challenging moments. He provides individual and couples therapy for teens and adults, offering a steady, nonjudgmental presence for those navigating anxiety, depression, relationship strain, and major life transitions. As part of LifeStance Health, he is committed to delivering accessible, highquality mental health care to communities throughout California. Matthew is especially passionate about working with individuals who have been recently discharged from a psychiatric hospital or who are participating in courtordered treatment. He understands the uncertainty, fear, and pressure that often come with these circumstances and offers structured, compassionate, and goalfocused support to help patients rebuild stability, confidence, and healthy daily functioning. His clinical expertise includes treating PTSDtrauma, anxiety, and coupleâs issues, and he offers additional support for conditions such as bipolar disorder, OCD, ADHD, and sleep disturbances. Matthew also helps patients facing grief, substancerelated challenges, or genderidentity exploration, providing a grounded and affirming therapeutic environment. Matthew draws from Cognitive Behavioral Therapy, Acceptance and Commitment Therapy, and EMDR, integrating additional modalities such as DBT, mindfulness, and exposurebased work depending on the needs of each patient. He works with diverse communities, including LGBTQ individuals and military veterans, and welcomes men and women seeking a collaborative and practical path toward emotional wellness. Outside of his professional role, Matthew values creativity and balance. In his personal time, he can often be found reading unexpected book recommendations, writing, or playing the guitar activities that help him remain present and energized for his clients. | AZ53: English | BC53: pt_06Ie2RxfpECXX_EgrAt4yB | BE53: Practitioner - Full Profile | BG53: No | BI53: =IFERROR(INDEX(ValidationAndReference!P:P, MATCH(BE53, ValidationAndReference!Q:Q, 0)), "") | BJ53: =IFERROR(INDEX(ValidationAndReference!F:F, MATCH(D53, ValidationAndReference!G:G, 0)), "") | BK53: =IFERROR(INDEX(ValidationAndReference!F:F, MATCH(E53, ValidationAndReference!G:G, 0)), "") | BL53: =IFERROR(INDEX(ValidationAndReference!F:F, MATCH(F53, ValidationAndReference!G:G, 0)), "") | BM53: 352 | BR53: lo_rxWWw-NmbE2Cw20LQT0ryR | BS53: lo_dQLBx9rcd0qebMEosApBMB | CL53: =IFERROR(INDEX(ValidationAndReference!V:V, MATCH(AZ53, ValidationAndReference!W:W, 0)), "") | CM53: =IFERROR(INDEX(ValidationAndReference!V:V, MATCH(BA53, ValidationAndReference!W:W, 0)), "") | CN53: =IFERROR(INDEX(ValidationAndReference!V:V, MATCH(BB53, ValidationAndReference!W:W, 0)), "") | CO53: 1640 Newport Blvd | CP53: Costa Mesa | CQ53: 92627 | CR53: CA | CT53: No - Facility Zip
A54: Katie | B54: Austin | C54: Female | D54: LCSW | G54: =IFERROR(VLOOKUP(BM54, ValidationAndReference!J:K, 2, FALSE), "") | L54: Both | M54: LifeStance Health | N54: =IFERROR(INDEX(Location!X:X, MATCH(BR54, Location!W:W, 0)), "") | O54: =IFERROR(INDEX(Location!X:X, MATCH(BS54, Location!W:W, 0)), "") | S54: 1679337349 | T54: https://prod-clinicians-photo.s3.amazonaws.com/1679337349.jpg | U54: Masters of Social Work, University of Southern California | Z54: Katie Austin, LCSW, helps adults of all ages in Virginia navigate lifeâs challenges with steadiness, compassion, and evidencebased care. She provides individual and group therapy at LifeStance Health, offering a grounded therapeutic presence for adults seeking meaningful change and greater emotional wellbeing. Drawing on years of clinical experience since 2018, she supports patients through concerns such as anxiety, depression, and trauma while honoring each personâs unique story. Katie is particularly committed to helping individuals move through traumarelated struggles, anxiety disorders, and alcohol or drug use issues. She understands the complex ways these concerns affect daily functioning, relationships, and selfconfidence. Her approach emphasizes restoring safety, building resilience, and empowering patients to reclaim parts of their lives that have felt overshadowed by fear, shame, or overwhelm. Katie also brings focused expertise to populations who often face distinct stressors, including first responders, LGBTQ individuals, and military members and veterans. She uses interventions such as Cognitive Behavioral Therapy, EMDR, and Mindfulness, integrating these methods to support healing from traumatic experiences, regulate emotions, and strengthen coping skills. She additionally offers specialized care for womenâs issues, midlife transitions, and postpartum anxiety or depression, along with other areas of support. Outside the therapy room, Katie values a balanced and creative life. She enjoys traveling, baking, cycling, and reading. | AZ54: English | BC54: pt_W-IrVfnCaEej1xnrhq3K_h | BE54: Practitioner - Full Profile | BG54: No | BI54: =IFERROR(INDEX(ValidationAndReference!P:P, MATCH(BE54, ValidationAndReference!Q:Q, 0)), "") | BJ54: =IFERROR(INDEX(ValidationAndReference!F:F, MATCH(D54, ValidationAndReference!G:G, 0)), "") | BK54: =IFERROR(INDEX(ValidationAndReference!F:F, MATCH(E54, ValidationAndReference!G:G, 0)), "") | BL54: =IFERROR(INDEX(ValidationAndReference!F:F, MATCH(F54, ValidationAndReference!G:G, 0)), "") | BM54: 352 | BR54: lo_L8Q-yA9P_UipUdReTq97jh | BS54: lo_wGz8e0hNkUiLg5nlg6w6yR | CL54: =IFERROR(INDEX(ValidationAndReference!V:V, MATCH(AZ54, ValidationAndReference!W:W, 0)), "") | CM54: =IFERROR(INDEX(ValidationAndReference!V:V, MATCH(BA54, ValidationAndReference!W:W, 0)), "") | CN54: =IFERROR(INDEX(ValidationAndReference!V:V, MATCH(BB54, ValidationAndReference!W:W, 0)), "") | CO54: 5360 Discovery Park Blvd | CP54: Williamsburg | CQ54: 23188 | CR54: VA | CT54: No - Facility Zip
A55: Chalon | B55: Murphy | C55: Female | D55: LMFT | G55: =IFERROR(VLOOKUP(BM55, ValidationAndReference!J:K, 2, FALSE), "") | L55: Both | M55: LifeStance Health | N55: =IFERROR(INDEX(Location!X:X, MATCH(BR55, Location!W:W, 0)), "") | O55: =IFERROR(INDEX(Location!X:X, MATCH(BS55, Location!W:W, 0)), "") | S55: 1699906685 | T55: https://prod-clinicians-photo.s3.amazonaws.com/1699906685.jpg | U55: Masters of Arts (MA), Brandman University | Z55: Chalon Murphy helps individuals, couples, and families across California navigate emotional challenges and strengthen their ability to cope with lifeâs transitions. She provides a supportive, compassionate, and empowering space for teens and adults to explore their emotions, build resilience, and develop strategies that promote longterm emotional wellness. Whether helping clients manage anxiety, depression, or relationship issues, Chalon focuses on restoring balance and helping each person reconnect with their sense of purpose and inner strength. Chalon specializes in traumainformed care and works extensively with clients navigating the effects of PTSD, grief, and loss. She is passionate about helping individuals who have experienced trauma reclaim safety, rebuild trust, and cultivate a sense of peace in their daily lives. Her warm and empathetic approach encourages healing through understanding and selfcompassion, while her use of structured therapeutic tools helps clients make sustainable progress toward their goals. Drawing from evidencebased methods such as Cognitive Behavioral Therapy CBT, Dialectical Behavior Therapy DBT, and Acceptance and Commitment Therapy ACT, Chalon integrates techniques that promote emotional regulation, mindfulness, and selfawareness. She also provides faithbased counseling for those who wish to incorporate spirituality into their healing process. Her work includes helping couples enhance communication and intimacy, supporting individuals managing ADHD or bipolar disorder, and guiding clients through midlife and later life transitions. Outside of her practice, Chalon enjoys spending time with her family and friends, traveling, listening to jazz, and reading or writing. These passions reflect her belief in the importance of creativity, connection, and balance in living a fulfilling life. | AZ55: English | BC55: pt_06Ie2RxfpECXX_EgrAt4yB | BE55: Practitioner - Full Profile | BG55: No | BI55: =IFERROR(INDEX(ValidationAndReference!P:P, MATCH(BE55, ValidationAndReference!Q:Q, 0)), "") | BJ55: =IFERROR(INDEX(ValidationAndReference!F:F, MATCH(D55, ValidationAndReference!G:G, 0)), "") | BK55: =IFERROR(INDEX(ValidationAndReference!F:F, MATCH(E55, ValidationAndReference!G:G, 0)), "") | BL55: =IFERROR(INDEX(ValidationAndReference!F:F, MATCH(F55, ValidationAndReference!G:G, 0)), "") | BM55: 352 | BR55: lo_MOAImLDNvk2X_M5s7bRn2B | BS55: lo_V8DXdn7DCUeq1hyIIkuLIB | CL55: =IFERROR(INDEX(ValidationAndReference!V:V, MATCH(AZ55, ValidationAndReference!W:W, 0)), "") | CM55: =IFERROR(INDEX(ValidationAndReference!V:V, MATCH(BA55, ValidationAndReference!W:W, 0)), "") | CN55: =IFERROR(INDEX(ValidationAndReference!V:V, MATCH(BB55, ValidationAndReference!W:W, 0)), "") | CO55: 4160 Temescal Cyn Rd | CP55: Corona | CQ55: 92883 | CR55: CA | CT55: No - Facility Zip
A56: Chalon | B56: Murphy | C56: Female | D56: LMFT | G56: =IFERROR(VLOOKUP(BM56, ValidationAndReference!J:K, 2, FALSE), "") | L56: Both | M56: LifeStance Health | N56: =IFERROR(INDEX(Location!X:X, MATCH(BR56, Location!W:W, 0)), "") | O56: =IFERROR(INDEX(Location!X:X, MATCH(BS56, Location!W:W, 0)), "") | S56: 1699906685 | T56: https://prod-clinicians-photo.s3.amazonaws.com/1699906685.jpg | U56: Masters of Arts (MA), Brandman University | Z56: Chalon Murphy helps individuals, couples, and families across California navigate emotional challenges and strengthen their ability to cope with lifeâs transitions. She provides a supportive, compassionate, and empowering space for teens and adults to explore their emotions, build resilience, and develop strategies that promote longterm emotional wellness. Whether helping clients manage anxiety, depression, or relationship issues, Chalon focuses on restoring balance and helping each person reconnect with their sense of purpose and inner strength. Chalon specializes in traumainformed care and works extensively with clients navigating the effects of PTSD, grief, and loss. She is passionate about helping individuals who have experienced trauma reclaim safety, rebuild trust, and cultivate a sense of peace in their daily lives. Her warm and empathetic approach encourages healing through understanding and selfcompassion, while her use of structured therapeutic tools helps clients make sustainable progress toward their goals. Drawing from evidencebased methods such as Cognitive Behavioral Therapy CBT, Dialectical Behavior Therapy DBT, and Acceptance and Commitment Therapy ACT, Chalon integrates techniques that promote emotional regulation, mindfulness, and selfawareness. She also provides faithbased counseling for those who wish to incorporate spirituality into their healing process. Her work includes helping couples enhance communication and intimacy, supporting individuals managing ADHD or bipolar disorder, and guiding clients through midlife and later life transitions. Outside of her practice, Chalon enjoys spending time with her family and friends, traveling, listening to jazz, and reading or writing. These passions reflect her belief in the importance of creativity, connection, and balance in living a fulfilling life. | AZ56: English | BC56: pt_06Ie2RxfpECXX_EgrAt4yB | BE56: Practitioner - Full Profile | BG56: No | BI56: =IFERROR(INDEX(ValidationAndReference!P:P, MATCH(BE56, ValidationAndReference!Q:Q, 0)), "") | BJ56: =IFERROR(INDEX(ValidationAndReference!F:F, MATCH(D56, ValidationAndReference!G:G, 0)), "") | BK56: =IFERROR(INDEX(ValidationAndReference!F:F, MATCH(E56, ValidationAndReference!G:G, 0)), "") | BL56: =IFERROR(INDEX(ValidationAndReference!F:F, MATCH(F56, ValidationAndReference!G:G, 0)), "") | BM56: 352 | BR56: lo_MOAImLDNvk2X_M5s7bRn2B | BS56: lo_V8DXdn7DCUeq1hyIIkuLIB | CL56: =IFERROR(INDEX(ValidationAndReference!V:V, MATCH(AZ56, ValidationAndReference!W:W, 0)), "") | CM56: =IFERROR(INDEX(ValidationAndReference!V:V, MATCH(BA56, ValidationAndReference!W:W, 0)), "") | CN56: =IFERROR(INDEX(ValidationAndReference!V:V, MATCH(BB56, ValidationAndReference!W:W, 0)), "") | CO56: 4160 Temescal Cyn Rd | CP56: Corona | CQ56: 92883 | CR56: CA | CT56: No - Facility Zip
A57: Alicia | B57: Carnevale | C57: Female | D57: LCSW | G57: =IFERROR(VLOOKUP(BM57, ValidationAndReference!J:K, 2, FALSE), "") | L57: Both | M57: LifeStance Health | N57: =IFERROR(INDEX(Location!X:X, MATCH(BR57, Location!W:W, 0)), "") | O57: =IFERROR(INDEX(Location!X:X, MATCH(BS57, Location!W:W, 0)), "") | S57: 1710406673 | T57: https://prod-clinicians-photo.s3.amazonaws.com/1710406673.jpg | U57: Masters of Social Work, Boston University | Z57: Alicia Carnevale helps patients in Massachusetts navigate emotional challenges with a blend of warmth, clinical insight, and evidencebased care. She supports adolescents, teens, and adults as they work through conditions such as anxiety, depression, and trauma, offering a stable therapeutic space where growth, healing, and clarity can take root. At LifeStance Health, Alicia provides individual, group, and family therapy with a focus on practical strategies that foster resilience and longterm wellbeing. She draws on Cognitive Behavioral Therapy, Mindfulness practices, and Exposure Therapy to support meaningful change, particularly for individuals managing anxietyrelated conditions, mood disorders, or complex stressors. Alicia is experienced in helping members of the LGBTQ community, individuals with developmental or autism spectrumrelated needs, and people navigating life after head injuries. She also supports those from foster or adoption backgrounds as they work through identity, belonging, and emotional processing. Alicia is especially passionate about helping patients address addictionrelated concerns, trauma and PTSD symptoms, and womenâs mental health. She approaches these areas with sensitivity, structure, and a strong respect for each patientâs lived experience, tailoring care to support both immediate relief and sustainable recovery. Over the course of her career, Alicia has developed a clinical style grounded in collaboration and empowerment. She welcomes adolescents and teens beginning their mental health journey, as well as adults seeking support for longstanding patterns, recent stressors, or major life transitions. Outside the therapy room, Alicia recharges through hiking, kayaking, camping, crafting, and writing poetry. She enjoys cooking and baking, and finds inspiration in animals, the arts, and time spent outdoors. | AZ57: English | BC57: pt_B8LtUoRcYkWdny_20xbxdB | BE57: Practitioner - Full Profile | BG57: No | BI57: =IFERROR(INDEX(ValidationAndReference!P:P, MATCH(BE57, ValidationAndReference!Q:Q, 0)), "") | BJ57: =IFERROR(INDEX(ValidationAndReference!F:F, MATCH(D57, ValidationAndReference!G:G, 0)), "") | BK57: =IFERROR(INDEX(ValidationAndReference!F:F, MATCH(E57, ValidationAndReference!G:G, 0)), "") | BL57: =IFERROR(INDEX(ValidationAndReference!F:F, MATCH(F57, ValidationAndReference!G:G, 0)), "") | BM57: 352 | BR57: lo_Vh5w3CxH0EykH5kx0U6tFB | BS57: lo_60MBmWeGhUW35I-sOeQCqB | CL57: =IFERROR(INDEX(ValidationAndReference!V:V, MATCH(AZ57, ValidationAndReference!W:W, 0)), "") | CM57: =IFERROR(INDEX(ValidationAndReference!V:V, MATCH(BA57, ValidationAndReference!W:W, 0)), "") | CN57: =IFERROR(INDEX(ValidationAndReference!V:V, MATCH(BB57, ValidationAndReference!W:W, 0)), "") | CO57: 11 Midstate Dr | CP57: Auburn | CQ57: 1501 | CR57: MA | CT57: No - Facility Zip
A58: Karlynn | B58: Ness | C58: Female | D58: MSN | E58: APRN | F58: PMHNP-BC | G58: =IFERROR(VLOOKUP(BM58, ValidationAndReference!J:K, 2, FALSE), "") | L58: Both | M58: LifeStance Health | N58: =IFERROR(INDEX(Location!X:X, MATCH(BR58, Location!W:W, 0)), "") | O58: =IFERROR(INDEX(Location!X:X, MATCH(BS58, Location!W:W, 0)), "") | S58: 1710792700 | T58: https://prod-clinicians-photo.s3.amazonaws.com/1710792700.jpg | U58: Master of Science in Nursing (MSN), Bradley University | Z58: Karlynn Ness, PMHNPBC, helps patients in Illinois find clarity, stability, and meaningful progress through compassionate and clinically grounded psychiatric care. She supports children, adolescents, teens, and adults with medication management, offering a thoughtful and individualized approach that honors each personâs strengths, challenges, and lived experience. Her goal is to create a space where patients feel understood, supported, and empowered to move toward lasting wellness. Karlynn is especially passionate about treating ADHD, anxiety, and depression. She works closely with children and adolescents who are navigating emotional, behavioral, or academic challenges, and partners with families to promote healthier communication, improved functioning, and longterm success. Her approach blends evidencebased care with warmth and practical guidance, helping young people and adults build skills that support everyday stability and resilience. In addition to these focus areas, she offers care for grief, bipolar disorder, PTSDtrauma, OCD, school avoidance, postpartum anxiety and depression, psychosis, womenâs mental health concerns, and various childhood behavior issues. She also supports individuals in the adoption and foster care community, patients with developmental disabilities or autism spectrum disorders, first responders, militaryveterans, and LGBTQ individuals. Karlynn uses medication management supported by Cognitive Behavioral Therapy and mindfulness strategies to help patients make sustainable progress, and she provides additional services beyond those noted here. Karlynn practices at LifeStance Health and brings a holistic mindset that respects the whole personâmind, body, and environment. She values genuine connection, collaboration, and transparency in treatment planning, ensuring that patients of all ages feel involved and informed at every step. Outside of her clinical work, Karlynn loves spending time with her family, exploring new places, visiting attractions, and discovering great food spots. | AZ58: English | BC58: pt_6BaNpinqtUOgby24rE9XXx | BE58: Practitioner - Full Profile | BG58: No | BI58: =IFERROR(INDEX(ValidationAndReference!P:P, MATCH(BE58, ValidationAndReference!Q:Q, 0)), "") | BJ58: =IFERROR(INDEX(ValidationAndReference!F:F, MATCH(D58, ValidationAndReference!G:G, 0)), "") | BK58: =IFERROR(INDEX(ValidationAndReference!F:F, MATCH(E58, ValidationAndReference!G:G, 0)), "") | BL58: =IFERROR(INDEX(ValidationAndReference!F:F, MATCH(F58, ValidationAndReference!G:G, 0)), "") | BM58: 405 | BR58: lo__jxoZS78nkW_V0ZsL3DiuB | BS58: lo_IFtE0WT26kOBnINkRdf4nh | CL58: =IFERROR(INDEX(ValidationAndReference!V:V, MATCH(AZ58, ValidationAndReference!W:W, 0)), "") | CM58: =IFERROR(INDEX(ValidationAndReference!V:V, MATCH(BA58, ValidationAndReference!W:W, 0)), "") | CN58: =IFERROR(INDEX(ValidationAndReference!V:V, MATCH(BB58, ValidationAndReference!W:W, 0)), "") | CO58: 55 E Loop Rd | CP58: Wheaton | CQ58: 60189 | CR58: IL | CT58: No - Facility Zip
A59: Karlynn | B59: Ness | C59: Female | D59: MSN | E59: APRN | F59: PMHNP-BC | G59: =IFERROR(VLOOKUP(BM59, ValidationAndReference!J:K, 2, FALSE), "") | L59: Both | M59: LifeStance Health | N59: =IFERROR(INDEX(Location!X:X, MATCH(BR59, Location!W:W, 0)), "") | O59: =IFERROR(INDEX(Location!X:X, MATCH(BS59, Location!W:W, 0)), "") | S59: 1710792700 | T59: https://prod-clinicians-photo.s3.amazonaws.com/1710792700.jpg | U59: Master of Science in Nursing (MSN), Bradley University | Z59: Karlynn Ness, PMHNPBC, helps patients in Illinois find clarity, stability, and meaningful progress through compassionate and clinically grounded psychiatric care. She supports children, adolescents, teens, and adults with medication management, offering a thoughtful and individualized approach that honors each personâs strengths, challenges, and lived experience. Her goal is to create a space where patients feel understood, supported, and empowered to move toward lasting wellness. Karlynn is especially passionate about treating ADHD, anxiety, and depression. She works closely with children and adolescents who are navigating emotional, behavioral, or academic challenges, and partners with families to promote healthier communication, improved functioning, and longterm success. Her approach blends evidencebased care with warmth and practical guidance, helping young people and adults build skills that support everyday stability and resilience. In addition to these focus areas, she offers care for grief, bipolar disorder, PTSDtrauma, OCD, school avoidance, postpartum anxiety and depression, psychosis, womenâs mental health concerns, and various childhood behavior issues. She also supports individuals in the adoption and foster care community, patients with developmental disabilities or autism spectrum disorders, first responders, militaryveterans, and LGBTQ individuals. Karlynn uses medication management supported by Cognitive Behavioral Therapy and mindfulness strategies to help patients make sustainable progress, and she provides additional services beyond those noted here. Karlynn practices at LifeStance Health and brings a holistic mindset that respects the whole personâmind, body, and environment. She values genuine connection, collaboration, and transparency in treatment planning, ensuring that patients of all ages feel involved and informed at every step. Outside of her clinical work, Karlynn loves spending time with her family, exploring new places, visiting attractions, and discovering great food spots. | AZ59: English | BC59: pt_6BaNpinqtUOgby24rE9XXx | BE59: Practitioner - Full Profile | BG59: No | BI59: =IFERROR(INDEX(ValidationAndReference!P:P, MATCH(BE59, ValidationAndReference!Q:Q, 0)), "") | BJ59: =IFERROR(INDEX(ValidationAndReference!F:F, MATCH(D59, ValidationAndReference!G:G, 0)), "") | BK59: =IFERROR(INDEX(ValidationAndReference!F:F, MATCH(E59, ValidationAndReference!G:G, 0)), "") | BL59: =IFERROR(INDEX(ValidationAndReference!F:F, MATCH(F59, ValidationAndReference!G:G, 0)), "") | BM59: 405 | BR59: lo__jxoZS78nkW_V0ZsL3DiuB | BS59: lo_IFtE0WT26kOBnINkRdf4nh | CL59: =IFERROR(INDEX(ValidationAndReference!V:V, MATCH(AZ59, ValidationAndReference!W:W, 0)), "") | CM59: =IFERROR(INDEX(ValidationAndReference!V:V, MATCH(BA59, ValidationAndReference!W:W, 0)), "") | CN59: =IFERROR(INDEX(ValidationAndReference!V:V, MATCH(BB59, ValidationAndReference!W:W, 0)), "") | CO59: 55 E Loop Rd | CP59: Wheaton | CQ59: 60189 | CR59: IL | CT59: No - Facility Zip
A60: Brittney | B60: Shegog | C60: Female | D60: LCSW | G60: =IFERROR(VLOOKUP(BM60, ValidationAndReference!J:K, 2, FALSE), "") | L60: Both | M60: LifeStance Health | N60: =IFERROR(INDEX(Location!X:X, MATCH(BR60, Location!W:W, 0)), "") | O60: =IFERROR(INDEX(Location!X:X, MATCH(BS60, Location!W:W, 0)), "") | S60: 1710853130 | T60: https://prod-clinicians-photo.s3.amazonaws.com/1710853130.jpg | U60: Master of Social Work, WAYNE STATE UNIVERSITY | Z60: Brittney Shegog, LCSW, helps patients across Michigan find steadiness, insight, and renewed confidence as they navigate lifeâs challenges. She provides compassionate, goaloriented care for adults and seniors, offering a supportive space where individuals can address concerns such as anxiety, depression, trauma, and womenâs mental health while developing practical tools for lasting change. Brittney works with adults ages 18 and up, tailoring treatment to each personâs unique needs, lived experiences, and values. Her clinical focus includes anxiety, depression, and PTSDtrauma, and she integrates strategies that emphasize emotional regulation, cognitive selfawareness, and daily functioning. She also works with LGBTQ individuals and supports men and women seeking therapy for a broad range of emotional and relational stressors. Brittney is especially passionate about helping people cope with postpartum depression and anxiety, as well as supporting individuals working through pain management and gender identity exploration. She approaches these areas with sensitivity and grounded expertise, helping patients process complex emotions while strengthening resilience and selftrust. Her therapeutic approach draws from Cognitive Behavioral Therapy CBT, exposure therapy, and Christian or faithbased treatment for those who wish to incorporate spirituality. She offers additional interventions including mindfulness, parenting skills, and comprehensive psychological testing. Brittney practices at LifeStance Health and brings warmth, balance, and thoughtful clinical presence to every session. Outside her practice, she enjoys spending meaningful time with her family, expressing creativity through coloring, attending live music events, reading, and exploring podcasts that inspire curiosity and growth. | AZ60: English | BC60: pt_2fAaDQkuJkeZYNO0YaxkCh | BE60: Practitioner - Full Profile | BG60: No | BI60: =IFERROR(INDEX(ValidationAndReference!P:P, MATCH(BE60, ValidationAndReference!Q:Q, 0)), "") | BJ60: =IFERROR(INDEX(ValidationAndReference!F:F, MATCH(D60, ValidationAndReference!G:G, 0)), "") | BK60: =IFERROR(INDEX(ValidationAndReference!F:F, MATCH(E60, ValidationAndReference!G:G, 0)), "") | BL60: =IFERROR(INDEX(ValidationAndReference!F:F, MATCH(F60, ValidationAndReference!G:G, 0)), "") | BM60: 352 | BR60: lo_BRTn0txJR0mRQSB-7QLaGh | BS60: lo_Sjb2xJj8o0ummoGM57inNB | CL60: =IFERROR(INDEX(ValidationAndReference!V:V, MATCH(AZ60, ValidationAndReference!W:W, 0)), "") | CM60: =IFERROR(INDEX(ValidationAndReference!V:V, MATCH(BA60, ValidationAndReference!W:W, 0)), "") | CN60: =IFERROR(INDEX(ValidationAndReference!V:V, MATCH(BB60, ValidationAndReference!W:W, 0)), "") | CO60: 1760 S Telegraph Rd | CP60: Bloomfield Hills | CQ60: 48302 | CR60: MI | CT60: No - Facility Zip
